Workbook
Name _dpx2: '[2]DHL City to Zone OB Vol'!$AF$7:$AO$45

Sheet 对账单-汇总页
D1: MIC Logistik GmbH对账单（9月）
G2: 报价版本号： | H2: YCD20250701
A3: 客户 | B3: 哈贝尔HUPPER TEK | D3: 海外仓地点 | E3: 德国北威州门兴格拉德巴赫（40670 ）
A4: 报价生效日期 | B4: 2025.07.01 | D4: 公司邮箱 | E4: info@miclogistik.de
A5: 对账期 | B5: 2025.09.09~2025.09.30 | D5: 公司网页 | E5: www.miclogistik.de
A7: 一、服务内容及对账明细 | G7: 计费币种：欧元/Euro
A8: 业务场景 | B8: 费用项 | C8: 库内基础费用 A | D8: 运输基础费用 B | E8: 附加费 C | F8: 开票费用合计 A-B+C | G8: 备注
A9: 1. 正向 | B9: 1.1 入库 | C9: ='1.1 正向-入库'!V1 -> 0 | D9: 0 | E9: 0 | F9: =C9+D9+E9 -> 0 | G9: 9月无入库
B10: 2.1 2B | C10: ='2.1 正向-2B'!BF1 -> 400.95 | D10: 0 | E10: ='2.1 正向-2B'!BX1+'2.1 正向-2B'!CA1 -> 0 | F10: =C10+D10+E10 -> 400.95
B11: 2.2 2C订单-GEL | C11: ='2.2 正向-2C-GEL'!AV1 -> 635.85 | D11: ='2.2 正向-2C-GEL'!BE1 -> 3647.4669 | E11: ='2.2 正向-2C-GEL'!BJ1+'2.2 正向-2C-GEL'!BM1 -> 509.6 | F11: =C11+D11+E11 -> 4792.9169
B12: 3.2 仓储费(9月） | C12: ='3.1 正向-普货-仓储费 '!AP1 -> 674.82506 | D12: 0 | E12: 0 | F12: =C12+D12+E12 -> 674.82506 | G12: 每月月底统一核算
A13: 3. 其他 | C13: 0 | D13: 0 | E13: 0 | F13: =C13+D13+E13 -> 0
A14: 合计 | C14: =SUM(C9:C13) -> 1711.6251 | D14: =SUM(D9:D13) -> 3647.4669 | E14: =SUM(E9:E13) -> 509.6 | F14: =C14+D14+E14 -> 5868.692
A15: 预付款（9月16日充值4000欧元+9月28日充值2700欧元） | C15: =4000+2700 -> 6700 | G15: 减去8月账单1632欧元
A16: 截止到9月30日余额 | C16: =C15-F14-1632 -> -800.69196 | G16: 9月已欠费（建议充值）
A18: 关键说明
A19: 1. 报价： | B19: 不含德国VAT，相关的附加费具体详见每项报价说明。
A20: 2. 账号使用前提： | B20: 采用预充值+保证金的方式： 预充值：根据未来2周或1个月预测消费额提前充值，按照不同重量段及对应报价，出单时进行预扣（含退货），充值余额不足则暂停出单； 保证金：主要是应对相关异常费用，不含常规的出单基础费、附加费，具体额度按月度预充值*15%来收取。
A21: 3. 结算： | B21: 结算币种为欧元，月结，开票与预充值核销。
A22: 4. 运输保险： | B22: 建议购买，发送丢失或损毁，按商业发票金额（需含运费）赔偿；若不购买，只能按照德国道理运输法则，货物实际重量*8.33欧/kg进行赔偿，运费也不赔偿。
A23: 5. 服务时间： | B23: 若遇当地国法定节假日，导致服务商不收货，我司会提前知会客户。
A24: 6. 报价申明： | B24: 卡派运输市场价格波动大，若变化浮动超过10%，MIC提前一个月书面/邮件通知确认。
A26: 客户签章 | F26: MIC Logistik GmbH
A31: 日期： | B31: 45933 | F31: 日期： | G31: =B31 -> 45933

Sheet 1.1 正向-入库
A1: MIC德国海外仓到货&收货&入库明细表 | U1: =SUM(U4:U7) -> 0 | V1: =SUM(V4:V7) -> 0
A2: 退货信息 | R2: 卸货&收货费 | V2: 合计
A3: 任务号 | B3: 入库月份 | C3: Carrier | D3: 收货日期 | E3: 入库状态 | F3: 客户 | G3: 批次号 | H3: 批次号行数 | I3: 批次数 | J3: 类型 | K3: 物品SKU | L3: 物品描述 | M3: 物品 总数 | N3: 货位 | O3: 箱数 | P3: 托盘数 | Q3: Remark | R3: 托盘数 | S3: 箱数 | T3: 单价 | U3: 金额

Sheet 2.1 正向-2B
A1: MIC德国海外仓一件代发明细表 | AP1: =SUM(AP5:AP8) -> 319.95 | AS1: =SUM(AS5:AS8) -> 0 | AV1: =SUM(AV5:AV8) -> 0 | AY1: =SUM(AY5:AY8) -> 0 | BB1: =SUM(BB5:BB8) -> 81 | BE1: =SUM(BE5:BE8) -> 0 | BF1: =SUM(BF5:BF8) -> 400.95 | BO1: =SUM(BO5:BO8) -> 0 | BQ1: =SUM(BQ5:BQ8) -> 0 | BX1: =SUM(BX5:BX8) -> 0 | CA1: =SUM(CA5:CA8) -> 0 | CB1: =SUM(CB5:CB8) -> 0 | CC1: =SUM(CC5:CC8) -> 400.95
A2: ,1m, | BG2: 尾程运输费 | CC2: 费用合计
A3: 出库指令 | Z3: 物品-拣料及最小包装 | AN3: 拣货&包装费 | AQ3: 拣货续件费 | AT3: 贴标费 | AW3: 包材费-包裹 | AZ3: 装车费 | BC3: 自提附加费 | BF3: 合计 | BG3: 基础费 | BP3: 续重费（超300公斤） | BR3: 附加费 | BY3: 3件包裹以上运输续件费 | CB3: 合计
A4: Order No. | B4: 订单 行数 | C4: 订单数 | D4: 对账 | E4: Warehouse | F4: 月份 | G4: Order Created At | H4: Shipped At | I4: Status | J4: Customer | K4: Original Reference | L4: Business Type | M4: Channel | N4: Creator | O4: 运单数 | P4: Priority | Q4: weight | R4: Carrier | S4: Carrier Return | T4: Shipments No1 | U4: Shipments No2 | V4: Retour No | W4: Postal Code | X4: 城市 | Y4: Country | Z4: Item ID | AA4: 物品描述 | AB4: 物品尺寸 长宽高cm | AC4: 单个物品 重量kg | AD4: Item Batch | AE4: Item Qty | AF4: 订单重量 kg | AG4: PltQty | AH4: PltDim | AI4: PltWeight | AJ4: BoxQty | AK4: BoxDim | AL4: BoxWeight | AM4: 备注 | AN4: 数量 套 | AO4: 单价 Euro | AP4: 金额 Euro | AQ4: 数量 pcs | AR4: 单价 Euro | AS4: 金额 Euro | AT4: 标签/张 | AU4: 单价 | AV4: 金额 | AW4: 数量 pcs | AX4: 单价 Euro | AY4: 金额 Euro | AZ4: 数量 /托 | BA4: 单价 Euro | BB4: 金额 Euro | BC4: 数量 /托 | BD4: 单价 Euro | BE4: 金额 Euro | BF4: 库内小计 | BG4: 数量 票 | BH4: 实际重kg | BI4: 体积重KG | BJ4: 计费 重量 kg | BK4: 邮编所属区域 | BL4: 城市 | BM4: 国家 | BN4: 单价 Euro | BO4: 金额 Euro | BP4: 单价 Euro | BQ4: 金额 Euro | BR4: 运输 订单 管理 * | BS4: 燃油 附加费 * | BT4: 过路 过桥 * | BU4: 运输 保险 | BV4: 预约 通知 * | BW4: 其它 | BX4: 附加费小计 | BY4: 包裹数 个 | BZ4: 单价 Euro | CA4: 金额 Euro | CD4: MIC回复
A5: MO202509230417 | B5: =COUNTIF(A:A,A5) -> 4 | C5: 1 | E5: M | F5: 202509 | G5: 2025-09-23 | H5: 2025-09-29 | I5: Shipped | J5: YCD-EX:HUPPER TEK | K5: ABM0009-250922-0010 | L5: B2B | N5: qianhui.xu@miclogistik.de | O5: 27 | P5: NORMAL | Q5: 15357.6 | R5: Self | Y5: DE | Z5: B07Q3SQT6C | AA5: =VLOOKUP(Z5,物品明细!A:B,2,0) -> 金属储物柜71英寸高 | AB5: =VLOOKUP(Z5,物品明细!A:I,9,0) -> 188x49x14 | AC5: =VLOOKUP(Z5,物品明细!A:D,4,0) -> 47.4 | AE5: 60 | AF5: =AE5*AC5 -> 2844 | AG5: 5 | AH5: 120x80x205 | AI5: 599 | AJ5: 60 | AL5: 47.4 | AM5: 原托整出 | AN5: =AG5 -> 5 | AO5: 11.85 | AP5: =AO5*AN5 -> 59.25 | AS5: =AR5*AQ5 -> 0 | AV5: =AU5*AT5 -> 0 | AY5: =AX5*AW5 -> 0 | AZ5: =AG5 -> 5 | BA5: 3 | BB5: =BA5*AZ5 -> 15 | BE5: =BD5*BC5 -> 0 | BF5: =AP5+AS5+AV5+AY5+BB5+BE5 -> 74.25 | CC5: =BF5+CB5 -> 74.25
A6: MO202509230417 | B6: =COUNTIF(A:A,A6) -> 4 | C6: 0 | E6: M | F6: 202509 | G6: 2025-09-23 | H6: 2025-09-29 | I6: Shipped | J6: YCD-EX:HUPPER TEK | K6: ABM0009-250922-0010 | L6: B2B | N6: qianhui.xu@miclogistik.de | O6: 27 | P6: NORMAL | Q6: 15357.6 | R6: Self | Y6: DE | Z6: B07BK8W5MF | AA6: =VLOOKUP(Z6,物品明细!A:B,2,0) -> 金属储物柜71英寸银色 | AB6: =VLOOKUP(Z6,物品明细!A:I,9,0) -> 188x49x14 | AC6: =VLOOKUP(Z6,物品明细!A:D,4,0) -> 47.4 | AE6: 120 | AF6: =AE6*AC6 -> 5688 | AG6: 10 | AH6: 120x80x205 | AI6: 599 | AJ6: 120 | AL6: 47.4 | AM6: 原托整出 | AN6: =AG6 -> 10 | AO6: 11.85 | AP6: =AO6*AN6 -> 118.5 | AS6: =AR6*AQ6 -> 0 | AV6: =AU6*AT6 -> 0 | AY6: =AX6*AW6 -> 0 | AZ6: =AG6 -> 10 | BA6: 3 | BB6: =BA6*AZ6 -> 30 | BE6: =BD6*BC6 -> 0 | BF6: =AP6+AS6+AV6+AY6+BB6+BE6 -> 148.5 | CC6: =BF6+CB6 -> 148.5
A7: MO202509230417 | B7: =COUNTIF(A:A,A7) -> 4 | C7: 0 | E7: M | F7: 202509 | G7: 2025-09-23 | H7: 2025-09-29 | I7: Shipped | J7: YCD-EX:HUPPER TEK | K7: ABM0009-250922-0010 | L7: B2B | N7: qianhui.xu@miclogistik.de | O7: 27 | P7: NORMAL | Q7: 15357.6 | R7: Self | Y7: DE | Z7: B076THQBHX | AA7: =VLOOKUP(Z7,物品明细!A:B,2,0) -> 金属储物柜71英寸灰色 | AB7: =VLOOKUP(Z7,物品明细!A:I,9,0) -> 188x49x14 | AC7: =VLOOKUP(Z7,物品明细!A:D,4,0) -> 47.4 | AE7: 72 | AF7: =AE7*AC7 -> 3412.8 | AG7: 6 | AH7: 120x80x205 | AI7: 599 | AJ7: 72 | AL7: 47.4 | AM7: 原托整出 | AN7: =AG7 -> 6 | AO7: 11.85 | AP7: =AO7*AN7 -> 71.1 | AS7: =AR7*AQ7 -> 0 | AV7: =AU7*AT7 -> 0 | AY7: =AX7*AW7 -> 0 | AZ7: =AG7 -> 6 | BA7: 3 | BB7: =BA7*AZ7 -> 18 | BE7: =BD7*BC7 -> 0 | BF7: =AP7+AS7+AV7+AY7+BB7+BE7 -> 89.1 | CC7: =BF7+CB7 -> 89.1
A8: MO202509230417 | B8: =COUNTIF(A:A,A8) -> 4 | C8: 0 | E8: M | F8: 202509 | G8: 2025-09-23 | H8: 2025-09-29 | I8: Shipped | J8: YCD-EX:HUPPER TEK | K8: ABM0009-250922-0010 | L8: B2B | N8: qianhui.xu@miclogistik.de | O8: 27 | P8: NORMAL | Q8: 15357.6 | R8: Self | Y8: DE | Z8: B077RVYZRF | AA8: =VLOOKUP(Z8,物品明细!A:B,2,0) -> 德国联邦快递金属储物柜 | AB8: =VLOOKUP(Z8,物品明细!A:I,9,0) -> 188x49x14 | AC8: =VLOOKUP(Z8,物品明细!A:D,4,0) -> 47.4 | AE8: 72 | AF8: =AE8*AC8 -> 3412.8 | AG8: 6 | AH8: 120x80x205 | AI8: 599 | AJ8: 72 | AL8: 47.4 | AM8: 原托整出 | AN8: =AG8 -> 6 | AO8: 11.85 | AP8: =AO8*AN8 -> 71.1 | AS8: =AR8*AQ8 -> 0 | AV8: =AU8*AT8 -> 0 | AY8: =AX8*AW8 -> 0 | AZ8: =AG8 -> 6 | BA8: 3 | BB8: =BA8*AZ8 -> 18 | BE8: =BD8*BC8 -> 0 | BF8: =AP8+AS8+AV8+AY8+BB8+BE8 -> 89.1 | CC8: =BF8+CB8 -> 89.1

Sheet 2.2 正向-2C-GEL
A1: MIC德国海外仓一件代发明细表 | AI1: =SUM(AI5:AI79) -> 392.85 | AL1: =SUM(AL5:AL79) -> 0 | AO1: =SUM(AO5:AO79) -> 0 | AR1: =SUM(AR5:AR79) -> 0 | AU1: =SUM(AU5:AU79) -> 243 | AV1: =SUM(AV5:AV79) -> 635.85 | BE1: =SUM(BE5:BE79) -> 3647.4669 | BJ1: =SUM(BJ5:BJ79) -> 499.6 | BM1: =SUM(BM5:BM79) -> 10 | BN1: =SUM(BN5:BN79) -> 4157.0669 | BO1: =SUM(BO5:BO79) -> 4792.9169
A2: ,1m, | AW2: 尾程运输费 | BO2: 总费用合计
A3: 出库指令 | Z3: 物品-拣料及最小包装 | AG3: 拣货&包装费 | AJ3: 拣货续件费 | AM3: 贴标费 | AP3: 包材费-包裹 | AS3: 装车费 | AV3: 库内小计 | AW3: 基础费 | BF3: 附加费 | BK3: 3件包裹以上运输续件费 | BN3: 尾程费用合计
A4: Order No. | B4: 订单 行数 | C4: 订单数 | D4: 对账 | E4: Warehouse | F4: 月份 | G4: Order Created At | H4: Shipped At | I4: Status | J4: Customer | K4: Original Reference | L4: Business Type | M4: Channel | N4: Creator | O4: 运单数 | P4: Priority | Q4: weight | R4: Carrier | S4: Carrier Return | T4: Shipments No1 | U4: Shipments No2 | V4: Retour No | W4: Postal Code | X4: 城市 | Y4: Country | Z4: Item ID | AA4: 物品描述 | AB4: 物品尺寸 长宽高cm | AC4: 单个物品 重量kg | AD4: Item Batch | AE4: Item Qty | AF4: 订单重量 kg | AG4: 数量 套 | AH4: 单价 Euro | AI4: 金额 Euro | AJ4: 数量 pcs | AK4: 单价 Euro | AL4: 金额 Euro | AM4: 标签/张 | AN4: 单价 | AO4: 金额 | AP4: 数量 pcs | AQ4: 单价 Euro | AR4: 金额 Euro | AS4: 数量 /托 | AT4: 单价 Euro | AU4: 金额 Euro | AW4: 数量 票 | AX4: 实际重kg | AY4: 体积重KG | AZ4: 计费 重量 kg | BA4: 邮编所属区域 | BB4: 城市 | BC4: 国家 | BD4: 单价 Euro | BE4: 金额 Euro | BF4: 运输 订单 管理 * | BG4: 过路 过桥 * | BH4: 预约 通知 * | BI4: 其它 | BJ4: 附加费小计 | BK4: 包裹数 个 | BL4: 单价 Euro | BM4: 金额 Euro | BP4: MIC回复
A5: MO202508290008 | B5: =COUNTIF(A:A,A5) -> 1 | C5: 1 | E5: M | F5: 202509 | G5: 2025-08-29 | H5: 2025-09-01 | I5: Delivered | J5: YCD-EX:HUPPER TEK | K5: PO-076-04297086148472146 | L5: B2C | N5: devindai@huppertek.com | O5: 1 | P5: NORMAL | Q5: 47.4 | R5: GELF-EML_HUPPERTEK | T5: 4618130043 | W5: 91723 | X5: Dittenheim | Y5: DE | Z5: B076THQBHX | AA5: =VLOOKUP(Z5,物品明细!A:B,2,0) -> 金属储物柜71英寸灰色 | AB5: =VLOOKUP(Z5,物品明细!A:I,9,0) -> 188x49x14 | AC5: =VLOOKUP(Z5,物品明细!A:D,4,0) -> 47.4 | AE5: 1 | AF5: =AE5*AC5 -> 47.4 | AG5: =AE5 -> 1 | AH5: 4.85 | AI5: =AH5*AG5 -> 4.85 | AS5: =AE5 -> 1 | AT5: 3 | AU5: =AT58*AS5 -> 3 | AV5: =AI5+AL5+AO5+AR5+AU5 -> 7.85 | AW5: 1 | AX5: 47.4 | AZ5: 50 | BA5: 91723 | BB5: Dittenheim | BC5: DE | BD5: 46.558575 | BE5: =BD5*AW5 -> 46.558575 | BF5: 2.5 | BG5: =AZ5*0.024 -> 1.2 | BH5: 2.5 | BJ5: =SUM(BF5:BI5) -> 6.2 | BN5: =BE5+BJ5+BM5 -> 52.758575 | BO5: =AV5+BN5 -> 60.608575 | BP5: 已对账
A6: MO202508290009 | B6: =COUNTIF(A:A,A6) -> 1 | C6: 1 | E6: M | F6: 202509 | G6: 2025-08-29 | H6: 2025-09-01 | I6: Delivered | J6: YCD-EX:HUPPER TEK | K6: PO-076-04170828474233442 | L6: B2C | N6: devindai@huppertek.com | O6: 1 | P6: NORMAL | Q6: 47.4 | R6: GELF-EML_HUPPERTEK | T6: 4618131309 | W6: 63075 | X6: Offenbach am Main | Y6: DE | Z6: B076THQBHX | AA6: =VLOOKUP(Z6,物品明细!A:B,2,0) -> 金属储物柜71英寸灰色 | AB6: =VLOOKUP(Z6,物品明细!A:I,9,0) -> 188x49x14 | AC6: =VLOOKUP(Z6,物品明细!A:D,4,0) -> 47.4 | AE6: 1 | AF6: =AE6*AC6 -> 47.4 | AG6: =AE6 -> 1 | AH6: 4.85 | AI6: =AH6*AG6 -> 4.85 | AS6: =AE6 -> 1 | AT6: 3 | AU6: =AT59*AS6 -> 3 | AV6: =AI6+AL6+AO6+AR6+AU6 -> 7.85 | AW6: 1 | AX6: 47.4 | AZ6: 50 | BA6: 63075 | BB6: Offenbach am Main | BC6: DE | BD6: 46.558575 | BE6: =BD6*AW6 -> 46.558575 | BF6: 2.5 | BG6: =AZ6*0.024 -> 1.2 | BH6: 2.5 | BJ6: =SUM(BF6:BI6) -> 6.2 | BN6: =BE6+BJ6+BM6 -> 52.758575 | BO6: =AV6+BN6 -> 60.608575 | BP6: 已对账
A7: MO202508290010 | B7: =COUNTIF(A:A,A7) -> 1 | C7: 1 | E7: M | F7: 202509 | G7: 2025-08-29 | H7: 2025-09-01 | I7: Delivery Notify | J7: YCD-EX:HUPPER TEK | K7: PO-076-04557322616951653 | L7: B2C | N7: devindai@huppertek.com | O7: 1 | P7: NORMAL | Q7: 47.4 | R7: GELF-EML_HUPPERTEK | T7: 4618129764 | W7: 93053 | X7: Regensburg | Y7: DE | Z7: B076THQBHX | AA7: =VLOOKUP(Z7,物品明细!A:B,2,0) -> 金属储物柜71英寸灰色 | AB7: =VLOOKUP(Z7,物品明细!A:I,9,0) -> 188x49x14 | AC7: =VLOOKUP(Z7,物品明细!A:D,4,0) -> 47.4 | AE7: 1 | AF7: =AE7*AC7 -> 47.4 | AG7: =AE7 -> 1 | AH7: 4.85 | AI7: =AH7*AG7 -> 4.85 | AS7: =AE7 -> 1 | AT7: 3 | AU7: =AT60*AS7 -> 3 | AV7: =AI7+AL7+AO7+AR7+AU7 -> 7.85 | AW7: 1 | AX7: 47.4 | AZ7: 50 | BA7: 93053 | BB7: Regensburg | BC7: DE | BD7: 46.558575 | BE7: =BD7*AW7 -> 46.558575 | BF7: 2.5 | BG7: =AZ7*0.024 -> 1.2 | BH7: 2.5 | BJ7: =SUM(BF7:BI7) -> 6.2 | BN7: =BE7+BJ7+BM7 -> 52.758575 | BO7: =AV7+BN7 -> 60.608575 | BP7: 已对账
A8: MO202509010338 | B8: =COUNTIF(A:A,A8) -> 1 | C8: 1 | E8: M | F8: 202509 | G8: 2025-09-01 | H8: 2025-09-01 | I8: Delivered | J8: YCD-EX:HUPPER TEK | K8: PO-076-10226771743350626 | L8: B2C | N8: devindai@huppertek.com | O8: 1 | P8: NORMAL | Q8: 47.4 | R8: GELF-EML_HUPPERTEK | S8: RetourHermes_M | T8: 4618131446 | W8: 42551 | X8: Velbert | Y8: DE | Z8: B07BK8W5MF | AA8: =VLOOKUP(Z8,物品明细!A:B,2,0) -> 金属储物柜71英寸银色 | AB8: =VLOOKUP(Z8,物品明细!A:I,9,0) -> 188x49x14 | AC8: =VLOOKUP(Z8,物品明细!A:D,4,0) -> 47.4 | AE8: 1 | AF8: =AE8*AC8 -> 47.4 | AG8: =AE8 -> 1 | AH8: 4.85 | AI8: =AH8*AG8 -> 4.85 | AS8: =AE8 -> 1 | AT8: 3 | AU8: =AT61*AS8 -> 3 | AV8: =AI8+AL8+AO8+AR8+AU8 -> 7.85 | AW8: 1 | AX8: 47.4 | AZ8: 50 | BA8: 42551 | BB8: Velbert | BC8: DE | BD8: 46.558575 | BE8: =BD8*AW8 -> 46.558575 | BF8: 2.5 | BG8: =AZ8*0.024 -> 1.2 | BH8: 2.5 | BJ8: =SUM(BF8:BI8) -> 6.2 | BN8: =BE8+BJ8+BM8 -> 52.758575 | BO8: =AV8+BN8 -> 60.608575 | BP8: 已对账
A9: MO202509010339 | B9: =COUNTIF(A:A,A9) -> 1 | E9: M | F9: 202509 | G9: 2025-09-01 | H9: 2025-09-01 | I9: Canceled | J9: YCD-EX:HUPPER TEK | K9: PO-076-09977348467831059 | L9: B2C | N9: devindai@huppertek.com | O9: 1 | P9: NORMAL | Q9: 47.4 | R9: GELF-EML_HUPPERTEK | S9: RetourHermes_M | W9: 21493 | X9: Schwarzenbek | Y9: DE | Z9: B076THQBHX | AA9: =VLOOKUP(Z9,物品明细!A:B,2,0) -> 金属储物柜71英寸灰色 | AB9: =VLOOKUP(Z9,物品明细!A:I,9,0) -> 188x49x14 | AC9: =VLOOKUP(Z9,物品明细!A:D,4,0) -> 47.4 | AF9: =AE9*AC9 -> 0 | AG9: =AE9 -> 0 | AH9: 4.85 | AI9: =AH9*AG9 -> 0 | AS9: =AE9 -> 0 | AT9: 3 | AU9: =AT62*AS9 -> 0 | AV9: =AI9+AL9+AO9+AR9+AU9 -> 0 | BN9: =BE9+BJ9+BM9 -> 0 | BO9: =AV9+BN9 -> 0 | BP9: 已对账
A10: MO202509010340 | B10: =COUNTIF(A:A,A10) -> 1 | C10: 1 | E10: M | F10: 202509 | G10: 2025-09-01 | H10: 2025-09-01 | I10: Delivered | J10: YCD-EX:HUPPER TEK | K10: PO-076-10182554455670378 | L10: B2C | N10: devindai@huppertek.com | O10: 1 | P10: NORMAL | Q10: 47.4 | R10: GELF-EML_HUPPERTEK | S10: RetourHermes_M | T10: 4618131460 | W10: 97650 | X10: Fladungen | Y10: DE | Z10: B076THQBHX | AA10: =VLOOKUP(Z10,物品明细!A:B,2,0) -> 金属储物柜71英寸灰色 | AB10: =VLOOKUP(Z10,物品明细!A:I,9,0) -> 188x49x14 | AC10: =VLOOKUP(Z10,物品明细!A:D,4,0) -> 47.4 | AE10: 1 | AF10: =AE10*AC10 -> 47.4 | AG10: =AE10 -> 1 | AH10: 4.85 | AI10: =AH10*AG10 -> 4.85 | AS10: =AE10 -> 1 | AT10: 3 | AU10: =AT63*AS10 -> 3 | AV10: =AI10+AL10+AO10+AR10+AU10 -> 7.85 | AW10: 1 | AX10: 47.4 | AZ10: 50 | BA10: 97650 | BB10: Fladungen | BC10: DE | BD10: 46.558575 | BE10: =BD10*AW10 -> 46.558575 | BF10: 2.5 | BG10: =AZ10*0.024 -> 1.2 | BH10: 2.5 | BJ10: =SUM(BF10:BI10) -> 6.2 | BN10: =BE10+BJ10+BM10 -> 52.758575 | BO10: =AV10+BN10 -> 60.608575 | BP10: 已对账
A11: MO202509020002 | B11: =COUNTIF(A:A,A11) -> 1 | C11: 1 | E11: M | F11: 202509 | G11: 2025-09-02 | H11: 2025-09-02 | I11: Delivered | J11: YCD-EX:HUPPER TEK | K11: PO-076-01718713105271130 | L11: B2C | N11: devindai@huppertek.com | O11: 1 | P11: NORMAL | Q11: 47.4 | R11: GELF-EML_HUPPERTEK | T11: 4618148529 | W11: 31840 | X11: Hessisch Oldendorf | Y11: DE | Z11: B076THQBHX | AA11: =VLOOKUP(Z11,物品明细!A:B,2,0) -> 金属储物柜71英寸灰色 | AB11: =VLOOKUP(Z11,物品明细!A:I,9,0) -> 188x49x14 | AC11: =VLOOKUP(Z11,物品明细!A:D,4,0) -> 47.4 | AE11: 1 | AF11: =AE11*AC11 -> 47.4 | AG11: =AE11 -> 1 | AH11: 4.85 | AI11: =AH11*AG11 -> 4.85 | AS11: =AE11 -> 1 | AT11: 3 | AU11: =AT64*AS11 -> 3 | AV11: =AI11+AL11+AO11+AR11+AU11 -> 7.85 | AW11: 1 | AX11: 47.4 | AZ11: 50 | BA11: 31840 | BB11: Hessisch Oldendorf | BC11: DE | BD11: 46.558575 | BE11: =BD11*AW11 -> 46.558575 | BF11: 2.5 | BG11: =AZ11*0.024 -> 1.2 | BH11: 2.5 | BJ11: =SUM(BF11:BI11) -> 6.2 | BN11: =BE11+BJ11+BM11 -> 52.758575 | BO11: =AV11+BN11 -> 60.608575 | BP11: 已对账
A12: MO202509020633 | B12: =COUNTIF(A:A,A12) -> 1 | C12: 1 | E12: M | F12: 202509 | G12: 2025-09-02 | H12: 2025-09-02 | I12: Delivered | J12: YCD-EX:HUPPER TEK | K12: PO-076-12878415094391975-1 | L12: B2C | N12: devindai@huppertek.com | O12: 1 | P12: NORMAL | Q12: 47.4 | R12: GELF-EML_HUPPERTEK | T12: 4618148741 | W12: 23866 | X12: Nahe | Y12: DE | Z12: B07Q3SQT6C | AA12: =VLOOKUP(Z12,物品明细!A:B,2,0) -> 金属储物柜71英寸高 | AB12: =VLOOKUP(Z12,物品明细!A:I,9,0) -> 188x49x14 | AC12: =VLOOKUP(Z12,物品明细!A:D,4,0) -> 47.4 | AE12: 1 | AF12: =AE12*AC12 -> 47.4 | AG12: =AE12 -> 1 | AH12: 4.85 | AI12: =AH12*AG12 -> 4.85 | AS12: =AE12 -> 1 | AT12: 3 | AU12: =AT65*AS12 -> 3 | AV12: =AI12+AL12+AO12+AR12+AU12 -> 7.85 | AW12: 1 | AX12: 47.4 | AZ12: 50 | BA12: 23866 | BB12: Nahe | BC12: DE | BD12: 46.558575 | BE12: =BD12*AW12 -> 46.558575 | BF12: 2.5 | BG12: =AZ12*0.024 -> 1.2 | BH12: 2.5 | BJ12: =SUM(BF12:BI12) -> 6.2 | BN12: =BE12+BJ12+BM12 -> 52.758575 | BO12: =AV12+BN12 -> 60.608575 | BP12: 已对账
A13: MO202509020633-01 | B13: =COUNTIF(A:A,A13) -> 1 | C13: 1 | E13: M | F13: 202509 | G13: 2025-09-02 | H13: 2025-09-02 | I13: Delivered | J13: YCD-EX:HUPPER TEK | K13: PO-076-12878415094391975-2 | L13: B2C | N13: devindai@huppertek.com | O13: 1 | P13: NORMAL | Q13: 47.4 | R13: GELF-EML_HUPPERTEK | T13: 4618148758 | W13: 23866 | X13: Nahe | Y13: DE | Z13: B07Q3SQT6C | AA13: =VLOOKUP(Z13,物品明细!A:B,2,0) -> 金属储物柜71英寸高 | AB13: =VLOOKUP(Z13,物品明细!A:I,9,0) -> 188x49x14 | AC13: =VLOOKUP(Z13,物品明细!A:D,4,0) -> 47.4 | AE13: 1 | AF13: =AE13*AC13 -> 47.4 | AG13: =AE13 -> 1 | AH13: 4.85 | AI13: =AH13*AG13 -> 4.85 | AS13: =AE13 -> 1 | AT13: 3 | AU13: =AT66*AS13 -> 3 | AV13: =AI13+AL13+AO13+AR13+AU13 -> 7.85 | AW13: 1 | AX13: 47.4 | AZ13: 50 | BA13: 23866 | BB13: Nahe | BC13: DE | BD13: 46.558575 | BE13: =BD13*AW13 -> 46.558575 | BF13: 2.5 | BG13: =AZ13*0.024 -> 1.2 | BH13: 2.5 | BJ13: =SUM(BF13:BI13) -> 6.2 | BN13: =BE13+BJ13+BM13 -> 52.758575 | BO13: =AV13+BN13 -> 60.608575 | BP13: 已对账
A14: MO202509030202 | B14: =COUNTIF(A:A,A14) -> 1 | C14: 1 | E14: M | F14: 202509 | G14: 2025-09-03 | H14: 2025-09-03 | I14: Shipped | J14: YCD-EX:HUPPER TEK | K14: PO-076-12612912981112500 | L14: B2C | N14: devindai@huppertek.com | O14: 1 | P14: NORMAL | Q14: 47.4 | R14: GELF-EML_HUPPERTEK | S14: RetourHermes_M | T14: 4618152489 | W14: 63776 | X14: Mömbris | Y14: DE | Z14: B07BK8W5MF | AA14: =VLOOKUP(Z14,物品明细!A:B,2,0) -> 金属储物柜71英寸银色 | AB14: =VLOOKUP(Z14,物品明细!A:I,9,0) -> 188x49x14 | AC14: =VLOOKUP(Z14,物品明细!A:D,4,0) -> 47.4 | AE14: 1 | AF14: =AE14*AC14 -> 47.4 | AG14: =AE14 -> 1 | AH14: 4.85 | AI14: =AH14*AG14 -> 4.85 | AS14: =AE14 -> 1 | AT14: 3 | AU14: =AT67*AS14 -> 3 | AV14: =AI14+AL14+AO14+AR14+AU14 -> 7.85 | AW14: 1 | AX14: 47.4 | AZ14: 50 | BA14: 63776 | BB14: Mömbris | BC14: DE | BD14: 46.558575 | BE14: =BD14*AW14 -> 46.558575 | BF14: 2.5 | BG14: =AZ14*0.024 -> 1.2 | BH14: 2.5 | BJ14: =SUM(BF14:BI14) -> 6.2 | BN14: =BE14+BJ14+BM14 -> 52.758575 | BO14: =AV14+BN14 -> 60.608575 | BP14: 已对账
A15: MO202509030203 | B15: =COUNTIF(A:A,A15) -> 1 | C15: 1 | E15: M | F15: 202509 | G15: 2025-09-03 | H15: 2025-09-03 | I15: Shipped | J15: YCD-EX:HUPPER TEK | K15: PO-076-12903771914870030 | L15: B2C | N15: devindai@huppertek.com | O15: 1 | P15: NORMAL | Q15: 47.4 | R15: GELF-EML_HUPPERTEK | S15: RetourHermes_M | T15: 4618152496 | W15: 90765 | X15: Fürth | Y15: DE | Z15: B077RVYZRF | AA15: =VLOOKUP(Z15,物品明细!A:B,2,0) -> 德国联邦快递金属储物柜 | AB15: =VLOOKUP(Z15,物品明细!A:I,9,0) -> 188x49x14 | AC15: =VLOOKUP(Z15,物品明细!A:D,4,0) -> 47.4 | AE15: 1 | AF15: =AE15*AC15 -> 47.4 | AG15: =AE15 -> 1 | AH15: 4.85 | AI15: =AH15*AG15 -> 4.85 | AS15: =AE15 -> 1 | AT15: 3 | AU15: =AT68*AS15 -> 3 | AV15: =AI15+AL15+AO15+AR15+AU15 -> 7.85 | AW15: 1 | AX15: 47.4 | AZ15: 50 | BA15: 90765 | BB15: Fürth | BC15: DE | BD15: 46.558575 | BE15: =BD15*AW15 -> 46.558575 | BF15: 2.5 | BG15: =AZ15*0.024 -> 1.2 | BH15: 2.5 | BJ15: =SUM(BF15:BI15) -> 6.2 | BN15: =BE15+BJ15+BM15 -> 52.758575 | BO15: =AV15+BN15 -> 60.608575 | BP15: 已对账
A16: MO202509030204 | B16: =COUNTIF(A:A,A16) -> 1 | C16: 1 | E16: M | F16: 202509 | G16: 2025-09-03 | H16: 2025-09-03 | I16: Shipped | J16: YCD-EX:HUPPER TEK | K16: PO-076-12499994650233943 | L16: B2C | N16: devindai@huppertek.com | O16: 1 | P16: NORMAL | Q16: 47.4 | R16: GELF-EML_HUPPERTEK | S16: RetourHermes_M | T16: 4618152502 | W16: 70794 | X16: Filderstadt | Y16: DE | Z16: B07Q3SQT6C | AA16: =VLOOKUP(Z16,物品明细!A:B,2,0) -> 金属储物柜71英寸高 | AB16: =VLOOKUP(Z16,物品明细!A:I,9,0) -> 188x49x14 | AC16: =VLOOKUP(Z16,物品明细!A:D,4,0) -> 47.4 | AE16: 1 | AF16: =AE16*AC16 -> 47.4 | AG16: =AE16 -> 1 | AH16: 4.85 | AI16: =AH16*AG16 -> 4.85 | AS16: =AE16 -> 1 | AT16: 3 | AU16: =AT69*AS16 -> 3 | AV16: =AI16+AL16+AO16+AR16+AU16 -> 7.85 | AW16: 1 | AX16: 47.4 | AZ16: 50 | BA16: 70794 | BB16: Filderstadt | BC16: DE | BD16: 46.558575 | BE16: =BD16*AW16 -> 46.558575 | BF16: 2.5 | BG16: =AZ16*0.024 -> 1.2 | BH16: 2.5 | BJ16: =SUM(BF16:BI16) -> 6.2 | BN16: =BE16+BJ16+BM16 -> 52.758575 | BO16: =AV16+BN16 -> 60.608575 | BP16: 已对账
A17: MO202509030363 | B17: =COUNTIF(A:A,A17) -> 1 | C17: 1 | E17: M | F17: 202509 | G17: 2025-09-03 | H17: 2025-09-03 | I17: Shipped | J17: YCD-EX:HUPPER TEK | K17: 11-13526-16962 | L17: B2C | N17: devindai@huppertek.com | O17: 1 | P17: NORMAL | Q17: 47.4 | R17: GELF_HUPPERTEK | S17: RetourHermes_M | T17: 4618154933 | W17: 40670 | X17: Meerbusch | Y17: DE | Z17: B07BK8W5MF | AA17: =VLOOKUP(Z17,物品明细!A:B,2,0) -> 金属储物柜71英寸银色 | AB17: =VLOOKUP(Z17,物品明细!A:I,9,0) -> 188x49x14 | AC17: =VLOOKUP(Z17,物品明细!A:D,4,0) -> 47.4 | AE17: 1 | AF17: =AE17*AC17 -> 47.4 | AG17: =AE17 -> 1 | AH17: 4.85 | AI17: =AH17*AG17 -> 4.85 | AS17: =AE17 -> 1 | AT17: 3 | AU17: =AT70*AS17 -> 3 | AV17: =AI17+AL17+AO17+AR17+AU17 -> 7.85 | AW17: 1 | AX17: 47.4 | AZ17: 50 | BA17: 40670 | BB17: Meerbusch | BC17: DE | BD17: 46.558575 | BE17: =BD17*AW17 -> 46.558575 | BF17: 2.5 | BG17: =AZ17*0.024 -> 1.2 | BH17: 2.5 | BJ17: =SUM(BF17:BI17) -> 6.2 | BN17: =BE17+BJ17+BM17 -> 52.758575 | BO17: =AV17+BN17 -> 60.608575 | BP17: 已对账
A18: MO202509040286 | B18: =COUNTIF(A:A,A18) -> 1 | C18: 1 | E18: M | F18: 202509 | G18: 2025-09-04 | H18: 2025-09-04 | I18: Shipped | J18: YCD-EX:HUPPER TEK | K18: PO-076-18014211876473843 | L18: B2C | N18: devindai@huppertek.com | O18: 1 | P18: NORMAL | Q18: 47.4 | R18: GELF-EML_HUPPERTEK | T18: 4618159570 | W18: 93170 | X18: Bernhardswald | Y18: DE | Z18: B076THQBHX | AA18: =VLOOKUP(Z18,物品明细!A:B,2,0) -> 金属储物柜71英寸灰色 | AB18: =VLOOKUP(Z18,物品明细!A:I,9,0) -> 188x49x14 | AC18: =VLOOKUP(Z18,物品明细!A:D,4,0) -> 47.4 | AE18: 1 | AF18: =AE18*AC18 -> 47.4 | AG18: =AE18 -> 1 | AH18: 4.85 | AI18: =AH18*AG18 -> 4.85 | AS18: =AE18 -> 1 | AT18: 3 | AU18: =AT71*AS18 -> 3 | AV18: =AI18+AL18+AO18+AR18+AU18 -> 7.85 | AW18: 1 | AX18: 47.4 | AZ18: 50 | BA18: 93170 | BB18: Bernhardswald | BC18: DE | BD18: 46.558575 | BE18: =BD18*AW18 -> 46.558575 | BF18: 2.5 | BG18: =AZ18*0.024 -> 1.2 | BH18: 2.5 | BJ18: =SUM(BF18:BI18) -> 6.2 | BN18: =BE18+BJ18+BM18 -> 52.758575 | BO18: =AV18+BN18 -> 60.608575 | BP18: 已对账
A19: MO202509080347 | B19: =COUNTIF(A:A,A19) -> 1 | C19: 1 | E19: M | F19: 202509 | G19: 2025-09-08 | H19: 2025-09-09 | I19: ReadyToShip | J19: YCD-EX:HUPPER TEK | K19: 12-13542-95015 | L19: B2C | N19: devindai@huppertek.com | O19: 2 | P19: NORMAL | Q19: 47.4 | R19: GELF_HUPPERTEK | S19: RetourHermes_M | T19: 4618174160 4618174177 | U19: 4618174160 4618174177 | W19: 46117 | X19: Oberhausen | Y19: DE | Z19: B07BK8W5MF | AA19: =VLOOKUP(Z19,物品明细!A:B,2,0) -> 金属储物柜71英寸银色 | AB19: =VLOOKUP(Z19,物品明细!A:I,9,0) -> 188x49x14 | AC19: =VLOOKUP(Z19,物品明细!A:D,4,0) -> 47.4 | AE19: 2 | AF19: =AE19*AC19 -> 94.8 | AG19: =AE19 -> 2 | AH19: 4.85 | AI19: =AH19*AG19 -> 9.7 | AL19: =AK19*AJ19 -> 0 | AS19: =AE19 -> 2 | AT19: 3 | AU19: =AT72*AS19 -> 6 | AV19: =AI19+AL19+AO19+AR19+AU19 -> 15.7 | AW19: 1 | AX19: 47.4 | AZ19: 100 | BA19: 46117 | BB19: Oberhausen | BC19: DE | BD19: 78.354675 | BE19: =BD19*AW19 -> 78.354675 | BF19: 2.5 | BG19: =AZ19*0.024 -> 2.4 | BH19: 2.5 | BJ19: =SUM(BF19:BI19) -> 7.4 | BN19: =BE19+BJ19+BM19 -> 85.754675 | BO19: =AV19+BN19 -> 101.45467 | BP19: 已对账
A20: MO202509080584 | B20: =COUNTIF(A:A,A20) -> 1 | C20: 1 | E20: M | F20: 202509 | G20: 2025-09-08 | H20: 2025-09-08 | I20: Shipped | J20: YCD-EX:HUPPER TEK | K20: PO-076-09412637668471865 | L20: B2C | N20: devindai@huppertek.com | O20: 1 | P20: NORMAL | Q20: 47.4 | R20: GELF-EML_HUPPERTEK | S20: RetourHermes_M | T20: 4618172968 | W20: 84405 | X20: Dorfen | Y20: DE | Z20: B07Q3SQT6C | AA20: =VLOOKUP(Z20,物品明细!A:B,2,0) -> 金属储物柜71英寸高 | AB20: =VLOOKUP(Z20,物品明细!A:I,9,0) -> 188x49x14 | AC20: =VLOOKUP(Z20,物品明细!A:D,4,0) -> 47.4 | AE20: 1 | AF20: =AE20*AC20 -> 47.4 | AG20: =AE20 -> 1 | AH20: 4.85 | AI20: =AH20*AG20 -> 4.85 | AS20: =AE20 -> 1 | AT20: 3 | AU20: =AT73*AS20 -> 3 | AV20: =AI20+AL20+AO20+AR20+AU20 -> 7.85 | AW20: 1 | AX20: 47.4 | AZ20: 50 | BA20: 84405 | BB20: Dorfen | BC20: DE | BD20: 46.558575 | BE20: =BD20*AW20 -> 46.558575 | BF20: 2.5 | BG20: =AZ20*0.024 -> 1.2 | BH20: 2.5 | BJ20: =SUM(BF20:BI20) -> 6.2 | BN20: =BE20+BJ20+BM20 -> 52.758575 | BO20: =AV20+BN20 -> 60.608575 | BP20: 已对账
A21: MO202509080585 | B21: =COUNTIF(A:A,A21) -> 1 | C21: 1 | E21: M | F21: 202509 | G21: 2025-09-08 | H21: 2025-09-08 | I21: Shipped | J21: YCD-EX:HUPPER TEK | K21: PO-076-09080733322873843 | L21: B2C | N21: devindai@huppertek.com | O21: 1 | P21: NORMAL | Q21: 47.4 | R21: GELF-EML_HUPPERTEK | S21: RetourHermes_M | T21: 4618172951 | W21: 93170 | X21: Bernhardswald | Y21: DE | Z21: B07BK8W5MF | AA21: =VLOOKUP(Z21,物品明细!A:B,2,0) -> 金属储物柜71英寸银色 | AB21: =VLOOKUP(Z21,物品明细!A:I,9,0) -> 188x49x14 | AC21: =VLOOKUP(Z21,物品明细!A:D,4,0) -> 47.4 | AE21: 1 | AF21: =AE21*AC21 -> 47.4 | AG21: =AE21 -> 1 | AH21: 4.85 | AI21: =AH21*AG21 -> 4.85 | AS21: =AE21 -> 1 | AT21: 3 | AU21: =AT74*AS21 -> 3 | AV21: =AI21+AL21+AO21+AR21+AU21 -> 7.85 | AW21: 1 | AX21: 47.4 | AZ21: 50 | BA21: 93170 | BB21: Bernhardswald | BC21: DE | BD21: 46.558575 | BE21: =BD21*AW21 -> 46.558575 | BF21: 2.5 | BG21: =AZ21*0.024 -> 1.2 | BH21: 2.5 | BJ21: =SUM(BF21:BI21) -> 6.2 | BN21: =BE21+BJ21+BM21 -> 52.758575 | BO21: =AV21+BN21 -> 60.608575 | BP21: 已对账
A22: MO202509080586 | B22: =COUNTIF(A:A,A22) -> 1 | C22: 1 | E22: M | F22: 202509 | G22: 2025-09-08 | H22: 2025-09-08 | I22: Shipped | J22: YCD-EX:HUPPER TEK | K22: PO-076-14513305964153460 | L22: B2C | N22: devindai@huppertek.com | O22: 1 | P22: NORMAL | Q22: 47.4 | R22: GELF-EML_HUPPERTEK | S22: RetourHermes_M | T22: 4618172944 | W22: 80933 | X22: München | Y22: DE | Z22: B077RVYZRF | AA22: =VLOOKUP(Z22,物品明细!A:B,2,0) -> 德国联邦快递金属储物柜 | AB22: =VLOOKUP(Z22,物品明细!A:I,9,0) -> 188x49x14 | AC22: =VLOOKUP(Z22,物品明细!A:D,4,0) -> 47.4 | AE22: 1 | AF22: =AE22*AC22 -> 47.4 | AG22: =AE22 -> 1 | AH22: 4.85 | AI22: =AH22*AG22 -> 4.85 | AS22: =AE22 -> 1 | AT22: 3 | AU22: =AT75*AS22 -> 3 | AV22: =AI22+AL22+AO22+AR22+AU22 -> 7.85 | AW22: 1 | AX22: 47.4 | AZ22: 50 | BA22: 80933 | BB22: München | BC22: DE | BD22: 46.558575 | BE22: =BD22*AW22 -> 46.558575 | BF22: 2.5 | BG22: =AZ22*0.024 -> 1.2 | BH22: 2.5 | BI22: 7.8 | BJ22: =SUM(BF22:BI22) -> 14 | BN22: =BE22+BJ22+BM22 -> 60.558575 | BO22: =AV22+BN22 -> 68.408575 | BP22: 已对账
A23: MO202509080587 | B23: =COUNTIF(A:A,A23) -> 1 | C23: 1 | E23: M | F23: 202509 | G23: 2025-09-08 | H23: 2025-09-08 | I23: Shipped | J23: YCD-EX:HUPPER TEK | K23: PO-076-15048957921910524 | L23: B2C | N23: devindai@huppertek.com | O23: 1 | P23: NORMAL | Q23: 47.4 | R23: GELF-EML_HUPPERTEK | S23: RetourHermes_M | T23: 4618172937 | W23: 14656 | X23: Brieselang | Y23: DE | Z23: B07Q3SQT6C | AA23: =VLOOKUP(Z23,物品明细!A:B,2,0) -> 金属储物柜71英寸高 | AB23: =VLOOKUP(Z23,物品明细!A:I,9,0) -> 188x49x14 | AC23: =VLOOKUP(Z23,物品明细!A:D,4,0) -> 47.4 | AE23: 1 | AF23: =AE23*AC23 -> 47.4 | AG23: =AE23 -> 1 | AH23: 4.85 | AI23: =AH23*AG23 -> 4.85 | AS23: =AE23 -> 1 | AT23: 3 | AU23: =AT76*AS23 -> 3 | AV23: =AI23+AL23+AO23+AR23+AU23 -> 7.85 | AW23: 1 | AX23: 47.4 | AZ23: 50 | BA23: 14656 | BB23: Brieselang | BC23: DE | BD23: 46.558575 | BE23: =BD23*AW23 -> 46.558575 | BF23: 2.5 | BG23: =AZ23*0.024 -> 1.2 | BH23: 2.5 | BJ23: =SUM(BF23:BI23) -> 6.2 | BN23: =BE23+BJ23+BM23 -> 52.758575 | BO23: =AV23+BN23 -> 60.608575 | BP23: 已对账
A24: MO202509080588 | B24: =COUNTIF(A:A,A24) -> 1 | C24: 1 | E24: M | F24: 202509 | G24: 2025-09-08 | H24: 2025-09-08 | I24: Shipped | J24: YCD-EX:HUPPER TEK | K24: PO-076-14897119923831719 | L24: B2C | N24: devindai@huppertek.com | O24: 1 | P24: NORMAL | Q24: 47.4 | R24: GELF-EML_HUPPERTEK | S24: RetourHermes_M | T24: 4618172920 | W24: 88427 | X24: Bad Schussenried | Y24: DE | Z24: B07Q3SQT6C | AA24: =VLOOKUP(Z24,物品明细!A:B,2,0) -> 金属储物柜71英寸高 | AB24: =VLOOKUP(Z24,物品明细!A:I,9,0) -> 188x49x14 | AC24: =VLOOKUP(Z24,物品明细!A:D,4,0) -> 47.4 | AE24: 1 | AF24: =AE24*AC24 -> 47.4 | AG24: =AE24 -> 1 | AH24: 4.85 | AI24: =AH24*AG24 -> 4.85 | AS24: =AE24 -> 1 | AT24: 3 | AU24: =AT77*AS24 -> 3 | AV24: =AI24+AL24+AO24+AR24+AU24 -> 7.85 | AW24: 1 | AX24: 47.4 | AZ24: 50 | BA24: 88427 | BB24: Bad Schussenried | BC24: DE | BD24: 46.558575 | BE24: =BD24*AW24 -> 46.558575 | BF24: 2.5 | BG24: =AZ24*0.024 -> 1.2 | BH24: 2.5 | BJ24: =SUM(BF24:BI24) -> 6.2 | BN24: =BE24+BJ24+BM24 -> 52.758575 | BO24: =AV24+BN24 -> 60.608575 | BP24: 已对账
A25: MO202509090010 | B25: =COUNTIF(A:A,A25) -> 1 | C25: 1 | E25: M | F25: 202509 | G25: 2025-09-09 | H25: 2025-09-09 | I25: Delivered | J25: YCD-EX:HUPPER TEK | K25: PO-076-20390142055031744 | L25: B2C | N25: devindai@huppertek.com | O25: 1 | P25: NORMAL | Q25: 47.4 | R25: GELF-EML_HUPPERTEK | T25: 4618180710 | W25: 92552 | X25: Teunz | Y25: DE | Z25: B07BK8W5MF | AA25: =VLOOKUP(Z25,物品明细!A:B,2,0) -> 金属储物柜71英寸银色 | AB25: =VLOOKUP(Z25,物品明细!A:I,9,0) -> 188x49x14 | AC25: =VLOOKUP(Z25,物品明细!A:D,4,0) -> 47.4 | AE25: 1 | AF25: =AE25*AC25 -> 47.4 | AG25: =AE25 -> 1 | AH25: 4.85 | AI25: =AH25*AG25 -> 4.85 | AL25: =AK25*AJ25 -> 0 | AO25: =AN25*AM25 -> 0 | AR25: =AQ25*AP25 -> 0 | AS25: =O25 -> 1 | AT25: 3 | AU25: =AT25*AS25 -> 3 | AV25: =AI25+AL25+AO25+AR25+AU25 -> 7.85 | AW25: 1 | AX25: =AF25 -> 47.4 | AZ25: 50 | BA25: =W25 -> 92552 | BB25: =X25 -> Teunz | BC25: =Y25 -> DE | BD25: 46.558575 | BE25: =AW25*BD25 -> 46.558575 | BF25: 2.5 | BG25: =0.024*AZ25 -> 1.2 | BH25: 2.5 | BJ25: =SUM(BF25:BI25) -> 6.2 | BM25: =BK25*BL25 -> 0 | BN25: =BE25+BJ25+BM25 -> 52.758575 | BO25: =AV25+BN25 -> 60.608575
A26: MO202509150298 | B26: =COUNTIF(A:A,A26) -> 1 | C26: 1 | D26: Y | E26: M | F26: 202509 | G26: 2025-09-15 | H26: 2025-09-15 | I26: Delivered | J26: YCD-EX:HUPPER TEK | K26: ABM0009-250915-0019 | L26: B2C | N26: devindai@huppertek.com | O26: 1 | P26: NORMAL | Q26: 47.4 | R26: GELF_HUPPERTEK | S26: RetourHermes_M | T26: 4618199057 | W26: 79418 | X26: schliengen | Y26: DE | Z26: B07BK8W5MF | AA26: =VLOOKUP(Z26,物品明细!A:B,2,0) -> 金属储物柜71英寸银色 | AB26: =VLOOKUP(Z26,物品明细!A:I,9,0) -> 188x49x14 | AC26: =VLOOKUP(Z26,物品明细!A:D,4,0) -> 47.4 | AE26: 1 | AF26: =AE26*AC26 -> 47.4 | AG26: =AE26 -> 1 | AH26: 4.85 | AI26: =AH26*AG26 -> 4.85 | AL26: =AK26*AJ26 -> 0 | AO26: =AN26*AM26 -> 0 | AR26: =AQ26*AP26 -> 0 | AS26: =O26 -> 1 | AT26: 3 | AU26: =AT26*AS26 -> 3 | AV26: =AI26+AL26+AO26+AR26+AU26 -> 7.85 | AW26: 1 | AX26: =AF26 -> 47.4 | AZ26: 50 | BA26: =W26 -> 79418 | BB26: =X26 -> schliengen | BC26: =Y26 -> DE | BD26: 46.558575 | BE26: =AW26*BD26 -> 46.558575 | BF26: 2.5 | BG26: =0.024*AZ26 -> 1.2 | BH26: 2.5 | BJ26: =SUM(BF26:BI26) -> 6.2 | BM26: =BK26*BL26 -> 0 | BN26: =BE26+BJ26+BM26 -> 52.758575 | BO26: =AV26+BN26 -> 60.608575
A27: MO202509150299 | B27: =COUNTIF(A:A,A27) -> 1 | C27: 1 | D27: Y | E27: M | F27: 202509 | G27: 2025-09-15 | H27: 2025-09-15 | I27: Delivered | J27: YCD-EX:HUPPER TEK | K27: ABM0009-250915-0018 | L27: B2C | N27: devindai@huppertek.com | O27: 1 | P27: NORMAL | Q27: 47.4 | R27: GELF_HUPPERTEK | S27: RetourHermes_M | T27: 4618199040 | W27: 44809 | X27: Bochum | Y27: DE | Z27: B07Q3SQT6C | AA27: =VLOOKUP(Z27,物品明细!A:B,2,0) -> 金属储物柜71英寸高 | AB27: =VLOOKUP(Z27,物品明细!A:I,9,0) -> 188x49x14 | AC27: =VLOOKUP(Z27,物品明细!A:D,4,0) -> 47.4 | AE27: 1 | AF27: =AE27*AC27 -> 47.4 | AG27: =AE27 -> 1 | AH27: 4.85 | AI27: =AH27*AG27 -> 4.85 | AL27: =AK27*AJ27 -> 0 | AO27: =AN27*AM27 -> 0 | AR27: =AQ27*AP27 -> 0 | AS27: =O27 -> 1 | AT27: 3 | AU27: =AT27*AS27 -> 3 | AV27: =AI27+AL27+AO27+AR27+AU27 -> 7.85 | AW27: 1 | AX27: =AF27 -> 47.4 | AZ27: 50 | BA27: =W27 -> 44809 | BB27: =X27 -> Bochum | BC27: =Y27 -> DE | BD27: 46.558575 | BE27: =AW27*BD27 -> 46.558575 | BF27: 2.5 | BG27: =0.024*AZ27 -> 1.2 | BH27: 2.5 | BJ27: =SUM(BF27:BI27) -> 6.2 | BM27: =BK27*BL27 -> 0 | BN27: =BE27+BJ27+BM27 -> 52.758575 | BO27: =AV27+BN27 -> 60.608575
A28: MO202509150300 | B28: =COUNTIF(A:A,A28) -> 1 | C28: 1 | D28: Y | E28: M | F28: 202509 | G28: 2025-09-15 | H28: 2025-09-15 | I28: Delivered | J28: YCD-EX:HUPPER TEK | K28: ABM0009-250915-0017 | L28: B2C | N28: devindai@huppertek.com | O28: 1 | P28: NORMAL | Q28: 47.4 | R28: GELF_HUPPERTEK | S28: RetourHermes_M | T28: 4618199033 | W28: 59399 | X28: Olfen | Y28: DE | Z28: B076THQBHX | AA28: =VLOOKUP(Z28,物品明细!A:B,2,0) -> 金属储物柜71英寸灰色 | AB28: =VLOOKUP(Z28,物品明细!A:I,9,0) -> 188x49x14 | AC28: =VLOOKUP(Z28,物品明细!A:D,4,0) -> 47.4 | AE28: 1 | AF28: =AE28*AC28 -> 47.4 | AG28: =AE28 -> 1 | AH28: 4.85 | AI28: =AH28*AG28 -> 4.85 | AL28: =AK28*AJ28 -> 0 | AO28: =AN28*AM28 -> 0 | AR28: =AQ28*AP28 -> 0 | AS28: =O28 -> 1 | AT28: 3 | AU28: =AT28*AS28 -> 3 | AV28: =AI28+AL28+AO28+AR28+AU28 -> 7.85 | AW28: 1 | AX28: =AF28 -> 47.4 | AZ28: 50 | BA28: =W28 -> 59399 | BB28: =X28 -> Olfen | BC28: =Y28 -> DE | BD28: 46.558575 | BE28: =AW28*BD28 -> 46.558575 | BF28: 2.5 | BG28: =0.024*AZ28 -> 1.2 | BH28: 2.5 | BJ28: =SUM(BF28:BI28) -> 6.2 | BM28: =BK28*BL28 -> 0 | BN28: =BE28+BJ28+BM28 -> 52.758575 | BO28: =AV28+BN28 -> 60.608575
A29: ABM0009-250915-0016 | B29: =COUNTIF(A:A,A29) -> 1 | C29: 1 | D29: Y | E29: M | F29: 202509 | G29: 2025-09-15 | H29: 2025-09-15 | I29: Delivered | J29: YCD-EX:HUPPER TEK | K29: ABM0009-250915-0016 | L29: B2C | N29: rossmo@miclogistik.de | O29: 1 | P29: NORMAL | Q29: 47.4 | R29: GELF-EML_HUPPERTEK | S29: RetourHermes_M | T29: 4618207998 | W29: 71665 | X29: Vaihingen an der Enz | Y29: DE | Z29: B07Q3SQT6C | AA29: =VLOOKUP(Z29,物品明细!A:B,2,0) -> 金属储物柜71英寸高 | AB29: =VLOOKUP(Z29,物品明细!A:I,9,0) -> 188x49x14 | AC29: =VLOOKUP(Z29,物品明细!A:D,4,0) -> 47.4 | AE29: 1 | AF29: =AE29*AC29 -> 47.4 | AG29: =AE29 -> 1 | AH29: 4.85 | AI29: =AH29*AG29 -> 4.85 | AL29: =AK29*AJ29 -> 0 | AO29: =AN29*AM29 -> 0 | AR29: =AQ29*AP29 -> 0 | AS29: =O29 -> 1 | AT29: 3 | AU29: =AT29*AS29 -> 3 | AV29: =AI29+AL29+AO29+AR29+AU29 -> 7.85 | AW29: 1 | AX29: =AF29 -> 47.4 | AZ29: 50 | BA29: =W29 -> 71665 | BB29: =X29 -> Vaihingen an der Enz | BC29: =Y29 -> DE | BD29: 46.558575 | BE29: =AW29*BD29 -> 46.558575 | BF29: 2.5 | BG29: =0.024*AZ29 -> 1.2 | BH29: 2.5 | BJ29: =SUM(BF29:BI29) -> 6.2 | BM29: =BK29*BL29 -> 0 | BN29: =BE29+BJ29+BM29 -> 52.758575 | BO29: =AV29+BN29 -> 60.608575
A30: ABM0009-250915-0015 | B30: =COUNTIF(A:A,A30) -> 1 | C30: 1 | D30: Y | E30: M | F30: 202509 | G30: 2025-09-15 | H30: 2025-09-15 | I30: Delivered | J30: YCD-EX:HUPPER TEK | K30: ABM0009-250915-0015 | L30: B2C | N30: rossmo@miclogistik.de | O30: 1 | P30: NORMAL | Q30: 47.4 | R30: GELF-EML_HUPPERTEK | S30: RetourHermes_M | T30: 4618207981 | W30: 33609 | X30: Bielefeld | Y30: DE | Z30: B076THQBHX | AA30: =VLOOKUP(Z30,物品明细!A:B,2,0) -> 金属储物柜71英寸灰色 | AB30: =VLOOKUP(Z30,物品明细!A:I,9,0) -> 188x49x14 | AC30: =VLOOKUP(Z30,物品明细!A:D,4,0) -> 47.4 | AE30: 1 | AF30: =AE30*AC30 -> 47.4 | AG30: =AE30 -> 1 | AH30: 4.85 | AI30: =AH30*AG30 -> 4.85 | AL30: =AK30*AJ30 -> 0 | AO30: =AN30*AM30 -> 0 | AR30: =AQ30*AP30 -> 0 | AS30: =O30 -> 1 | AT30: 3 | AU30: =AT30*AS30 -> 3 | AV30: =AI30+AL30+AO30+AR30+AU30 -> 7.85 | AW30: 1 | AX30: =AF30 -> 47.4 | AZ30: 50 | BA30: =W30 -> 33609 | BB30: =X30 -> Bielefeld | BC30: =Y30 -> DE | BD30: 46.558575 | BE30: =AW30*BD30 -> 46.558575 | BF30: 2.5 | BG30: =0.024*AZ30 -> 1.2 | BH30: 2.5 | BJ30: =SUM(BF30:BI30) -> 6.2 | BM30: =BK30*BL30 -> 0 | BN30: =BE30+BJ30+BM30 -> 52.758575 | BO30: =AV30+BN30 -> 60.608575
A31: ABM0009-250915-0014 | B31: =COUNTIF(A:A,A31) -> 1 | C31: 1 | D31: Y | E31: M | F31: 202509 | G31: 2025-09-15 | H31: 2025-09-15 | I31: Delivered | J31: YCD-EX:HUPPER TEK | K31: ABM0009-250915-0014 | L31: B2C | N31: rossmo@miclogistik.de | O31: 1 | P31: NORMAL | Q31: 47.4 | R31: GELF-EML_HUPPERTEK | S31: RetourHermes_M | T31: 4618207974 | W31: 24963 | X31: Tarp | Y31: DE | Z31: B07Q3SQT6C | AA31: =VLOOKUP(Z31,物品明细!A:B,2,0) -> 金属储物柜71英寸高 | AB31: =VLOOKUP(Z31,物品明细!A:I,9,0) -> 188x49x14 | AC31: =VLOOKUP(Z31,物品明细!A:D,4,0) -> 47.4 | AE31: 1 | AF31: =AE31*AC31 -> 47.4 | AG31: =AE31 -> 1 | AH31: 4.85 | AI31: =AH31*AG31 -> 4.85 | AL31: =AK31*AJ31 -> 0 | AO31: =AN31*AM31 -> 0 | AR31: =AQ31*AP31 -> 0 | AS31: =O31 -> 1 | AT31: 3 | AU31: =AT31*AS31 -> 3 | AV31: =AI31+AL31+AO31+AR31+AU31 -> 7.85 | AW31: 1 | AX31: =AF31 -> 47.4 | AZ31: 50 | BA31: =W31 -> 24963 | BB31: =X31 -> Tarp | BC31: =Y31 -> DE | BD31: 46.558575 | BE31: =AW31*BD31 -> 46.558575 | BF31: 2.5 | BG31: =0.024*AZ31 -> 1.2 | BH31: 2.5 | BJ31: =SUM(BF31:BI31) -> 6.2 | BM31: =BK31*BL31 -> 0 | BN31: =BE31+BJ31+BM31 -> 52.758575 | BO31: =AV31+BN31 -> 60.608575
A32: ABM0009-250915-0013 | B32: =COUNTIF(A:A,A32) -> 1 | C32: 1 | D32: Y | E32: M | F32: 202509 | G32: 2025-09-15 | H32: 2025-09-15 | I32: Delivered | J32: YCD-EX:HUPPER TEK | K32: ABM0009-250915-0013 | L32: B2C | N32: rossmo@miclogistik.de | O32: 1 | P32: NORMAL | Q32: 47.4 | R32: GELF-EML_HUPPERTEK | S32: RetourHermes_M | T32: 4618207967 | W32: 99996 | X32: Unstruttal | Y32: DE | Z32: B07BK8W5MF | AA32: =VLOOKUP(Z32,物品明细!A:B,2,0) -> 金属储物柜71英寸银色 | AB32: =VLOOKUP(Z32,物品明细!A:I,9,0) -> 188x49x14 | AC32: =VLOOKUP(Z32,物品明细!A:D,4,0) -> 47.4 | AE32: 1 | AF32: =AE32*AC32 -> 47.4 | AG32: =AE32 -> 1 | AH32: 4.85 | AI32: =AH32*AG32 -> 4.85 | AL32: =AK32*AJ32 -> 0 | AO32: =AN32*AM32 -> 0 | AR32: =AQ32*AP32 -> 0 | AS32: =O32 -> 1 | AT32: 3 | AU32: =AT32*AS32 -> 3 | AV32: =AI32+AL32+AO32+AR32+AU32 -> 7.85 | AW32: 1 | AX32: =AF32 -> 47.4 | AZ32: 50 | BA32: =W32 -> 99996 | BB32: =X32 -> Unstruttal | BC32: =Y32 -> DE | BD32: 46.558575 | BE32: =AW32*BD32 -> 46.558575 | BF32: 2.5 | BG32: =0.024*AZ32 -> 1.2 | BH32: 2.5 | BJ32: =SUM(BF32:BI32) -> 6.2 | BM32: =BK32*BL32 -> 0 | BN32: =BE32+BJ32+BM32 -> 52.758575 | BO32: =AV32+BN32 -> 60.608575
A33: ABM0009-250915-0012 | B33: =COUNTIF(A:A,A33) -> 1 | C33: 1 | D33: Y | E33: M | F33: 202509 | G33: 2025-09-15 | H33: 2025-09-15 | I33: Delivered | J33: YCD-EX:HUPPER TEK | K33: ABM0009-250915-0012 | L33: B2C | N33: rossmo@miclogistik.de | O33: 1 | P33: NORMAL | Q33: 47.4 | R33: GELF-EML_HUPPERTEK | S33: RetourHermes_M | T33: 4618207950 | W33: 33378 | X33: Rheda-Wiedenbrück | Y33: DE | Z33: B07Q3SQT6C | AA33: =VLOOKUP(Z33,物品明细!A:B,2,0) -> 金属储物柜71英寸高 | AB33: =VLOOKUP(Z33,物品明细!A:I,9,0) -> 188x49x14 | AC33: =VLOOKUP(Z33,物品明细!A:D,4,0) -> 47.4 | AE33: 1 | AF33: =AE33*AC33 -> 47.4 | AG33: =AE33 -> 1 | AH33: 4.85 | AI33: =AH33*AG33 -> 4.85 | AL33: =AK33*AJ33 -> 0 | AO33: =AN33*AM33 -> 0 | AR33: =AQ33*AP33 -> 0 | AS33: =O33 -> 1 | AT33: 3 | AU33: =AT33*AS33 -> 3 | AV33: =AI33+AL33+AO33+AR33+AU33 -> 7.85 | AW33: 1 | AX33: =AF33 -> 47.4 | AZ33: 50 | BA33: =W33 -> 33378 | BB33: =X33 -> Rheda-Wiedenbrück | BC33: =Y33 -> DE | BD33: 46.558575 | BE33: =AW33*BD33 -> 46.558575 | BF33: 2.5 | BG33: =0.024*AZ33 -> 1.2 | BH33: 2.5 | BJ33: =SUM(BF33:BI33) -> 6.2 | BM33: =BK33*BL33 -> 0 | BN33: =BE33+BJ33+BM33 -> 52.758575 | BO33: =AV33+BN33 -> 60.608575
A34: ABM0009-250915-0011 | B34: =COUNTIF(A:A,A34) -> 1 | C34: 1 | D34: Y | E34: M | F34: 202509 | G34: 2025-09-15 | H34: 2025-09-15 | I34: Delivered | J34: YCD-EX:HUPPER TEK | K34: ABM0009-250915-0011 | L34: B2C | N34: rossmo@miclogistik.de | O34: 1 | P34: NORMAL | Q34: 47.4 | R34: GELF-EML_HUPPERTEK | S34: RetourHermes_M | T34: 4618207943 | W34: 77694 | X34: Kehl | Y34: DE | Z34: B076THQBHX | AA34: =VLOOKUP(Z34,物品明细!A:B,2,0) -> 金属储物柜71英寸灰色 | AB34: =VLOOKUP(Z34,物品明细!A:I,9,0) -> 188x49x14 | AC34: =VLOOKUP(Z34,物品明细!A:D,4,0) -> 47.4 | AE34: 1 | AF34: =AE34*AC34 -> 47.4 | AG34: =AE34 -> 1 | AH34: 4.85 | AI34: =AH34*AG34 -> 4.85 | AL34: =AK34*AJ34 -> 0 | AO34: =AN34*AM34 -> 0 | AR34: =AQ34*AP34 -> 0 | AS34: =O34 -> 1 | AT34: 3 | AU34: =AT34*AS34 -> 3 | AV34: =AI34+AL34+AO34+AR34+AU34 -> 7.85 | AW34: 1 | AX34: =AF34 -> 47.4 | AZ34: 50 | BA34: =W34 -> 77694 | BB34: =X34 -> Kehl | BC34: =Y34 -> DE | BD34: 46.558575 | BE34: =AW34*BD34 -> 46.558575 | BF34: 2.5 | BG34: =0.024*AZ34 -> 1.2 | BH34: 2.5 | BJ34: =SUM(BF34:BI34) -> 6.2 | BM34: =BK34*BL34 -> 0 | BN34: =BE34+BJ34+BM34 -> 52.758575 | BO34: =AV34+BN34 -> 60.608575
A35: ABM0009-250915-0010 | B35: =COUNTIF(A:A,A35) -> 1 | C35: 1 | D35: Y | E35: M | F35: 202509 | G35: 2025-09-15 | H35: 2025-09-15 | I35: Delivered | J35: YCD-EX:HUPPER TEK | K35: ABM0009-250915-0010 | L35: B2C | N35: rossmo@miclogistik.de | O35: 1 | P35: NORMAL | Q35: 47.4 | R35: GELF-EML_HUPPERTEK | S35: RetourHermes_M | T35: 4618207936 | W35: 91616 | X35: Neusitz | Y35: DE | Z35: B076THQBHX | AA35: =VLOOKUP(Z35,物品明细!A:B,2,0) -> 金属储物柜71英寸灰色 | AB35: =VLOOKUP(Z35,物品明细!A:I,9,0) -> 188x49x14 | AC35: =VLOOKUP(Z35,物品明细!A:D,4,0) -> 47.4 | AE35: 1 | AF35: =AE35*AC35 -> 47.4 | AG35: =AE35 -> 1 | AH35: 4.85 | AI35: =AH35*AG35 -> 4.85 | AL35: =AK35*AJ35 -> 0 | AO35: =AN35*AM35 -> 0 | AR35: =AQ35*AP35 -> 0 | AS35: =O35 -> 1 | AT35: 3 | AU35: =AT35*AS35 -> 3 | AV35: =AI35+AL35+AO35+AR35+AU35 -> 7.85 | AW35: 1 | AX35: =AF35 -> 47.4 | AZ35: 50 | BA35: =W35 -> 91616 | BB35: =X35 -> Neusitz | BC35: =Y35 -> DE | BD35: 46.558575 | BE35: =AW35*BD35 -> 46.558575 | BF35: 2.5 | BG35: =0.024*AZ35 -> 1.2 | BH35: 2.5 | BJ35: =SUM(BF35:BI35) -> 6.2 | BM35: =BK35*BL35 -> 0 | BN35: =BE35+BJ35+BM35 -> 52.758575 | BO35: =AV35+BN35 -> 60.608575
A36: ABM0009-250915-0009 | B36: =COUNTIF(A:A,A36) -> 1 | C36: 1 | D36: Y | E36: M | F36: 202509 | G36: 2025-09-15 | H36: 2025-09-15 | I36: Delivered | J36: YCD-EX:HUPPER TEK | K36: ABM0009-250915-0009 | L36: B2C | N36: rossmo@miclogistik.de | O36: 1 | P36: NORMAL | Q36: 47.4 | R36: GELF-EML_HUPPERTEK | S36: RetourHermes_M | T36: 4618207929 | W36: 37120 | X36: Bovenden | Y36: DE | Z36: B076THQBHX | AA36: =VLOOKUP(Z36,物品明细!A:B,2,0) -> 金属储物柜71英寸灰色 | AB36: =VLOOKUP(Z36,物品明细!A:I,9,0) -> 188x49x14 | AC36: =VLOOKUP(Z36,物品明细!A:D,4,0) -> 47.4 | AE36: 1 | AF36: =AE36*AC36 -> 47.4 | AG36: =AE36 -> 1 | AH36: 4.85 | AI36: =AH36*AG36 -> 4.85 | AL36: =AK36*AJ36 -> 0 | AO36: =AN36*AM36 -> 0 | AR36: =AQ36*AP36 -> 0 | AS36: =O36 -> 1 | AT36: 3 | AU36: =AT36*AS36 -> 3 | AV36: =AI36+AL36+AO36+AR36+AU36 -> 7.85 | AW36: 1 | AX36: =AF36 -> 47.4 | AZ36: 50 | BA36: =W36 -> 37120 | BB36: =X36 -> Bovenden | BC36: =Y36 -> DE | BD36: 46.558575 | BE36: =AW36*BD36 -> 46.558575 | BF36: 2.5 | BG36: =0.024*AZ36 -> 1.2 | BH36: 2.5 | BJ36: =SUM(BF36:BI36) -> 6.2 | BM36: =BK36*BL36 -> 0 | BN36: =BE36+BJ36+BM36 -> 52.758575 | BO36: =AV36+BN36 -> 60.608575
A37: ABM0009-250915-0008 | B37: =COUNTIF(A:A,A37) -> 1 | C37: 1 | D37: Y | E37: M | F37: 202509 | G37: 2025-09-15 | H37: 2025-09-15 | I37: Delivered | J37: YCD-EX:HUPPER TEK | K37: ABM0009-250915-0008 | L37: B2C | N37: rossmo@miclogistik.de | O37: 1 | P37: NORMAL | Q37: 47.4 | R37: GELF-EML_HUPPERTEK | S37: RetourHermes_M | T37: 4618207912 | W37: 1662 | X37: Meißen | Y37: DE | Z37: B076THQBHX | AA37: =VLOOKUP(Z37,物品明细!A:B,2,0) -> 金属储物柜71英寸灰色 | AB37: =VLOOKUP(Z37,物品明细!A:I,9,0) -> 188x49x14 | AC37: =VLOOKUP(Z37,物品明细!A:D,4,0) -> 47.4 | AE37: 1 | AF37: =AE37*AC37 -> 47.4 | AG37: =AE37 -> 1 | AH37: 4.85 | AI37: =AH37*AG37 -> 4.85 | AL37: =AK37*AJ37 -> 0 | AO37: =AN37*AM37 -> 0 | AR37: =AQ37*AP37 -> 0 | AS37: =O37 -> 1 | AT37: 3 | AU37: =AT37*AS37 -> 3 | AV37: =AI37+AL37+AO37+AR37+AU37 -> 7.85 | AW37: 1 | AX37: =AF37 -> 47.4 | AZ37: 50 | BA37: =W37 -> 1662 | BB37: =X37 -> Meißen | BC37: =Y37 -> DE | BD37: 46.558575 | BE37: =AW37*BD37 -> 46.558575 | BF37: 2.5 | BG37: =0.024*AZ37 -> 1.2 | BH37: 2.5 | BJ37: =SUM(BF37:BI37) -> 6.2 | BM37: =BK37*BL37 -> 0 | BN37: =BE37+BJ37+BM37 -> 52.758575 | BO37: =AV37+BN37 -> 60.608575
A38: ABM0009-250916-0003 | B38: =COUNTIF(A:A,A38) -> 1 | C38: 1 | D38: Y | E38: M | F38: 202509 | G38: 2025-09-16 | H38: 2025-09-16 | I38: Delivered | J38: YCD-EX:HUPPER TEK | K38: ABM0009-250916-0003 | L38: B2C | N38: rossmo@miclogistik.de | O38: 2 | P38: NORMAL | Q38: 94.8 | R38: GELF-EML_HUPPERTEK | S38: RetourHermes_M | T38: 4618214088 4618214095 | U38: 4618214088 4618214095 | W38: 72461 | X38: Albstadt | Y38: DE | Z38: B076THQBHX | AA38: =VLOOKUP(Z38,物品明细!A:B,2,0) -> 金属储物柜71英寸灰色 | AB38: =VLOOKUP(Z38,物品明细!A:I,9,0) -> 188x49x14 | AC38: =VLOOKUP(Z38,物品明细!A:D,4,0) -> 47.4 | AE38: 2 | AF38: =AE38*AC38 -> 94.8 | AG38: =AE38 -> 2 | AH38: 4.85 | AI38: =AH38*AG38 -> 9.7 | AL38: =AK38*AJ38 -> 0 | AO38: =AN38*AM38 -> 0 | AR38: =AQ38*AP38 -> 0 | AS38: =O38 -> 2 | AT38: 3 | AU38: =AT38*AS38 -> 6 | AV38: =AI38+AL38+AO38+AR38+AU38 -> 15.7 | AW38: 1 | AX38: =AF38 -> 94.8 | AZ38: 100 | BA38: =W38 -> 72461 | BB38: =X38 -> Albstadt | BC38: =Y38 -> DE | BD38: 78.354675 | BE38: =AW38*BD38 -> 78.354675 | BF38: 2.5 | BG38: =0.024*AZ38 -> 2.4 | BH38: 2.5 | BJ38: =SUM(BF38:BI38) -> 7.4 | BM38: =BK38*BL38 -> 0 | BN38: =BE38+BJ38+BM38 -> 85.754675 | BO38: =AV38+BN38 -> 101.45467
A39: ABM0009-250917-0004 | B39: =COUNTIF(A:A,A39) -> 1 | C39: 1 | D39: Y | E39: M | F39: 202509 | G39: 2025-09-17 | H39: 2025-09-18 | I39: Delivered | J39: YCD-EX:HUPPER TEK | K39: ABM0009-250917-0004 | L39: B2C | N39: rossmo@miclogistik.de | O39: 1 | P39: NORMAL | Q39: 47.4 | R39: GELF-EML_HUPPERTEK | S39: RetourHermes_M | T39: 4618219007 | W39: 86860 | X39: Jengen | Y39: DE | Z39: B07Q3SQT6C | AA39: =VLOOKUP(Z39,物品明细!A:B,2,0) -> 金属储物柜71英寸高 | AB39: =VLOOKUP(Z39,物品明细!A:I,9,0) -> 188x49x14 | AC39: =VLOOKUP(Z39,物品明细!A:D,4,0) -> 47.4 | AE39: 1 | AF39: =AE39*AC39 -> 47.4 | AG39: =AE39 -> 1 | AH39: 4.85 | AI39: =AH39*AG39 -> 4.85 | AL39: =AK39*AJ39 -> 0 | AO39: =AN39*AM39 -> 0 | AR39: =AQ39*AP39 -> 0 | AS39: =O39 -> 1 | AT39: 3 | AU39: =AT39*AS39 -> 3 | AV39: =AI39+AL39+AO39+AR39+AU39 -> 7.85 | AW39: 1 | AX39: =AF39 -> 47.4 | AZ39: 50 | BA39: =W39 -> 86860 | BB39: =X39 -> Jengen | BC39: =Y39 -> DE | BD39: 46.558575 | BE39: =AW39*BD39 -> 46.558575 | BF39: 2.5 | BG39: =0.024*AZ39 -> 1.2 | BH39: 2.5 | BJ39: =SUM(BF39:BI39) -> 6.2 | BM39: =BK39*BL39 -> 0 | BN39: =BE39+BJ39+BM39 -> 52.758575 | BO39: =AV39+BN39 -> 60.608575
A40: ABM0009-250917-0003 | B40: =COUNTIF(A:A,A40) -> 1 | C40: 1 | D40: Y | E40: M | F40: 202509 | G40: 2025-09-17 | H40: 2025-09-18 | I40: Delivered | J40: YCD-EX:HUPPER TEK | K40: ABM0009-250917-0003 | L40: B2C | N40: rossmo@miclogistik.de | O40: 1 | P40: NORMAL | Q40: 47.4 | R40: GELF-EML_HUPPERTEK | S40: RetourHermes_M | T40: 4618219038 | W40: 94405 | X40: Landau a.d.Isar | Y40: DE | Z40: B07BK8W5MF | AA40: =VLOOKUP(Z40,物品明细!A:B,2,0) -> 金属储物柜71英寸银色 | AB40: =VLOOKUP(Z40,物品明细!A:I,9,0) -> 188x49x14 | AC40: =VLOOKUP(Z40,物品明细!A:D,4,0) -> 47.4 | AE40: 1 | AF40: =AE40*AC40 -> 47.4 | AG40: =AE40 -> 1 | AH40: 4.85 | AI40: =AH40*AG40 -> 4.85 | AL40: =AK40*AJ40 -> 0 | AO40: =AN40*AM40 -> 0 | AR40: =AQ40*AP40 -> 0 | AS40: =O40 -> 1 | AT40: 3 | AU40: =AT40*AS40 -> 3 | AV40: =AI40+AL40+AO40+AR40+AU40 -> 7.85 | AW40: 1 | AX40: =AF40 -> 47.4 | AZ40: 50 | BA40: =W40 -> 94405 | BB40: =X40 -> Landau a.d.Isar | BC40: =Y40 -> DE | BD40: 46.558575 | BE40: =AW40*BD40 -> 46.558575 | BF40: 2.5 | BG40: =0.024*AZ40 -> 1.2 | BH40: 2.5 | BJ40: =SUM(BF40:BI40) -> 6.2 | BM40: =BK40*BL40 -> 0 | BN40: =BE40+BJ40+BM40 -> 52.758575 | BO40: =AV40+BN40 -> 60.608575
A41: ABM0009-250918-0005 | B41: =COUNTIF(A:A,A41) -> 1 | C41: 1 | D41: Y | E41: M | F41: 202509 | G41: 2025-09-18 | H41: 2025-09-18 | I41: Delivered | J41: YCD-EX:HUPPER TEK | K41: ABM0009-250918-0005 | L41: B2C | N41: qianhui.xu@miclogistik.de | O41: 2 | P41: NORMAL | Q41: 94.8 | R41: GELF-EML_HUPPERTEK | S41: RetourHermes_M | T41: 4618223318 4618223325 | U41: 4618223318 4618223325 | W41: 17033 | X41: Neubrandenburg | Y41: DE | Z41: B07Q3SQT6C | AA41: =VLOOKUP(Z41,物品明细!A:B,2,0) -> 金属储物柜71英寸高 | AB41: =VLOOKUP(Z41,物品明细!A:I,9,0) -> 188x49x14 | AC41: =VLOOKUP(Z41,物品明细!A:D,4,0) -> 47.4 | AE41: 2 | AF41: =AE41*AC41 -> 94.8 | AG41: =AE41 -> 2 | AH41: 4.85 | AI41: =AH41*AG41 -> 9.7 | AL41: =AK41*AJ41 -> 0 | AO41: =AN41*AM41 -> 0 | AR41: =AQ41*AP41 -> 0 | AS41: =O41 -> 2 | AT41: 3 | AU41: =AT41*AS41 -> 6 | AV41: =AI41+AL41+AO41+AR41+AU41 -> 15.7 | AW41: 1 | AX41: =AF41 -> 94.8 | AZ41: 100 | BA41: =W41 -> 17033 | BB41: =X41 -> Neubrandenburg | BC41: =Y41 -> DE | BD41: 78.354675 | BE41: =AW41*BD41 -> 78.354675 | BF41: 2.5 | BG41: =0.024*AZ41 -> 2.4 | BH41: 2.5 | BI41: 9 | BJ41: =SUM(BF41:BI41) -> 16.4 | BM41: =BK41*BL41 -> 0 | BN41: =BE41+BJ41+BM41 -> 94.754675 | BO41: =AV41+BN41 -> 110.45467
A42: ABM0009-250918-0003 | B42: =COUNTIF(A:A,A42) -> 1 | C42: 1 | D42: Y | E42: M | F42: 202509 | G42: 2025-09-18 | H42: 2025-09-18 | I42: Delivered | J42: YCD-EX:HUPPER TEK | K42: ABM0009-250918-0003 | L42: B2C | N42: qianhui.xu@miclogistik.de | O42: 1 | P42: NORMAL | Q42: 47.4 | R42: GELF-EML_HUPPERTEK | S42: RetourHermes_M | T42: 4618223301 | W42: 38461 | X42: Danndorf | Y42: DE | Z42: B07Q3SQT6C | AA42: =VLOOKUP(Z42,物品明细!A:B,2,0) -> 金属储物柜71英寸高 | AB42: =VLOOKUP(Z42,物品明细!A:I,9,0) -> 188x49x14 | AC42: =VLOOKUP(Z42,物品明细!A:D,4,0) -> 47.4 | AE42: 1 | AF42: =AE42*AC42 -> 47.4 | AG42: =AE42 -> 1 | AH42: 4.85 | AI42: =AH42*AG42 -> 4.85 | AL42: =AK42*AJ42 -> 0 | AO42: =AN42*AM42 -> 0 | AR42: =AQ42*AP42 -> 0 | AS42: =O42 -> 1 | AT42: 3 | AU42: =AT42*AS42 -> 3 | AV42: =AI42+AL42+AO42+AR42+AU42 -> 7.85 | AW42: 1 | AX42: =AF42 -> 47.4 | AZ42: 50 | BA42: =W42 -> 38461 | BB42: =X42 -> Danndorf | BC42: =Y42 -> DE | BD42: 46.558575 | BE42: =AW42*BD42 -> 46.558575 | BF42: 2.5 | BG42: =0.024*AZ42 -> 1.2 | BH42: 2.5 | BJ42: =SUM(BF42:BI42) -> 6.2 | BM42: =BK42*BL42 -> 0 | BN42: =BE42+BJ42+BM42 -> 52.758575 | BO42: =AV42+BN42 -> 60.608575
A43: ABM0009-250918-0002 | B43: =COUNTIF(A:A,A43) -> 1 | C43: 1 | D43: Y | E43: M | F43: 202509 | G43: 2025-09-18 | H43: 2025-09-19 | I43: Delivery Notify | J43: YCD-EX:HUPPER TEK | K43: ABM0009-250918-0002 | L43: B2C | N43: qianhui.xu@miclogistik.de | O43: 1 | P43: NORMAL | Q43: 47.4 | R43: GELF-EML_HUPPERTEK | S43: RetourHermes_M | T43: 4618227477 | W43: 91729 | X43: Haundorf | Y43: DE | Z43: B076THQBHX | AA43: =VLOOKUP(Z43,物品明细!A:B,2,0) -> 金属储物柜71英寸灰色 | AB43: =VLOOKUP(Z43,物品明细!A:I,9,0) -> 188x49x14 | AC43: =VLOOKUP(Z43,物品明细!A:D,4,0) -> 47.4 | AE43: 1 | AF43: =AE43*AC43 -> 47.4 | AG43: =AE43 -> 1 | AH43: 4.85 | AI43: =AH43*AG43 -> 4.85 | AL43: =AK43*AJ43 -> 0 | AO43: =AN43*AM43 -> 0 | AR43: =AQ43*AP43 -> 0 | AS43: =O43 -> 1 | AT43: 3 | AU43: =AT43*AS43 -> 3 | AV43: =AI43+AL43+AO43+AR43+AU43 -> 7.85 | AW43: 1 | AX43: =AF43 -> 47.4 | AZ43: 50 | BA43: =W43 -> 91729 | BB43: =X43 -> Haundorf | BC43: =Y43 -> DE | BD43: 46.558575 | BE43: =AW43*BD43 -> 46.558575 | BF43: 2.5 | BG43: =0.024*AZ43 -> 1.2 | BH43: 2.5 | BJ43: =SUM(BF43:BI43) -> 6.2 | BM43: =BK43*BL43 -> 0 | BN43: =BE43+BJ43+BM43 -> 52.758575 | BO43: =AV43+BN43 -> 60.608575 | BP43: 旧的运单号4618223295
A44: ABM0009-250919-0001 | B44: =COUNTIF(A:A,A44) -> 1 | C44: 1 | D44: Y | E44: M | F44: 202509 | G44: 2025-09-19 | H44: 2025-09-19 | I44: Delivered | J44: YCD-EX:HUPPER TEK | K44: ABM0009-250919-0001 | L44: B2C | N44: qianhui.xu@miclogistik.de | O44: 2 | P44: NORMAL | Q44: 94.8 | R44: GELF-EML_HUPPERTEK | S44: RetourHermes_M | T44: 4618227866 4618227873 | U44: 4618227866 4618227873 | W44: 97494 | X44: Bundorf | Y44: DE | Z44: B07Q3SQT6C | AA44: =VLOOKUP(Z44,物品明细!A:B,2,0) -> 金属储物柜71英寸高 | AB44: =VLOOKUP(Z44,物品明细!A:I,9,0) -> 188x49x14 | AC44: =VLOOKUP(Z44,物品明细!A:D,4,0) -> 47.4 | AE44: 2 | AF44: =AE44*AC44 -> 94.8 | AG44: =AE44 -> 2 | AH44: 4.85 | AI44: =AH44*AG44 -> 9.7 | AL44: =AK44*AJ44 -> 0 | AO44: =AN44*AM44 -> 0 | AR44: =AQ44*AP44 -> 0 | AS44: =O44 -> 2 | AT44: 3 | AU44: =AT44*AS44 -> 6 | AV44: =AI44+AL44+AO44+AR44+AU44 -> 15.7 | AW44: 1 | AX44: =AF44 -> 94.8 | AZ44: 100 | BA44: =W44 -> 97494 | BB44: =X44 -> Bundorf | BC44: =Y44 -> DE | BD44: 78.354675 | BE44: =AW44*BD44 -> 78.354675 | BF44: 2.5 | BG44: =0.024*AZ44 -> 2.4 | BH44: 2.5 | BJ44: =SUM(BF44:BI44) -> 7.4 | BM44: =BK44*BL44 -> 0 | BN44: =BE44+BJ44+BM44 -> 85.754675 | BO44: =AV44+BN44 -> 101.45467
A45: ABM0009-250922-0009 | B45: =COUNTIF(A:A,A45) -> 1 | C45: 1 | D45: Y | E45: M | F45: 202509 | G45: 2025-09-22 | H45: 2025-09-22 | I45: Delivered | J45: YCD-EX:HUPPER TEK | K45: ABM0009-250922-0009 | L45: B2C | N45: qianhui.xu@miclogistik.de | O45: 1 | P45: NORMAL | Q45: 47.4 | R45: GELF-EML_HUPPERTEK | S45: RetourHermes_M | T45: 4618237612 | W45: 48369 | X45: Saerbeck | Y45: DE | Z45: B07BK8W5MF | AA45: =VLOOKUP(Z45,物品明细!A:B,2,0) -> 金属储物柜71英寸银色 | AB45: =VLOOKUP(Z45,物品明细!A:I,9,0) -> 188x49x14 | AC45: =VLOOKUP(Z45,物品明细!A:D,4,0) -> 47.4 | AE45: 1 | AF45: =AE45*AC45 -> 47.4 | AG45: =AE45 -> 1 | AH45: 4.85 | AI45: =AH45*AG45 -> 4.85 | AL45: =AK45*AJ45 -> 0 | AO45: =AN45*AM45 -> 0 | AR45: =AQ45*AP45 -> 0 | AS45: =O45 -> 1 | AT45: 3 | AU45: =AT45*AS45 -> 3 | AV45: =AI45+AL45+AO45+AR45+AU45 -> 7.85 | AW45: 1 | AX45: =AF45 -> 47.4 | AZ45: 50 | BA45: =W45 -> 48369 | BB45: =X45 -> Saerbeck | BC45: =Y45 -> DE | BD45: 46.558575 | BE45: =AW45*BD45 -> 46.558575 | BF45: 2.5 | BG45: =0.024*AZ45 -> 1.2 | BH45: 2.5 | BJ45: =SUM(BF45:BI45) -> 6.2 | BM45: =BK45*BL45 -> 0 | BN45: =BE45+BJ45+BM45 -> 52.758575 | BO45: =AV45+BN45 -> 60.608575
A46: ABM0009-250922-0008 | B46: =COUNTIF(A:A,A46) -> 1 | C46: 1 | D46: Y | E46: M | F46: 202509 | G46: 2025-09-22 | H46: 2025-09-22 | I46: Delivered | J46: YCD-EX:HUPPER TEK | K46: ABM0009-250922-0008 | L46: B2C | N46: qianhui.xu@miclogistik.de | O46: 1 | P46: NORMAL | Q46: 47.4 | R46: GELF-EML_HUPPERTEK | S46: RetourHermes_M | T46: 4618237605 | W46: 74586 | X46: Frankenhardt | Y46: DE | Z46: B076THQBHX | AA46: =VLOOKUP(Z46,物品明细!A:B,2,0) -> 金属储物柜71英寸灰色 | AB46: =VLOOKUP(Z46,物品明细!A:I,9,0) -> 188x49x14 | AC46: =VLOOKUP(Z46,物品明细!A:D,4,0) -> 47.4 | AE46: 1 | AF46: =AE46*AC46 -> 47.4 | AG46: =AE46 -> 1 | AH46: 4.85 | AI46: =AH46*AG46 -> 4.85 | AL46: =AK46*AJ46 -> 0 | AO46: =AN46*AM46 -> 0 | AR46: =AQ46*AP46 -> 0 | AS46: =O46 -> 1 | AT46: 3 | AU46: =AT46*AS46 -> 3 | AV46: =AI46+AL46+AO46+AR46+AU46 -> 7.85 | AW46: 1 | AX46: =AF46 -> 47.4 | AZ46: 50 | BA46: =W46 -> 74586 | BB46: =X46 -> Frankenhardt | BC46: =Y46 -> DE | BD46: 46.558575 | BE46: =AW46*BD46 -> 46.558575 | BF46: 2.5 | BG46: =0.024*AZ46 -> 1.2 | BH46: 2.5 | BJ46: =SUM(BF46:BI46) -> 6.2 | BM46: =BK46*BL46 -> 0 | BN46: =BE46+BJ46+BM46 -> 52.758575 | BO46: =AV46+BN46 -> 60.608575
A47: ABM0009-250922-0007 | B47: =COUNTIF(A:A,A47) -> 1 | C47: 1 | D47: Y | E47: M | F47: 202509 | G47: 2025-09-22 | H47: 2025-09-22 | I47: Delivered | J47: YCD-EX:HUPPER TEK | K47: ABM0009-250922-0007 | L47: B2C | N47: qianhui.xu@miclogistik.de | O47: 4 | P47: NORMAL | Q47: 189.6 | R47: GELF-EML_HUPPERTEK | S47: RetourHermes_M | T47: 4618237568 4618237575 4618237582 4618237599 | U47: 4618237568 4618237575 4618237582 4618237599 | W47: 66629 | X47: Freisen | Y47: DE | Z47: B07BK8W5MF | AA47: =VLOOKUP(Z47,物品明细!A:B,2,0) -> 金属储物柜71英寸银色 | AB47: =VLOOKUP(Z47,物品明细!A:I,9,0) -> 188x49x14 | AC47: =VLOOKUP(Z47,物品明细!A:D,4,0) -> 47.4 | AE47: 4 | AF47: =AE47*AC47 -> 189.6 | AG47: =AE47 -> 4 | AH47: 4.85 | AI47: =AH47*AG47 -> 19.4 | AL47: =AK47*AJ47 -> 0 | AO47: =AN47*AM47 -> 0 | AR47: =AQ47*AP47 -> 0 | AS47: =O47 -> 4 | AT47: 3 | AU47: =AT47*AS47 -> 12 | AV47: =AI47+AL47+AO47+AR47+AU47 -> 31.4 | AW47: 1 | AX47: =AF47 -> 189.6 | AZ47: 200 | BA47: =W47 -> 66629 | BB47: =X47 -> Freisen | BC47: =Y47 -> DE | BD47: 121.50652 | BE47: =AW47*BD47 -> 121.50652 | BF47: 2.5 | BG47: =0.024*AZ47 -> 4.8 | BH47: 2.5 | BJ47: =SUM(BF47:BI47) -> 9.8 | BK47: =O47 -> 4 | BL47: 2.5 | BM47: =BK47*BL47 -> 10 | BN47: =BE47+BJ47+BM47 -> 141.30652 | BO47: =AV47+BN47 -> 172.70652
A48: ABM0009-250922-0006 | B48: =COUNTIF(A:A,A48) -> 1 | C48: 1 | D48: Y | E48: M | F48: 202509 | G48: 2025-09-22 | H48: 2025-09-22 | I48: Delivered | J48: YCD-EX:HUPPER TEK | K48: ABM0009-250922-0006 | L48: B2C | N48: qianhui.xu@miclogistik.de | O48: 1 | P48: NORMAL | Q48: 47.4 | R48: GELF-EML_HUPPERTEK | S48: RetourHermes_M | T48: 4618237551 | W48: 65205 | X48: Wiesbaden | Y48: DE | Z48: B076THQBHX | AA48: =VLOOKUP(Z48,物品明细!A:B,2,0) -> 金属储物柜71英寸灰色 | AB48: =VLOOKUP(Z48,物品明细!A:I,9,0) -> 188x49x14 | AC48: =VLOOKUP(Z48,物品明细!A:D,4,0) -> 47.4 | AE48: 1 | AF48: =AE48*AC48 -> 47.4 | AG48: =AE48 -> 1 | AH48: 4.85 | AI48: =AH48*AG48 -> 4.85 | AL48: =AK48*AJ48 -> 0 | AO48: =AN48*AM48 -> 0 | AR48: =AQ48*AP48 -> 0 | AS48: =O48 -> 1 | AT48: 3 | AU48: =AT48*AS48 -> 3 | AV48: =AI48+AL48+AO48+AR48+AU48 -> 7.85 | AW48: 1 | AX48: =AF48 -> 47.4 | AZ48: 50 | BA48: =W48 -> 65205 | BB48: =X48 -> Wiesbaden | BC48: =Y48 -> DE | BD48: 46.558575 | BE48: =AW48*BD48 -> 46.558575 | BF48: 2.5 | BG48: =0.024*AZ48 -> 1.2 | BH48: 2.5 | BJ48: =SUM(BF48:BI48) -> 6.2 | BM48: =BK48*BL48 -> 0 | BN48: =BE48+BJ48+BM48 -> 52.758575 | BO48: =AV48+BN48 -> 60.608575
A49: ABM0009-250922-0005 | B49: =COUNTIF(A:A,A49) -> 1 | C49: 1 | D49: Y | E49: M | F49: 202509 | G49: 2025-09-22 | H49: 2025-09-22 | I49: Delivered | J49: YCD-EX:HUPPER TEK | K49: ABM0009-250922-0005 | L49: B2C | N49: qianhui.xu@miclogistik.de | O49: 1 | P49: NORMAL | Q49: 47.4 | R49: GELF-EML_HUPPERTEK | S49: RetourHermes_M | T49: 4618237544 | W49: 53619 | X49: Rheinbreitbach | Y49: DE | Z49: B07Q3SQT6C | AA49: =VLOOKUP(Z49,物品明细!A:B,2,0) -> 金属储物柜71英寸高 | AB49: =VLOOKUP(Z49,物品明细!A:I,9,0) -> 188x49x14 | AC49: =VLOOKUP(Z49,物品明细!A:D,4,0) -> 47.4 | AE49: 1 | AF49: =AE49*AC49 -> 47.4 | AG49: =AE49 -> 1 | AH49: 4.85 | AI49: =AH49*AG49 -> 4.85 | AL49: =AK49*AJ49 -> 0 | AO49: =AN49*AM49 -> 0 | AR49: =AQ49*AP49 -> 0 | AS49: =O49 -> 1 | AT49: 3 | AU49: =AT49*AS49 -> 3 | AV49: =AI49+AL49+AO49+AR49+AU49 -> 7.85 | AW49: 1 | AX49: =AF49 -> 47.4 | AZ49: 50 | BA49: =W49 -> 53619 | BB49: =X49 -> Rheinbreitbach | BC49: =Y49 -> DE | BD49: 46.558575 | BE49: =AW49*BD49 -> 46.558575 | BF49: 2.5 | BG49: =0.024*AZ49 -> 1.2 | BH49: 2.5 | BJ49: =SUM(BF49:BI49) -> 6.2 | BM49: =BK49*BL49 -> 0 | BN49: =BE49+BJ49+BM49 -> 52.758575 | BO49: =AV49+BN49 -> 60.608575
A50: ABM0009-250922-0004 | B50: =COUNTIF(A:A,A50) -> 1 | C50: 1 | D50: Y | E50: M | F50: 202509 | G50: 2025-09-22 | H50: 2025-09-22 | I50: Delivered | J50: YCD-EX:HUPPER TEK | K50: ABM0009-250922-0004 | L50: B2C | N50: qianhui.xu@miclogistik.de | O50: 1 | P50: NORMAL | Q50: 47.4 | R50: GELF-EML_HUPPERTEK | S50: RetourHermes_M | T50: 4618237537 | W50: 45138 | X50: Essen | Y50: DE | Z50: B076THQBHX | AA50: =VLOOKUP(Z50,物品明细!A:B,2,0) -> 金属储物柜71英寸灰色 | AB50: =VLOOKUP(Z50,物品明细!A:I,9,0) -> 188x49x14 | AC50: =VLOOKUP(Z50,物品明细!A:D,4,0) -> 47.4 | AE50: 1 | AF50: =AE50*AC50 -> 47.4 | AG50: =AE50 -> 1 | AH50: 4.85 | AI50: =AH50*AG50 -> 4.85 | AL50: =AK50*AJ50 -> 0 | AO50: =AN50*AM50 -> 0 | AR50: =AQ50*AP50 -> 0 | AS50: =O50 -> 1 | AT50: 3 | AU50: =AT50*AS50 -> 3 | AV50: =AI50+AL50+AO50+AR50+AU50 -> 7.85 | AW50: 1 | AX50: =AF50 -> 47.4 | AZ50: 50 | BA50: =W50 -> 45138 | BB50: =X50 -> Essen | BC50: =Y50 -> DE | BD50: 46.558575 | BE50: =AW50*BD50 -> 46.558575 | BF50: 2.5 | BG50: =0.024*AZ50 -> 1.2 | BH50: 2.5 | BJ50: =SUM(BF50:BI50) -> 6.2 | BM50: =BK50*BL50 -> 0 | BN50: =BE50+BJ50+BM50 -> 52.758575 | BO50: =AV50+BN50 -> 60.608575
A51: ABM0009-250922-0003 | B51: =COUNTIF(A:A,A51) -> 1 | C51: 1 | D51: Y | E51: M | F51: 202509 | G51: 2025-09-22 | H51: 2025-09-22 | I51: Delivery Notify | J51: YCD-EX:HUPPER TEK | K51: ABM0009-250922-0003 | L51: B2C | N51: qianhui.xu@miclogistik.de | O51: 1 | P51: NORMAL | Q51: 47.4 | R51: GELF-EML_HUPPERTEK | S51: RetourHermes_M | T51: 4618237520 | W51: 12559 | X51: Berlin | Y51: DE | Z51: B076THQBHX | AA51: =VLOOKUP(Z51,物品明细!A:B,2,0) -> 金属储物柜71英寸灰色 | AB51: =VLOOKUP(Z51,物品明细!A:I,9,0) -> 188x49x14 | AC51: =VLOOKUP(Z51,物品明细!A:D,4,0) -> 47.4 | AE51: 1 | AF51: =AE51*AC51 -> 47.4 | AG51: =AE51 -> 1 | AH51: 4.85 | AI51: =AH51*AG51 -> 4.85 | AL51: =AK51*AJ51 -> 0 | AO51: =AN51*AM51 -> 0 | AR51: =AQ51*AP51 -> 0 | AS51: =O51 -> 1 | AT51: 3 | AU51: =AT51*AS51 -> 3 | AV51: =AI51+AL51+AO51+AR51+AU51 -> 7.85 | AW51: 1 | AX51: =AF51 -> 47.4 | AZ51: 50 | BA51: =W51 -> 12559 | BB51: =X51 -> Berlin | BC51: =Y51 -> DE | BD51: 46.558575 | BE51: =AW51*BD51 -> 46.558575 | BF51: 2.5 | BG51: =0.024*AZ51 -> 1.2 | BH51: 2.5 | BI51: 7.8 | BJ51: =SUM(BF51:BI51) -> 14 | BM51: =BK51*BL51 -> 0 | BN51: =BE51+BJ51+BM51 -> 60.558575 | BO51: =AV51+BN51 -> 68.408575
A52: ABM0009-250922-0002 | B52: =COUNTIF(A:A,A52) -> 1 | C52: 1 | D52: Y | E52: M | F52: 202509 | G52: 2025-09-22 | H52: 2025-09-22 | I52: Delivered | J52: YCD-EX:HUPPER TEK | K52: ABM0009-250922-0002 | L52: B2C | N52: qianhui.xu@miclogistik.de | O52: 1 | P52: NORMAL | Q52: 47.4 | R52: GELF-EML_HUPPERTEK | S52: RetourHermes_M | T52: 4618237513 | W52: 12207 | X52: Berlin | Y52: DE | Z52: B077RVYZRF | AA52: =VLOOKUP(Z52,物品明细!A:B,2,0) -> 德国联邦快递金属储物柜 | AB52: =VLOOKUP(Z52,物品明细!A:I,9,0) -> 188x49x14 | AC52: =VLOOKUP(Z52,物品明细!A:D,4,0) -> 47.4 | AE52: 1 | AF52: =AE52*AC52 -> 47.4 | AG52: =AE52 -> 1 | AH52: 4.85 | AI52: =AH52*AG52 -> 4.85 | AL52: =AK52*AJ52 -> 0 | AO52: =AN52*AM52 -> 0 | AR52: =AQ52*AP52 -> 0 | AS52: =O52 -> 1 | AT52: 3 | AU52: =AT52*AS52 -> 3 | AV52: =AI52+AL52+AO52+AR52+AU52 -> 7.85 | AW52: 1 | AX52: =AF52 -> 47.4 | AZ52: 50 | BA52: =W52 -> 12207 | BB52: =X52 -> Berlin | BC52: =Y52 -> DE | BD52: 46.558575 | BE52: =AW52*BD52 -> 46.558575 | BF52: 2.5 | BG52: =0.024*AZ52 -> 1.2 | BH52: 2.5 | BI52: 7.8 | BJ52: =SUM(BF52:BI52) -> 14 | BM52: =BK52*BL52 -> 0 | BN52: =BE52+BJ52+BM52 -> 60.558575 | BO52: =AV52+BN52 -> 68.408575
A53: ABM0009-250922-0001 | B53: =COUNTIF(A:A,A53) -> 1 | C53: 1 | D53: Y | E53: M | F53: 202509 | G53: 2025-09-22 | H53: 2025-09-22 | I53: Delivery Notify | J53: YCD-EX:HUPPER TEK | K53: ABM0009-250922-0001 | L53: B2C | N53: qianhui.xu@miclogistik.de | O53: 1 | P53: NORMAL | Q53: 47.4 | R53: GELF-EML_HUPPERTEK | S53: RetourHermes_M | T53: 4618237506 | W53: 27476 | X53: Cuxhaven | Y53: DE | Z53: B07Q3SQT6C | AA53: =VLOOKUP(Z53,物品明细!A:B,2,0) -> 金属储物柜71英寸高 | AB53: =VLOOKUP(Z53,物品明细!A:I,9,0) -> 188x49x14 | AC53: =VLOOKUP(Z53,物品明细!A:D,4,0) -> 47.4 | AE53: 1 | AF53: =AE53*AC53 -> 47.4 | AG53: =AE53 -> 1 | AH53: 4.85 | AI53: =AH53*AG53 -> 4.85 | AL53: =AK53*AJ53 -> 0 | AO53: =AN53*AM53 -> 0 | AR53: =AQ53*AP53 -> 0 | AS53: =O53 -> 1 | AT53: 3 | AU53: =AT53*AS53 -> 3 | AV53: =AI53+AL53+AO53+AR53+AU53 -> 7.85 | AW53: 1 | AX53: =AF53 -> 47.4 | AZ53: 50 | BA53: =W53 -> 27476 | BB53: =X53 -> Cuxhaven | BC53: =Y53 -> DE | BD53: 46.558575 | BE53: =AW53*BD53 -> 46.558575 | BF53: 2.5 | BG53: =0.024*AZ53 -> 1.2 | BH53: 2.5 | BJ53: =SUM(BF53:BI53) -> 6.2 | BM53: =BK53*BL53 -> 0 | BN53: =BE53+BJ53+BM53 -> 52.758575 | BO53: =AV53+BN53 -> 60.608575
A54: ABM0009-250923-0002 | B54: =COUNTIF(A:A,A54) -> 1 | C54: 1 | D54: Y | E54: M | F54: 202509 | G54: 2025-09-23 | H54: 2025-09-23 | I54: Delivery Notify | J54: YCD-EX:HUPPER TEK | K54: ABM0009-250923-0002 | L54: B2C | N54: qianhui.xu@miclogistik.de | O54: 1 | P54: NORMAL | Q54: 47.4 | R54: GELF-EML_HUPPERTEK | S54: RetourHermes_M | T54: 4618242524 | W54: 65618 | X54: Selters (taunus) | Y54: DE | Z54: B076THQBHX | AA54: =VLOOKUP(Z54,物品明细!A:B,2,0) -> 金属储物柜71英寸灰色 | AB54: =VLOOKUP(Z54,物品明细!A:I,9,0) -> 188x49x14 | AC54: =VLOOKUP(Z54,物品明细!A:D,4,0) -> 47.4 | AE54: 1 | AF54: =AE54*AC54 -> 47.4 | AG54: =AE54 -> 1 | AH54: 4.85 | AI54: =AH54*AG54 -> 4.85 | AL54: =AK54*AJ54 -> 0 | AO54: =AN54*AM54 -> 0 | AR54: =AQ54*AP54 -> 0 | AS54: =O54 -> 1 | AT54: 3 | AU54: =AT54*AS54 -> 3 | AV54: =AI54+AL54+AO54+AR54+AU54 -> 7.85 | AW54: 1 | AX54: =AF54 -> 47.4 | AZ54: 50 | BA54: =W54 -> 65618 | BB54: =X54 -> Selters (taunus) | BC54: =Y54 -> DE | BD54: 46.558575 | BE54: =AW54*BD54 -> 46.558575 | BF54: 2.5 | BG54: =0.024*AZ54 -> 1.2 | BH54: 2.5 | BJ54: =SUM(BF54:BI54) -> 6.2 | BM54: =BK54*BL54 -> 0 | BN54: =BE54+BJ54+BM54 -> 52.758575 | BO54: =AV54+BN54 -> 60.608575
A55: ABM0009-250923-0001 | B55: =COUNTIF(A:A,A55) -> 1 | C55: 1 | D55: Y | E55: M | F55: 202509 | G55: 2025-09-23 | H55: 2025-09-23 | I55: Delivered | J55: YCD-EX:HUPPER TEK | K55: ABM0009-250923-0001 | L55: B2C | N55: qianhui.xu@miclogistik.de | O55: 1 | P55: NORMAL | Q55: 47.4 | R55: GELF-EML_HUPPERTEK | S55: RetourHermes_M | T55: 4618242517 | W55: 35690 | X55: Dillenburg | Y55: DE | Z55: B07Q3SQT6C | AA55: =VLOOKUP(Z55,物品明细!A:B,2,0) -> 金属储物柜71英寸高 | AB55: =VLOOKUP(Z55,物品明细!A:I,9,0) -> 188x49x14 | AC55: =VLOOKUP(Z55,物品明细!A:D,4,0) -> 47.4 | AE55: 1 | AF55: =AE55*AC55 -> 47.4 | AG55: =AE55 -> 1 | AH55: 4.85 | AI55: =AH55*AG55 -> 4.85 | AL55: =AK55*AJ55 -> 0 | AO55: =AN55*AM55 -> 0 | AR55: =AQ55*AP55 -> 0 | AS55: =O55 -> 1 | AT55: 3 | AU55: =AT55*AS55 -> 3 | AV55: =AI55+AL55+AO55+AR55+AU55 -> 7.85 | AW55: 1 | AX55: =AF55 -> 47.4 | AZ55: 50 | BA55: =W55 -> 35690 | BB55: =X55 -> Dillenburg | BC55: =Y55 -> DE | BD55: 46.558575 | BE55: =AW55*BD55 -> 46.558575 | BF55: 2.5 | BG55: =0.024*AZ55 -> 1.2 | BH55: 2.5 | BJ55: =SUM(BF55:BI55) -> 6.2 | BM55: =BK55*BL55 -> 0 | BN55: =BE55+BJ55+BM55 -> 52.758575 | BO55: =AV55+BN55 -> 60.608575
A56: ABM0009-250924-0003 | B56: =COUNTIF(A:A,A56) -> 1 | C56: 1 | D56: Y | E56: M | F56: 202509 | G56: 2025-09-24 | H56: 2025-09-24 | I56: Delivered | J56: YCD-EX:HUPPER TEK | K56: ABM0009-250924-0003 | L56: B2C | N56: qianhui.xu@miclogistik.de | O56: 1 | P56: NORMAL | Q56: 47.4 | R56: GELF-EML_HUPPERTEK | S56: RetourHermes_M | T56: 4618246553 | W56: 53940 | X56: Hellenthal | Y56: DE | Z56: B07Q3SQT6C | AA56: =VLOOKUP(Z56,物品明细!A:B,2,0) -> 金属储物柜71英寸高 | AB56: =VLOOKUP(Z56,物品明细!A:I,9,0) -> 188x49x14 | AC56: =VLOOKUP(Z56,物品明细!A:D,4,0) -> 47.4 | AE56: 1 | AF56: =AE56*AC56 -> 47.4 | AG56: =AE56 -> 1 | AH56: 4.85 | AI56: =AH56*AG56 -> 4.85 | AL56: =AK56*AJ56 -> 0 | AO56: =AN56*AM56 -> 0 | AR56: =AQ56*AP56 -> 0 | AS56: =O56 -> 1 | AT56: 3 | AU56: =AT56*AS56 -> 3 | AV56: =AI56+AL56+AO56+AR56+AU56 -> 7.85 | AW56: 1 | AX56: =AF56 -> 47.4 | AZ56: 50 | BA56: =W56 -> 53940 | BB56: =X56 -> Hellenthal | BC56: =Y56 -> DE | BD56: 46.558575 | BE56: =AW56*BD56 -> 46.558575 | BF56: 2.5 | BG56: =0.024*AZ56 -> 1.2 | BH56: 2.5 | BJ56: =SUM(BF56:BI56) -> 6.2 | BM56: =BK56*BL56 -> 0 | BN56: =BE56+BJ56+BM56 -> 52.758575 | BO56: =AV56+BN56 -> 60.608575
A57: ABM0009-250924-0002 | B57: =COUNTIF(A:A,A57) -> 1 | C57: 1 | D57: Y | E57: M | F57: 202509 | G57: 2025-09-24 | H57: 2025-09-24 | I57: Delivered | J57: YCD-EX:HUPPER TEK | K57: ABM0009-250924-0002 | L57: B2C | N57: qianhui.xu@miclogistik.de | O57: 1 | P57: NORMAL | Q57: 47.4 | R57: GELF-EML_HUPPERTEK | S57: RetourHermes_M | T57: 4618246546 | W57: 38489 | X57: Jübar | Y57: DE | Z57: B07Q3SQT6C | AA57: =VLOOKUP(Z57,物品明细!A:B,2,0) -> 金属储物柜71英寸高 | AB57: =VLOOKUP(Z57,物品明细!A:I,9,0) -> 188x49x14 | AC57: =VLOOKUP(Z57,物品明细!A:D,4,0) -> 47.4 | AE57: 1 | AF57: =AE57*AC57 -> 47.4 | AG57: =AE57 -> 1 | AH57: 4.85 | AI57: =AH57*AG57 -> 4.85 | AL57: =AK57*AJ57 -> 0 | AO57: =AN57*AM57 -> 0 | AR57: =AQ57*AP57 -> 0 | AS57: =O57 -> 1 | AT57: 3 | AU57: =AT57*AS57 -> 3 | AV57: =AI57+AL57+AO57+AR57+AU57 -> 7.85 | AW57: 1 | AX57: =AF57 -> 47.4 | AZ57: 50 | BA57: =W57 -> 38489 | BB57: =X57 -> Jübar | BC57: =Y57 -> DE | BD57: 46.558575 | BE57: =AW57*BD57 -> 46.558575 | BF57: 2.5 | BG57: =0.024*AZ57 -> 1.2 | BH57: 2.5 | BJ57: =SUM(BF57:BI57) -> 6.2 | BM57: =BK57*BL57 -> 0 | BN57: =BE57+BJ57+BM57 -> 52.758575 | BO57: =AV57+BN57 -> 60.608575
A58: ABM0009-250924-0001 | B58: =COUNTIF(A:A,A58) -> 1 | C58: 1 | D58: Y | E58: M | F58: 202509 | G58: 2025-09-24 | H58: 2025-09-24 | I58: Delivered | J58: YCD-EX:HUPPER TEK | K58: ABM0009-250924-0001 | L58: B2C | N58: qianhui.xu@miclogistik.de | O58: 1 | P58: NORMAL | Q58: 47.4 | R58: GELF-EML_HUPPERTEK | S58: RetourHermes_M | T58: 4618246539 | W58: 74229 | X58: Oedheim | Y58: DE | Z58: B07Q3SQT6C | AA58: =VLOOKUP(Z58,物品明细!A:B,2,0) -> 金属储物柜71英寸高 | AB58: =VLOOKUP(Z58,物品明细!A:I,9,0) -> 188x49x14 | AC58: =VLOOKUP(Z58,物品明细!A:D,4,0) -> 47.4 | AE58: 1 | AF58: =AE58*AC58 -> 47.4 | AG58: =AE58 -> 1 | AH58: 4.85 | AI58: =AH58*AG58 -> 4.85 | AL58: =AK58*AJ58 -> 0 | AO58: =AN58*AM58 -> 0 | AR58: =AQ58*AP58 -> 0 | AS58: =O58 -> 1 | AT58: 3 | AU58: =AT58*AS58 -> 3 | AV58: =AI58+AL58+AO58+AR58+AU58 -> 7.85 | AW58: 1 | AX58: =AF58 -> 47.4 | AZ58: 50 | BA58: =W58 -> 74229 | BB58: =X58 -> Oedheim | BC58: =Y58 -> DE | BD58: 46.558575 | BE58: =AW58*BD58 -> 46.558575 | BF58: 2.5 | BG58: =0.024*AZ58 -> 1.2 | BH58: 2.5 | BJ58: =SUM(BF58:BI58) -> 6.2 | BM58: =BK58*BL58 -> 0 | BN58: =BE58+BJ58+BM58 -> 52.758575 | BO58: =AV58+BN58 -> 60.608575
A59: ABM0009-250923-0003 | B59: =COUNTIF(A:A,A59) -> 1 | C59: 1 | D59: Y | E59: M | F59: 202509 | G59: 2025-09-24 | H59: 2025-09-24 | I59: Delivered | J59: YCD-EX:HUPPER TEK | K59: ABM0009-250923-0003 | L59: B2C | N59: qianhui.xu@miclogistik.de | O59: 1 | P59: NORMAL | Q59: 47.4 | R59: GELF-EML_HUPPERTEK | S59: RetourHermes_M | T59: 4618246522 | W59: 23758 | X59: Oldenburg in Holstein | Y59: DE | Z59: B07Q3SQT6C | AA59: =VLOOKUP(Z59,物品明细!A:B,2,0) -> 金属储物柜71英寸高 | AB59: =VLOOKUP(Z59,物品明细!A:I,9,0) -> 188x49x14 | AC59: =VLOOKUP(Z59,物品明细!A:D,4,0) -> 47.4 | AE59: 1 | AF59: =AE59*AC59 -> 47.4 | AG59: =AE59 -> 1 | AH59: 4.85 | AI59: =AH59*AG59 -> 4.85 | AL59: =AK59*AJ59 -> 0 | AO59: =AN59*AM59 -> 0 | AR59: =AQ59*AP59 -> 0 | AS59: =O59 -> 1 | AT59: 3 | AU59: =AT59*AS59 -> 3 | AV59: =AI59+AL59+AO59+AR59+AU59 -> 7.85 | AW59: 1 | AX59: =AF59 -> 47.4 | AZ59: 50 | BA59: =W59 -> 23758 | BB59: =X59 -> Oldenburg in Holstein | BC59: =Y59 -> DE | BD59: 46.558575 | BE59: =AW59*BD59 -> 46.558575 | BF59: 2.5 | BG59: =0.024*AZ59 -> 1.2 | BH59: 2.5 | BJ59: =SUM(BF59:BI59) -> 6.2 | BM59: =BK59*BL59 -> 0 | BN59: =BE59+BJ59+BM59 -> 52.758575 | BO59: =AV59+BN59 -> 60.608575
A60: ABM0009-250925-0017 | B60: =COUNTIF(A:A,A60) -> 1 | C60: 1 | D60: Y | E60: M | F60: 202509 | G60: 2025-09-25 | H60: 2025-09-25 | I60: Shipped | J60: YCD-EX:HUPPER TEK | K60: ABM0009-250925-0017 | L60: B2C | N60: qianhui.xu@miclogistik.de | O60: 1 | P60: NORMAL | Q60: 47.4 | R60: GELF-EML_HUPPERTEK | S60: RetourHermes_M | T60: 4618251434 | W60: 21337 | X60: Lüneburg | Y60: DE | Z60: B07Q3SQT6C | AA60: =VLOOKUP(Z60,物品明细!A:B,2,0) -> 金属储物柜71英寸高 | AB60: =VLOOKUP(Z60,物品明细!A:I,9,0) -> 188x49x14 | AC60: =VLOOKUP(Z60,物品明细!A:D,4,0) -> 47.4 | AE60: 1 | AF60: =AE60*AC60 -> 47.4 | AG60: =AE60 -> 1 | AH60: 4.85 | AI60: =AH60*AG60 -> 4.85 | AL60: =AK60*AJ60 -> 0 | AO60: =AN60*AM60 -> 0 | AR60: =AQ60*AP60 -> 0 | AS60: =O60 -> 1 | AT60: 3 | AU60: =AT60*AS60 -> 3 | AV60: =AI60+AL60+AO60+AR60+AU60 -> 7.85 | AW60: 1 | AX60: =AF60 -> 47.4 | AZ60: 50 | BA60: =W60 -> 21337 | BB60: =X60 -> Lüneburg | BC60: =Y60 -> DE | BD60: 46.558575 | BE60: =AW60*BD60 -> 46.558575 | BF60: 2.5 | BG60: =0.024*AZ60 -> 1.2 | BH60: 2.5 | BJ60: =SUM(BF60:BI60) -> 6.2 | BM60: =BK60*BL60 -> 0 | BN60: =BE60+BJ60+BM60 -> 52.758575 | BO60: =AV60+BN60 -> 60.608575
A61: ABM0009-250925-0016 | B61: =COUNTIF(A:A,A61) -> 1 | C61: 1 | D61: Y | E61: M | F61: 202509 | G61: 2025-09-25 | H61: 2025-09-25 | I61: Shipped | J61: YCD-EX:HUPPER TEK | K61: ABM0009-250925-0016 | L61: B2C | N61: qianhui.xu@miclogistik.de | O61: 1 | P61: NORMAL | Q61: 47.4 | R61: GELF-EML_HUPPERTEK | S61: RetourHermes_M | T61: 4618251427 | W61: 32602 | X61: Vlotho | Y61: DE | Z61: B07Q3SQT6C | AA61: =VLOOKUP(Z61,物品明细!A:B,2,0) -> 金属储物柜71英寸高 | AB61: =VLOOKUP(Z61,物品明细!A:I,9,0) -> 188x49x14 | AC61: =VLOOKUP(Z61,物品明细!A:D,4,0) -> 47.4 | AE61: 1 | AF61: =AE61*AC61 -> 47.4 | AG61: =AE61 -> 1 | AH61: 4.85 | AI61: =AH61*AG61 -> 4.85 | AL61: =AK61*AJ61 -> 0 | AO61: =AN61*AM61 -> 0 | AR61: =AQ61*AP61 -> 0 | AS61: =O61 -> 1 | AT61: 3 | AU61: =AT61*AS61 -> 3 | AV61: =AI61+AL61+AO61+AR61+AU61 -> 7.85 | AW61: 1 | AX61: =AF61 -> 47.4 | AZ61: 50 | BA61: =W61 -> 32602 | BB61: =X61 -> Vlotho | BC61: =Y61 -> DE | BD61: 46.558575 | BE61: =AW61*BD61 -> 46.558575 | BF61: 2.5 | BG61: =0.024*AZ61 -> 1.2 | BH61: 2.5 | BJ61: =SUM(BF61:BI61) -> 6.2 | BM61: =BK61*BL61 -> 0 | BN61: =BE61+BJ61+BM61 -> 52.758575 | BO61: =AV61+BN61 -> 60.608575
A62: ABM0009-250925-0015 | B62: =COUNTIF(A:A,A62) -> 1 | C62: 1 | D62: Y | E62: M | F62: 202509 | G62: 2025-09-25 | H62: 2025-09-25 | I62: Shipped | J62: YCD-EX:HUPPER TEK | K62: ABM0009-250925-0015 | L62: B2C | N62: qianhui.xu@miclogistik.de | O62: 1 | P62: NORMAL | Q62: 47.4 | R62: GELF-EML_HUPPERTEK | S62: RetourHermes_M | T62: 4618251410 | W62: 65618 | X62: Selters (taunus) | Y62: DE | Z62: B07BK8W5MF | AA62: =VLOOKUP(Z62,物品明细!A:B,2,0) -> 金属储物柜71英寸银色 | AB62: =VLOOKUP(Z62,物品明细!A:I,9,0) -> 188x49x14 | AC62: =VLOOKUP(Z62,物品明细!A:D,4,0) -> 47.4 | AE62: 1 | AF62: =AE62*AC62 -> 47.4 | AG62: =AE62 -> 1 | AH62: 4.85 | AI62: =AH62*AG62 -> 4.85 | AL62: =AK62*AJ62 -> 0 | AO62: =AN62*AM62 -> 0 | AR62: =AQ62*AP62 -> 0 | AS62: =O62 -> 1 | AT62: 3 | AU62: =AT62*AS62 -> 3 | AV62: =AI62+AL62+AO62+AR62+AU62 -> 7.85 | AW62: 1 | AX62: =AF62 -> 47.4 | AZ62: 50 | BA62: =W62 -> 65618 | BB62: =X62 -> Selters (taunus) | BC62: =Y62 -> DE | BD62: 46.558575 | BE62: =AW62*BD62 -> 46.558575 | BF62: 2.5 | BG62: =0.024*AZ62 -> 1.2 | BH62: 2.5 | BJ62: =SUM(BF62:BI62) -> 6.2 | BM62: =BK62*BL62 -> 0 | BN62: =BE62+BJ62+BM62 -> 52.758575 | BO62: =AV62+BN62 -> 60.608575
A63: ABM0009-250925-0014 | B63: =COUNTIF(A:A,A63) -> 1 | C63: 1 | D63: Y | E63: M | F63: 202509 | G63: 2025-09-25 | H63: 2025-09-25 | I63: Shipped | J63: YCD-EX:HUPPER TEK | K63: ABM0009-250925-0014 | L63: B2C | N63: qianhui.xu@miclogistik.de | O63: 1 | P63: NORMAL | Q63: 47.4 | R63: GELF-EML_HUPPERTEK | S63: RetourHermes_M | T63: 4618251403 | W63: 68229 | X63: Mannheim | Y63: DE | Z63: B07Q3SQT6C | AA63: =VLOOKUP(Z63,物品明细!A:B,2,0) -> 金属储物柜71英寸高 | AB63: =VLOOKUP(Z63,物品明细!A:I,9,0) -> 188x49x14 | AC63: =VLOOKUP(Z63,物品明细!A:D,4,0) -> 47.4 | AE63: 1 | AF63: =AE63*AC63 -> 47.4 | AG63: =AE63 -> 1 | AH63: 4.85 | AI63: =AH63*AG63 -> 4.85 | AL63: =AK63*AJ63 -> 0 | AO63: =AN63*AM63 -> 0 | AR63: =AQ63*AP63 -> 0 | AS63: =O63 -> 1 | AT63: 3 | AU63: =AT63*AS63 -> 3 | AV63: =AI63+AL63+AO63+AR63+AU63 -> 7.85 | AW63: 1 | AX63: =AF63 -> 47.4 | AZ63: 50 | BA63: =W63 -> 68229 | BB63: =X63 -> Mannheim | BC63: =Y63 -> DE | BD63: 46.558575 | BE63: =AW63*BD63 -> 46.558575 | BF63: 2.5 | BG63: =0.024*AZ63 -> 1.2 | BH63: 2.5 | BJ63: =SUM(BF63:BI63) -> 6.2 | BM63: =BK63*BL63 -> 0 | BN63: =BE63+BJ63+BM63 -> 52.758575 | BO63: =AV63+BN63 -> 60.608575
A64: ABM0009-250925-0013 | B64: =COUNTIF(A:A,A64) -> 1 | C64: 1 | D64: Y | E64: M | F64: 202509 | G64: 2025-09-25 | H64: 2025-09-25 | I64: Shipped | J64: YCD-EX:HUPPER TEK | K64: ABM0009-250925-0013 | L64: B2C | N64: qianhui.xu@miclogistik.de | O64: 1 | P64: NORMAL | Q64: 47.4 | R64: GELF-EML_HUPPERTEK | S64: RetourHermes_M | T64: 4618251397 | W64: 93170 | X64: Bernhardswald | Y64: DE | Z64: B077RVYZRF | AA64: =VLOOKUP(Z64,物品明细!A:B,2,0) -> 德国联邦快递金属储物柜 | AB64: =VLOOKUP(Z64,物品明细!A:I,9,0) -> 188x49x14 | AC64: =VLOOKUP(Z64,物品明细!A:D,4,0) -> 47.4 | AE64: 1 | AF64: =AE64*AC64 -> 47.4 | AG64: =AE64 -> 1 | AH64: 4.85 | AI64: =AH64*AG64 -> 4.85 | AL64: =AK64*AJ64 -> 0 | AO64: =AN64*AM64 -> 0 | AR64: =AQ64*AP64 -> 0 | AS64: =O64 -> 1 | AT64: 3 | AU64: =AT64*AS64 -> 3 | AV64: =AI64+AL64+AO64+AR64+AU64 -> 7.85 | AW64: 1 | AX64: =AF64 -> 47.4 | AZ64: 50 | BA64: =W64 -> 93170 | BB64: =X64 -> Bernhardswald | BC64: =Y64 -> DE | BD64: 46.558575 | BE64: =AW64*BD64 -> 46.558575 | BF64: 2.5 | BG64: =0.024*AZ64 -> 1.2 | BH64: 2.5 | BJ64: =SUM(BF64:BI64) -> 6.2 | BM64: =BK64*BL64 -> 0 | BN64: =BE64+BJ64+BM64 -> 52.758575 | BO64: =AV64+BN64 -> 60.608575
... A79: ABM0009-250930-0001 | B79: =COUNTIF(A:A,A79) -> 1 | C79: 1 | D79: Y | E79: M | F79: 202509 | G79: 2025-09-30 | H79: 2025-09-30 | I79: Shipped | J79: YCD-EX:HUPPER TEK | K79: ABM0009-250930-0001 | L79: B2C | N79: qianhui.xu@miclogistik.de | O79: 1 | P79: NORMAL | Q79: 47.4 | R79: GELF-EML_HUPPERTEK | S79: RetourHermes_M | T79: 4618271227 | W79: 71034 | X79: Böblingen | Y79: DE | Z79: B076THQBHX | AA79: =VLOOKUP(Z79,物品明细!A:B,2,0) -> 金属储物柜71英寸灰色 | AB79: =VLOOKUP(Z79,物品明细!A:I,9,0) -> 188x49x14 | AC79: =VLOOKUP(Z79,物品明细!A:D,4,0) -> 47.4 | AE79: 1 | AF79: =AE79*AC79 -> 47.4 | AG79: =AE79 -> 1 | AH79: 4.85 | AI79: =AH79*AG79 -> 4.85 | AL79: =AK79*AJ79 -> 0 | AO79: =AN79*AM79 -> 0 | AR79: =AQ79*AP79 -> 0 | AS79: =O79 -> 1 | AT79: 3 | AU79: =AT79*AS79 -> 3 | AV79: =AI79+AL79+AO79+AR79+AU79 -> 7.85 | AW79: 1 | AX79: =AF79 -> 47.4 | AZ79: 50 | BA79: =W79 -> 71034 | BB79: =X79 -> Böblingen | BC79: =Y79 -> DE | BD79: 46.558575 | BE79: =AW79*BD79 -> 46.558575 | BF79: 2.5 | BG79: =0.024*AZ79 -> 1.2 | BH79: 2.5 | BJ79: =SUM(BF79:BI79) -> 6.2 | BM79: =BK79*BL79 -> 0 | BN79: =BE79+BJ79+BM79 -> 52.758575 | BO79: =AV79+BN79 -> 60.608575

Sheet 3.1 正向-普货-仓储费 
AP1: =SUM(AP6:AP10000) -> 674.82506
A2: 计费时间IStorage Charge Date | C2: 入仓信息Inbound Information | I2: 商品信息Product Information | Q2: 装箱信息 | V2: 打托信息 | AA2: 原始入仓数量 | AE2: 进销存信息 | AJ2: 仓储费计费信息/Storage Charge Infromation | AQ2: 备注
A3: 月份 | B3: 日期 | C3: 仓库名称 | D3: 仓库编码 | E3: 客户代码 | F3: 入库任务号 | G3: 原始参考号 | H3: 入库上架时间 | I3: 编码 | J3: 条码 | K3: 商品名称 | L3: 件型 | M3: 长 | N3: 宽 | O3: 高 | P3: 单品体积A | Q3: 装箱数 | R3: 长 | S3: 宽 | T3: 高 | U3: 单箱体积B | V3: 打托数 | W3: 长 | X3: 宽 | Y3: 高 | Z3: 单托体积C | AA3: 托数 | AB3: 箱数 | AC3: 总数 | AD3: 批次号 | AE3: 期初库存数 | AF3: 入库数 | AG3: 出库数 | AH3: 期末库存数 | AI3: 计费单元 | AJ3: 库存体积E | AK3: 实际计费体积F | AL3: 库龄 | AM3: 库龄段 | AN3: 计费单价 | AO3: 币种 | AP3: 仓储费
A4: / | B4: / | C4: / | D4: / | E4: / | F4: / | G4: / | H4: / | I4: / | J4: / | K4: / | M4: cm | N4: cm | O4: cm | P4: CBM/m³ | Q4: pcs | R4: cm | S4: cm | T4: cm | U4: CBM/m³ | V4: pcs/box | W4: cm | X4: cm | Y4: cm | Z4: CBM/m³ | AA4: 托/Pallet | AB4: 箱/Box | AC4: 件/pcs | AE4: 件/pcs | AF4: 件/pcs | AG4: 件/pcs | AH4: 件/pcs | AI4: pcs/box/pallet | AJ4: CBM/m³ | AK4: CBM/m³ | AL4: 天/day | AM4: 天/day | AN4: / | AO4: Euro | AP4: Euro
A5: Month | B5: Date | C5: Warehouse Name | D5: Warehouse Code | E5: Client Code | F5: Task No. | G5: Original Ref. No. | H5: Inbound Time | I5: SKU | J5: Barcode | K5: Product Name | L5: Product Type | M5: Lenth | N5: Width | O5: Height | P5: Product Volume-A | Q5: Qty per Box | R5: Lenth | S5: Width | T5: Height | U5: Box Volume-B | V5: Qty per Pallet | W5: Lenth | X5: Width | Y5: Height | Z5: Pallet Volume-B | AA5: Qty of Pallet | AB5: Qty of Carton | AC5: Total Qty. | AD5: Batch No. | AE5: Beginning Inv | AF5: Inbound | AG5: Outbound | AH5: Ending Inv. | AI5: Charge Unit | AJ5: INV Volume-E | AK5: Charge Volume-F | AL5: Storage Age | AM5: Storage Age Range | AN5: Charge Price | AO5: Curreny | AP5: Storage Amount | AQ5: Rermar
A6: 202509 | B6: 45901 | C6: MIC德国仓 | D6: M » N2 - 1 | E6: YCD-EX:HUPPER TEK | F6: MI202508130012 | G6: DE2508031-G7-MIC | H6: 45889 | I6: B07BK8W5MF | K6: =VLOOKUP(I6,物品明细!A:B,2,0) -> 金属储物柜71英寸银色 | M6: =VLOOKUP(I6,物品明细!A:E,5,0) -> 188 | N6: =VLOOKUP(I6,物品明细!A:F,6,0) -> 49 | O6: =VLOOKUP(I6,物品明细!A:G,7,0) -> 14 | P6: =M6*N6*O6/1000000 -> 0.128968 | R6: =VLOOKUP(I6,物品明细!A:E,5,0) -> 188 | S6: =VLOOKUP(I6,物品明细!A:F,6,0) -> 49 | T6: =VLOOKUP(I6,物品明细!A:G,7,0) -> 14 | U6: =R6*S6*T6/1000000 -> 0.128968 | AA6: 21 | AB6: 247 | AC6: 247 | AD6: 0 | AE6: 247 | AG6: 1 | AH6: =AE6+AF6-AG6 -> 246 | AI6: pcs | AJ6: =AH6*P6 -> 31.726128 | AK6: =AJ6 -> 31.726128 | AL6: =B6-H6+1 -> 13 | AM6: =IF(AL6<=0,"0天",IF(AL6<=30,"30天内",IF(AL6<=90,"31-90天","91天以上"))) -> 30天内 | AN6: =IF(AM6="0天",0,IF(AM6="30天内",0,IF(AM6="31-90天",0.6,1))) -> 0 | AO6: Euro | AP6: =AK6*AN6 -> 0
A7: 202509 | B7: 45902 | C7: MIC德国仓 | D7: =D6 -> M » N2 - 1 | E7: =E6 -> YCD-EX:HUPPER TEK | F7: =F6 -> MI202508130012 | G7: =G6 -> DE2508031-G7-MIC | H7: =H6 -> 45889 | I7: =I6 -> B07BK8W5MF | K7: =K6 -> 金属储物柜71英寸银色 | M7: =M6 -> 188 | N7: =N6 -> 49 | O7: =O6 -> 14 | P7: =M7*N7*O7/1000000 -> 0.128968 | R7: =R6 -> 188 | S7: =S6 -> 49 | T7: =T6 -> 14 | U7: =R7*S7*T7/1000000 -> 0.128968 | AA7: =AA6 -> 21 | AB7: =AB6 -> 247 | AC7: =AC6 -> 247 | AD7: 0 | AE7: =AH6 -> 246 | AH7: =AE7+AF7-AG7 -> 246 | AI7: pcs | AJ7: =AH7*P7 -> 31.726128 | AK7: =AJ7 -> 31.726128 | AL7: =B7-H7+1 -> 14 | AM7: =IF(AL7<=0,"0天",IF(AL7<=30,"30天内",IF(AL7<=90,"31-90天","91天以上"))) -> 30天内 | AN7: =IF(AM7="0天",0,IF(AM7="30天内",0,IF(AM7="31-90天",0.6,1))) -> 0 | AO7: Euro | AP7: =AK7*AN7 -> 0
A8: 202509 | B8: 45903 | C8: MIC德国仓 | D8: =D7 -> M » N2 - 1 | E8: =E7 -> YCD-EX:HUPPER TEK | F8: =F7 -> MI202508130012 | G8: =G7 -> DE2508031-G7-MIC | H8: =H7 -> 45889 | I8: =I7 -> B07BK8W5MF | K8: =K7 -> 金属储物柜71英寸银色 | M8: =M7 -> 188 | N8: =N7 -> 49 | O8: =O7 -> 14 | P8: =M8*N8*O8/1000000 -> 0.128968 | R8: =R7 -> 188 | S8: =S7 -> 49 | T8: =T7 -> 14 | U8: =R8*S8*T8/1000000 -> 0.128968 | AA8: =AA7 -> 21 | AB8: =AB7 -> 247 | AC8: =AC7 -> 247 | AD8: 0 | AE8: =AH7 -> 246 | AG8: 2 | AH8: =AE8+AF8-AG8 -> 244 | AI8: pcs | AJ8: =AH8*P8 -> 31.468192 | AK8: =AJ8 -> 31.468192 | AL8: =B8-H8+1 -> 15 | AM8: =IF(AL8<=0,"0天",IF(AL8<=30,"30天内",IF(AL8<=90,"31-90天","91天以上"))) -> 30天内 | AN8: =IF(AM8="0天",0,IF(AM8="30天内",0,IF(AM8="31-90天",0.6,1))) -> 0 | AO8: Euro | AP8: =AK8*AN8 -> 0
A9: 202509 | B9: 45904 | C9: MIC德国仓 | D9: =D8 -> M » N2 - 1 | E9: =E8 -> YCD-EX:HUPPER TEK | F9: =F8 -> MI202508130012 | G9: =G8 -> DE2508031-G7-MIC | H9: =H8 -> 45889 | I9: =I8 -> B07BK8W5MF | K9: =K8 -> 金属储物柜71英寸银色 | M9: =M8 -> 188 | N9: =N8 -> 49 | O9: =O8 -> 14 | P9: =M9*N9*O9/1000000 -> 0.128968 | R9: =R8 -> 188 | S9: =S8 -> 49 | T9: =T8 -> 14 | U9: =R9*S9*T9/1000000 -> 0.128968 | AA9: =AA8 -> 21 | AB9: =AB8 -> 247 | AC9: =AC8 -> 247 | AD9: 0 | AE9: =AH8 -> 244 | AH9: =AE9+AF9-AG9 -> 244 | AI9: pcs | AJ9: =AH9*P9 -> 31.468192 | AK9: =AJ9 -> 31.468192 | AL9: =B9-H9+1 -> 16 | AM9: =IF(AL9<=0,"0天",IF(AL9<=30,"30天内",IF(AL9<=90,"31-90天","91天以上"))) -> 30天内 | AN9: =IF(AM9="0天",0,IF(AM9="30天内",0,IF(AM9="31-90天",0.6,1))) -> 0 | AO9: Euro | AP9: =AK9*AN9 -> 0
A10: 202509 | B10: 45905 | C10: MIC德国仓 | D10: =D9 -> M » N2 - 1 | E10: =E9 -> YCD-EX:HUPPER TEK | F10: =F9 -> MI202508130012 | G10: =G9 -> DE2508031-G7-MIC | H10: =H9 -> 45889 | I10: =I9 -> B07BK8W5MF | K10: =K9 -> 金属储物柜71英寸银色 | M10: =M9 -> 188 | N10: =N9 -> 49 | O10: =O9 -> 14 | P10: =M10*N10*O10/1000000 -> 0.128968 | R10: =R9 -> 188 | S10: =S9 -> 49 | T10: =T9 -> 14 | U10: =R10*S10*T10/1000000 -> 0.128968 | AA10: =AA9 -> 21 | AB10: =AB9 -> 247 | AC10: =AC9 -> 247 | AD10: 0 | AE10: =AH9 -> 244 | AH10: =AE10+AF10-AG10 -> 244 | AI10: pcs | AJ10: =AH10*P10 -> 31.468192 | AK10: =AJ10 -> 31.468192 | AL10: =B10-H10+1 -> 17 | AM10: =IF(AL10<=0,"0天",IF(AL10<=30,"30天内",IF(AL10<=90,"31-90天","91天以上"))) -> 30天内 | AN10: =IF(AM10="0天",0,IF(AM10="30天内",0,IF(AM10="31-90天",0.6,1))) -> 0 | AO10: Euro | AP10: =AK10*AN10 -> 0
A11: 202509 | B11: 45906 | C11: MIC德国仓 | D11: =D10 -> M » N2 - 1 | E11: =E10 -> YCD-EX:HUPPER TEK | F11: =F10 -> MI202508130012 | G11: =G10 -> DE2508031-G7-MIC | H11: =H10 -> 45889 | I11: =I10 -> B07BK8W5MF | K11: =K10 -> 金属储物柜71英寸银色 | M11: =M10 -> 188 | N11: =N10 -> 49 | O11: =O10 -> 14 | P11: =M11*N11*O11/1000000 -> 0.128968 | R11: =R10 -> 188 | S11: =S10 -> 49 | T11: =T10 -> 14 | U11: =R11*S11*T11/1000000 -> 0.128968 | AA11: =AA10 -> 21 | AB11: =AB10 -> 247 | AC11: =AC10 -> 247 | AD11: 0 | AE11: =AH10 -> 244 | AH11: =AE11+AF11-AG11 -> 244 | AI11: pcs | AJ11: =AH11*P11 -> 31.468192 | AK11: =AJ11 -> 31.468192 | AL11: =B11-H11+1 -> 18 | AM11: =IF(AL11<=0,"0天",IF(AL11<=30,"30天内",IF(AL11<=90,"31-90天","91天以上"))) -> 30天内 | AN11: =IF(AM11="0天",0,IF(AM11="30天内",0,IF(AM11="31-90天",0.6,1))) -> 0 | AO11: Euro | AP11: =AK11*AN11 -> 0
A12: 202509 | B12: 45907 | C12: MIC德国仓 | D12: =D11 -> M » N2 - 1 | E12: =E11 -> YCD-EX:HUPPER TEK | F12: =F11 -> MI202508130012 | G12: =G11 -> DE2508031-G7-MIC | H12: =H11 -> 45889 | I12: =I11 -> B07BK8W5MF | K12: =K11 -> 金属储物柜71英寸银色 | M12: =M11 -> 188 | N12: =N11 -> 49 | O12: =O11 -> 14 | P12: =M12*N12*O12/1000000 -> 0.128968 | R12: =R11 -> 188 | S12: =S11 -> 49 | T12: =T11 -> 14 | U12: =R12*S12*T12/1000000 -> 0.128968 | AA12: =AA11 -> 21 | AB12: =AB11 -> 247 | AC12: =AC11 -> 247 | AD12: 0 | AE12: =AH11 -> 244 | AH12: =AE12+AF12-AG12 -> 244 | AI12: pcs | AJ12: =AH12*P12 -> 31.468192 | AK12: =AJ12 -> 31.468192 | AL12: =B12-H12+1 -> 19 | AM12: =IF(AL12<=0,"0天",IF(AL12<=30,"30天内",IF(AL12<=90,"31-90天","91天以上"))) -> 30天内 | AN12: =IF(AM12="0天",0,IF(AM12="30天内",0,IF(AM12="31-90天",0.6,1))) -> 0 | AO12: Euro | AP12: =AK12*AN12 -> 0
A13: 202509 | B13: 45908 | C13: MIC德国仓 | D13: =D12 -> M » N2 - 1 | E13: =E12 -> YCD-EX:HUPPER TEK | F13: =F12 -> MI202508130012 | G13: =G12 -> DE2508031-G7-MIC | H13: =H12 -> 45889 | I13: =I12 -> B07BK8W5MF | K13: =K12 -> 金属储物柜71英寸银色 | M13: =M12 -> 188 | N13: =N12 -> 49 | O13: =O12 -> 14 | P13: =M13*N13*O13/1000000 -> 0.128968 | R13: =R12 -> 188 | S13: =S12 -> 49 | T13: =T12 -> 14 | U13: =R13*S13*T13/1000000 -> 0.128968 | AA13: =AA12 -> 21 | AB13: =AB12 -> 247 | AC13: =AC12 -> 247 | AD13: 0 | AE13: =AH12 -> 244 | AG13: 1 | AH13: =AE13+AF13-AG13 -> 243 | AI13: pcs | AJ13: =AH13*P13 -> 31.339224 | AK13: =AJ13 -> 31.339224 | AL13: =B13-H13+1 -> 20 | AM13: =IF(AL13<=0,"0天",IF(AL13<=30,"30天内",IF(AL13<=90,"31-90天","91天以上"))) -> 30天内 | AN13: =IF(AM13="0天",0,IF(AM13="30天内",0,IF(AM13="31-90天",0.6,1))) -> 0 | AO13: Euro | AP13: =AK13*AN13 -> 0
A14: 202509 | B14: 45909 | C14: MIC德国仓 | D14: =D13 -> M » N2 - 1 | E14: =E13 -> YCD-EX:HUPPER TEK | F14: =F13 -> MI202508130012 | G14: =G13 -> DE2508031-G7-MIC | H14: =H13 -> 45889 | I14: =I13 -> B07BK8W5MF | K14: =K13 -> 金属储物柜71英寸银色 | M14: =M13 -> 188 | N14: =N13 -> 49 | O14: =O13 -> 14 | P14: =M14*N14*O14/1000000 -> 0.128968 | R14: =R13 -> 188 | S14: =S13 -> 49 | T14: =T13 -> 14 | U14: =R14*S14*T14/1000000 -> 0.128968 | AA14: =AA13 -> 21 | AB14: =AB13 -> 247 | AC14: =AC13 -> 247 | AD14: 0 | AE14: =AH13 -> 243 | AG14: 3 | AH14: =AE14+AF14-AG14 -> 240 | AI14: pcs | AJ14: =AH14*P14 -> 30.95232 | AK14: =AJ14 -> 30.95232 | AL14: =B14-H14+1 -> 21 | AM14: =IF(AL14<=0,"0天",IF(AL14<=30,"30天内",IF(AL14<=90,"31-90天","91天以上"))) -> 30天内 | AN14: =IF(AM14="0天",0,IF(AM14="30天内",0,IF(AM14="31-90天",0.6,1))) -> 0 | AO14: Euro | AP14: =AK14*AN14 -> 0
A15: 202509 | B15: 45910 | C15: MIC德国仓 | D15: =D14 -> M » N2 - 1 | E15: =E14 -> YCD-EX:HUPPER TEK | F15: =F14 -> MI202508130012 | G15: =G14 -> DE2508031-G7-MIC | H15: =H14 -> 45889 | I15: =I14 -> B07BK8W5MF | K15: =K14 -> 金属储物柜71英寸银色 | M15: =M14 -> 188 | N15: =N14 -> 49 | O15: =O14 -> 14 | P15: =M15*N15*O15/1000000 -> 0.128968 | R15: =R14 -> 188 | S15: =S14 -> 49 | T15: =T14 -> 14 | U15: =R15*S15*T15/1000000 -> 0.128968 | AA15: =AA14 -> 21 | AB15: =AB14 -> 247 | AC15: =AC14 -> 247 | AD15: 0 | AE15: =AH14 -> 240 | AH15: =AE15+AF15-AG15 -> 240 | AI15: pcs | AJ15: =AH15*P15 -> 30.95232 | AK15: =AJ15 -> 30.95232 | AL15: =B15-H15+1 -> 22 | AM15: =IF(AL15<=0,"0天",IF(AL15<=30,"30天内",IF(AL15<=90,"31-90天","91天以上"))) -> 30天内 | AN15: =IF(AM15="0天",0,IF(AM15="30天内",0,IF(AM15="31-90天",0.6,1))) -> 0 | AO15: Euro | AP15: =AK15*AN15 -> 0
A16: 202509 | B16: 45911 | C16: MIC德国仓 | D16: =D15 -> M » N2 - 1 | E16: =E15 -> YCD-EX:HUPPER TEK | F16: =F15 -> MI202508130012 | G16: =G15 -> DE2508031-G7-MIC | H16: =H15 -> 45889 | I16: =I15 -> B07BK8W5MF | K16: =K15 -> 金属储物柜71英寸银色 | M16: =M15 -> 188 | N16: =N15 -> 49 | O16: =O15 -> 14 | P16: =M16*N16*O16/1000000 -> 0.128968 | R16: =R15 -> 188 | S16: =S15 -> 49 | T16: =T15 -> 14 | U16: =R16*S16*T16/1000000 -> 0.128968 | AA16: =AA15 -> 21 | AB16: =AB15 -> 247 | AC16: =AC15 -> 247 | AD16: 0 | AE16: =AH15 -> 240 | AH16: =AE16+AF16-AG16 -> 240 | AI16: pcs | AJ16: =AH16*P16 -> 30.95232 | AK16: =AJ16 -> 30.95232 | AL16: =B16-H16+1 -> 23 | AM16: =IF(AL16<=0,"0天",IF(AL16<=30,"30天内",IF(AL16<=90,"31-90天","91天以上"))) -> 30天内 | AN16: =IF(AM16="0天",0,IF(AM16="30天内",0,IF(AM16="31-90天",0.6,1))) -> 0 | AO16: Euro | AP16: =AK16*AN16 -> 0
A17: 202509 | B17: 45912 | C17: MIC德国仓 | D17: =D16 -> M » N2 - 1 | E17: =E16 -> YCD-EX:HUPPER TEK | F17: =F16 -> MI202508130012 | G17: =G16 -> DE2508031-G7-MIC | H17: =H16 -> 45889 | I17: =I16 -> B07BK8W5MF | K17: =K16 -> 金属储物柜71英寸银色 | M17: =M16 -> 188 | N17: =N16 -> 49 | O17: =O16 -> 14 | P17: =M17*N17*O17/1000000 -> 0.128968 | R17: =R16 -> 188 | S17: =S16 -> 49 | T17: =T16 -> 14 | U17: =R17*S17*T17/1000000 -> 0.128968 | AA17: =AA16 -> 21 | AB17: =AB16 -> 247 | AC17: =AC16 -> 247 | AD17: 0 | AE17: =AH16 -> 240 | AH17: =AE17+AF17-AG17 -> 240 | AI17: pcs | AJ17: =AH17*P17 -> 30.95232 | AK17: =AJ17 -> 30.95232 | AL17: =B17-H17+1 -> 24 | AM17: =IF(AL17<=0,"0天",IF(AL17<=30,"30天内",IF(AL17<=90,"31-90天","91天以上"))) -> 30天内 | AN17: =IF(AM17="0天",0,IF(AM17="30天内",0,IF(AM17="31-90天",0.6,1))) -> 0 | AO17: Euro | AP17: =AK17*AN17 -> 0
A18: 202509 | B18: 45913 | C18: MIC德国仓 | D18: =D17 -> M » N2 - 1 | E18: =E17 -> YCD-EX:HUPPER TEK | F18: =F17 -> MI202508130012 | G18: =G17 -> DE2508031-G7-MIC | H18: =H17 -> 45889 | I18: =I17 -> B07BK8W5MF | K18: =K17 -> 金属储物柜71英寸银色 | M18: =M17 -> 188 | N18: =N17 -> 49 | O18: =O17 -> 14 | P18: =M18*N18*O18/1000000 -> 0.128968 | R18: =R17 -> 188 | S18: =S17 -> 49 | T18: =T17 -> 14 | U18: =R18*S18*T18/1000000 -> 0.128968 | AA18: =AA17 -> 21 | AB18: =AB17 -> 247 | AC18: =AC17 -> 247 | AD18: 0 | AE18: =AH17 -> 240 | AH18: =AE18+AF18-AG18 -> 240 | AI18: pcs | AJ18: =AH18*P18 -> 30.95232 | AK18: =AJ18 -> 30.95232 | AL18: =B18-H18+1 -> 25 | AM18: =IF(AL18<=0,"0天",IF(AL18<=30,"30天内",IF(AL18<=90,"31-90天","91天以上"))) -> 30天内 | AN18: =IF(AM18="0天",0,IF(AM18="30天内",0,IF(AM18="31-90天",0.6,1))) -> 0 | AO18: Euro | AP18: =AK18*AN18 -> 0
A19: 202509 | B19: 45914 | C19: MIC德国仓 | D19: =D18 -> M » N2 - 1 | E19: =E18 -> YCD-EX:HUPPER TEK | F19: =F18 -> MI202508130012 | G19: =G18 -> DE2508031-G7-MIC | H19: =H18 -> 45889 | I19: =I18 -> B07BK8W5MF | K19: =K18 -> 金属储物柜71英寸银色 | M19: =M18 -> 188 | N19: =N18 -> 49 | O19: =O18 -> 14 | P19: =M19*N19*O19/1000000 -> 0.128968 | R19: =R18 -> 188 | S19: =S18 -> 49 | T19: =T18 -> 14 | U19: =R19*S19*T19/1000000 -> 0.128968 | AA19: =AA18 -> 21 | AB19: =AB18 -> 247 | AC19: =AC18 -> 247 | AD19: 0 | AE19: =AH18 -> 240 | AH19: =AE19+AF19-AG19 -> 240 | AI19: pcs | AJ19: =AH19*P19 -> 30.95232 | AK19: =AJ19 -> 30.95232 | AL19: =B19-H19+1 -> 26 | AM19: =IF(AL19<=0,"0天",IF(AL19<=30,"30天内",IF(AL19<=90,"31-90天","91天以上"))) -> 30天内 | AN19: =IF(AM19="0天",0,IF(AM19="30天内",0,IF(AM19="31-90天",0.6,1))) -> 0 | AO19: Euro | AP19: =AK19*AN19 -> 0
A20: 202509 | B20: 45915 | C20: MIC德国仓 | D20: =D19 -> M » N2 - 1 | E20: =E19 -> YCD-EX:HUPPER TEK | F20: =F19 -> MI202508130012 | G20: =G19 -> DE2508031-G7-MIC | H20: =H19 -> 45889 | I20: =I19 -> B07BK8W5MF | K20: =K19 -> 金属储物柜71英寸银色 | M20: =M19 -> 188 | N20: =N19 -> 49 | O20: =O19 -> 14 | P20: =M20*N20*O20/1000000 -> 0.128968 | R20: =R19 -> 188 | S20: =S19 -> 49 | T20: =T19 -> 14 | U20: =R20*S20*T20/1000000 -> 0.128968 | AA20: =AA19 -> 21 | AB20: =AB19 -> 247 | AC20: =AC19 -> 247 | AD20: 0 | AE20: =AH19 -> 240 | AG20: 2 | AH20: =AE20+AF20-AG20 -> 238 | AI20: pcs | AJ20: =AH20*P20 -> 30.694384 | AK20: =AJ20 -> 30.694384 | AL20: =B20-H20+1 -> 27 | AM20: =IF(AL20<=0,"0天",IF(AL20<=30,"30天内",IF(AL20<=90,"31-90天","91天以上"))) -> 30天内 | AN20: =IF(AM20="0天",0,IF(AM20="30天内",0,IF(AM20="31-90天",0.6,1))) -> 0 | AO20: Euro | AP20: =AK20*AN20 -> 0
A21: 202509 | B21: 45916 | C21: MIC德国仓 | D21: =D20 -> M » N2 - 1 | E21: =E20 -> YCD-EX:HUPPER TEK | F21: =F20 -> MI202508130012 | G21: =G20 -> DE2508031-G7-MIC | H21: =H20 -> 45889 | I21: =I20 -> B07BK8W5MF | K21: =K20 -> 金属储物柜71英寸银色 | M21: =M20 -> 188 | N21: =N20 -> 49 | O21: =O20 -> 14 | P21: =M21*N21*O21/1000000 -> 0.128968 | R21: =R20 -> 188 | S21: =S20 -> 49 | T21: =T20 -> 14 | U21: =R21*S21*T21/1000000 -> 0.128968 | AA21: =AA20 -> 21 | AB21: =AB20 -> 247 | AC21: =AC20 -> 247 | AD21: 0 | AE21: =AH20 -> 238 | AH21: =AE21+AF21-AG21 -> 238 | AI21: pcs | AJ21: =AH21*P21 -> 30.694384 | AK21: =AJ21 -> 30.694384 | AL21: =B21-H21+1 -> 28 | AM21: =IF(AL21<=0,"0天",IF(AL21<=30,"30天内",IF(AL21<=90,"31-90天","91天以上"))) -> 30天内 | AN21: =IF(AM21="0天",0,IF(AM21="30天内",0,IF(AM21="31-90天",0.6,1))) -> 0 | AO21: Euro | AP21: =AK21*AN21 -> 0
A22: 202509 | B22: 45917 | C22: MIC德国仓 | D22: =D21 -> M » N2 - 1 | E22: =E21 -> YCD-EX:HUPPER TEK | F22: =F21 -> MI202508130012 | G22: =G21 -> DE2508031-G7-MIC | H22: =H21 -> 45889 | I22: =I21 -> B07BK8W5MF | K22: =K21 -> 金属储物柜71英寸银色 | M22: =M21 -> 188 | N22: =N21 -> 49 | O22: =O21 -> 14 | P22: =M22*N22*O22/1000000 -> 0.128968 | R22: =R21 -> 188 | S22: =S21 -> 49 | T22: =T21 -> 14 | U22: =R22*S22*T22/1000000 -> 0.128968 | AA22: =AA21 -> 21 | AB22: =AB21 -> 247 | AC22: =AC21 -> 247 | AD22: 0 | AE22: =AH21 -> 238 | AH22: =AE22+AF22-AG22 -> 238 | AI22: pcs | AJ22: =AH22*P22 -> 30.694384 | AK22: =AJ22 -> 30.694384 | AL22: =B22-H22+1 -> 29 | AM22: =IF(AL22<=0,"0天",IF(AL22<=30,"30天内",IF(AL22<=90,"31-90天","91天以上"))) -> 30天内 | AN22: =IF(AM22="0天",0,IF(AM22="30天内",0,IF(AM22="31-90天",0.6,1))) -> 0 | AO22: Euro | AP22: =AK22*AN22 -> 0
A23: 202509 | B23: 45918 | C23: MIC德国仓 | D23: =D22 -> M » N2 - 1 | E23: =E22 -> YCD-EX:HUPPER TEK | F23: =F22 -> MI202508130012 | G23: =G22 -> DE2508031-G7-MIC | H23: =H22 -> 45889 | I23: =I22 -> B07BK8W5MF | K23: =K22 -> 金属储物柜71英寸银色 | M23: =M22 -> 188 | N23: =N22 -> 49 | O23: =O22 -> 14 | P23: =M23*N23*O23/1000000 -> 0.128968 | R23: =R22 -> 188 | S23: =S22 -> 49 | T23: =T22 -> 14 | U23: =R23*S23*T23/1000000 -> 0.128968 | AA23: =AA22 -> 21 | AB23: =AB22 -> 247 | AC23: =AC22 -> 247 | AD23: 0 | AE23: =AH22 -> 238 | AG23: 1 | AH23: =AE23+AF23-AG23 -> 237 | AI23: pcs | AJ23: =AH23*P23 -> 30.565416 | AK23: =AJ23 -> 30.565416 | AL23: =B23-H23+1 -> 30 | AM23: =IF(AL23<=0,"0天",IF(AL23<=30,"30天内",IF(AL23<=90,"31-90天","91天以上"))) -> 30天内 | AN23: =IF(AM23="0天",0,IF(AM23="30天内",0,IF(AM23="31-90天",0.6,1))) -> 0 | AO23: Euro | AP23: =AK23*AN23 -> 0
A24: 202509 | B24: 45919 | C24: MIC德国仓 | D24: =D23 -> M » N2 - 1 | E24: =E23 -> YCD-EX:HUPPER TEK | F24: =F23 -> MI202508130012 | G24: =G23 -> DE2508031-G7-MIC | H24: =H23 -> 45889 | I24: =I23 -> B07BK8W5MF | K24: =K23 -> 金属储物柜71英寸银色 | M24: =M23 -> 188 | N24: =N23 -> 49 | O24: =O23 -> 14 | P24: =M24*N24*O24/1000000 -> 0.128968 | R24: =R23 -> 188 | S24: =S23 -> 49 | T24: =T23 -> 14 | U24: =R24*S24*T24/1000000 -> 0.128968 | AA24: =AA23 -> 21 | AB24: =AB23 -> 247 | AC24: =AC23 -> 247 | AD24: 0 | AE24: =AH23 -> 237 | AH24: =AE24+AF24-AG24 -> 237 | AI24: pcs | AJ24: =AH24*P24 -> 30.565416 | AK24: =AJ24 -> 30.565416 | AL24: =B24-H24+1 -> 31 | AM24: =IF(AL24<=0,"0天",IF(AL24<=30,"30天内",IF(AL24<=90,"31-90天","91天以上"))) -> 31-90天 | AN24: 0.7 | AO24: Euro | AP24: =AK24*AN24 -> 21.395791
A25: 202509 | B25: 45920 | C25: MIC德国仓 | D25: =D24 -> M » N2 - 1 | E25: =E24 -> YCD-EX:HUPPER TEK | F25: =F24 -> MI202508130012 | G25: =G24 -> DE2508031-G7-MIC | H25: =H24 -> 45889 | I25: =I24 -> B07BK8W5MF | K25: =K24 -> 金属储物柜71英寸银色 | M25: =M24 -> 188 | N25: =N24 -> 49 | O25: =O24 -> 14 | P25: =M25*N25*O25/1000000 -> 0.128968 | R25: =R24 -> 188 | S25: =S24 -> 49 | T25: =T24 -> 14 | U25: =R25*S25*T25/1000000 -> 0.128968 | AA25: =AA24 -> 21 | AB25: =AB24 -> 247 | AC25: =AC24 -> 247 | AD25: 0 | AE25: =AH24 -> 237 | AH25: =AE25+AF25-AG25 -> 237 | AI25: pcs | AJ25: =AH25*P25 -> 30.565416 | AK25: =AJ25 -> 30.565416 | AL25: =B25-H25+1 -> 32 | AM25: =IF(AL25<=0,"0天",IF(AL25<=30,"30天内",IF(AL25<=90,"31-90天","91天以上"))) -> 31-90天 | AN25: 0.7 | AO25: Euro | AP25: =AK25*AN25 -> 21.395791
A26: 202509 | B26: 45921 | C26: MIC德国仓 | D26: =D25 -> M » N2 - 1 | E26: =E25 -> YCD-EX:HUPPER TEK | F26: =F25 -> MI202508130012 | G26: =G25 -> DE2508031-G7-MIC | H26: =H25 -> 45889 | I26: =I25 -> B07BK8W5MF | K26: =K25 -> 金属储物柜71英寸银色 | M26: =M25 -> 188 | N26: =N25 -> 49 | O26: =O25 -> 14 | P26: =M26*N26*O26/1000000 -> 0.128968 | R26: =R25 -> 188 | S26: =S25 -> 49 | T26: =T25 -> 14 | U26: =R26*S26*T26/1000000 -> 0.128968 | AA26: =AA25 -> 21 | AB26: =AB25 -> 247 | AC26: =AC25 -> 247 | AD26: 0 | AE26: =AH25 -> 237 | AH26: =AE26+AF26-AG26 -> 237 | AI26: pcs | AJ26: =AH26*P26 -> 30.565416 | AK26: =AJ26 -> 30.565416 | AL26: =B26-H26+1 -> 33 | AM26: =IF(AL26<=0,"0天",IF(AL26<=30,"30天内",IF(AL26<=90,"31-90天","91天以上"))) -> 31-90天 | AN26: 0.7 | AO26: Euro | AP26: =AK26*AN26 -> 21.395791
A27: 202509 | B27: 45922 | C27: MIC德国仓 | D27: =D26 -> M » N2 - 1 | E27: =E26 -> YCD-EX:HUPPER TEK | F27: =F26 -> MI202508130012 | G27: =G26 -> DE2508031-G7-MIC | H27: =H26 -> 45889 | I27: =I26 -> B07BK8W5MF | K27: =K26 -> 金属储物柜71英寸银色 | M27: =M26 -> 188 | N27: =N26 -> 49 | O27: =O26 -> 14 | P27: =M27*N27*O27/1000000 -> 0.128968 | R27: =R26 -> 188 | S27: =S26 -> 49 | T27: =T26 -> 14 | U27: =R27*S27*T27/1000000 -> 0.128968 | AA27: =AA26 -> 21 | AB27: =AB26 -> 247 | AC27: =AC26 -> 247 | AD27: 0 | AE27: =AH26 -> 237 | AG27: 5 | AH27: =AE27+AF27-AG27 -> 232 | AI27: pcs | AJ27: =AH27*P27 -> 29.920576 | AK27: =AJ27 -> 29.920576 | AL27: =B27-H27+1 -> 34 | AM27: =IF(AL27<=0,"0天",IF(AL27<=30,"30天内",IF(AL27<=90,"31-90天","91天以上"))) -> 31-90天 | AN27: 0.7 | AO27: Euro | AP27: =AK27*AN27 -> 20.944403
A28: 202509 | B28: 45923 | C28: MIC德国仓 | D28: =D27 -> M » N2 - 1 | E28: =E27 -> YCD-EX:HUPPER TEK | F28: =F27 -> MI202508130012 | G28: =G27 -> DE2508031-G7-MIC | H28: =H27 -> 45889 | I28: =I27 -> B07BK8W5MF | K28: =K27 -> 金属储物柜71英寸银色 | M28: =M27 -> 188 | N28: =N27 -> 49 | O28: =O27 -> 14 | P28: =M28*N28*O28/1000000 -> 0.128968 | R28: =R27 -> 188 | S28: =S27 -> 49 | T28: =T27 -> 14 | U28: =R28*S28*T28/1000000 -> 0.128968 | AA28: =AA27 -> 21 | AB28: =AB27 -> 247 | AC28: =AC27 -> 247 | AD28: 0 | AE28: =AH27 -> 232 | AH28: =AE28+AF28-AG28 -> 232 | AI28: pcs | AJ28: =AH28*P28 -> 29.920576 | AK28: =AJ28 -> 29.920576 | AL28: =B28-H28+1 -> 35 | AM28: =IF(AL28<=0,"0天",IF(AL28<=30,"30天内",IF(AL28<=90,"31-90天","91天以上"))) -> 31-90天 | AN28: 0.7 | AO28: Euro | AP28: =AK28*AN28 -> 20.944403
A29: 202509 | B29: 45924 | C29: MIC德国仓 | D29: =D28 -> M » N2 - 1 | E29: =E28 -> YCD-EX:HUPPER TEK | F29: =F28 -> MI202508130012 | G29: =G28 -> DE2508031-G7-MIC | H29: =H28 -> 45889 | I29: =I28 -> B07BK8W5MF | K29: =K28 -> 金属储物柜71英寸银色 | M29: =M28 -> 188 | N29: =N28 -> 49 | O29: =O28 -> 14 | P29: =M29*N29*O29/1000000 -> 0.128968 | R29: =R28 -> 188 | S29: =S28 -> 49 | T29: =T28 -> 14 | U29: =R29*S29*T29/1000000 -> 0.128968 | AA29: =AA28 -> 21 | AB29: =AB28 -> 247 | AC29: =AC28 -> 247 | AD29: 0 | AE29: =AH28 -> 232 | AH29: =AE29+AF29-AG29 -> 232 | AI29: pcs | AJ29: =AH29*P29 -> 29.920576 | AK29: =AJ29 -> 29.920576 | AL29: =B29-H29+1 -> 36 | AM29: =IF(AL29<=0,"0天",IF(AL29<=30,"30天内",IF(AL29<=90,"31-90天","91天以上"))) -> 31-90天 | AN29: 0.7 | AO29: Euro | AP29: =AK29*AN29 -> 20.944403
A30: 202509 | B30: 45925 | C30: MIC德国仓 | D30: =D29 -> M » N2 - 1 | E30: =E29 -> YCD-EX:HUPPER TEK | F30: =F29 -> MI202508130012 | G30: =G29 -> DE2508031-G7-MIC | H30: =H29 -> 45889 | I30: =I29 -> B07BK8W5MF | K30: =K29 -> 金属储物柜71英寸银色 | M30: =M29 -> 188 | N30: =N29 -> 49 | O30: =O29 -> 14 | P30: =M30*N30*O30/1000000 -> 0.128968 | R30: =R29 -> 188 | S30: =S29 -> 49 | T30: =T29 -> 14 | U30: =R30*S30*T30/1000000 -> 0.128968 | AA30: =AA29 -> 21 | AB30: =AB29 -> 247 | AC30: =AC29 -> 247 | AD30: 0 | AE30: =AH29 -> 232 | AG30: 1 | AH30: =AE30+AF30-AG30 -> 231 | AI30: pcs | AJ30: =AH30*P30 -> 29.791608 | AK30: =AJ30 -> 29.791608 | AL30: =B30-H30+1 -> 37 | AM30: =IF(AL30<=0,"0天",IF(AL30<=30,"30天内",IF(AL30<=90,"31-90天","91天以上"))) -> 31-90天 | AN30: 0.7 | AO30: Euro | AP30: =AK30*AN30 -> 20.854126
A31: 202509 | B31: 45926 | C31: MIC德国仓 | D31: =D30 -> M » N2 - 1 | E31: =E30 -> YCD-EX:HUPPER TEK | F31: =F30 -> MI202508130012 | G31: =G30 -> DE2508031-G7-MIC | H31: =H30 -> 45889 | I31: =I30 -> B07BK8W5MF | K31: =K30 -> 金属储物柜71英寸银色 | M31: =M30 -> 188 | N31: =N30 -> 49 | O31: =O30 -> 14 | P31: =M31*N31*O31/1000000 -> 0.128968 | R31: =R30 -> 188 | S31: =S30 -> 49 | T31: =T30 -> 14 | U31: =R31*S31*T31/1000000 -> 0.128968 | AA31: =AA30 -> 21 | AB31: =AB30 -> 247 | AC31: =AC30 -> 247 | AD31: 0 | AE31: =AH30 -> 231 | AH31: =AE31+AF31-AG31 -> 231 | AI31: pcs | AJ31: =AH31*P31 -> 29.791608 | AK31: =AJ31 -> 29.791608 | AL31: =B31-H31+1 -> 38 | AM31: =IF(AL31<=0,"0天",IF(AL31<=30,"30天内",IF(AL31<=90,"31-90天","91天以上"))) -> 31-90天 | AN31: 0.7 | AO31: Euro | AP31: =AK31*AN31 -> 20.854126
A32: 202509 | B32: 45927 | C32: MIC德国仓 | D32: =D31 -> M » N2 - 1 | E32: =E31 -> YCD-EX:HUPPER TEK | F32: =F31 -> MI202508130012 | G32: =G31 -> DE2508031-G7-MIC | H32: =H31 -> 45889 | I32: =I31 -> B07BK8W5MF | K32: =K31 -> 金属储物柜71英寸银色 | M32: =M31 -> 188 | N32: =N31 -> 49 | O32: =O31 -> 14 | P32: =M32*N32*O32/1000000 -> 0.128968 | R32: =R31 -> 188 | S32: =S31 -> 49 | T32: =T31 -> 14 | U32: =R32*S32*T32/1000000 -> 0.128968 | AA32: =AA31 -> 21 | AB32: =AB31 -> 247 | AC32: =AC31 -> 247 | AD32: 0 | AE32: =AH31 -> 231 | AH32: =AE32+AF32-AG32 -> 231 | AI32: pcs | AJ32: =AH32*P32 -> 29.791608 | AK32: =AJ32 -> 29.791608 | AL32: =B32-H32+1 -> 39 | AM32: =IF(AL32<=0,"0天",IF(AL32<=30,"30天内",IF(AL32<=90,"31-90天","91天以上"))) -> 31-90天 | AN32: 0.7 | AO32: Euro | AP32: =AK32*AN32 -> 20.854126
A33: 202509 | B33: 45928 | C33: MIC德国仓 | D33: =D32 -> M » N2 - 1 | E33: =E32 -> YCD-EX:HUPPER TEK | F33: =F32 -> MI202508130012 | G33: =G32 -> DE2508031-G7-MIC | H33: =H32 -> 45889 | I33: =I32 -> B07BK8W5MF | K33: =K32 -> 金属储物柜71英寸银色 | M33: =M32 -> 188 | N33: =N32 -> 49 | O33: =O32 -> 14 | P33: =M33*N33*O33/1000000 -> 0.128968 | R33: =R32 -> 188 | S33: =S32 -> 49 | T33: =T32 -> 14 | U33: =R33*S33*T33/1000000 -> 0.128968 | AA33: =AA32 -> 21 | AB33: =AB32 -> 247 | AC33: =AC32 -> 247 | AD33: 0 | AE33: =AH32 -> 231 | AH33: =AE33+AF33-AG33 -> 231 | AI33: pcs | AJ33: =AH33*P33 -> 29.791608 | AK33: =AJ33 -> 29.791608 | AL33: =B33-H33+1 -> 40 | AM33: =IF(AL33<=0,"0天",IF(AL33<=30,"30天内",IF(AL33<=90,"31-90天","91天以上"))) -> 31-90天 | AN33: 0.7 | AO33: Euro | AP33: =AK33*AN33 -> 20.854126
A34: 202509 | B34: 45929 | C34: MIC德国仓 | D34: =D33 -> M » N2 - 1 | E34: =E33 -> YCD-EX:HUPPER TEK | F34: =F33 -> MI202508130012 | G34: =G33 -> DE2508031-G7-MIC | H34: =H33 -> 45889 | I34: =I33 -> B07BK8W5MF | K34: =K33 -> 金属储物柜71英寸银色 | M34: =M33 -> 188 | N34: =N33 -> 49 | O34: =O33 -> 14 | P34: =M34*N34*O34/1000000 -> 0.128968 | R34: =R33 -> 188 | S34: =S33 -> 49 | T34: =T33 -> 14 | U34: =R34*S34*T34/1000000 -> 0.128968 | AA34: =AA33 -> 21 | AB34: =AB33 -> 247 | AC34: =AC33 -> 247 | AD34: 0 | AE34: =AH33 -> 231 | AG34: 122 | AH34: =AE34+AF34-AG34 -> 109 | AI34: pcs | AJ34: =AH34*P34 -> 14.057512 | AK34: =AJ34 -> 14.057512 | AL34: =B34-H34+1 -> 41 | AM34: =IF(AL34<=0,"0天",IF(AL34<=30,"30天内",IF(AL34<=90,"31-90天","91天以上"))) -> 31-90天 | AN34: 0.7 | AO34: Euro | AP34: =AK34*AN34 -> 9.8402584
A35: 202509 | B35: 45930 | C35: MIC德国仓 | D35: =D34 -> M » N2 - 1 | E35: =E34 -> YCD-EX:HUPPER TEK | F35: =F34 -> MI202508130012 | G35: =G34 -> DE2508031-G7-MIC | H35: =H34 -> 45889 | I35: =I34 -> B07BK8W5MF | K35: =K34 -> 金属储物柜71英寸银色 | M35: =M34 -> 188 | N35: =N34 -> 49 | O35: =O34 -> 14 | P35: =M35*N35*O35/1000000 -> 0.128968 | R35: =R34 -> 188 | S35: =S34 -> 49 | T35: =T34 -> 14 | U35: =R35*S35*T35/1000000 -> 0.128968 | AA35: =AA34 -> 21 | AB35: =AB34 -> 247 | AC35: =AC34 -> 247 | AD35: 0 | AE35: =AH34 -> 109 | AG35: 1 | AH35: =AE35+AF35-AG35 -> 108 | AI35: pcs | AJ35: =AH35*P35 -> 13.928544 | AK35: =AJ35 -> 13.928544 | AL35: =B35-H35+1 -> 42 | AM35: =IF(AL35<=0,"0天",IF(AL35<=30,"30天内",IF(AL35<=90,"31-90天","91天以上"))) -> 31-90天 | AN35: 0.7 | AO35: Euro | AP35: =AK35*AN35 -> 9.7499808
A36: 202509 | B36: 0 | C36: MIC德国仓 | D36: =D35 -> M » N2 - 1 | E36: =E35 -> YCD-EX:HUPPER TEK | F36: =F35 -> MI202508130012 | G36: =G35 -> DE2508031-G7-MIC | H36: =H35 -> 45889 | I36: =I35 -> B07BK8W5MF | K36: =K35 -> 金属储物柜71英寸银色 | M36: =M35 -> 188 | N36: =N35 -> 49 | O36: =O35 -> 14 | P36: =M36*N36*O36/1000000 -> 0.128968 | R36: =R35 -> 188 | S36: =S35 -> 49 | T36: =T35 -> 14 | U36: =R36*S36*T36/1000000 -> 0.128968 | AA36: =AA35 -> 21 | AB36: =AB35 -> 247 | AC36: =AC35 -> 247 | AD36: 0 | AE36: =AH35 -> 108 | AH36: =AE36+AF36-AG36 -> 108 | AI36: pcs | AJ36: =AH36*P36 -> 13.928544 | AK36: =AJ36 -> 13.928544 | AL36: =B36-H36+1 -> -45888 | AM36: =IF(AL36<=0,"0天",IF(AL36<=30,"30天内",IF(AL36<=90,"31-90天","91天以上"))) -> 0天 | AN36: =IF(AM36="0天",0,IF(AM36="30天内",0,IF(AM36="31-90天",0.6,1))) -> 0 | AO36: Euro | AP36: =AK36*AN36 -> 0
A37: 202509 | B37: 45901 | C37: MIC德国仓 | D37: M » N2 - 1 | E37: YCD-EX:HUPPER TEK | F37: MI202508130012 | G37: DE2508031-G7-MIC | H37: 45889 | I37: B076THQBHX | K37: =VLOOKUP(I37,物品明细!A:B,2,0) -> 金属储物柜71英寸灰色 | M37: =VLOOKUP(I37,物品明细!A:E,5,0) -> 188 | N37: =VLOOKUP(I37,物品明细!A:F,6,0) -> 49 | O37: =VLOOKUP(I37,物品明细!A:G,7,0) -> 14 | P37: =M37*N37*O37/1000000 -> 0.128968 | R37: =VLOOKUP(I37,物品明细!A:E,5,0) -> 188 | S37: =VLOOKUP(I37,物品明细!A:F,6,0) -> 49 | T37: =VLOOKUP(I37,物品明细!A:G,7,0) -> 14 | U37: =R37*S37*T37/1000000 -> 0.128968 | AA37: 19 | AB37: 223 | AC37: 223 | AD37: 0 | AE37: 223 | AG37: 4 | AH37: =AE37+AF37-AG37 -> 219 | AI37: pcs | AJ37: =AH37*P37 -> 28.243992 | AK37: =AJ37 -> 28.243992 | AL37: =B37-H37+1 -> 13 | AM37: =IF(AL37<=0,"0天",IF(AL37<=30,"30天内",IF(AL37<=90,"31-90天","91天以上"))) -> 30天内 | AN37: =IF(AM37="0天",0,IF(AM37="30天内",0,IF(AM37="31-90天",0.6,1))) -> 0 | AO37: Euro | AP37: =AK37*AN37 -> 0
A38: 202509 | B38: 45902 | C38: MIC德国仓 | D38: =D37 -> M » N2 - 1 | E38: =E37 -> YCD-EX:HUPPER TEK | F38: =F37 -> MI202508130012 | G38: =G37 -> DE2508031-G7-MIC | H38: =H37 -> 45889 | I38: =I37 -> B076THQBHX | K38: =K37 -> 金属储物柜71英寸灰色 | M38: =M37 -> 188 | N38: =N37 -> 49 | O38: =O37 -> 14 | P38: =M38*N38*O38/1000000 -> 0.128968 | R38: =R37 -> 188 | S38: =S37 -> 49 | T38: =T37 -> 14 | U38: =R38*S38*T38/1000000 -> 0.128968 | AA38: =AA37 -> 19 | AB38: =AB37 -> 223 | AC38: =AC37 -> 223 | AD38: 0 | AE38: =AH37 -> 219 | AG38: 1 | AH38: =AE38+AF38-AG38 -> 218 | AI38: pcs | AJ38: =AH38*P38 -> 28.115024 | AK38: =AJ38 -> 28.115024 | AL38: =B38-H38+1 -> 14 | AM38: =IF(AL38<=0,"0天",IF(AL38<=30,"30天内",IF(AL38<=90,"31-90天","91天以上"))) -> 30天内 | AN38: =IF(AM38="0天",0,IF(AM38="30天内",0,IF(AM38="31-90天",0.6,1))) -> 0 | AO38: Euro | AP38: =AK38*AN38 -> 0
A39: 202509 | B39: 45903 | C39: MIC德国仓 | D39: =D38 -> M » N2 - 1 | E39: =E38 -> YCD-EX:HUPPER TEK | F39: =F38 -> MI202508130012 | G39: =G38 -> DE2508031-G7-MIC | H39: =H38 -> 45889 | I39: =I38 -> B076THQBHX | K39: =K38 -> 金属储物柜71英寸灰色 | M39: =M38 -> 188 | N39: =N38 -> 49 | O39: =O38 -> 14 | P39: =M39*N39*O39/1000000 -> 0.128968 | R39: =R38 -> 188 | S39: =S38 -> 49 | T39: =T38 -> 14 | U39: =R39*S39*T39/1000000 -> 0.128968 | AA39: =AA38 -> 19 | AB39: =AB38 -> 223 | AC39: =AC38 -> 223 | AD39: 0 | AE39: =AH38 -> 218 | AH39: =AE39+AF39-AG39 -> 218 | AI39: pcs | AJ39: =AH39*P39 -> 28.115024 | AK39: =AJ39 -> 28.115024 | AL39: =B39-H39+1 -> 15 | AM39: =IF(AL39<=0,"0天",IF(AL39<=30,"30天内",IF(AL39<=90,"31-90天","91天以上"))) -> 30天内 | AN39: =IF(AM39="0天",0,IF(AM39="30天内",0,IF(AM39="31-90天",0.6,1))) -> 0 | AO39: Euro | AP39: =AK39*AN39 -> 0
A40: 202509 | B40: 45904 | C40: MIC德国仓 | D40: =D39 -> M » N2 - 1 | E40: =E39 -> YCD-EX:HUPPER TEK | F40: =F39 -> MI202508130012 | G40: =G39 -> DE2508031-G7-MIC | H40: =H39 -> 45889 | I40: =I39 -> B076THQBHX | K40: =K39 -> 金属储物柜71英寸灰色 | M40: =M39 -> 188 | N40: =N39 -> 49 | O40: =O39 -> 14 | P40: =M40*N40*O40/1000000 -> 0.128968 | R40: =R39 -> 188 | S40: =S39 -> 49 | T40: =T39 -> 14 | U40: =R40*S40*T40/1000000 -> 0.128968 | AA40: =AA39 -> 19 | AB40: =AB39 -> 223 | AC40: =AC39 -> 223 | AD40: 0 | AE40: =AH39 -> 218 | AG40: 1 | AH40: =AE40+AF40-AG40 -> 217 | AI40: pcs | AJ40: =AH40*P40 -> 27.986056 | AK40: =AJ40 -> 27.986056 | AL40: =B40-H40+1 -> 16 | AM40: =IF(AL40<=0,"0天",IF(AL40<=30,"30天内",IF(AL40<=90,"31-90天","91天以上"))) -> 30天内 | AN40: =IF(AM40="0天",0,IF(AM40="30天内",0,IF(AM40="31-90天",0.6,1))) -> 0 | AO40: Euro | AP40: =AK40*AN40 -> 0
A41: 202509 | B41: 45905 | C41: MIC德国仓 | D41: =D40 -> M » N2 - 1 | E41: =E40 -> YCD-EX:HUPPER TEK | F41: =F40 -> MI202508130012 | G41: =G40 -> DE2508031-G7-MIC | H41: =H40 -> 45889 | I41: =I40 -> B076THQBHX | K41: =K40 -> 金属储物柜71英寸灰色 | M41: =M40 -> 188 | N41: =N40 -> 49 | O41: =O40 -> 14 | P41: =M41*N41*O41/1000000 -> 0.128968 | R41: =R40 -> 188 | S41: =S40 -> 49 | T41: =T40 -> 14 | U41: =R41*S41*T41/1000000 -> 0.128968 | AA41: =AA40 -> 19 | AB41: =AB40 -> 223 | AC41: =AC40 -> 223 | AD41: 0 | AE41: =AH40 -> 217 | AH41: =AE41+AF41-AG41 -> 217 | AI41: pcs | AJ41: =AH41*P41 -> 27.986056 | AK41: =AJ41 -> 27.986056 | AL41: =B41-H41+1 -> 17 | AM41: =IF(AL41<=0,"0天",IF(AL41<=30,"30天内",IF(AL41<=90,"31-90天","91天以上"))) -> 30天内 | AN41: =IF(AM41="0天",0,IF(AM41="30天内",0,IF(AM41="31-90天",0.6,1))) -> 0 | AO41: Euro | AP41: =AK41*AN41 -> 0
A42: 202509 | B42: 45906 | C42: MIC德国仓 | D42: =D41 -> M » N2 - 1 | E42: =E41 -> YCD-EX:HUPPER TEK | F42: =F41 -> MI202508130012 | G42: =G41 -> DE2508031-G7-MIC | H42: =H41 -> 45889 | I42: =I41 -> B076THQBHX | K42: =K41 -> 金属储物柜71英寸灰色 | M42: =M41 -> 188 | N42: =N41 -> 49 | O42: =O41 -> 14 | P42: =M42*N42*O42/1000000 -> 0.128968 | R42: =R41 -> 188 | S42: =S41 -> 49 | T42: =T41 -> 14 | U42: =R42*S42*T42/1000000 -> 0.128968 | AA42: =AA41 -> 19 | AB42: =AB41 -> 223 | AC42: =AC41 -> 223 | AD42: 0 | AE42: =AH41 -> 217 | AH42: =AE42+AF42-AG42 -> 217 | AI42: pcs | AJ42: =AH42*P42 -> 27.986056 | AK42: =AJ42 -> 27.986056 | AL42: =B42-H42+1 -> 18 | AM42: =IF(AL42<=0,"0天",IF(AL42<=30,"30天内",IF(AL42<=90,"31-90天","91天以上"))) -> 30天内 | AN42: =IF(AM42="0天",0,IF(AM42="30天内",0,IF(AM42="31-90天",0.6,1))) -> 0 | AO42: Euro | AP42: =AK42*AN42 -> 0
A43: 202509 | B43: 45907 | C43: MIC德国仓 | D43: =D42 -> M » N2 - 1 | E43: =E42 -> YCD-EX:HUPPER TEK | F43: =F42 -> MI202508130012 | G43: =G42 -> DE2508031-G7-MIC | H43: =H42 -> 45889 | I43: =I42 -> B076THQBHX | K43: =K42 -> 金属储物柜71英寸灰色 | M43: =M42 -> 188 | N43: =N42 -> 49 | O43: =O42 -> 14 | P43: =M43*N43*O43/1000000 -> 0.128968 | R43: =R42 -> 188 | S43: =S42 -> 49 | T43: =T42 -> 14 | U43: =R43*S43*T43/1000000 -> 0.128968 | AA43: =AA42 -> 19 | AB43: =AB42 -> 223 | AC43: =AC42 -> 223 | AD43: 0 | AE43: =AH42 -> 217 | AH43: =AE43+AF43-AG43 -> 217 | AI43: pcs | AJ43: =AH43*P43 -> 27.986056 | AK43: =AJ43 -> 27.986056 | AL43: =B43-H43+1 -> 19 | AM43: =IF(AL43<=0,"0天",IF(AL43<=30,"30天内",IF(AL43<=90,"31-90天","91天以上"))) -> 30天内 | AN43: =IF(AM43="0天",0,IF(AM43="30天内",0,IF(AM43="31-90天",0.6,1))) -> 0 | AO43: Euro | AP43: =AK43*AN43 -> 0
A44: 202509 | B44: 45908 | C44: MIC德国仓 | D44: =D43 -> M » N2 - 1 | E44: =E43 -> YCD-EX:HUPPER TEK | F44: =F43 -> MI202508130012 | G44: =G43 -> DE2508031-G7-MIC | H44: =H43 -> 45889 | I44: =I43 -> B076THQBHX | K44: =K43 -> 金属储物柜71英寸灰色 | M44: =M43 -> 188 | N44: =N43 -> 49 | O44: =O43 -> 14 | P44: =M44*N44*O44/1000000 -> 0.128968 | R44: =R43 -> 188 | S44: =S43 -> 49 | T44: =T43 -> 14 | U44: =R44*S44*T44/1000000 -> 0.128968 | AA44: =AA43 -> 19 | AB44: =AB43 -> 223 | AC44: =AC43 -> 223 | AD44: 0 | AE44: =AH43 -> 217 | AH44: =AE44+AF44-AG44 -> 217 | AI44: pcs | AJ44: =AH44*P44 -> 27.986056 | AK44: =AJ44 -> 27.986056 | AL44: =B44-H44+1 -> 20 | AM44: =IF(AL44<=0,"0天",IF(AL44<=30,"30天内",IF(AL44<=90,"31-90天","91天以上"))) -> 30天内 | AN44: =IF(AM44="0天",0,IF(AM44="30天内",0,IF(AM44="31-90天",0.6,1))) -> 0 | AO44: Euro | AP44: =AK44*AN44 -> 0
A45: 202509 | B45: 45909 | C45: MIC德国仓 | D45: =D44 -> M » N2 - 1 | E45: =E44 -> YCD-EX:HUPPER TEK | F45: =F44 -> MI202508130012 | G45: =G44 -> DE2508031-G7-MIC | H45: =H44 -> 45889 | I45: =I44 -> B076THQBHX | K45: =K44 -> 金属储物柜71英寸灰色 | M45: =M44 -> 188 | N45: =N44 -> 49 | O45: =O44 -> 14 | P45: =M45*N45*O45/1000000 -> 0.128968 | R45: =R44 -> 188 | S45: =S44 -> 49 | T45: =T44 -> 14 | U45: =R45*S45*T45/1000000 -> 0.128968 | AA45: =AA44 -> 19 | AB45: =AB44 -> 223 | AC45: =AC44 -> 223 | AD45: 0 | AE45: =AH44 -> 217 | AH45: =AE45+AF45-AG45 -> 217 | AI45: pcs | AJ45: =AH45*P45 -> 27.986056 | AK45: =AJ45 -> 27.986056 | AL45: =B45-H45+1 -> 21 | AM45: =IF(AL45<=0,"0天",IF(AL45<=30,"30天内",IF(AL45<=90,"31-90天","91天以上"))) -> 30天内 | AN45: =IF(AM45="0天",0,IF(AM45="30天内",0,IF(AM45="31-90天",0.6,1))) -> 0 | AO45: Euro | AP45: =AK45*AN45 -> 0
A46: 202509 | B46: 45910 | C46: MIC德国仓 | D46: =D45 -> M » N2 - 1 | E46: =E45 -> YCD-EX:HUPPER TEK | F46: =F45 -> MI202508130012 | G46: =G45 -> DE2508031-G7-MIC | H46: =H45 -> 45889 | I46: =I45 -> B076THQBHX | K46: =K45 -> 金属储物柜71英寸灰色 | M46: =M45 -> 188 | N46: =N45 -> 49 | O46: =O45 -> 14 | P46: =M46*N46*O46/1000000 -> 0.128968 | R46: =R45 -> 188 | S46: =S45 -> 49 | T46: =T45 -> 14 | U46: =R46*S46*T46/1000000 -> 0.128968 | AA46: =AA45 -> 19 | AB46: =AB45 -> 223 | AC46: =AC45 -> 223 | AD46: 0 | AE46: =AH45 -> 217 | AH46: =AE46+AF46-AG46 -> 217 | AI46: pcs | AJ46: =AH46*P46 -> 27.986056 | AK46: =AJ46 -> 27.986056 | AL46: =B46-H46+1 -> 22 | AM46: =IF(AL46<=0,"0天",IF(AL46<=30,"30天内",IF(AL46<=90,"31-90天","91天以上"))) -> 30天内 | AN46: =IF(AM46="0天",0,IF(AM46="30天内",0,IF(AM46="31-90天",0.6,1))) -> 0 | AO46: Euro | AP46: =AK46*AN46 -> 0
A47: 202509 | B47: 45911 | C47: MIC德国仓 | D47: =D46 -> M » N2 - 1 | E47: =E46 -> YCD-EX:HUPPER TEK | F47: =F46 -> MI202508130012 | G47: =G46 -> DE2508031-G7-MIC | H47: =H46 -> 45889 | I47: =I46 -> B076THQBHX | K47: =K46 -> 金属储物柜71英寸灰色 | M47: =M46 -> 188 | N47: =N46 -> 49 | O47: =O46 -> 14 | P47: =M47*N47*O47/1000000 -> 0.128968 | R47: =R46 -> 188 | S47: =S46 -> 49 | T47: =T46 -> 14 | U47: =R47*S47*T47/1000000 -> 0.128968 | AA47: =AA46 -> 19 | AB47: =AB46 -> 223 | AC47: =AC46 -> 223 | AD47: 0 | AE47: =AH46 -> 217 | AH47: =AE47+AF47-AG47 -> 217 | AI47: pcs | AJ47: =AH47*P47 -> 27.986056 | AK47: =AJ47 -> 27.986056 | AL47: =B47-H47+1 -> 23 | AM47: =IF(AL47<=0,"0天",IF(AL47<=30,"30天内",IF(AL47<=90,"31-90天","91天以上"))) -> 30天内 | AN47: =IF(AM47="0天",0,IF(AM47="30天内",0,IF(AM47="31-90天",0.6,1))) -> 0 | AO47: Euro | AP47: =AK47*AN47 -> 0
A48: 202509 | B48: 45912 | C48: MIC德国仓 | D48: =D47 -> M » N2 - 1 | E48: =E47 -> YCD-EX:HUPPER TEK | F48: =F47 -> MI202508130012 | G48: =G47 -> DE2508031-G7-MIC | H48: =H47 -> 45889 | I48: =I47 -> B076THQBHX | K48: =K47 -> 金属储物柜71英寸灰色 | M48: =M47 -> 188 | N48: =N47 -> 49 | O48: =O47 -> 14 | P48: =M48*N48*O48/1000000 -> 0.128968 | R48: =R47 -> 188 | S48: =S47 -> 49 | T48: =T47 -> 14 | U48: =R48*S48*T48/1000000 -> 0.128968 | AA48: =AA47 -> 19 | AB48: =AB47 -> 223 | AC48: =AC47 -> 223 | AD48: 0 | AE48: =AH47 -> 217 | AH48: =AE48+AF48-AG48 -> 217 | AI48: pcs | AJ48: =AH48*P48 -> 27.986056 | AK48: =AJ48 -> 27.986056 | AL48: =B48-H48+1 -> 24 | AM48: =IF(AL48<=0,"0天",IF(AL48<=30,"30天内",IF(AL48<=90,"31-90天","91天以上"))) -> 30天内 | AN48: =IF(AM48="0天",0,IF(AM48="30天内",0,IF(AM48="31-90天",0.6,1))) -> 0 | AO48: Euro | AP48: =AK48*AN48 -> 0
A49: 202509 | B49: 45913 | C49: MIC德国仓 | D49: =D48 -> M » N2 - 1 | E49: =E48 -> YCD-EX:HUPPER TEK | F49: =F48 -> MI202508130012 | G49: =G48 -> DE2508031-G7-MIC | H49: =H48 -> 45889 | I49: =I48 -> B076THQBHX | K49: =K48 -> 金属储物柜71英寸灰色 | M49: =M48 -> 188 | N49: =N48 -> 49 | O49: =O48 -> 14 | P49: =M49*N49*O49/1000000 -> 0.128968 | R49: =R48 -> 188 | S49: =S48 -> 49 | T49: =T48 -> 14 | U49: =R49*S49*T49/1000000 -> 0.128968 | AA49: =AA48 -> 19 | AB49: =AB48 -> 223 | AC49: =AC48 -> 223 | AD49: 0 | AE49: =AH48 -> 217 | AH49: =AE49+AF49-AG49 -> 217 | AI49: pcs | AJ49: =AH49*P49 -> 27.986056 | AK49: =AJ49 -> 27.986056 | AL49: =B49-H49+1 -> 25 | AM49: =IF(AL49<=0,"0天",IF(AL49<=30,"30天内",IF(AL49<=90,"31-90天","91天以上"))) -> 30天内 | AN49: =IF(AM49="0天",0,IF(AM49="30天内",0,IF(AM49="31-90天",0.6,1))) -> 0 | AO49: Euro | AP49: =AK49*AN49 -> 0
A50: 202509 | B50: 45914 | C50: MIC德国仓 | D50: =D49 -> M » N2 - 1 | E50: =E49 -> YCD-EX:HUPPER TEK | F50: =F49 -> MI202508130012 | G50: =G49 -> DE2508031-G7-MIC | H50: =H49 -> 45889 | I50: =I49 -> B076THQBHX | K50: =K49 -> 金属储物柜71英寸灰色 | M50: =M49 -> 188 | N50: =N49 -> 49 | O50: =O49 -> 14 | P50: =M50*N50*O50/1000000 -> 0.128968 | R50: =R49 -> 188 | S50: =S49 -> 49 | T50: =T49 -> 14 | U50: =R50*S50*T50/1000000 -> 0.128968 | AA50: =AA49 -> 19 | AB50: =AB49 -> 223 | AC50: =AC49 -> 223 | AD50: 0 | AE50: =AH49 -> 217 | AH50: =AE50+AF50-AG50 -> 217 | AI50: pcs | AJ50: =AH50*P50 -> 27.986056 | AK50: =AJ50 -> 27.986056 | AL50: =B50-H50+1 -> 26 | AM50: =IF(AL50<=0,"0天",IF(AL50<=30,"30天内",IF(AL50<=90,"31-90天","91天以上"))) -> 30天内 | AN50: =IF(AM50="0天",0,IF(AM50="30天内",0,IF(AM50="31-90天",0.6,1))) -> 0 | AO50: Euro | AP50: =AK50*AN50 -> 0
A51: 202509 | B51: 45915 | C51: MIC德国仓 | D51: =D50 -> M » N2 - 1 | E51: =E50 -> YCD-EX:HUPPER TEK | F51: =F50 -> MI202508130012 | G51: =G50 -> DE2508031-G7-MIC | H51: =H50 -> 45889 | I51: =I50 -> B076THQBHX | K51: =K50 -> 金属储物柜71英寸灰色 | M51: =M50 -> 188 | N51: =N50 -> 49 | O51: =O50 -> 14 | P51: =M51*N51*O51/1000000 -> 0.128968 | R51: =R50 -> 188 | S51: =S50 -> 49 | T51: =T50 -> 14 | U51: =R51*S51*T51/1000000 -> 0.128968 | AA51: =AA50 -> 19 | AB51: =AB50 -> 223 | AC51: =AC50 -> 223 | AD51: 0 | AE51: =AH50 -> 217 | AG51: 6 | AH51: =AE51+AF51-AG51 -> 211 | AI51: pcs | AJ51: =AH51*P51 -> 27.212248 | AK51: =AJ51 -> 27.212248 | AL51: =B51-H51+1 -> 27 | AM51: =IF(AL51<=0,"0天",IF(AL51<=30,"30天内",IF(AL51<=90,"31-90天","91天以上"))) -> 30天内 | AN51: =IF(AM51="0天",0,IF(AM51="30天内",0,IF(AM51="31-90天",0.6,1))) -> 0 | AO51: Euro | AP51: =AK51*AN51 -> 0
A52: 202509 | B52: 45916 | C52: MIC德国仓 | D52: =D51 -> M » N2 - 1 | E52: =E51 -> YCD-EX:HUPPER TEK | F52: =F51 -> MI202508130012 | G52: =G51 -> DE2508031-G7-MIC | H52: =H51 -> 45889 | I52: =I51 -> B076THQBHX | K52: =K51 -> 金属储物柜71英寸灰色 | M52: =M51 -> 188 | N52: =N51 -> 49 | O52: =O51 -> 14 | P52: =M52*N52*O52/1000000 -> 0.128968 | R52: =R51 -> 188 | S52: =S51 -> 49 | T52: =T51 -> 14 | U52: =R52*S52*T52/1000000 -> 0.128968 | AA52: =AA51 -> 19 | AB52: =AB51 -> 223 | AC52: =AC51 -> 223 | AD52: 0 | AE52: =AH51 -> 211 | AG52: 2 | AH52: =AE52+AF52-AG52 -> 209 | AI52: pcs | AJ52: =AH52*P52 -> 26.954312 | AK52: =AJ52 -> 26.954312 | AL52: =B52-H52+1 -> 28 | AM52: =IF(AL52<=0,"0天",IF(AL52<=30,"30天内",IF(AL52<=90,"31-90天","91天以上"))) -> 30天内 | AN52: =IF(AM52="0天",0,IF(AM52="30天内",0,IF(AM52="31-90天",0.6,1))) -> 0 | AO52: Euro | AP52: =AK52*AN52 -> 0
A53: 202509 | B53: 45917 | C53: MIC德国仓 | D53: =D52 -> M » N2 - 1 | E53: =E52 -> YCD-EX:HUPPER TEK | F53: =F52 -> MI202508130012 | G53: =G52 -> DE2508031-G7-MIC | H53: =H52 -> 45889 | I53: =I52 -> B076THQBHX | K53: =K52 -> 金属储物柜71英寸灰色 | M53: =M52 -> 188 | N53: =N52 -> 49 | O53: =O52 -> 14 | P53: =M53*N53*O53/1000000 -> 0.128968 | R53: =R52 -> 188 | S53: =S52 -> 49 | T53: =T52 -> 14 | U53: =R53*S53*T53/1000000 -> 0.128968 | AA53: =AA52 -> 19 | AB53: =AB52 -> 223 | AC53: =AC52 -> 223 | AD53: 0 | AE53: =AH52 -> 209 | AH53: =AE53+AF53-AG53 -> 209 | AI53: pcs | AJ53: =AH53*P53 -> 26.954312 | AK53: =AJ53 -> 26.954312 | AL53: =B53-H53+1 -> 29 | AM53: =IF(AL53<=0,"0天",IF(AL53<=30,"30天内",IF(AL53<=90,"31-90天","91天以上"))) -> 30天内 | AN53: =IF(AM53="0天",0,IF(AM53="30天内",0,IF(AM53="31-90天",0.6,1))) -> 0 | AO53: Euro | AP53: =AK53*AN53 -> 0
A54: 202509 | B54: 45918 | C54: MIC德国仓 | D54: =D53 -> M » N2 - 1 | E54: =E53 -> YCD-EX:HUPPER TEK | F54: =F53 -> MI202508130012 | G54: =G53 -> DE2508031-G7-MIC | H54: =H53 -> 45889 | I54: =I53 -> B076THQBHX | K54: =K53 -> 金属储物柜71英寸灰色 | M54: =M53 -> 188 | N54: =N53 -> 49 | O54: =O53 -> 14 | P54: =M54*N54*O54/1000000 -> 0.128968 | R54: =R53 -> 188 | S54: =S53 -> 49 | T54: =T53 -> 14 | U54: =R54*S54*T54/1000000 -> 0.128968 | AA54: =AA53 -> 19 | AB54: =AB53 -> 223 | AC54: =AC53 -> 223 | AD54: 0 | AE54: =AH53 -> 209 | AH54: =AE54+AF54-AG54 -> 209 | AI54: pcs | AJ54: =AH54*P54 -> 26.954312 | AK54: =AJ54 -> 26.954312 | AL54: =B54-H54+1 -> 30 | AM54: =IF(AL54<=0,"0天",IF(AL54<=30,"30天内",IF(AL54<=90,"31-90天","91天以上"))) -> 30天内 | AN54: =IF(AM54="0天",0,IF(AM54="30天内",0,IF(AM54="31-90天",0.6,1))) -> 0 | AO54: Euro | AP54: =AK54*AN54 -> 0
A55: 202509 | B55: 45919 | C55: MIC德国仓 | D55: =D54 -> M » N2 - 1 | E55: =E54 -> YCD-EX:HUPPER TEK | F55: =F54 -> MI202508130012 | G55: =G54 -> DE2508031-G7-MIC | H55: =H54 -> 45889 | I55: =I54 -> B076THQBHX | K55: =K54 -> 金属储物柜71英寸灰色 | M55: =M54 -> 188 | N55: =N54 -> 49 | O55: =O54 -> 14 | P55: =M55*N55*O55/1000000 -> 0.128968 | R55: =R54 -> 188 | S55: =S54 -> 49 | T55: =T54 -> 14 | U55: =R55*S55*T55/1000000 -> 0.128968 | AA55: =AA54 -> 19 | AB55: =AB54 -> 223 | AC55: =AC54 -> 223 | AD55: 0 | AE55: =AH54 -> 209 | AG55: 1 | AH55: =AE55+AF55-AG55 -> 208 | AI55: pcs | AJ55: =AH55*P55 -> 26.825344 | AK55: =AJ55 -> 26.825344 | AL55: =B55-H55+1 -> 31 | AM55: =IF(AL55<=0,"0天",IF(AL55<=30,"30天内",IF(AL55<=90,"31-90天","91天以上"))) -> 31-90天 | AN55: 0.7 | AO55: Euro | AP55: =AK55*AN55 -> 18.777741
A56: 202509 | B56: 45920 | C56: MIC德国仓 | D56: =D55 -> M » N2 - 1 | E56: =E55 -> YCD-EX:HUPPER TEK | F56: =F55 -> MI202508130012 | G56: =G55 -> DE2508031-G7-MIC | H56: =H55 -> 45889 | I56: =I55 -> B076THQBHX | K56: =K55 -> 金属储物柜71英寸灰色 | M56: =M55 -> 188 | N56: =N55 -> 49 | O56: =O55 -> 14 | P56: =M56*N56*O56/1000000 -> 0.128968 | R56: =R55 -> 188 | S56: =S55 -> 49 | T56: =T55 -> 14 | U56: =R56*S56*T56/1000000 -> 0.128968 | AA56: =AA55 -> 19 | AB56: =AB55 -> 223 | AC56: =AC55 -> 223 | AD56: 0 | AE56: =AH55 -> 208 | AH56: =AE56+AF56-AG56 -> 208 | AI56: pcs | AJ56: =AH56*P56 -> 26.825344 | AK56: =AJ56 -> 26.825344 | AL56: =B56-H56+1 -> 32 | AM56: =IF(AL56<=0,"0天",IF(AL56<=30,"30天内",IF(AL56<=90,"31-90天","91天以上"))) -> 31-90天 | AN56: 0.7 | AO56: Euro | AP56: =AK56*AN56 -> 18.777741
A57: 202509 | B57: 45921 | C57: MIC德国仓 | D57: =D56 -> M » N2 - 1 | E57: =E56 -> YCD-EX:HUPPER TEK | F57: =F56 -> MI202508130012 | G57: =G56 -> DE2508031-G7-MIC | H57: =H56 -> 45889 | I57: =I56 -> B076THQBHX | K57: =K56 -> 金属储物柜71英寸灰色 | M57: =M56 -> 188 | N57: =N56 -> 49 | O57: =O56 -> 14 | P57: =M57*N57*O57/1000000 -> 0.128968 | R57: =R56 -> 188 | S57: =S56 -> 49 | T57: =T56 -> 14 | U57: =R57*S57*T57/1000000 -> 0.128968 | AA57: =AA56 -> 19 | AB57: =AB56 -> 223 | AC57: =AC56 -> 223 | AD57: 0 | AE57: =AH56 -> 208 | AH57: =AE57+AF57-AG57 -> 208 | AI57: pcs | AJ57: =AH57*P57 -> 26.825344 | AK57: =AJ57 -> 26.825344 | AL57: =B57-H57+1 -> 33 | AM57: =IF(AL57<=0,"0天",IF(AL57<=30,"30天内",IF(AL57<=90,"31-90天","91天以上"))) -> 31-90天 | AN57: 0.7 | AO57: Euro | AP57: =AK57*AN57 -> 18.777741
A58: 202509 | B58: 45922 | C58: MIC德国仓 | D58: =D57 -> M » N2 - 1 | E58: =E57 -> YCD-EX:HUPPER TEK | F58: =F57 -> MI202508130012 | G58: =G57 -> DE2508031-G7-MIC | H58: =H57 -> 45889 | I58: =I57 -> B076THQBHX | K58: =K57 -> 金属储物柜71英寸灰色 | M58: =M57 -> 188 | N58: =N57 -> 49 | O58: =O57 -> 14 | P58: =M58*N58*O58/1000000 -> 0.128968 | R58: =R57 -> 188 | S58: =S57 -> 49 | T58: =T57 -> 14 | U58: =R58*S58*T58/1000000 -> 0.128968 | AA58: =AA57 -> 19 | AB58: =AB57 -> 223 | AC58: =AC57 -> 223 | AD58: 0 | AE58: =AH57 -> 208 | AG58: 4 | AH58: =AE58+AF58-AG58 -> 204 | AI58: pcs | AJ58: =AH58*P58 -> 26.309472 | AK58: =AJ58 -> 26.309472 | AL58: =B58-H58+1 -> 34 | AM58: =IF(AL58<=0,"0天",IF(AL58<=30,"30天内",IF(AL58<=90,"31-90天","91天以上"))) -> 31-90天 | AN58: 0.7 | AO58: Euro | AP58: =AK58*AN58 -> 18.41663
A59: 202509 | B59: 45923 | C59: MIC德国仓 | D59: =D58 -> M » N2 - 1 | E59: =E58 -> YCD-EX:HUPPER TEK | F59: =F58 -> MI202508130012 | G59: =G58 -> DE2508031-G7-MIC | H59: =H58 -> 45889 | I59: =I58 -> B076THQBHX | K59: =K58 -> 金属储物柜71英寸灰色 | M59: =M58 -> 188 | N59: =N58 -> 49 | O59: =O58 -> 14 | P59: =M59*N59*O59/1000000 -> 0.128968 | R59: =R58 -> 188 | S59: =S58 -> 49 | T59: =T58 -> 14 | U59: =R59*S59*T59/1000000 -> 0.128968 | AA59: =AA58 -> 19 | AB59: =AB58 -> 223 | AC59: =AC58 -> 223 | AD59: 0 | AE59: =AH58 -> 204 | AG59: 1 | AH59: =AE59+AF59-AG59 -> 203 | AI59: pcs | AJ59: =AH59*P59 -> 26.180504 | AK59: =AJ59 -> 26.180504 | AL59: =B59-H59+1 -> 35 | AM59: =IF(AL59<=0,"0天",IF(AL59<=30,"30天内",IF(AL59<=90,"31-90天","91天以上"))) -> 31-90天 | AN59: 0.7 | AO59: Euro | AP59: =AK59*AN59 -> 18.326353
A60: 202509 | B60: 45924 | C60: MIC德国仓 | D60: =D59 -> M » N2 - 1 | E60: =E59 -> YCD-EX:HUPPER TEK | F60: =F59 -> MI202508130012 | G60: =G59 -> DE2508031-G7-MIC | H60: =H59 -> 45889 | I60: =I59 -> B076THQBHX | K60: =K59 -> 金属储物柜71英寸灰色 | M60: =M59 -> 188 | N60: =N59 -> 49 | O60: =O59 -> 14 | P60: =M60*N60*O60/1000000 -> 0.128968 | R60: =R59 -> 188 | S60: =S59 -> 49 | T60: =T59 -> 14 | U60: =R60*S60*T60/1000000 -> 0.128968 | AA60: =AA59 -> 19 | AB60: =AB59 -> 223 | AC60: =AC59 -> 223 | AD60: 0 | AE60: =AH59 -> 203 | AH60: =AE60+AF60-AG60 -> 203 | AI60: pcs | AJ60: =AH60*P60 -> 26.180504 | AK60: =AJ60 -> 26.180504 | AL60: =B60-H60+1 -> 36 | AM60: =IF(AL60<=0,"0天",IF(AL60<=30,"30天内",IF(AL60<=90,"31-90天","91天以上"))) -> 31-90天 | AN60: 0.7 | AO60: Euro | AP60: =AK60*AN60 -> 18.326353
A61: 202509 | B61: 45925 | C61: MIC德国仓 | D61: =D60 -> M » N2 - 1 | E61: =E60 -> YCD-EX:HUPPER TEK | F61: =F60 -> MI202508130012 | G61: =G60 -> DE2508031-G7-MIC | H61: =H60 -> 45889 | I61: =I60 -> B076THQBHX | K61: =K60 -> 金属储物柜71英寸灰色 | M61: =M60 -> 188 | N61: =N60 -> 49 | O61: =O60 -> 14 | P61: =M61*N61*O61/1000000 -> 0.128968 | R61: =R60 -> 188 | S61: =S60 -> 49 | T61: =T60 -> 14 | U61: =R61*S61*T61/1000000 -> 0.128968 | AA61: =AA60 -> 19 | AB61: =AB60 -> 223 | AC61: =AC60 -> 223 | AD61: 0 | AE61: =AH60 -> 203 | AH61: =AE61+AF61-AG61 -> 203 | AI61: pcs | AJ61: =AH61*P61 -> 26.180504 | AK61: =AJ61 -> 26.180504 | AL61: =B61-H61+1 -> 37 | AM61: =IF(AL61<=0,"0天",IF(AL61<=30,"30天内",IF(AL61<=90,"31-90天","91天以上"))) -> 31-90天 | AN61: 0.7 | AO61: Euro | AP61: =AK61*AN61 -> 18.326353
A62: 202509 | B62: 45926 | C62: MIC德国仓 | D62: =D61 -> M » N2 - 1 | E62: =E61 -> YCD-EX:HUPPER TEK | F62: =F61 -> MI202508130012 | G62: =G61 -> DE2508031-G7-MIC | H62: =H61 -> 45889 | I62: =I61 -> B076THQBHX | K62: =K61 -> 金属储物柜71英寸灰色 | M62: =M61 -> 188 | N62: =N61 -> 49 | O62: =O61 -> 14 | P62: =M62*N62*O62/1000000 -> 0.128968 | R62: =R61 -> 188 | S62: =S61 -> 49 | T62: =T61 -> 14 | U62: =R62*S62*T62/1000000 -> 0.128968 | AA62: =AA61 -> 19 | AB62: =AB61 -> 223 | AC62: =AC61 -> 223 | AD62: 0 | AE62: =AH61 -> 203 | AH62: =AE62+AF62-AG62 -> 203 | AI62: pcs | AJ62: =AH62*P62 -> 26.180504 | AK62: =AJ62 -> 26.180504 | AL62: =B62-H62+1 -> 38 | AM62: =IF(AL62<=0,"0天",IF(AL62<=30,"30天内",IF(AL62<=90,"31-90天","91天以上"))) -> 31-90天 | AN62: 0.7 | AO62: Euro | AP62: =AK62*AN62 -> 18.326353
A63: 202509 | B63: 45927 | C63: MIC德国仓 | D63: =D62 -> M » N2 - 1 | E63: =E62 -> YCD-EX:HUPPER TEK | F63: =F62 -> MI202508130012 | G63: =G62 -> DE2508031-G7-MIC | H63: =H62 -> 45889 | I63: =I62 -> B076THQBHX | K63: =K62 -> 金属储物柜71英寸灰色 | M63: =M62 -> 188 | N63: =N62 -> 49 | O63: =O62 -> 14 | P63: =M63*N63*O63/1000000 -> 0.128968 | R63: =R62 -> 188 | S63: =S62 -> 49 | T63: =T62 -> 14 | U63: =R63*S63*T63/1000000 -> 0.128968 | AA63: =AA62 -> 19 | AB63: =AB62 -> 223 | AC63: =AC62 -> 223 | AD63: 0 | AE63: =AH62 -> 203 | AH63: =AE63+AF63-AG63 -> 203 | AI63: pcs | AJ63: =AH63*P63 -> 26.180504 | AK63: =AJ63 -> 26.180504 | AL63: =B63-H63+1 -> 39 | AM63: =IF(AL63<=0,"0天",IF(AL63<=30,"30天内",IF(AL63<=90,"31-90天","91天以上"))) -> 31-90天 | AN63: 0.7 | AO63: Euro | AP63: =AK63*AN63 -> 18.326353
A64: 202509 | B64: 45928 | C64: MIC德国仓 | D64: =D63 -> M » N2 - 1 | E64: =E63 -> YCD-EX:HUPPER TEK | F64: =F63 -> MI202508130012 | G64: =G63 -> DE2508031-G7-MIC | H64: =H63 -> 45889 | I64: =I63 -> B076THQBHX | K64: =K63 -> 金属储物柜71英寸灰色 | M64: =M63 -> 188 | N64: =N63 -> 49 | O64: =O63 -> 14 | P64: =M64*N64*O64/1000000 -> 0.128968 | R64: =R63 -> 188 | S64: =S63 -> 49 | T64: =T63 -> 14 | U64: =R64*S64*T64/1000000 -> 0.128968 | AA64: =AA63 -> 19 | AB64: =AB63 -> 223 | AC64: =AC63 -> 223 | AD64: 0 | AE64: =AH63 -> 203 | AH64: =AE64+AF64-AG64 -> 203 | AI64: pcs | AJ64: =AH64*P64 -> 26.180504 | AK64: =AJ64 -> 26.180504 | AL64: =B64-H64+1 -> 40 | AM64: =IF(AL64<=0,"0天",IF(AL64<=30,"30天内",IF(AL64<=90,"31-90天","91天以上"))) -> 31-90天 | AN64: 0.7 | AO64: Euro | AP64: =AK64*AN64 -> 18.326353
A65: 202509 | B65: 45929 | C65: MIC德国仓 | D65: =D64 -> M » N2 - 1 | E65: =E64 -> YCD-EX:HUPPER TEK | F65: =F64 -> MI202508130012 | G65: =G64 -> DE2508031-G7-MIC | H65: =H64 -> 45889 | I65: =I64 -> B076THQBHX | K65: =K64 -> 金属储物柜71英寸灰色 | M65: =M64 -> 188 | N65: =N64 -> 49 | O65: =O64 -> 14 | P65: =M65*N65*O65/1000000 -> 0.128968 | R65: =R64 -> 188 | S65: =S64 -> 49 | T65: =T64 -> 14 | U65: =R65*S65*T65/1000000 -> 0.128968 | AA65: =AA64 -> 19 | AB65: =AB64 -> 223 | AC65: =AC64 -> 223 | AD65: 0 | AE65: =AH64 -> 203 | AG65: 72 | AH65: =AE65+AF65-AG65 -> 131 | AI65: pcs | AJ65: =AH65*P65 -> 16.894808 | AK65: =AJ65 -> 16.894808 | AL65: =B65-H65+1 -> 41 | AM65: =IF(AL65<=0,"0天",IF(AL65<=30,"30天内",IF(AL65<=90,"31-90天","91天以上"))) -> 31-90天 | AN65: 0.7 | AO65: Euro | AP65: =AK65*AN65 -> 11.826366
A66: 202509 | B66: 45930 | C66: MIC德国仓 | D66: =D65 -> M » N2 - 1 | E66: =E65 -> YCD-EX:HUPPER TEK | F66: =F65 -> MI202508130012 | G66: =G65 -> DE2508031-G7-MIC | H66: =H65 -> 45889 | I66: =I65 -> B076THQBHX | K66: =K65 -> 金属储物柜71英寸灰色 | M66: =M65 -> 188 | N66: =N65 -> 49 | O66: =O65 -> 14 | P66: =M66*N66*O66/1000000 -> 0.128968 | R66: =R65 -> 188 | S66: =S65 -> 49 | T66: =T65 -> 14 | U66: =R66*S66*T66/1000000 -> 0.128968 | AA66: =AA65 -> 19 | AB66: =AB65 -> 223 | AC66: =AC65 -> 223 | AD66: 0 | AE66: =AH65 -> 131 | AG66: 2 | AH66: =AE66+AF66-AG66 -> 129 | AI66: pcs | AJ66: =AH66*P66 -> 16.636872 | AK66: =AJ66 -> 16.636872 | AL66: =B66-H66+1 -> 42 | AM66: =IF(AL66<=0,"0天",IF(AL66<=30,"30天内",IF(AL66<=90,"31-90天","91天以上"))) -> 31-90天 | AN66: 0.7 | AO66: Euro | AP66: =AK66*AN66 -> 11.64581
A67: 202509 | B67: 0 | C67: MIC德国仓 | D67: =D66 -> M » N2 - 1 | E67: =E66 -> YCD-EX:HUPPER TEK | F67: =F66 -> MI202508130012 | G67: =G66 -> DE2508031-G7-MIC | H67: =H66 -> 45889 | I67: =I66 -> B076THQBHX | K67: =K66 -> 金属储物柜71英寸灰色 | M67: =M66 -> 188 | N67: =N66 -> 49 | O67: =O66 -> 14 | P67: =M67*N67*O67/1000000 -> 0.128968 | R67: =R66 -> 188 | S67: =S66 -> 49 | T67: =T66 -> 14 | U67: =R67*S67*T67/1000000 -> 0.128968 | AA67: =AA66 -> 19 | AB67: =AB66 -> 223 | AC67: =AC66 -> 223 | AD67: 0 | AE67: =AH66 -> 129 | AH67: =AE67+AF67-AG67 -> 129 | AI67: pcs | AJ67: =AH67*P67 -> 16.636872 | AK67: =AJ67 -> 16.636872 | AL67: =B67-H67+1 -> -45888 | AM67: =IF(AL67<=0,"0天",IF(AL67<=30,"30天内",IF(AL67<=90,"31-90天","91天以上"))) -> 0天 | AN67: =IF(AM67="0天",0,IF(AM67="30天内",0,IF(AM67="31-90天",0.6,1))) -> 0 | AO67: Euro | AP67: =AK67*AN67 -> 0
A68: 202509 | B68: 45901 | C68: MIC德国仓 | D68: M » N2 - 1 | E68: YCD-EX:HUPPER TEK | F68: MI202508130012 | G68: DE2508031-G7-MIC | H68: 45889 | I68: B07Q3SQT6C | K68: =VLOOKUP(I68,物品明细!A:B,2,0) -> 金属储物柜71英寸高 | M68: =VLOOKUP(I68,物品明细!A:E,5,0) -> 188 | N68: =VLOOKUP(I68,物品明细!A:F,6,0) -> 49 | O68: =VLOOKUP(I68,物品明细!A:G,7,0) -> 14 | P68: =M68*N68*O68/1000000 -> 0.128968 | R68: =VLOOKUP(I68,物品明细!A:E,5,0) -> 188 | S68: =VLOOKUP(I68,物品明细!A:F,6,0) -> 49 | T68: =VLOOKUP(I68,物品明细!A:G,7,0) -> 14 | U68: =R68*S68*T68/1000000 -> 0.128968 | AA68: 13 | AB68: 151 | AC68: 151 | AD68: 0 | AE68: 151 | AH68: =AE68+AF68-AG68 -> 151 | AI68: pcs | AJ68: =AH68*P68 -> 19.474168 | AK68: =AJ68 -> 19.474168 | AL68: =B68-H68+1 -> 13 | AM68: =IF(AL68<=0,"0天",IF(AL68<=30,"30天内",IF(AL68<=90,"31-90天","91天以上"))) -> 30天内 | AN68: =IF(AM68="0天",0,IF(AM68="30天内",0,IF(AM68="31-90天",0.6,1))) -> 0 | AO68: Euro | AP68: =AK68*AN68 -> 0
A69: 202509 | B69: 45902 | C69: MIC德国仓 | D69: =D68 -> M » N2 - 1 | E69: =E68 -> YCD-EX:HUPPER TEK | F69: =F68 -> MI202508130012 | G69: =G68 -> DE2508031-G7-MIC | H69: =H68 -> 45889 | I69: =I68 -> B07Q3SQT6C | K69: =K68 -> 金属储物柜71英寸高 | M69: =M68 -> 188 | N69: =N68 -> 49 | O69: =O68 -> 14 | P69: =M69*N69*O69/1000000 -> 0.128968 | R69: =R68 -> 188 | S69: =S68 -> 49 | T69: =T68 -> 14 | U69: =R69*S69*T69/1000000 -> 0.128968 | AA69: =AA68 -> 13 | AB69: =AB68 -> 151 | AC69: =AC68 -> 151 | AD69: 0 | AE69: =AH68 -> 151 | AG69: 2 | AH69: =AE69+AF69-AG69 -> 149 | AI69: pcs | AJ69: =AH69*P69 -> 19.216232 | AK69: =AJ69 -> 19.216232 | AL69: =B69-H69+1 -> 14 | AM69: =IF(AL69<=0,"0天",IF(AL69<=30,"30天内",IF(AL69<=90,"31-90天","91天以上"))) -> 30天内 | AN69: =IF(AM69="0天",0,IF(AM69="30天内",0,IF(AM69="31-90天",0.6,1))) -> 0 | AO69: Euro | AP69: =AK69*AN69 -> 0
A70: 202509 | B70: 45903 | C70: MIC德国仓 | D70: =D69 -> M » N2 - 1 | E70: =E69 -> YCD-EX:HUPPER TEK | F70: =F69 -> MI202508130012 | G70: =G69 -> DE2508031-G7-MIC | H70: =H69 -> 45889 | I70: =I69 -> B07Q3SQT6C | K70: =K69 -> 金属储物柜71英寸高 | M70: =M69 -> 188 | N70: =N69 -> 49 | O70: =O69 -> 14 | P70: =M70*N70*O70/1000000 -> 0.128968 | R70: =R69 -> 188 | S70: =S69 -> 49 | T70: =T69 -> 14 | U70: =R70*S70*T70/1000000 -> 0.128968 | AA70: =AA69 -> 13 | AB70: =AB69 -> 151 | AC70: =AC69 -> 151 | AD70: 0 | AE70: =AH69 -> 149 | AG70: 1 | AH70: =AE70+AF70-AG70 -> 148 | AI70: pcs | AJ70: =AH70*P70 -> 19.087264 | AK70: =AJ70 -> 19.087264 | AL70: =B70-H70+1 -> 15 | AM70: =IF(AL70<=0,"0天",IF(AL70<=30,"30天内",IF(AL70<=90,"31-90天","91天以上"))) -> 30天内 | AN70: =IF(AM70="0天",0,IF(AM70="30天内",0,IF(AM70="31-90天",0.6,1))) -> 0 | AO70: Euro | AP70: =AK70*AN70 -> 0
A71: 202509 | B71: 45904 | C71: MIC德国仓 | D71: =D70 -> M » N2 - 1 | E71: =E70 -> YCD-EX:HUPPER TEK | F71: =F70 -> MI202508130012 | G71: =G70 -> DE2508031-G7-MIC | H71: =H70 -> 45889 | I71: =I70 -> B07Q3SQT6C | K71: =K70 -> 金属储物柜71英寸高 | M71: =M70 -> 188 | N71: =N70 -> 49 | O71: =O70 -> 14 | P71: =M71*N71*O71/1000000 -> 0.128968 | R71: =R70 -> 188 | S71: =S70 -> 49 | T71: =T70 -> 14 | U71: =R71*S71*T71/1000000 -> 0.128968 | AA71: =AA70 -> 13 | AB71: =AB70 -> 151 | AC71: =AC70 -> 151 | AD71: 0 | AE71: =AH70 -> 148 | AH71: =AE71+AF71-AG71 -> 148 | AI71: pcs | AJ71: =AH71*P71 -> 19.087264 | AK71: =AJ71 -> 19.087264 | AL71: =B71-H71+1 -> 16 | AM71: =IF(AL71<=0,"0天",IF(AL71<=30,"30天内",IF(AL71<=90,"31-90天","91天以上"))) -> 30天内 | AN71: =IF(AM71="0天",0,IF(AM71="30天内",0,IF(AM71="31-90天",0.6,1))) -> 0 | AO71: Euro | AP71: =AK71*AN71 -> 0
A72: 202509 | B72: 45905 | C72: MIC德国仓 | D72: =D71 -> M » N2 - 1 | E72: =E71 -> YCD-EX:HUPPER TEK | F72: =F71 -> MI202508130012 | G72: =G71 -> DE2508031-G7-MIC | H72: =H71 -> 45889 | I72: =I71 -> B07Q3SQT6C | K72: =K71 -> 金属储物柜71英寸高 | M72: =M71 -> 188 | N72: =N71 -> 49 | O72: =O71 -> 14 | P72: =M72*N72*O72/1000000 -> 0.128968 | R72: =R71 -> 188 | S72: =S71 -> 49 | T72: =T71 -> 14 | U72: =R72*S72*T72/1000000 -> 0.128968 | AA72: =AA71 -> 13 | AB72: =AB71 -> 151 | AC72: =AC71 -> 151 | AD72: 0 | AE72: =AH71 -> 148 | AH72: =AE72+AF72-AG72 -> 148 | AI72: pcs | AJ72: =AH72*P72 -> 19.087264 | AK72: =AJ72 -> 19.087264 | AL72: =B72-H72+1 -> 17 | AM72: =IF(AL72<=0,"0天",IF(AL72<=30,"30天内",IF(AL72<=90,"31-90天","91天以上"))) -> 30天内 | AN72: =IF(AM72="0天",0,IF(AM72="30天内",0,IF(AM72="31-90天",0.6,1))) -> 0 | AO72: Euro | AP72: =AK72*AN72 -> 0
A73: 202509 | B73: 45906 | C73: MIC德国仓 | D73: =D72 -> M » N2 - 1 | E73: =E72 -> YCD-EX:HUPPER TEK | F73: =F72 -> MI202508130012 | G73: =G72 -> DE2508031-G7-MIC | H73: =H72 -> 45889 | I73: =I72 -> B07Q3SQT6C | K73: =K72 -> 金属储物柜71英寸高 | M73: =M72 -> 188 | N73: =N72 -> 49 | O73: =O72 -> 14 | P73: =M73*N73*O73/1000000 -> 0.128968 | R73: =R72 -> 188 | S73: =S72 -> 49 | T73: =T72 -> 14 | U73: =R73*S73*T73/1000000 -> 0.128968 | AA73: =AA72 -> 13 | AB73: =AB72 -> 151 | AC73: =AC72 -> 151 | AD73: 0 | AE73: =AH72 -> 148 | AH73: =AE73+AF73-AG73 -> 148 | AI73: pcs | AJ73: =AH73*P73 -> 19.087264 | AK73: =AJ73 -> 19.087264 | AL73: =B73-H73+1 -> 18 | AM73: =IF(AL73<=0,"0天",IF(AL73<=30,"30天内",IF(AL73<=90,"31-90天","91天以上"))) -> 30天内 | AN73: =IF(AM73="0天",0,IF(AM73="30天内",0,IF(AM73="31-90天",0.6,1))) -> 0 | AO73: Euro | AP73: =AK73*AN73 -> 0
A74: 202509 | B74: 45907 | C74: MIC德国仓 | D74: =D73 -> M » N2 - 1 | E74: =E73 -> YCD-EX:HUPPER TEK | F74: =F73 -> MI202508130012 | G74: =G73 -> DE2508031-G7-MIC | H74: =H73 -> 45889 | I74: =I73 -> B07Q3SQT6C | K74: =K73 -> 金属储物柜71英寸高 | M74: =M73 -> 188 | N74: =N73 -> 49 | O74: =O73 -> 14 | P74: =M74*N74*O74/1000000 -> 0.128968 | R74: =R73 -> 188 | S74: =S73 -> 49 | T74: =T73 -> 14 | U74: =R74*S74*T74/1000000 -> 0.128968 | AA74: =AA73 -> 13 | AB74: =AB73 -> 151 | AC74: =AC73 -> 151 | AD74: 0 | AE74: =AH73 -> 148 | AH74: =AE74+AF74-AG74 -> 148 | AI74: pcs | AJ74: =AH74*P74 -> 19.087264 | AK74: =AJ74 -> 19.087264 | AL74: =B74-H74+1 -> 19 | AM74: =IF(AL74<=0,"0天",IF(AL74<=30,"30天内",IF(AL74<=90,"31-90天","91天以上"))) -> 30天内 | AN74: =IF(AM74="0天",0,IF(AM74="30天内",0,IF(AM74="31-90天",0.6,1))) -> 0 | AO74: Euro | AP74: =AK74*AN74 -> 0
A75: 202509 | B75: 45908 | C75: MIC德国仓 | D75: =D74 -> M » N2 - 1 | E75: =E74 -> YCD-EX:HUPPER TEK | F75: =F74 -> MI202508130012 | G75: =G74 -> DE2508031-G7-MIC | H75: =H74 -> 45889 | I75: =I74 -> B07Q3SQT6C | K75: =K74 -> 金属储物柜71英寸高 | M75: =M74 -> 188 | N75: =N74 -> 49 | O75: =O74 -> 14 | P75: =M75*N75*O75/1000000 -> 0.128968 | R75: =R74 -> 188 | S75: =S74 -> 49 | T75: =T74 -> 14 | U75: =R75*S75*T75/1000000 -> 0.128968 | AA75: =AA74 -> 13 | AB75: =AB74 -> 151 | AC75: =AC74 -> 151 | AD75: 0 | AE75: =AH74 -> 148 | AG75: 3 | AH75: =AE75+AF75-AG75 -> 145 | AI75: pcs | AJ75: =AH75*P75 -> 18.70036 | AK75: =AJ75 -> 18.70036 | AL75: =B75-H75+1 -> 20 | AM75: =IF(AL75<=0,"0天",IF(AL75<=30,"30天内",IF(AL75<=90,"31-90天","91天以上"))) -> 30天内 | AN75: =IF(AM75="0天",0,IF(AM75="30天内",0,IF(AM75="31-90天",0.6,1))) -> 0 | AO75: Euro | AP75: =AK75*AN75 -> 0
A76: 202509 | B76: 45909 | C76: MIC德国仓 | D76: =D75 -> M » N2 - 1 | E76: =E75 -> YCD-EX:HUPPER TEK | F76: =F75 -> MI202508130012 | G76: =G75 -> DE2508031-G7-MIC | H76: =H75 -> 45889 | I76: =I75 -> B07Q3SQT6C | K76: =K75 -> 金属储物柜71英寸高 | M76: =M75 -> 188 | N76: =N75 -> 49 | O76: =O75 -> 14 | P76: =M76*N76*O76/1000000 -> 0.128968 | R76: =R75 -> 188 | S76: =S75 -> 49 | T76: =T75 -> 14 | U76: =R76*S76*T76/1000000 -> 0.128968 | AA76: =AA75 -> 13 | AB76: =AB75 -> 151 | AC76: =AC75 -> 151 | AD76: 0 | AE76: =AH75 -> 145 | AH76: =AE76+AF76-AG76 -> 145 | AI76: pcs | AJ76: =AH76*P76 -> 18.70036 | AK76: =AJ76 -> 18.70036 | AL76: =B76-H76+1 -> 21 | AM76: =IF(AL76<=0,"0天",IF(AL76<=30,"30天内",IF(AL76<=90,"31-90天","91天以上"))) -> 30天内 | AN76: =IF(AM76="0天",0,IF(AM76="30天内",0,IF(AM76="31-90天",0.6,1))) -> 0 | AO76: Euro | AP76: =AK76*AN76 -> 0
A77: 202509 | B77: 45910 | C77: MIC德国仓 | D77: =D76 -> M » N2 - 1 | E77: =E76 -> YCD-EX:HUPPER TEK | F77: =F76 -> MI202508130012 | G77: =G76 -> DE2508031-G7-MIC | H77: =H76 -> 45889 | I77: =I76 -> B07Q3SQT6C | K77: =K76 -> 金属储物柜71英寸高 | M77: =M76 -> 188 | N77: =N76 -> 49 | O77: =O76 -> 14 | P77: =M77*N77*O77/1000000 -> 0.128968 | R77: =R76 -> 188 | S77: =S76 -> 49 | T77: =T76 -> 14 | U77: =R77*S77*T77/1000000 -> 0.128968 | AA77: =AA76 -> 13 | AB77: =AB76 -> 151 | AC77: =AC76 -> 151 | AD77: 0 | AE77: =AH76 -> 145 | AH77: =AE77+AF77-AG77 -> 145 | AI77: pcs | AJ77: =AH77*P77 -> 18.70036 | AK77: =AJ77 -> 18.70036 | AL77: =B77-H77+1 -> 22 | AM77: =IF(AL77<=0,"0天",IF(AL77<=30,"30天内",IF(AL77<=90,"31-90天","91天以上"))) -> 30天内 | AN77: =IF(AM77="0天",0,IF(AM77="30天内",0,IF(AM77="31-90天",0.6,1))) -> 0 | AO77: Euro | AP77: =AK77*AN77 -> 0
A78: 202509 | B78: 45911 | C78: MIC德国仓 | D78: =D77 -> M » N2 - 1 | E78: =E77 -> YCD-EX:HUPPER TEK | F78: =F77 -> MI202508130012 | G78: =G77 -> DE2508031-G7-MIC | H78: =H77 -> 45889 | I78: =I77 -> B07Q3SQT6C | K78: =K77 -> 金属储物柜71英寸高 | M78: =M77 -> 188 | N78: =N77 -> 49 | O78: =O77 -> 14 | P78: =M78*N78*O78/1000000 -> 0.128968 | R78: =R77 -> 188 | S78: =S77 -> 49 | T78: =T77 -> 14 | U78: =R78*S78*T78/1000000 -> 0.128968 | AA78: =AA77 -> 13 | AB78: =AB77 -> 151 | AC78: =AC77 -> 151 | AD78: 0 | AE78: =AH77 -> 145 | AH78: =AE78+AF78-AG78 -> 145 | AI78: pcs | AJ78: =AH78*P78 -> 18.70036 | AK78: =AJ78 -> 18.70036 | AL78: =B78-H78+1 -> 23 | AM78: =IF(AL78<=0,"0天",IF(AL78<=30,"30天内",IF(AL78<=90,"31-90天","91天以上"))) -> 30天内 | AN78: =IF(AM78="0天",0,IF(AM78="30天内",0,IF(AM78="31-90天",0.6,1))) -> 0 | AO78: Euro | AP78: =AK78*AN78 -> 0
A79: 202509 | B79: 45912 | C79: MIC德国仓 | D79: =D78 -> M » N2 - 1 | E79: =E78 -> YCD-EX:HUPPER TEK | F79: =F78 -> MI202508130012 | G79: =G78 -> DE2508031-G7-MIC | H79: =H78 -> 45889 | I79: =I78 -> B07Q3SQT6C | K79: =K78 -> 金属储物柜71英寸高 | M79: =M78 -> 188 | N79: =N78 -> 49 | O79: =O78 -> 14 | P79: =M79*N79*O79/1000000 -> 0.128968 | R79: =R78 -> 188 | S79: =S78 -> 49 | T79: =T78 -> 14 | U79: =R79*S79*T79/1000000 -> 0.128968 | AA79: =AA78 -> 13 | AB79: =AB78 -> 151 | AC79: =AC78 -> 151 | AD79: 0 | AE79: =AH78 -> 145 | AH79: =AE79+AF79-AG79 -> 145 | AI79: pcs | AJ79: =AH79*P79 -> 18.70036 | AK79: =AJ79 -> 18.70036 | AL79: =B79-H79+1 -> 24 | AM79: =IF(AL79<=0,"0天",IF(AL79<=30,"30天内",IF(AL79<=90,"31-90天","91天以上"))) -> 30天内 | AN79: =IF(AM79="0天",0,IF(AM79="30天内",0,IF(AM79="31-90天",0.6,1))) -> 0 | AO79: Euro | AP79: =AK79*AN79 -> 0
A80: 202509 | B80: 45913 | C80: MIC德国仓 | D80: =D79 -> M » N2 - 1 | E80: =E79 -> YCD-EX:HUPPER TEK | F80: =F79 -> MI202508130012 | G80: =G79 -> DE2508031-G7-MIC | H80: =H79 -> 45889 | I80: =I79 -> B07Q3SQT6C | K80: =K79 -> 金属储物柜71英寸高 | M80: =M79 -> 188 | N80: =N79 -> 49 | O80: =O79 -> 14 | P80: =M80*N80*O80/1000000 -> 0.128968 | R80: =R79 -> 188 | S80: =S79 -> 49 | T80: =T79 -> 14 | U80: =R80*S80*T80/1000000 -> 0.128968 | AA80: =AA79 -> 13 | AB80: =AB79 -> 151 | AC80: =AC79 -> 151 | AD80: 0 | AE80: =AH79 -> 145 | AH80: =AE80+AF80-AG80 -> 145 | AI80: pcs | AJ80: =AH80*P80 -> 18.70036 | AK80: =AJ80 -> 18.70036 | AL80: =B80-H80+1 -> 25 | AM80: =IF(AL80<=0,"0天",IF(AL80<=30,"30天内",IF(AL80<=90,"31-90天","91天以上"))) -> 30天内 | AN80: =IF(AM80="0天",0,IF(AM80="30天内",0,IF(AM80="31-90天",0.6,1))) -> 0 | AO80: Euro | AP80: =AK80*AN80 -> 0
A81: 202509 | B81: 45914 | C81: MIC德国仓 | D81: =D80 -> M » N2 - 1 | E81: =E80 -> YCD-EX:HUPPER TEK | F81: =F80 -> MI202508130012 | G81: =G80 -> DE2508031-G7-MIC | H81: =H80 -> 45889 | I81: =I80 -> B07Q3SQT6C | K81: =K80 -> 金属储物柜71英寸高 | M81: =M80 -> 188 | N81: =N80 -> 49 | O81: =O80 -> 14 | P81: =M81*N81*O81/1000000 -> 0.128968 | R81: =R80 -> 188 | S81: =S80 -> 49 | T81: =T80 -> 14 | U81: =R81*S81*T81/1000000 -> 0.128968 | AA81: =AA80 -> 13 | AB81: =AB80 -> 151 | AC81: =AC80 -> 151 | AD81: 0 | AE81: =AH80 -> 145 | AH81: =AE81+AF81-AG81 -> 145 | AI81: pcs | AJ81: =AH81*P81 -> 18.70036 | AK81: =AJ81 -> 18.70036 | AL81: =B81-H81+1 -> 26 | AM81: =IF(AL81<=0,"0天",IF(AL81<=30,"30天内",IF(AL81<=90,"31-90天","91天以上"))) -> 30天内 | AN81: =IF(AM81="0天",0,IF(AM81="30天内",0,IF(AM81="31-90天",0.6,1))) -> 0 | AO81: Euro | AP81: =AK81*AN81 -> 0
A82: 202509 | B82: 45915 | C82: MIC德国仓 | D82: =D81 -> M » N2 - 1 | E82: =E81 -> YCD-EX:HUPPER TEK | F82: =F81 -> MI202508130012 | G82: =G81 -> DE2508031-G7-MIC | H82: =H81 -> 45889 | I82: =I81 -> B07Q3SQT6C | K82: =K81 -> 金属储物柜71英寸高 | M82: =M81 -> 188 | N82: =N81 -> 49 | O82: =O81 -> 14 | P82: =M82*N82*O82/1000000 -> 0.128968 | R82: =R81 -> 188 | S82: =S81 -> 49 | T82: =T81 -> 14 | U82: =R82*S82*T82/1000000 -> 0.128968 | AA82: =AA81 -> 13 | AB82: =AB81 -> 151 | AC82: =AC81 -> 151 | AD82: 0 | AE82: =AH81 -> 145 | AG82: 4 | AH82: =AE82+AF82-AG82 -> 141 | AI82: pcs | AJ82: =AH82*P82 -> 18.184488 | AK82: =AJ82 -> 18.184488 | AL82: =B82-H82+1 -> 27 | AM82: =IF(AL82<=0,"0天",IF(AL82<=30,"30天内",IF(AL82<=90,"31-90天","91天以上"))) -> 30天内 | AN82: =IF(AM82="0天",0,IF(AM82="30天内",0,IF(AM82="31-90天",0.6,1))) -> 0 | AO82: Euro | AP82: =AK82*AN82 -> 0
A83: 202509 | B83: 45916 | C83: MIC德国仓 | D83: =D82 -> M » N2 - 1 | E83: =E82 -> YCD-EX:HUPPER TEK | F83: =F82 -> MI202508130012 | G83: =G82 -> DE2508031-G7-MIC | H83: =H82 -> 45889 | I83: =I82 -> B07Q3SQT6C | K83: =K82 -> 金属储物柜71英寸高 | M83: =M82 -> 188 | N83: =N82 -> 49 | O83: =O82 -> 14 | P83: =M83*N83*O83/1000000 -> 0.128968 | R83: =R82 -> 188 | S83: =S82 -> 49 | T83: =T82 -> 14 | U83: =R83*S83*T83/1000000 -> 0.128968 | AA83: =AA82 -> 13 | AB83: =AB82 -> 151 | AC83: =AC82 -> 151 | AD83: 0 | AE83: =AH82 -> 141 | AH83: =AE83+AF83-AG83 -> 141 | AI83: pcs | AJ83: =AH83*P83 -> 18.184488 | AK83: =AJ83 -> 18.184488 | AL83: =B83-H83+1 -> 28 | AM83: =IF(AL83<=0,"0天",IF(AL83<=30,"30天内",IF(AL83<=90,"31-90天","91天以上"))) -> 30天内 | AN83: =IF(AM83="0天",0,IF(AM83="30天内",0,IF(AM83="31-90天",0.6,1))) -> 0 | AO83: Euro | AP83: =AK83*AN83 -> 0
A84: 202509 | B84: 45917 | C84: MIC德国仓 | D84: =D83 -> M » N2 - 1 | E84: =E83 -> YCD-EX:HUPPER TEK | F84: =F83 -> MI202508130012 | G84: =G83 -> DE2508031-G7-MIC | H84: =H83 -> 45889 | I84: =I83 -> B07Q3SQT6C | K84: =K83 -> 金属储物柜71英寸高 | M84: =M83 -> 188 | N84: =N83 -> 49 | O84: =O83 -> 14 | P84: =M84*N84*O84/1000000 -> 0.128968 | R84: =R83 -> 188 | S84: =S83 -> 49 | T84: =T83 -> 14 | U84: =R84*S84*T84/1000000 -> 0.128968 | AA84: =AA83 -> 13 | AB84: =AB83 -> 151 | AC84: =AC83 -> 151 | AD84: 0 | AE84: =AH83 -> 141 | AH84: =AE84+AF84-AG84 -> 141 | AI84: pcs | AJ84: =AH84*P84 -> 18.184488 | AK84: =AJ84 -> 18.184488 | AL84: =B84-H84+1 -> 29 | AM84: =IF(AL84<=0,"0天",IF(AL84<=30,"30天内",IF(AL84<=90,"31-90天","91天以上"))) -> 30天内 | AN84: =IF(AM84="0天",0,IF(AM84="30天内",0,IF(AM84="31-90天",0.6,1))) -> 0 | AO84: Euro | AP84: =AK84*AN84 -> 0
A85: 202509 | B85: 45918 | C85: MIC德国仓 | D85: =D84 -> M » N2 - 1 | E85: =E84 -> YCD-EX:HUPPER TEK | F85: =F84 -> MI202508130012 | G85: =G84 -> DE2508031-G7-MIC | H85: =H84 -> 45889 | I85: =I84 -> B07Q3SQT6C | K85: =K84 -> 金属储物柜71英寸高 | M85: =M84 -> 188 | N85: =N84 -> 49 | O85: =O84 -> 14 | P85: =M85*N85*O85/1000000 -> 0.128968 | R85: =R84 -> 188 | S85: =S84 -> 49 | T85: =T84 -> 14 | U85: =R85*S85*T85/1000000 -> 0.128968 | AA85: =AA84 -> 13 | AB85: =AB84 -> 151 | AC85: =AC84 -> 151 | AD85: 0 | AE85: =AH84 -> 141 | AG85: 4 | AH85: =AE85+AF85-AG85 -> 137 | AI85: pcs | AJ85: =AH85*P85 -> 17.668616 | AK85: =AJ85 -> 17.668616 | AL85: =B85-H85+1 -> 30 | AM85: =IF(AL85<=0,"0天",IF(AL85<=30,"30天内",IF(AL85<=90,"31-90天","91天以上"))) -> 30天内 | AN85: =IF(AM85="0天",0,IF(AM85="30天内",0,IF(AM85="31-90天",0.6,1))) -> 0 | AO85: Euro | AP85: =AK85*AN85 -> 0
A86: 202509 | B86: 45919 | C86: MIC德国仓 | D86: =D85 -> M » N2 - 1 | E86: =E85 -> YCD-EX:HUPPER TEK | F86: =F85 -> MI202508130012 | G86: =G85 -> DE2508031-G7-MIC | H86: =H85 -> 45889 | I86: =I85 -> B07Q3SQT6C | K86: =K85 -> 金属储物柜71英寸高 | M86: =M85 -> 188 | N86: =N85 -> 49 | O86: =O85 -> 14 | P86: =M86*N86*O86/1000000 -> 0.128968 | R86: =R85 -> 188 | S86: =S85 -> 49 | T86: =T85 -> 14 | U86: =R86*S86*T86/1000000 -> 0.128968 | AA86: =AA85 -> 13 | AB86: =AB85 -> 151 | AC86: =AC85 -> 151 | AD86: 0 | AE86: =AH85 -> 137 | AG86: 2 | AH86: =AE86+AF86-AG86 -> 135 | AI86: pcs | AJ86: =AH86*P86 -> 17.41068 | AK86: =AJ86 -> 17.41068 | AL86: =B86-H86+1 -> 31 | AM86: =IF(AL86<=0,"0天",IF(AL86<=30,"30天内",IF(AL86<=90,"31-90天","91天以上"))) -> 31-90天 | AN86: 0.7 | AO86: Euro | AP86: =AK86*AN86 -> 12.187476
A87: 202509 | B87: 45920 | C87: MIC德国仓 | D87: =D86 -> M » N2 - 1 | E87: =E86 -> YCD-EX:HUPPER TEK | F87: =F86 -> MI202508130012 | G87: =G86 -> DE2508031-G7-MIC | H87: =H86 -> 45889 | I87: =I86 -> B07Q3SQT6C | K87: =K86 -> 金属储物柜71英寸高 | M87: =M86 -> 188 | N87: =N86 -> 49 | O87: =O86 -> 14 | P87: =M87*N87*O87/1000000 -> 0.128968 | R87: =R86 -> 188 | S87: =S86 -> 49 | T87: =T86 -> 14 | U87: =R87*S87*T87/1000000 -> 0.128968 | AA87: =AA86 -> 13 | AB87: =AB86 -> 151 | AC87: =AC86 -> 151 | AD87: 0 | AE87: =AH86 -> 135 | AH87: =AE87+AF87-AG87 -> 135 | AI87: pcs | AJ87: =AH87*P87 -> 17.41068 | AK87: =AJ87 -> 17.41068 | AL87: =B87-H87+1 -> 32 | AM87: =IF(AL87<=0,"0天",IF(AL87<=30,"30天内",IF(AL87<=90,"31-90天","91天以上"))) -> 31-90天 | AN87: 0.7 | AO87: Euro | AP87: =AK87*AN87 -> 12.187476
A88: 202509 | B88: 45921 | C88: MIC德国仓 | D88: =D87 -> M » N2 - 1 | E88: =E87 -> YCD-EX:HUPPER TEK | F88: =F87 -> MI202508130012 | G88: =G87 -> DE2508031-G7-MIC | H88: =H87 -> 45889 | I88: =I87 -> B07Q3SQT6C | K88: =K87 -> 金属储物柜71英寸高 | M88: =M87 -> 188 | N88: =N87 -> 49 | O88: =O87 -> 14 | P88: =M88*N88*O88/1000000 -> 0.128968 | R88: =R87 -> 188 | S88: =S87 -> 49 | T88: =T87 -> 14 | U88: =R88*S88*T88/1000000 -> 0.128968 | AA88: =AA87 -> 13 | AB88: =AB87 -> 151 | AC88: =AC87 -> 151 | AD88: 0 | AE88: =AH87 -> 135 | AH88: =AE88+AF88-AG88 -> 135 | AI88: pcs | AJ88: =AH88*P88 -> 17.41068 | AK88: =AJ88 -> 17.41068 | AL88: =B88-H88+1 -> 33 | AM88: =IF(AL88<=0,"0天",IF(AL88<=30,"30天内",IF(AL88<=90,"31-90天","91天以上"))) -> 31-90天 | AN88: 0.7 | AO88: Euro | AP88: =AK88*AN88 -> 12.187476
A89: 202509 | B89: 45922 | C89: MIC德国仓 | D89: =D88 -> M » N2 - 1 | E89: =E88 -> YCD-EX:HUPPER TEK | F89: =F88 -> MI202508130012 | G89: =G88 -> DE2508031-G7-MIC | H89: =H88 -> 45889 | I89: =I88 -> B07Q3SQT6C | K89: =K88 -> 金属储物柜71英寸高 | M89: =M88 -> 188 | N89: =N88 -> 49 | O89: =O88 -> 14 | P89: =M89*N89*O89/1000000 -> 0.128968 | R89: =R88 -> 188 | S89: =S88 -> 49 | T89: =T88 -> 14 | U89: =R89*S89*T89/1000000 -> 0.128968 | AA89: =AA88 -> 13 | AB89: =AB88 -> 151 | AC89: =AC88 -> 151 | AD89: 0 | AE89: =AH88 -> 135 | AG89: 2 | AH89: =AE89+AF89-AG89 -> 133 | AI89: pcs | AJ89: =AH89*P89 -> 17.152744 | AK89: =AJ89 -> 17.152744 | AL89: =B89-H89+1 -> 34 | AM89: =IF(AL89<=0,"0天",IF(AL89<=30,"30天内",IF(AL89<=90,"31-90天","91天以上"))) -> 31-90天 | AN89: 0.7 | AO89: Euro | AP89: =AK89*AN89 -> 12.006921
A90: 202509 | B90: 45923 | C90: MIC德国仓 | D90: =D89 -> M » N2 - 1 | E90: =E89 -> YCD-EX:HUPPER TEK | F90: =F89 -> MI202508130012 | G90: =G89 -> DE2508031-G7-MIC | H90: =H89 -> 45889 | I90: =I89 -> B07Q3SQT6C | K90: =K89 -> 金属储物柜71英寸高 | M90: =M89 -> 188 | N90: =N89 -> 49 | O90: =O89 -> 14 | P90: =M90*N90*O90/1000000 -> 0.128968 | R90: =R89 -> 188 | S90: =S89 -> 49 | T90: =T89 -> 14 | U90: =R90*S90*T90/1000000 -> 0.128968 | AA90: =AA89 -> 13 | AB90: =AB89 -> 151 | AC90: =AC89 -> 151 | AD90: 0 | AE90: =AH89 -> 133 | AG90: 1 | AH90: =AE90+AF90-AG90 -> 132 | AI90: pcs | AJ90: =AH90*P90 -> 17.023776 | AK90: =AJ90 -> 17.023776 | AL90: =B90-H90+1 -> 35 | AM90: =IF(AL90<=0,"0天",IF(AL90<=30,"30天内",IF(AL90<=90,"31-90天","91天以上"))) -> 31-90天 | AN90: 0.7 | AO90: Euro | AP90: =AK90*AN90 -> 11.916643
A91: 202509 | B91: 45924 | C91: MIC德国仓 | D91: =D90 -> M » N2 - 1 | E91: =E90 -> YCD-EX:HUPPER TEK | F91: =F90 -> MI202508130012 | G91: =G90 -> DE2508031-G7-MIC | H91: =H90 -> 45889 | I91: =I90 -> B07Q3SQT6C | K91: =K90 -> 金属储物柜71英寸高 | M91: =M90 -> 188 | N91: =N90 -> 49 | O91: =O90 -> 14 | P91: =M91*N91*O91/1000000 -> 0.128968 | R91: =R90 -> 188 | S91: =S90 -> 49 | T91: =T90 -> 14 | U91: =R91*S91*T91/1000000 -> 0.128968 | AA91: =AA90 -> 13 | AB91: =AB90 -> 151 | AC91: =AC90 -> 151 | AD91: 0 | AE91: =AH90 -> 132 | AG91: 4 | AH91: =AE91+AF91-AG91 -> 128 | AI91: pcs | AJ91: =AH91*P91 -> 16.507904 | AK91: =AJ91 -> 16.507904 | AL91: =B91-H91+1 -> 36 | AM91: =IF(AL91<=0,"0天",IF(AL91<=30,"30天内",IF(AL91<=90,"31-90天","91天以上"))) -> 31-90天 | AN91: 0.7 | AO91: Euro | AP91: =AK91*AN91 -> 11.555533
A92: 202509 | B92: 45925 | C92: MIC德国仓 | D92: =D91 -> M » N2 - 1 | E92: =E91 -> YCD-EX:HUPPER TEK | F92: =F91 -> MI202508130012 | G92: =G91 -> DE2508031-G7-MIC | H92: =H91 -> 45889 | I92: =I91 -> B07Q3SQT6C | K92: =K91 -> 金属储物柜71英寸高 | M92: =M91 -> 188 | N92: =N91 -> 49 | O92: =O91 -> 14 | P92: =M92*N92*O92/1000000 -> 0.128968 | R92: =R91 -> 188 | S92: =S91 -> 49 | T92: =T91 -> 14 | U92: =R92*S92*T92/1000000 -> 0.128968 | AA92: =AA91 -> 13 | AB92: =AB91 -> 151 | AC92: =AC91 -> 151 | AD92: 0 | AE92: =AH91 -> 128 | AG92: 4 | AH92: =AE92+AF92-AG92 -> 124 | AI92: pcs | AJ92: =AH92*P92 -> 15.992032 | AK92: =AJ92 -> 15.992032 | AL92: =B92-H92+1 -> 37 | AM92: =IF(AL92<=0,"0天",IF(AL92<=30,"30天内",IF(AL92<=90,"31-90天","91天以上"))) -> 31-90天 | AN92: 0.7 | AO92: Euro | AP92: =AK92*AN92 -> 11.194422
A93: 202509 | B93: 45926 | C93: MIC德国仓 | D93: =D92 -> M » N2 - 1 | E93: =E92 -> YCD-EX:HUPPER TEK | F93: =F92 -> MI202508130012 | G93: =G92 -> DE2508031-G7-MIC | H93: =H92 -> 45889 | I93: =I92 -> B07Q3SQT6C | K93: =K92 -> 金属储物柜71英寸高 | M93: =M92 -> 188 | N93: =N92 -> 49 | O93: =O92 -> 14 | P93: =M93*N93*O93/1000000 -> 0.128968 | R93: =R92 -> 188 | S93: =S92 -> 49 | T93: =T92 -> 14 | U93: =R93*S93*T93/1000000 -> 0.128968 | AA93: =AA92 -> 13 | AB93: =AB92 -> 151 | AC93: =AC92 -> 151 | AD93: 0 | AE93: =AH92 -> 124 | AG93: 2 | AH93: =AE93+AF93-AG93 -> 122 | AI93: pcs | AJ93: =AH93*P93 -> 15.734096 | AK93: =AJ93 -> 15.734096 | AL93: =B93-H93+1 -> 38 | AM93: =IF(AL93<=0,"0天",IF(AL93<=30,"30天内",IF(AL93<=90,"31-90天","91天以上"))) -> 31-90天 | AN93: 0.7 | AO93: Euro | AP93: =AK93*AN93 -> 11.013867
A94: 202509 | B94: 45927 | C94: MIC德国仓 | D94: =D93 -> M » N2 - 1 | E94: =E93 -> YCD-EX:HUPPER TEK | F94: =F93 -> MI202508130012 | G94: =G93 -> DE2508031-G7-MIC | H94: =H93 -> 45889 | I94: =I93 -> B07Q3SQT6C | K94: =K93 -> 金属储物柜71英寸高 | M94: =M93 -> 188 | N94: =N93 -> 49 | O94: =O93 -> 14 | P94: =M94*N94*O94/1000000 -> 0.128968 | R94: =R93 -> 188 | S94: =S93 -> 49 | T94: =T93 -> 14 | U94: =R94*S94*T94/1000000 -> 0.128968 | AA94: =AA93 -> 13 | AB94: =AB93 -> 151 | AC94: =AC93 -> 151 | AD94: 0 | AE94: =AH93 -> 122 | AH94: =AE94+AF94-AG94 -> 122 | AI94: pcs | AJ94: =AH94*P94 -> 15.734096 | AK94: =AJ94 -> 15.734096 | AL94: =B94-H94+1 -> 39 | AM94: =IF(AL94<=0,"0天",IF(AL94<=30,"30天内",IF(AL94<=90,"31-90天","91天以上"))) -> 31-90天 | AN94: 0.7 | AO94: Euro | AP94: =AK94*AN94 -> 11.013867
A95: 202509 | B95: 45928 | C95: MIC德国仓 | D95: =D94 -> M » N2 - 1 | E95: =E94 -> YCD-EX:HUPPER TEK | F95: =F94 -> MI202508130012 | G95: =G94 -> DE2508031-G7-MIC | H95: =H94 -> 45889 | I95: =I94 -> B07Q3SQT6C | K95: =K94 -> 金属储物柜71英寸高 | M95: =M94 -> 188 | N95: =N94 -> 49 | O95: =O94 -> 14 | P95: =M95*N95*O95/1000000 -> 0.128968 | R95: =R94 -> 188 | S95: =S94 -> 49 | T95: =T94 -> 14 | U95: =R95*S95*T95/1000000 -> 0.128968 | AA95: =AA94 -> 13 | AB95: =AB94 -> 151 | AC95: =AC94 -> 151 | AD95: 0 | AE95: =AH94 -> 122 | AH95: =AE95+AF95-AG95 -> 122 | AI95: pcs | AJ95: =AH95*P95 -> 15.734096 | AK95: =AJ95 -> 15.734096 | AL95: =B95-H95+1 -> 40 | AM95: =IF(AL95<=0,"0天",IF(AL95<=30,"30天内",IF(AL95<=90,"31-90天","91天以上"))) -> 31-90天 | AN95: 0.7 | AO95: Euro | AP95: =AK95*AN95 -> 11.013867
A96: 202509 | B96: 45929 | C96: MIC德国仓 | D96: =D95 -> M » N2 - 1 | E96: =E95 -> YCD-EX:HUPPER TEK | F96: =F95 -> MI202508130012 | G96: =G95 -> DE2508031-G7-MIC | H96: =H95 -> 45889 | I96: =I95 -> B07Q3SQT6C | K96: =K95 -> 金属储物柜71英寸高 | M96: =M95 -> 188 | N96: =N95 -> 49 | O96: =O95 -> 14 | P96: =M96*N96*O96/1000000 -> 0.128968 | R96: =R95 -> 188 | S96: =S95 -> 49 | T96: =T95 -> 14 | U96: =R96*S96*T96/1000000 -> 0.128968 | AA96: =AA95 -> 13 | AB96: =AB95 -> 151 | AC96: =AC95 -> 151 | AD96: 0 | AE96: =AH95 -> 122 | AG96: 65 | AH96: =AE96+AF96-AG96 -> 57 | AI96: pcs | AJ96: =AH96*P96 -> 7.351176 | AK96: =AJ96 -> 7.351176 | AL96: =B96-H96+1 -> 41 | AM96: =IF(AL96<=0,"0天",IF(AL96<=30,"30天内",IF(AL96<=90,"31-90天","91天以上"))) -> 31-90天 | AN96: 0.7 | AO96: Euro | AP96: =AK96*AN96 -> 5.1458232
A97: 202509 | B97: 45930 | C97: MIC德国仓 | D97: =D96 -> M » N2 - 1 | E97: =E96 -> YCD-EX:HUPPER TEK | F97: =F96 -> MI202508130012 | G97: =G96 -> DE2508031-G7-MIC | H97: =H96 -> 45889 | I97: =I96 -> B07Q3SQT6C | K97: =K96 -> 金属储物柜71英寸高 | M97: =M96 -> 188 | N97: =N96 -> 49 | O97: =O96 -> 14 | P97: =M97*N97*O97/1000000 -> 0.128968 | R97: =R96 -> 188 | S97: =S96 -> 49 | T97: =T96 -> 14 | U97: =R97*S97*T97/1000000 -> 0.128968 | AA97: =AA96 -> 13 | AB97: =AB96 -> 151 | AC97: =AC96 -> 151 | AD97: 0 | AE97: =AH96 -> 57 | AH97: =AE97+AF97-AG97 -> 57 | AI97: pcs | AJ97: =AH97*P97 -> 7.351176 | AK97: =AJ97 -> 7.351176 | AL97: =B97-H97+1 -> 42 | AM97: =IF(AL97<=0,"0天",IF(AL97<=30,"30天内",IF(AL97<=90,"31-90天","91天以上"))) -> 31-90天 | AN97: 0.7 | AO97: Euro | AP97: =AK97*AN97 -> 5.1458232
A98: 202509 | B98: 0 | C98: MIC德国仓 | D98: =D97 -> M » N2 - 1 | E98: =E97 -> YCD-EX:HUPPER TEK | F98: =F97 -> MI202508130012 | G98: =G97 -> DE2508031-G7-MIC | H98: =H97 -> 45889 | I98: =I97 -> B07Q3SQT6C | K98: =K97 -> 金属储物柜71英寸高 | M98: =M97 -> 188 | N98: =N97 -> 49 | O98: =O97 -> 14 | P98: =M98*N98*O98/1000000 -> 0.128968 | R98: =R97 -> 188 | S98: =S97 -> 49 | T98: =T97 -> 14 | U98: =R98*S98*T98/1000000 -> 0.128968 | AA98: =AA97 -> 13 | AB98: =AB97 -> 151 | AC98: =AC97 -> 151 | AD98: 0 | AE98: =AH97 -> 57 | AG98: 1 | AH98: =AE98+AF98-AG98 -> 56 | AI98: pcs | AJ98: =AH98*P98 -> 7.222208 | AK98: =AJ98 -> 7.222208 | AL98: =B98-H98+1 -> -45888 | AM98: =IF(AL98<=0,"0天",IF(AL98<=30,"30天内",IF(AL98<=90,"31-90天","91天以上"))) -> 0天 | AN98: =IF(AM98="0天",0,IF(AM98="30天内",0,IF(AM98="31-90天",0.6,1))) -> 0 | AO98: Euro | AP98: =AK98*AN98 -> 0
A99: 202509 | B99: 45901 | C99: MIC德国仓 | D99: M » N2 - 1 | E99: YCD-EX:HUPPER TEK | F99: MI202508130012 | G99: DE2508031-G7-MIC | H99: 45889 | I99: B077RVYZRF | K99: =VLOOKUP(I99,物品明细!A:B,2,0) -> 德国联邦快递金属储物柜 | M99: =VLOOKUP(I99,物品明细!A:E,5,0) -> 188 | N99: =VLOOKUP(I99,物品明细!A:F,6,0) -> 49 | O99: =VLOOKUP(I99,物品明细!A:G,7,0) -> 14 | P99: =M99*N99*O99/1000000 -> 0.128968 | R99: =VLOOKUP(I99,物品明细!A:E,5,0) -> 188 | S99: =VLOOKUP(I99,物品明细!A:F,6,0) -> 49 | T99: =VLOOKUP(I99,物品明细!A:G,7,0) -> 14 | U99: =R99*S99*T99/1000000 -> 0.128968 | AA99: 10 | AB99: 117 | AC99: 117 | AD99: 0 | AE99: 117 | AH99: =AE99+AF99-AG99 -> 117 | AI99: pcs | AJ99: =AH99*P99 -> 15.089256 | AK99: =AJ99 -> 15.089256 | AL99: =B99-H99+1 -> 13 | AM99: =IF(AL99<=0,"0天",IF(AL99<=30,"30天内",IF(AL99<=90,"31-90天","91天以上"))) -> 30天内 | AN99: =IF(AM99="0天",0,IF(AM99="30天内",0,IF(AM99="31-90天",0.6,1))) -> 0 | AO99: Euro | AP99: =AK99*AN99 -> 0
A100: 202509 | B100: 45902 | C100: MIC德国仓 | D100: =D99 -> M » N2 - 1 | E100: =E99 -> YCD-EX:HUPPER TEK | F100: =F99 -> MI202508130012 | G100: =G99 -> DE2508031-G7-MIC | H100: =H99 -> 45889 | I100: =I99 -> B077RVYZRF | K100: =K99 -> 德国联邦快递金属储物柜 | M100: =M99 -> 188 | N100: =N99 -> 49 | O100: =O99 -> 14 | P100: =M100*N100*O100/1000000 -> 0.128968 | R100: =R99 -> 188 | S100: =S99 -> 49 | T100: =T99 -> 14 | U100: =R100*S100*T100/1000000 -> 0.128968 | AA100: =AA99 -> 10 | AB100: =AB99 -> 117 | AC100: =AC99 -> 117 | AD100: 0 | AE100: =AH99 -> 117 | AH100: =AE100+AF100-AG100 -> 117 | AI100: pcs | AJ100: =AH100*P100 -> 15.089256 | AK100: =AJ100 -> 15.089256 | AL100: =B100-H100+1 -> 14 | AM100: =IF(AL100<=0,"0天",IF(AL100<=30,"30天内",IF(AL100<=90,"31-90天","91天以上"))) -> 30天内 | AN100: =IF(AM100="0天",0,IF(AM100="30天内",0,IF(AM100="31-90天",0.6,1))) -> 0 | AO100: Euro | AP100: =AK100*AN100 -> 0
...

Sheet 物品明细
A1: Item ID | B1: Name | C1: Barcode | D1: Weight | E1: Length | F1: Width | G1: Height | H1: HS Code | I1: 规格 | J1: 体积 | K1: 原始名称 | L1: 打托数
A2: B076THQBHX | B2: 金属储物柜71英寸灰色 | C2: 7434503987965 | D2: 47.4 | E2: 188 | F2: 49 | G2: 14 | I2: =E2&"x"&F2&"x"&G2 -> 188x49x14 | J2: =E2*F2*G2/1000000 -> 0.128968 | K2: Metal Storage Cabinet 71 inches Gray | L2: 12个/托
A3: B07BK8W5MF | B3: 金属储物柜71英寸银色 | C3: 7434503791791 | D3: 47.4 | E3: 188 | F3: 49 | G3: 14 | I3: =E3&"x"&F3&"x"&G3 -> 188x49x14 | J3: =E3*F3*G3/1000000 -> 0.128968 | K3: Metal Storage Cabinet 71 inches Silver | L3: 12个/托
A4: B077RVYZRF | B4: 德国联邦快递金属储物柜 | C4: 7434503188171 | D4: 47.4 | E4: 188 | F4: 49 | G4: 14 | I4: =E4&"x"&F4&"x"&G4 -> 188x49x14 | J4: =E4*F4*G4/1000000 -> 0.128968 | K4: DE - Fedmax Metal Storage Cabinet | L4: 12个/托
A5: B07Q3SQT6C | B5: 金属储物柜71英寸高 | C5: 600413399021 | D5: 47.4 | E5: 188 | F5: 49 | G5: 14 | I5: =E5&"x"&F5&"x"&G5 -> 188x49x14 | J5: =E5*F5*G5/1000000 -> 0.128968 | K5: Metal Storage Cabinet 71" Tall | L5: 12个/托
