Workbook
Name _dpx2: '[2]DHL City to Zone OB Vol'!$AF$7:$AO$45
Name _dpx2: '[4]DHL City to Zone OB Vol'!$AF$7:$AO$45

Sheet 2025年应收汇总表
A1: 对账单汇总
A2: 客户名称： | B2: 哈贝尔（HUPPER TEK)
A3: 序号 | B3: 账单日期 | C3: 充值日期 | D3: 充值金额 | E3: 账单金额 | F3: 应收总额 | G3: 备注
A4: 1 | B4: 8月账单 | E4: 1632 | F4: =D4-E4 -> -1632
A5: 2 | B5: 9月账单 | C5: 45928 | D5: =4000+2700 -> 6700 | E5: 5868.692 | F5: =F4+D5-E5 -> -800.69196
A6: 3 | B6: 10月账单 | C6: 45959 | D6: =2500+3000 -> 5500 | E6: ='对账单-汇总页'!F18 -> 5902.5777 | F6: =F5+D6-E6 -> -1203.2696
A7: 4 | F7: =F6+D7-E7 -> -1203.2696
A8: 5 | F8: =F7+D8-E8 -> -1203.2696
A9: 6 | F9: =F8+D9-E9 -> -1203.2696
A10: 7 | F10: =F9+D10-E10 -> -1203.2696
A11: 8 | F11: =F10+D11-E11 -> -1203.2696
A12: 9 | F12: =F11+D12-E12 -> -1203.2696
A13: 10 | F13: =F12+D13-E13 -> -1203.2696
A14: 11 | F14: =F13+D14-E14 -> -1203.2696
A15: 12 | F15: =F14+D15-E15 -> -1203.2696
A16: 13 | F16: =F15+D16-E16 -> -1203.2696
A17: 14 | F17: =F16+D17-E17 -> -1203.2696
A18: 15 | F18: =F17+D18-E18 -> -1203.2696
... A22: 19 | F22: =F21+D22-E22 -> -1203.2696
A23: 应收汇总： | F23: =F22+D23-E23 -> -1203.2696 | G23: 负数为欠费

Sheet 对账单-汇总页
D1: MIC Logistik GmbH对账单
A3: 客户 | B3: 哈贝尔（HUPPER TEK) | D3: 海外仓地点 | E3: 德国北威州门兴格拉德巴赫
A4: 报价生效日期 | D4: 公司邮箱 | E4: info@miclogistik.de
A5: 对账期 | B5: 2025.10.01~2025.10.31 | D5: 公司网页 | E5: www.miclogistik.de
A7: 一、服务内容及对账明细 | G7: 计费币种：欧元/Euro
A8: 业务场景 | B8: 费用项 | C8: 库内基础费用 A | D8: 运输基础费用 B | E8: 附加费 C | F8: 开票费用合计 A-B+C | G8: 备注
A9: 1. 正向 | B9: 1.1 入库 | C9: ='1.1 正向-入库'!V1 -> 70 | D9: 0 | E9: 0 | F9: =C9+D9+E9 -> 70
B10: 2.1 2B | C10: 0 | D10: 0 | E10: ='2.1 正向-2B'!BX1+'2.1 正向-2B'!CA1 -> 0 | F10: =C10+D10+E10 -> 0 | G10: 10月无2B
B11: 2.2 2C订单-GEL | C11: ='2.2 正向-2C-GEL'!AZ1 -> 573.05 | D11: ='2.2 正向-2C-GEL'!BI1 -> 3296.5742 | E11: ='2.2 正向-2C-GEL'!BR1-'2.2 正向-2C-GEL'!BI1 -> 462.8 | F11: =C11+D11+E11 -> 4332.4242
B12: 2.3 2C订单-DHL | C12: ='2.3 正向-2C-DHL'!AZ1 -> 4.8 | D12: ='2.3 正向-2C-DHL'!BF1 -> 33.14115 | E12: ='2.3 正向-2C-DHL'!BJ1 -> 123.06851 | F12: =C12+D12+E12 -> 161.00966
B13: 2.4 2C订单-PlanB | C13: 0 | D13: ='2.4 正向-2C-PlanB '!AY1 -> 264 | E13: ='2.4 正向-2C-PlanB '!BH1-'2.4 正向-2C-PlanB '!AY1 -> 0 | F13: =C13+D13+E13 -> 264
A14: 2. 仓储费 | B14: 3.1 正向仓储费(10月） | C14: ='3.1 正向-普货-仓储费 '!AP1 -> 829.10948 | D14: 0 | E14: 0 | F14: =C14+D14+E14 -> 829.10948 | G14: 每月月底统一核算
A15: 3. 逆向退货 | B15: 4.1 逆向退货费 | C15: ='4.1 逆向退货&仓租费'!AJ1 -> 19.4 | D15: ='4.1 逆向退货&仓租费'!AQ1 -> 186.2343 | E15: ='4.1 逆向退货&仓租费'!BH1 -> 40.4 | F15: =C15+D15+E15 -> 246.0343 | G15: 每月月底统一核算
B16: 4.1 逆向退货仓租费 | C16: ='4.1 逆向退货&仓租费'!BW1 -> 0 | D16: 0 | E16: ='4.1 逆向退货&仓租费'!BW1 -> 0 | F16: =C16+D16+E16 -> 0 | G16: 每月月底统一核算
A17: 4. 其他 | C17: 0 | D17: 0 | E17: 0 | F17: =C17+D17+E17 -> 0
A18: 合计 | C18: =SUM(C9:C17) -> 1496.3595 | D18: =SUM(D9:D17) -> 3779.9497 | E18: =SUM(E9:E17) -> 626.26851 | F18: =SUM(F9:F17) -> 5902.5777
A19: 截止到9月30日余额 | C19: ='2025年应收汇总表'!F5 -> -800.69196
A20: 10.9日充值 | C20: 2500
A21: 10.29日充值 | C21: 3000
A22: 截止到10月31日余额 | C22: =C21+C20+C19-F18 -> -1203.2696 | G22: 10月已欠费（建议充值）
A24: 关键说明
A25: 1. 报价： | B25: 不含德国VAT，相关的附加费具体详见每项报价说明。
A26: 2. 账号使用前提： | B26: 采用预充值+保证金的方式： 预充值：根据未来2周或1个月预测消费额提前充值，按照不同重量段及对应报价，出单时进行预扣（含退货），充值余额不足则暂停出单； 保证金：主要是应对相关异常费用，不含常规的出单基础费、附加费，具体额度按月度预充值*15%来收取。
A27: 3. 结算： | B27: 结算币种为欧元，月结，开票与预充值核销。
A28: 4. 运输保险： | B28: 建议购买，发送丢失或损毁，按商业发票金额（需含运费）赔偿；若不购买，只能按照德国道理运输法则，货物实际重量*8.33欧/kg进行赔偿，运费也不赔偿。
A29: 5. 服务时间： | B29: 若遇当地国法定节假日，导致服务商不收货，我司会提前知会客户。
A30: 6. 报价申明： | B30: 卡派运输市场价格波动大，若变化浮动超过10%，MIC提前一个月书面/邮件通知确认。
A32: 客户签章 | F32: MIC Logistik GmbH
A37: 日期： | B37: 45965 | F37: 日期： | G37: =B37 -> 45965

Sheet 1.1 正向-入库
A1: MIC德国海外仓到货&收货&入库明细表 | U1: =SUM(U4:U4) -> 70 | V1: =SUM(V4:V4) -> 70
A2: 退货信息 | R2: 卸货&收货费 | V2: 合计
A3: 任务号 | B3: 入库月份 | C3: Carrier | D3: 收货日期 | E3: 入库状态 | F3: 客户 | G3: 批次号 | H3: 批次号行数 | I3: 批次数 | J3: 类型 | K3: 物品SKU | L3: 物品描述 | M3: 物品 总数 | N3: 货位 | O3: 箱数 | P3: 托盘数 | Q3: Remark | R3: 托盘数 | S3: 箱数 | T3: 单价 | U3: 金额
A4: MI202510300003 | B4: 202510 | C4: Truck | D4: 2025-10-30 12:57:02 | E4: Inbound Completed | F4: YCD-EX:HUPPER TEK | G4: 易仓入库单号：RVABM0009-251021-0001 | K4: ABM0009-B07GSF11XX | L4: 白板 | M4: 87 | N4: M » Vir1 | O4: 87 | P4: 5 | R4: =P4 -> 5 | T4: 14 | U4: =T4*R4 -> 70 | V4: =U4+Q4 -> 70

Sheet 2.1 正向-2B
A1: MIC德国海外仓一件代发明细表 | AP1: =SUM(AP5:AP8) -> 0 | AS1: =SUM(AS5:AS8) -> 0 | AV1: =SUM(AV5:AV8) -> 0 | AY1: =SUM(AY5:AY8) -> 0 | BB1: =SUM(BB5:BB8) -> 0 | BE1: =SUM(BE5:BE8) -> 0 | BF1: =SUM(BF5:BF8) -> 0 | BO1: =SUM(BO5:BO8) -> 0 | BQ1: =SUM(BQ5:BQ8) -> 0 | BX1: =SUM(BX5:BX8) -> 0 | CA1: =SUM(CA5:CA8) -> 0 | CB1: =SUM(CB5:CB8) -> 0 | CC1: 0
A2: ,1m, | BG2: 尾程运输费 | CC2: 费用合计
A3: 出库指令 | Z3: 物品-拣料及最小包装 | AN3: 拣货&包装费 | AQ3: 拣货续件费 | AT3: 贴标费 | AW3: 包材费-包裹 | AZ3: 装车费 | BC3: 自提附加费 | BF3: 合计 | BG3: 基础费 | BP3: 续重费（超300公斤） | BR3: 附加费 | BY3: 3件包裹以上运输续件费 | CB3: 合计
A4: Order No. | B4: 订单 行数 | C4: 订单数 | D4: 对账 | E4: Warehouse | F4: 月份 | G4: Order Created At | H4: Shipped At | I4: Status | J4: Customer | K4: Original Reference | L4: Business Type | M4: Channel | N4: Creator | O4: 运单数 | P4: Priority | Q4: weight | R4: Carrier | S4: Carrier Return | T4: Shipments No1 | U4: Shipments No2 | V4: Retour No | W4: Postal Code | X4: 城市 | Y4: Country | Z4: Item ID | AA4: 物品描述 | AB4: 物品尺寸 长宽高cm | AC4: 单个物品 重量kg | AD4: Item Batch | AE4: Item Qty | AF4: 订单重量 kg | AG4: PltQty | AH4: PltDim | AI4: PltWeight | AJ4: BoxQty | AK4: BoxDim | AL4: BoxWeight | AM4: 备注 | AN4: 数量 套 | AO4: 单价 Euro | AP4: 金额 Euro | AQ4: 数量 pcs | AR4: 单价 Euro | AS4: 金额 Euro | AT4: 标签/张 | AU4: 单价 | AV4: 金额 | AW4: 数量 pcs | AX4: 单价 Euro | AY4: 金额 Euro | AZ4: 数量 /托 | BA4: 单价 Euro | BB4: 金额 Euro | BC4: 数量 /托 | BD4: 单价 Euro | BE4: 金额 Euro | BF4: 库内小计 | BG4: 数量 票 | BH4: 实际重kg | BI4: 体积重KG | BJ4: 计费 重量 kg | BK4: 邮编所属区域 | BL4: 城市 | BM4: 国家 | BN4: 单价 Euro | BO4: 金额 Euro | BP4: 单价 Euro | BQ4: 金额 Euro | BR4: 运输 订单 管理 * | BS4: 燃油 附加费 * | BT4: 过路 过桥 * | BU4: 运输 保险 | BV4: 预约 通知 * | BW4: 其它 | BX4: 附加费小计 | BY4: 包裹数 个 | BZ4: 单价 Euro | CA4: 金额 Euro | CD4: MIC回复
A9: 10月无2B订单

Sheet 2.2 正向-2C-GEL
A1: MIC德国海外仓一件代发明细表 | AM1: =SUM(AM5:AM71) -> 354.05 | AP1: =SUM(AP5:AP71) -> 0 | AS1: =SUM(AS5:AS71) -> 0 | AV1: =SUM(AV5:AV71) -> 0 | AY1: =SUM(AY5:AY71) -> 219 | AZ1: =SUM(AZ5:AZ71) -> 573.05 | BI1: =SUM(BI5:BI71) -> 3296.5742 | BN1: =SUM(BN5:BN71) -> 462.8 | BQ1: =SUM(BQ5:BQ71) -> 0 | BR1: =SUM(BR5:BR71) -> 3759.3742 | BS1: =SUM(BS5:BS71) -> 4332.7716
A2: ,1m, | BA2: 尾程运输费 | BS2: 总费用合计
A3: 出库指令 | AD3: 物品-拣料及最小包装 | AK3: 拣货&包装费 | AN3: 拣货续件费 | AQ3: 贴标费 | AT3: 包材费-包裹 | AW3: 装车费/搬运到卡车 | AZ3: 库内小计 | BA3: 基础费 | BJ3: 附加费 | BO3: 3件包裹以上运输续件费 | BR3: 尾程费用合计
A4: Order No. | B4: 订单 行数 | C4: 订单数 | D4: 对账 | E4: Warehouse | F4: 月份 | G4: Order Created At | H4: Shipped At | I4: Status | J4: Customer | K4: Original Reference | L4: Business Type | M4: Channel | N4: Creator | O4: 运单数 | P4: Priority | Q4: weight | R4: Carrier | S4: Carrier Return | T4: Shipments No1 | U4: Shipments No2 | V4: Retour No | W4: Postal Code | X4: 城市 | Y4: Country | Z4: sndZip | AA4: sndCity | AB4: sndCountry | AC4: RefOnLabel | AD4: Item ID | AE4: 物品描述 | AF4: 物品尺寸 长宽高cm | AG4: 单个物品 重量kg | AH4: Item Batch | AI4: Item Qty | AJ4: 订单重量 kg | AK4: 数量 套 | AL4: 单价 Euro | AM4: 金额 Euro | AN4: 数量 pcs | AO4: 单价 Euro | AP4: 金额 Euro | AQ4: 标签/张 | AR4: 单价 | AS4: 金额 | AT4: 数量 pcs | AU4: 单价 Euro | AV4: 金额 Euro | AW4: 托盘或散件 | AX4: 单价 Euro | AY4: 金额 Euro | BA4: 数量 票 | BB4: 实际重kg | BC4: 体积重KG | BD4: 计费 重量 kg | BE4: 邮编所属区域 | BF4: 城市 | BG4: 国家 | BH4: 单价 Euro | BI4: 金额 Euro | BJ4: 运输 订单 管理 * | BK4: 过路 过桥 * | BL4: 预约 通知 * | BM4: 其它 | BN4: 附加费小计 | BO4: 包裹数 个 | BP4: 单价 Euro | BQ4: 金额 Euro | BR4: 尾程费用合计 | BS4: 总费用合计
A5: ABM0009-251001-0002 | B5: =COUNTIF(A:A,A5) -> 1 | C5: 1 | E5: M | F5: 202510 | G5: 2025-10-01 | H5: 2025-10-01 | I5: Delivered | J5: YCD-EX:HUPPER TEK | K5: ABM0009-251001-0002 | L5: B2C | N5: qianhui.xu@miclogistik.de | O5: 1 | P5: NORMAL | Q5: 47.4 | R5: GELF-EML_HUPPERTEK | S5: RetourHermes_M | T5: 4618276352 | U5: =VLOOKUP(T5,[5]semitemu_order_export_251110144!$R:$S,2,0) -> PO-076-15674187067513743 | W5: 45699 | X5: Herten | Y5: DE | AC5: ABM0009-251001-0002 | AD5: B07BK8W5MF | AE5: 金属储物柜71英寸银色 | AF5: 188x49x14 | AG5: 47.4 | AI5: 1 | AJ5: =AI5*AG5 -> 47.4 | AK5: =AI5 -> 1 | AL5: 4.85 | AM5: =AL5*AK5 -> 4.85 | AP5: =AO5*AN5 -> 0 | AS5: =AR5*AQ5 -> 0 | AV5: =AU5*AT5 -> 0 | AW5: =O5 -> 1 | AX5: 3 | AY5: =AX5*AW5 -> 3 | AZ5: =AM5+AP5+AS5+AV5+AY5 -> 7.85 | BA5: 1 | BB5: =AJ5 -> 47.4 | BD5: 50 | BE5: =W5 -> 45699 | BF5: =X5 -> Herten | BG5: =Y5 -> DE | BH5: 46.558575 | BI5: =BH5 -> 46.558575 | BJ5: 2.5 | BK5: =0.024*BD5 -> 1.2 | BL5: 2.5 | BN5: =SUM(BJ5:BM5) -> 6.2 | BQ5: =BO5*BP5 -> 0 | BR5: =BI5+BN5+BQ5 -> 52.758575 | BS5: =AZ5+BR5 -> 60.608575
A6: ABM0009-251001-0001 | B6: =COUNTIF(A:A,A6) -> 1 | C6: 1 | E6: M | F6: 202510 | G6: 2025-10-01 | H6: 2025-10-01 | I6: Delivered | J6: YCD-EX:HUPPER TEK | K6: ABM0009-251001-0001 | L6: B2C | N6: qianhui.xu@miclogistik.de | O6: 1 | P6: NORMAL | Q6: 47.4 | R6: GELF-EML_HUPPERTEK | S6: RetourHermes_M | T6: 4618276345 | U6: =VLOOKUP(T6,[5]semitemu_order_export_251110144!$R:$S,2,0) -> PO-076-15674190083193743 | W6: 45699 | X6: Herten | Y6: DE | AC6: ABM0009-251001-0001 | AD6: B077RVYZRF | AE6: 德国联邦快递金属储物柜 | AF6: 188x49x14 | AG6: 47.4 | AI6: 1 | AJ6: =AI6*AG6 -> 47.4 | AK6: =AI6 -> 1 | AL6: 4.85 | AM6: =AL6*AK6 -> 4.85 | AP6: =AO6*AN6 -> 0 | AS6: =AR6*AQ6 -> 0 | AV6: =AU6*AT6 -> 0 | AW6: =O6 -> 1 | AX6: 3 | AY6: =AX6*AW6 -> 3 | AZ6: =AM6+AP6+AS6+AV6+AY6 -> 7.85 | BA6: 1 | BB6: =AJ6 -> 47.4 | BD6: 50 | BE6: =W6 -> 45699 | BF6: =X6 -> Herten | BG6: =Y6 -> DE | BH6: 46.558575 | BI6: =BH6 -> 46.558575 | BJ6: 2.5 | BK6: =0.024*BD6 -> 1.2 | BL6: 2.5 | BN6: =SUM(BJ6:BM6) -> 6.2 | BQ6: =BO6*BP6 -> 0 | BR6: =BI6+BN6+BQ6 -> 52.758575 | BS6: =AZ6+BR6 -> 60.608575
A7: ABM0009-251006-0003 | B7: =COUNTIF(A:A,A7) -> 1 | C7: 1 | E7: M | F7: 202510 | G7: 2025-10-06 | H7: 2025-10-06 | I7: Delivered | J7: YCD-EX:HUPPER TEK | K7: ABM0009-251006-0003 | L7: B2C | N7: qianhui.xu@miclogistik.de | O7: 1 | P7: NORMAL | Q7: 47.4 | R7: GELF-EML_HUPPERTEK | S7: RetourHermes_M | T7: 4618295421 | U7: =VLOOKUP(T7,[5]semitemu_order_export_251110144!$R:$S,2,0) -> PO-076-07335299241592215 | W7: 17033 | X7: Neubrandenburg | Y7: DE | AC7: ABM0009-251006-0003 | AD7: B07Q3SQT6C | AE7: 金属储物柜71英寸高 | AF7: 188x49x14 | AG7: 47.4 | AI7: 1 | AJ7: =AI7*AG7 -> 47.4 | AK7: =AI7 -> 1 | AL7: 4.85 | AM7: =AL7*AK7 -> 4.85 | AP7: =AO7*AN7 -> 0 | AS7: =AR7*AQ7 -> 0 | AV7: =AU7*AT7 -> 0 | AW7: =O7 -> 1 | AX7: 3 | AY7: =AX7*AW7 -> 3 | AZ7: =AM7+AP7+AS7+AV7+AY7 -> 7.85 | BA7: 1 | BB7: =AJ7 -> 47.4 | BD7: 50 | BE7: =W7 -> 17033 | BF7: =X7 -> Neubrandenburg | BG7: =Y7 -> DE | BH7: 46.558575 | BI7: =BH7 -> 46.558575 | BJ7: 2.5 | BK7: =0.024*BD7 -> 1.2 | BL7: 2.5 | BM7: 9 | BN7: =SUM(BJ7:BM7) -> 15.2 | BQ7: =BO7*BP7 -> 0 | BR7: =BI7+BN7+BQ7 -> 61.758575 | BS7: =AZ7+BR7 -> 69.608575
A8: ABM0009-251006-0002 | B8: =COUNTIF(A:A,A8) -> 1 | C8: 1 | E8: M | F8: 202510 | G8: 2025-10-06 | H8: 2025-10-06 | I8: Delivered | J8: YCD-EX:HUPPER TEK | K8: ABM0009-251006-0002 | L8: B2C | N8: qianhui.xu@miclogistik.de | O8: 1 | P8: NORMAL | Q8: 47.4 | R8: GELF-EML_HUPPERTEK | S8: RetourHermes_M | T8: 4618295414 | U8: =VLOOKUP(T8,[5]semitemu_order_export_251110144!$R:$S,2,0) -> PO-076-07375657288312516 | W8: 86169 | X8: Augsburg | Y8: DE | AC8: ABM0009-251006-0002 | AD8: B07Q3SQT6C | AE8: 金属储物柜71英寸高 | AF8: 188x49x14 | AG8: 47.4 | AI8: 1 | AJ8: =AI8*AG8 -> 47.4 | AK8: =AI8 -> 1 | AL8: 4.85 | AM8: =AL8*AK8 -> 4.85 | AP8: =AO8*AN8 -> 0 | AS8: =AR8*AQ8 -> 0 | AV8: =AU8*AT8 -> 0 | AW8: =O8 -> 1 | AX8: 3 | AY8: =AX8*AW8 -> 3 | AZ8: =AM8+AP8+AS8+AV8+AY8 -> 7.85 | BA8: 1 | BB8: =AJ8 -> 47.4 | BD8: 50 | BE8: =W8 -> 86169 | BF8: =X8 -> Augsburg | BG8: =Y8 -> DE | BH8: 46.558575 | BI8: =BH8 -> 46.558575 | BJ8: 2.5 | BK8: =0.024*BD8 -> 1.2 | BL8: 2.5 | BN8: =SUM(BJ8:BM8) -> 6.2 | BQ8: =BO8*BP8 -> 0 | BR8: =BI8+BN8+BQ8 -> 52.758575 | BS8: =AZ8+BR8 -> 60.608575
A9: ABM0009-251006-0001 | B9: =COUNTIF(A:A,A9) -> 1 | C9: 1 | E9: M | F9: 202510 | G9: 2025-10-06 | H9: 2025-10-06 | I9: Delivered | J9: YCD-EX:HUPPER TEK | K9: ABM0009-251006-0001 | L9: B2C | N9: qianhui.xu@miclogistik.de | O9: 1 | P9: NORMAL | Q9: 47.4 | R9: GELF-EML_HUPPERTEK | S9: RetourHermes_M | T9: 4618295407 | U9: =VLOOKUP(T9,[5]semitemu_order_export_251110144!$R:$S,2,0) -> PO-076-07324324385912278 | W9: 8626 | X9: Adorf/Vogtl. | Y9: DE | AC9: ABM0009-251006-0001 | AD9: B07Q3SQT6C | AE9: 金属储物柜71英寸高 | AF9: 188x49x14 | AG9: 47.4 | AI9: 1 | AJ9: =AI9*AG9 -> 47.4 | AK9: =AI9 -> 1 | AL9: 4.85 | AM9: =AL9*AK9 -> 4.85 | AP9: =AO9*AN9 -> 0 | AS9: =AR9*AQ9 -> 0 | AV9: =AU9*AT9 -> 0 | AW9: =O9 -> 1 | AX9: 3 | AY9: =AX9*AW9 -> 3 | AZ9: =AM9+AP9+AS9+AV9+AY9 -> 7.85 | BA9: 1 | BB9: =AJ9 -> 47.4 | BD9: 50 | BE9: =W9 -> 8626 | BF9: =X9 -> Adorf/Vogtl. | BG9: =Y9 -> DE | BH9: 46.558575 | BI9: =BH9 -> 46.558575 | BJ9: 2.5 | BK9: =0.024*BD9 -> 1.2 | BL9: 2.5 | BN9: =SUM(BJ9:BM9) -> 6.2 | BQ9: =BO9*BP9 -> 0 | BR9: =BI9+BN9+BQ9 -> 52.758575 | BS9: =AZ9+BR9 -> 60.608575
A10: ABM0009-251005-0005 | B10: =COUNTIF(A:A,A10) -> 1 | C10: 1 | E10: M | F10: 202510 | G10: 2025-10-06 | H10: 2025-10-06 | I10: Delivered | J10: YCD-EX:HUPPER TEK | K10: ABM0009-251005-0005 | L10: B2C | N10: qianhui.xu@miclogistik.de | O10: 1 | P10: NORMAL | Q10: 47.4 | R10: GELF-EML_HUPPERTEK | S10: RetourHermes_M | T10: 4618295391 | U10: =VLOOKUP(T10,[5]semitemu_order_export_251110144!$R:$S,2,0) -> PO-076-12849033505912372 | W10: 65618 | X10: Selters (taunus) | Y10: DE | AC10: ABM0009-251005-0005 | AD10: B07BK8W5MF | AE10: 金属储物柜71英寸银色 | AF10: 188x49x14 | AG10: 47.4 | AI10: 1 | AJ10: =AI10*AG10 -> 47.4 | AK10: =AI10 -> 1 | AL10: 4.85 | AM10: =AL10*AK10 -> 4.85 | AP10: =AO10*AN10 -> 0 | AS10: =AR10*AQ10 -> 0 | AV10: =AU10*AT10 -> 0 | AW10: =O10 -> 1 | AX10: 3 | AY10: =AX10*AW10 -> 3 | AZ10: =AM10+AP10+AS10+AV10+AY10 -> 7.85 | BA10: 1 | BB10: =AJ10 -> 47.4 | BD10: 50 | BE10: =W10 -> 65618 | BF10: =X10 -> Selters (taunus) | BG10: =Y10 -> DE | BH10: 46.558575 | BI10: =BH10 -> 46.558575 | BJ10: 2.5 | BK10: =0.024*BD10 -> 1.2 | BL10: 2.5 | BN10: =SUM(BJ10:BM10) -> 6.2 | BQ10: =BO10*BP10 -> 0 | BR10: =BI10+BN10+BQ10 -> 52.758575 | BS10: =AZ10+BR10 -> 60.608575
A11: ABM0009-251005-0004 | B11: =COUNTIF(A:A,A11) -> 1 | C11: 1 | E11: M | F11: 202510 | G11: 2025-10-06 | H11: 2025-10-06 | I11: Delivered | J11: YCD-EX:HUPPER TEK | K11: ABM0009-251005-0004 | L11: B2C | N11: qianhui.xu@miclogistik.de | O11: 1 | P11: NORMAL | Q11: 47.4 | R11: GELF-EML_HUPPERTEK | S11: RetourHermes_M | T11: 4618295384 | U11: =VLOOKUP(T11,[5]semitemu_order_export_251110144!$R:$S,2,0) -> PO-076-13025640325753368 | W11: 47226 | X11: Duisburg | Y11: DE | AC11: ABM0009-251005-0004 | AD11: B07Q3SQT6C | AE11: 金属储物柜71英寸高 | AF11: 188x49x14 | AG11: 47.4 | AI11: 1 | AJ11: =AI11*AG11 -> 47.4 | AK11: =AI11 -> 1 | AL11: 4.85 | AM11: =AL11*AK11 -> 4.85 | AP11: =AO11*AN11 -> 0 | AS11: =AR11*AQ11 -> 0 | AV11: =AU11*AT11 -> 0 | AW11: =O11 -> 1 | AX11: 3 | AY11: =AX11*AW11 -> 3 | AZ11: =AM11+AP11+AS11+AV11+AY11 -> 7.85 | BA11: 1 | BB11: =AJ11 -> 47.4 | BD11: 50 | BE11: =W11 -> 47226 | BF11: =X11 -> Duisburg | BG11: =Y11 -> DE | BH11: 46.558575 | BI11: =BH11 -> 46.558575 | BJ11: 2.5 | BK11: =0.024*BD11 -> 1.2 | BL11: 2.5 | BN11: =SUM(BJ11:BM11) -> 6.2 | BQ11: =BO11*BP11 -> 0 | BR11: =BI11+BN11+BQ11 -> 52.758575 | BS11: =AZ11+BR11 -> 60.608575
A12: ABM0009-251005-0003 | B12: =COUNTIF(A:A,A12) -> 1 | C12: 1 | E12: M | F12: 202510 | G12: 2025-10-06 | H12: 2025-10-06 | I12: Delivery Notify | J12: YCD-EX:HUPPER TEK | K12: ABM0009-251005-0003 | L12: B2C | N12: qianhui.xu@miclogistik.de | O12: 1 | P12: NORMAL | Q12: 47.4 | R12: GELF-EML_HUPPERTEK | S12: RetourHermes_M | T12: 4618295377 | U12: =VLOOKUP(T12,[5]semitemu_order_export_251110144!$R:$S,2,0) -> PO-076-12663615570551207 | W12: 10997 | X12: Berlin | Y12: DE | AC12: ABM0009-251005-0003 | AD12: B077RVYZRF | AE12: 德国联邦快递金属储物柜 | AF12: 188x49x14 | AG12: 47.4 | AI12: 1 | AJ12: =AI12*AG12 -> 47.4 | AK12: =AI12 -> 1 | AL12: 4.85 | AM12: =AL12*AK12 -> 4.85 | AP12: =AO12*AN12 -> 0 | AS12: =AR12*AQ12 -> 0 | AV12: =AU12*AT12 -> 0 | AW12: =O12 -> 1 | AX12: 3 | AY12: =AX12*AW12 -> 3 | AZ12: =AM12+AP12+AS12+AV12+AY12 -> 7.85 | BA12: 1 | BB12: =AJ12 -> 47.4 | BD12: 50 | BE12: =W12 -> 10997 | BF12: =X12 -> Berlin | BG12: =Y12 -> DE | BH12: 46.558575 | BI12: =BH12 -> 46.558575 | BJ12: 2.5 | BK12: =0.024*BD12 -> 1.2 | BL12: 2.5 | BM12: 7.8 | BN12: =SUM(BJ12:BM12) -> 14 | BQ12: =BO12*BP12 -> 0 | BR12: =BI12+BN12+BQ12 -> 60.558575 | BS12: =AZ12+BR12 -> 68.408575
A13: ABM0009-251005-0002 | B13: =COUNTIF(A:A,A13) -> 1 | C13: 1 | E13: M | F13: 202510 | G13: 2025-10-06 | H13: 2025-10-06 | I13: Delivered | J13: YCD-EX:HUPPER TEK | K13: ABM0009-251005-0002 | L13: B2C | N13: qianhui.xu@miclogistik.de | O13: 1 | P13: NORMAL | Q13: 47.4 | R13: GELF-EML_HUPPERTEK | S13: RetourHermes_M | T13: 4618295360 | U13: =VLOOKUP(T13,[5]semitemu_order_export_251110144!$R:$S,2,0) -> PO-076-12550580616311625 | W13: 78073 | X13: Bad Dürrheim | Y13: DE | AC13: ABM0009-251005-0002 | AD13: B07Q3SQT6C | AE13: 金属储物柜71英寸高 | AF13: 188x49x14 | AG13: 47.4 | AI13: 1 | AJ13: =AI13*AG13 -> 47.4 | AK13: =AI13 -> 1 | AL13: 4.85 | AM13: =AL13*AK13 -> 4.85 | AP13: =AO13*AN13 -> 0 | AS13: =AR13*AQ13 -> 0 | AV13: =AU13*AT13 -> 0 | AW13: =O13 -> 1 | AX13: 3 | AY13: =AX13*AW13 -> 3 | AZ13: =AM13+AP13+AS13+AV13+AY13 -> 7.85 | BA13: 1 | BB13: =AJ13 -> 47.4 | BD13: 50 | BE13: =W13 -> 78073 | BF13: =X13 -> Bad Dürrheim | BG13: =Y13 -> DE | BH13: 46.558575 | BI13: =BH13 -> 46.558575 | BJ13: 2.5 | BK13: =0.024*BD13 -> 1.2 | BL13: 2.5 | BN13: =SUM(BJ13:BM13) -> 6.2 | BQ13: =BO13*BP13 -> 0 | BR13: =BI13+BN13+BQ13 -> 52.758575 | BS13: =AZ13+BR13 -> 60.608575
A14: ABM0009-251005-0001 | B14: =COUNTIF(A:A,A14) -> 1 | C14: 1 | E14: M | F14: 202510 | G14: 2025-10-06 | H14: 2025-10-06 | I14: Delivered | J14: YCD-EX:HUPPER TEK | K14: ABM0009-251005-0001 | L14: B2C | N14: qianhui.xu@miclogistik.de | O14: 1 | P14: NORMAL | Q14: 47.4 | R14: GELF-EML_HUPPERTEK | S14: RetourHermes_M | T14: 4618295353 | U14: =VLOOKUP(T14,[5]semitemu_order_export_251110144!$R:$S,2,0) -> PO-076-13035591900793564 | W14: 52399 | X14: Merzenich | Y14: DE | AC14: ABM0009-251005-0001 | AD14: B076THQBHX | AE14: 金属储物柜71英寸灰色 | AF14: 188x49x14 | AG14: 47.4 | AI14: 1 | AJ14: =AI14*AG14 -> 47.4 | AK14: =AI14 -> 1 | AL14: 4.85 | AM14: =AL14*AK14 -> 4.85 | AP14: =AO14*AN14 -> 0 | AS14: =AR14*AQ14 -> 0 | AV14: =AU14*AT14 -> 0 | AW14: =O14 -> 1 | AX14: 3 | AY14: =AX14*AW14 -> 3 | AZ14: =AM14+AP14+AS14+AV14+AY14 -> 7.85 | BA14: 1 | BB14: =AJ14 -> 47.4 | BD14: 50 | BE14: =W14 -> 52399 | BF14: =X14 -> Merzenich | BG14: =Y14 -> DE | BH14: 46.558575 | BI14: =BH14 -> 46.558575 | BJ14: 2.5 | BK14: =0.024*BD14 -> 1.2 | BL14: 2.5 | BN14: =SUM(BJ14:BM14) -> 6.2 | BQ14: =BO14*BP14 -> 0 | BR14: =BI14+BN14+BQ14 -> 52.758575 | BS14: =AZ14+BR14 -> 60.608575
A15: ABM0009-251004-0002 | B15: =COUNTIF(A:A,A15) -> 1 | C15: 1 | E15: M | F15: 202510 | G15: 2025-10-06 | H15: 2025-10-06 | I15: Delivered | J15: YCD-EX:HUPPER TEK | K15: ABM0009-251004-0002 | L15: B2C | N15: qianhui.xu@miclogistik.de | O15: 1 | P15: NORMAL | Q15: 47.4 | R15: GELF-EML_HUPPERTEK | S15: RetourHermes_M | T15: 4618295346 | U15: =VLOOKUP(T15,[5]semitemu_order_export_251110144!$R:$S,2,0) -> PO-076-01386897395830548 | W15: 21073 | X15: Hamburg | Y15: DE | AC15: ABM0009-251004-0002 | AD15: B076THQBHX | AE15: 金属储物柜71英寸灰色 | AF15: 188x49x14 | AG15: 47.4 | AI15: 1 | AJ15: =AI15*AG15 -> 47.4 | AK15: =AI15 -> 1 | AL15: 4.85 | AM15: =AL15*AK15 -> 4.85 | AP15: =AO15*AN15 -> 0 | AS15: =AR15*AQ15 -> 0 | AV15: =AU15*AT15 -> 0 | AW15: =O15 -> 1 | AX15: 3 | AY15: =AX15*AW15 -> 3 | AZ15: =AM15+AP15+AS15+AV15+AY15 -> 7.85 | BA15: 1 | BB15: =AJ15 -> 47.4 | BD15: 50 | BE15: =W15 -> 21073 | BF15: =X15 -> Hamburg | BG15: =Y15 -> DE | BH15: 46.558575 | BI15: =BH15 -> 46.558575 | BJ15: 2.5 | BK15: =0.024*BD15 -> 1.2 | BL15: 2.5 | BM15: 7.8 | BN15: =SUM(BJ15:BM15) -> 14 | BQ15: =BO15*BP15 -> 0 | BR15: =BI15+BN15+BQ15 -> 60.558575 | BS15: =AZ15+BR15 -> 68.408575
A16: ABM0009-251004-0001 | B16: =COUNTIF(A:A,A16) -> 1 | C16: 1 | E16: M | F16: 202510 | G16: 2025-10-06 | H16: 2025-10-06 | I16: Delivered | J16: YCD-EX:HUPPER TEK | K16: ABM0009-251004-0001 | L16: B2C | N16: qianhui.xu@miclogistik.de | O16: 1 | P16: NORMAL | Q16: 47.4 | R16: GELF-EML_HUPPERTEK | S16: RetourHermes_M | T16: 4618295339 | U16: =VLOOKUP(T16,[5]semitemu_order_export_251110144!$R:$S,2,0) -> PO-076-01536533002870424 | W16: 37120 | X16: Bovenden | Y16: DE | AC16: ABM0009-251004-0001 | AD16: B07BK8W5MF | AE16: 金属储物柜71英寸银色 | AF16: 188x49x14 | AG16: 47.4 | AI16: 1 | AJ16: =AI16*AG16 -> 47.4 | AK16: =AI16 -> 1 | AL16: 4.85 | AM16: =AL16*AK16 -> 4.85 | AP16: =AO16*AN16 -> 0 | AS16: =AR16*AQ16 -> 0 | AV16: =AU16*AT16 -> 0 | AW16: =O16 -> 1 | AX16: 3 | AY16: =AX16*AW16 -> 3 | AZ16: =AM16+AP16+AS16+AV16+AY16 -> 7.85 | BA16: 1 | BB16: =AJ16 -> 47.4 | BD16: 50 | BE16: =W16 -> 37120 | BF16: =X16 -> Bovenden | BG16: =Y16 -> DE | BH16: 46.558575 | BI16: =BH16 -> 46.558575 | BJ16: 2.5 | BK16: =0.024*BD16 -> 1.2 | BL16: 2.5 | BN16: =SUM(BJ16:BM16) -> 6.2 | BQ16: =BO16*BP16 -> 0 | BR16: =BI16+BN16+BQ16 -> 52.758575 | BS16: =AZ16+BR16 -> 60.608575
A17: ABM0009-251002-0007 | B17: =COUNTIF(A:A,A17) -> 1 | C17: 1 | E17: M | F17: 202510 | G17: 2025-10-06 | H17: 2025-10-06 | I17: Delivered | J17: YCD-EX:HUPPER TEK | K17: ABM0009-251002-0007 | L17: B2C | N17: qianhui.xu@miclogistik.de | O17: 1 | P17: NORMAL | Q17: 47.4 | R17: GELF-EML_HUPPERTEK | S17: RetourHermes_M | T17: 4618295322 | U17: =VLOOKUP(T17,[5]semitemu_order_export_251110144!$R:$S,2,0) -> PO-076-10112202624632335 | W17: 23758 | X17: Oldenburg in Holstein | Y17: DE | AC17: ABM0009-251002-0007 | AD17: B07Q3SQT6C | AE17: 金属储物柜71英寸高 | AF17: 188x49x14 | AG17: 47.4 | AI17: 1 | AJ17: =AI17*AG17 -> 47.4 | AK17: =AI17 -> 1 | AL17: 4.85 | AM17: =AL17*AK17 -> 4.85 | AP17: =AO17*AN17 -> 0 | AS17: =AR17*AQ17 -> 0 | AV17: =AU17*AT17 -> 0 | AW17: =O17 -> 1 | AX17: 3 | AY17: =AX17*AW17 -> 3 | AZ17: =AM17+AP17+AS17+AV17+AY17 -> 7.85 | BA17: 1 | BB17: =AJ17 -> 47.4 | BD17: 50 | BE17: =W17 -> 23758 | BF17: =X17 -> Oldenburg in Holstein | BG17: =Y17 -> DE | BH17: 46.558575 | BI17: =BH17 -> 46.558575 | BJ17: 2.5 | BK17: =0.024*BD17 -> 1.2 | BL17: 2.5 | BN17: =SUM(BJ17:BM17) -> 6.2 | BQ17: =BO17*BP17 -> 0 | BR17: =BI17+BN17+BQ17 -> 52.758575 | BS17: =AZ17+BR17 -> 60.608575
A18: ABM0009-251002-0006 | B18: =COUNTIF(A:A,A18) -> 1 | C18: 1 | E18: M | F18: 202510 | G18: 2025-10-06 | H18: 2025-10-06 | I18: Delivered | J18: YCD-EX:HUPPER TEK | K18: ABM0009-251002-0006 | L18: B2C | N18: qianhui.xu@miclogistik.de | O18: 1 | P18: NORMAL | Q18: 47.4 | R18: GELF-EML_HUPPERTEK | S18: RetourHermes_M | T18: 4618295315 | U18: =VLOOKUP(T18,[5]semitemu_order_export_251110144!$R:$S,2,0) -> PO-076-10112202624632335 | W18: 23758 | X18: Oldenburg in Holstein | Y18: DE | AC18: ABM0009-251002-0006 | AD18: B07Q3SQT6C | AE18: 金属储物柜71英寸高 | AF18: 188x49x14 | AG18: 47.4 | AI18: 1 | AJ18: =AI18*AG18 -> 47.4 | AK18: =AI18 -> 1 | AL18: 4.85 | AM18: =AL18*AK18 -> 4.85 | AP18: =AO18*AN18 -> 0 | AS18: =AR18*AQ18 -> 0 | AV18: =AU18*AT18 -> 0 | AW18: =O18 -> 1 | AX18: 3 | AY18: =AX18*AW18 -> 3 | AZ18: =AM18+AP18+AS18+AV18+AY18 -> 7.85 | BA18: 1 | BB18: =AJ18 -> 47.4 | BD18: 50 | BE18: =W18 -> 23758 | BF18: =X18 -> Oldenburg in Holstein | BG18: =Y18 -> DE | BH18: 46.558575 | BI18: =BH18 -> 46.558575 | BJ18: 2.5 | BK18: =0.024*BD18 -> 1.2 | BL18: 2.5 | BN18: =SUM(BJ18:BM18) -> 6.2 | BQ18: =BO18*BP18 -> 0 | BR18: =BI18+BN18+BQ18 -> 52.758575 | BS18: =AZ18+BR18 -> 60.608575
A19: ABM0009-251002-0005 | B19: =COUNTIF(A:A,A19) -> 1 | C19: 1 | E19: M | F19: 202510 | G19: 2025-10-06 | H19: 2025-10-06 | I19: Delivered | J19: YCD-EX:HUPPER TEK | K19: ABM0009-251002-0005 | L19: B2C | N19: qianhui.xu@miclogistik.de | O19: 1 | P19: NORMAL | Q19: 47.4 | R19: GELF-EML_HUPPERTEK | S19: RetourHermes_M | T19: 4618295308 | U19: =VLOOKUP(T19,[5]semitemu_order_export_251110144!$R:$S,2,0) -> PO-076-10197391601273843 | W19: 93170 | X19: Bernhardswald | Y19: DE | AC19: ABM0009-251002-0005 | AD19: B07Q3SQT6C | AE19: 金属储物柜71英寸高 | AF19: 188x49x14 | AG19: 47.4 | AI19: 1 | AJ19: =AI19*AG19 -> 47.4 | AK19: =AI19 -> 1 | AL19: 4.85 | AM19: =AL19*AK19 -> 4.85 | AP19: =AO19*AN19 -> 0 | AS19: =AR19*AQ19 -> 0 | AV19: =AU19*AT19 -> 0 | AW19: =O19 -> 1 | AX19: 3 | AY19: =AX19*AW19 -> 3 | AZ19: =AM19+AP19+AS19+AV19+AY19 -> 7.85 | BA19: 1 | BB19: =AJ19 -> 47.4 | BD19: 50 | BE19: =W19 -> 93170 | BF19: =X19 -> Bernhardswald | BG19: =Y19 -> DE | BH19: 46.558575 | BI19: =BH19 -> 46.558575 | BJ19: 2.5 | BK19: =0.024*BD19 -> 1.2 | BL19: 2.5 | BN19: =SUM(BJ19:BM19) -> 6.2 | BQ19: =BO19*BP19 -> 0 | BR19: =BI19+BN19+BQ19 -> 52.758575 | BS19: =AZ19+BR19 -> 60.608575
A20: ABM0009-251002-0004 | B20: =COUNTIF(A:A,A20) -> 1 | C20: 1 | E20: M | F20: 202510 | G20: 2025-10-06 | H20: 2025-10-06 | I20: Delivered | J20: YCD-EX:HUPPER TEK | K20: ABM0009-251002-0004 | L20: B2C | N20: qianhui.xu@miclogistik.de | O20: 1 | P20: NORMAL | Q20: 47.4 | R20: GELF-EML_HUPPERTEK | S20: RetourHermes_M | T20: 4618295292 | U20: =VLOOKUP(T20,[5]semitemu_order_export_251110144!$R:$S,2,0) -> PO-076-10100283011192372 | W20: 65618 | X20: Selters (taunus) | Y20: DE | AC20: ABM0009-251002-0004 | AD20: B07Q3SQT6C | AE20: 金属储物柜71英寸高 | AF20: 188x49x14 | AG20: 47.4 | AI20: 1 | AJ20: =AI20*AG20 -> 47.4 | AK20: =AI20 -> 1 | AL20: 4.85 | AM20: =AL20*AK20 -> 4.85 | AP20: =AO20*AN20 -> 0 | AS20: =AR20*AQ20 -> 0 | AV20: =AU20*AT20 -> 0 | AW20: =O20 -> 1 | AX20: 3 | AY20: =AX20*AW20 -> 3 | AZ20: =AM20+AP20+AS20+AV20+AY20 -> 7.85 | BA20: 1 | BB20: =AJ20 -> 47.4 | BD20: 50 | BE20: =W20 -> 65618 | BF20: =X20 -> Selters (taunus) | BG20: =Y20 -> DE | BH20: 46.558575 | BI20: =BH20 -> 46.558575 | BJ20: 2.5 | BK20: =0.024*BD20 -> 1.2 | BL20: 2.5 | BN20: =SUM(BJ20:BM20) -> 6.2 | BQ20: =BO20*BP20 -> 0 | BR20: =BI20+BN20+BQ20 -> 52.758575 | BS20: =AZ20+BR20 -> 60.608575
A21: ABM0009-251002-0003 | B21: =COUNTIF(A:A,A21) -> 1 | C21: 1 | E21: M | F21: 202510 | G21: 2025-10-06 | H21: 2025-10-06 | I21: Delivered | J21: YCD-EX:HUPPER TEK | K21: ABM0009-251002-0003 | L21: B2C | N21: qianhui.xu@miclogistik.de | O21: 1 | P21: NORMAL | Q21: 47.4 | R21: GELF-EML_HUPPERTEK | S21: RetourHermes_M | T21: 4618295285 | U21: =VLOOKUP(T21,[5]semitemu_order_export_251110144!$R:$S,2,0) -> PO-076-09867602550392001 | W21: 37308 | X21: Bodenrode-Westhausen | Y21: DE | AC21: ABM0009-251002-0003 | AD21: B07BK8W5MF | AE21: 金属储物柜71英寸银色 | AF21: 188x49x14 | AG21: 47.4 | AI21: 1 | AJ21: =AI21*AG21 -> 47.4 | AK21: =AI21 -> 1 | AL21: 4.85 | AM21: =AL21*AK21 -> 4.85 | AP21: =AO21*AN21 -> 0 | AS21: =AR21*AQ21 -> 0 | AV21: =AU21*AT21 -> 0 | AW21: =O21 -> 1 | AX21: 3 | AY21: =AX21*AW21 -> 3 | AZ21: =AM21+AP21+AS21+AV21+AY21 -> 7.85 | BA21: 1 | BB21: =AJ21 -> 47.4 | BD21: 50 | BE21: =W21 -> 37308 | BF21: =X21 -> Bodenrode-Westhausen | BG21: =Y21 -> DE | BH21: 46.558575 | BI21: =BH21 -> 46.558575 | BJ21: 2.5 | BK21: =0.024*BD21 -> 1.2 | BL21: 2.5 | BN21: =SUM(BJ21:BM21) -> 6.2 | BQ21: =BO21*BP21 -> 0 | BR21: =BI21+BN21+BQ21 -> 52.758575 | BS21: =AZ21+BR21 -> 60.608575
A22: ABM0009-251002-0002 | B22: =COUNTIF(A:A,A22) -> 1 | C22: 1 | E22: M | F22: 202510 | G22: 2025-10-06 | H22: 2025-10-06 | I22: Delivered | J22: YCD-EX:HUPPER TEK | K22: ABM0009-251002-0002 | L22: B2C | N22: qianhui.xu@miclogistik.de | O22: 1 | P22: NORMAL | Q22: 47.4 | R22: GELF-EML_HUPPERTEK | S22: RetourHermes_M | T22: 4618295278 | U22: =VLOOKUP(T22,[5]semitemu_order_export_251110144!$R:$S,2,0) -> PO-076-10301733824633509 | W22: 97494 | X22: Bundorf | Y22: DE | AC22: ABM0009-251002-0002 | AD22: B07Q3SQT6C | AE22: 金属储物柜71英寸高 | AF22: 188x49x14 | AG22: 47.4 | AI22: 1 | AJ22: =AI22*AG22 -> 47.4 | AK22: =AI22 -> 1 | AL22: 4.85 | AM22: =AL22*AK22 -> 4.85 | AP22: =AO22*AN22 -> 0 | AS22: =AR22*AQ22 -> 0 | AV22: =AU22*AT22 -> 0 | AW22: =O22 -> 1 | AX22: 3 | AY22: =AX22*AW22 -> 3 | AZ22: =AM22+AP22+AS22+AV22+AY22 -> 7.85 | BA22: 1 | BB22: =AJ22 -> 47.4 | BD22: 50 | BE22: =W22 -> 97494 | BF22: =X22 -> Bundorf | BG22: =Y22 -> DE | BH22: 46.558575 | BI22: =BH22 -> 46.558575 | BJ22: 2.5 | BK22: =0.024*BD22 -> 1.2 | BL22: 2.5 | BN22: =SUM(BJ22:BM22) -> 6.2 | BQ22: =BO22*BP22 -> 0 | BR22: =BI22+BN22+BQ22 -> 52.758575 | BS22: =AZ22+BR22 -> 60.608575
A23: ABM0009-251002-0001 | B23: =COUNTIF(A:A,A23) -> 1 | C23: 1 | E23: M | F23: 202510 | G23: 2025-10-06 | H23: 2025-10-06 | I23: Delivered | J23: YCD-EX:HUPPER TEK | K23: ABM0009-251002-0001 | L23: B2C | N23: qianhui.xu@miclogistik.de | O23: 1 | P23: NORMAL | Q23: 47.4 | R23: GELF-EML_HUPPERTEK | S23: RetourHermes_M | T23: 4618295247 | U23: =VLOOKUP(T23,[5]semitemu_order_export_251110144!$R:$S,2,0) -> PO-076-20903654042231245 | W23: 83620 | X23: Feldkirchen-westerham | Y23: DE | AC23: ABM0009-251002-0001 | AD23: B076THQBHX | AE23: 金属储物柜71英寸灰色 | AF23: 188x49x14 | AG23: 47.4 | AI23: 1 | AJ23: =AI23*AG23 -> 47.4 | AK23: =AI23 -> 1 | AL23: 4.85 | AM23: =AL23*AK23 -> 4.85 | AP23: =AO23*AN23 -> 0 | AS23: =AR23*AQ23 -> 0 | AV23: =AU23*AT23 -> 0 | AW23: =O23 -> 1 | AX23: 3 | AY23: =AX23*AW23 -> 3 | AZ23: =AM23+AP23+AS23+AV23+AY23 -> 7.85 | BA23: 1 | BB23: =AJ23 -> 47.4 | BD23: 50 | BE23: =W23 -> 83620 | BF23: =X23 -> Feldkirchen-westerham | BG23: =Y23 -> DE | BH23: 46.558575 | BI23: =BH23 -> 46.558575 | BJ23: 2.5 | BK23: =0.024*BD23 -> 1.2 | BL23: 2.5 | BN23: =SUM(BJ23:BM23) -> 6.2 | BQ23: =BO23*BP23 -> 0 | BR23: =BI23+BN23+BQ23 -> 52.758575 | BS23: =AZ23+BR23 -> 60.608575
A24: ABM0009-251007-0002 | B24: =COUNTIF(A:A,A24) -> 1 | C24: 1 | E24: M | F24: 202510 | G24: 2025-10-07 | H24: 2025-10-07 | I24: Delivered | J24: YCD-EX:HUPPER TEK | K24: ABM0009-251007-0002 | L24: B2C | N24: qianhui.xu@miclogistik.de | O24: 1 | P24: NORMAL | Q24: 47.4 | R24: GELF-EML_HUPPERTEK | S24: RetourHermes_M | T24: 4618302853 | U24: =VLOOKUP(T24,[5]semitemu_order_export_251110144!$R:$S,2,0) -> PO-076-18114922916471963 | W24: 26871 | X24: Aschendorf | Y24: DE | AC24: ABM0009-251007-0002 | AD24: B076THQBHX | AE24: 金属储物柜71英寸灰色 | AF24: 188x49x14 | AG24: 47.4 | AI24: 1 | AJ24: =AI24*AG24 -> 47.4 | AK24: =AI24 -> 1 | AL24: 4.85 | AM24: =AL24*AK24 -> 4.85 | AP24: =AO24*AN24 -> 0 | AS24: =AR24*AQ24 -> 0 | AV24: =AU24*AT24 -> 0 | AW24: =O24 -> 1 | AX24: 3 | AY24: =AX24*AW24 -> 3 | AZ24: =AM24+AP24+AS24+AV24+AY24 -> 7.85 | BA24: 1 | BB24: =AJ24 -> 47.4 | BD24: 50 | BE24: =W24 -> 26871 | BF24: =X24 -> Aschendorf | BG24: =Y24 -> DE | BH24: 46.558575 | BI24: =BH24 -> 46.558575 | BJ24: 2.5 | BK24: =0.024*BD24 -> 1.2 | BL24: 2.5 | BN24: =SUM(BJ24:BM24) -> 6.2 | BQ24: =BO24*BP24 -> 0 | BR24: =BI24+BN24+BQ24 -> 52.758575 | BS24: =AZ24+BR24 -> 60.608575
A25: ABM0009-251007-0001 | B25: =COUNTIF(A:A,A25) -> 1 | C25: 1 | E25: M | F25: 202510 | G25: 2025-10-07 | H25: 2025-10-07 | I25: Delivered | J25: YCD-EX:HUPPER TEK | K25: ABM0009-251007-0001 | L25: B2C | N25: qianhui.xu@miclogistik.de | O25: 1 | P25: NORMAL | Q25: 47.4 | R25: GELF-EML_HUPPERTEK | S25: RetourHermes_M | T25: 4618302846 | U25: =VLOOKUP(T25,[5]semitemu_order_export_251110144!$R:$S,2,0) -> PO-076-18438716672633873 | W25: 85375 | X25: Neufahrn b. Freising | Y25: DE | AC25: ABM0009-251007-0001 | AD25: B07Q3SQT6C | AE25: 金属储物柜71英寸高 | AF25: 188x49x14 | AG25: 47.4 | AI25: 1 | AJ25: =AI25*AG25 -> 47.4 | AK25: =AI25 -> 1 | AL25: 4.85 | AM25: =AL25*AK25 -> 4.85 | AP25: =AO25*AN25 -> 0 | AS25: =AR25*AQ25 -> 0 | AV25: =AU25*AT25 -> 0 | AW25: =O25 -> 1 | AX25: 3 | AY25: =AX25*AW25 -> 3 | AZ25: =AM25+AP25+AS25+AV25+AY25 -> 7.85 | BA25: 1 | BB25: =AJ25 -> 47.4 | BD25: 50 | BE25: =W25 -> 85375 | BF25: =X25 -> Neufahrn b. Freising | BG25: =Y25 -> DE | BH25: 46.558575 | BI25: =BH25 -> 46.558575 | BJ25: 2.5 | BK25: =0.024*BD25 -> 1.2 | BL25: 2.5 | BN25: =SUM(BJ25:BM25) -> 6.2 | BQ25: =BO25*BP25 -> 0 | BR25: =BI25+BN25+BQ25 -> 52.758575 | BS25: =AZ25+BR25 -> 60.608575
A26: ABM0009-251008-0003 | B26: =COUNTIF(A:A,A26) -> 1 | C26: 1 | E26: M | F26: 202510 | G26: 2025-10-08 | H26: 2025-10-08 | I26: Delivered | J26: YCD-EX:HUPPER TEK | K26: ABM0009-251008-0003 | L26: B2C | N26: qianhui.xu@miclogistik.de | O26: 1 | P26: NORMAL | Q26: 47.4 | R26: GELF-EML_HUPPERTEK | S26: RetourHermes_M | T26: 4618317444 | U26: =VLOOKUP(T26,[5]semitemu_order_export_251110144!$R:$S,2,0) -> PO-076-03898465820792218 | W26: 45145 | X26: Essen | Y26: DE | AC26: ABM0009-251008-0003 | AD26: B07Q3SQT6C | AE26: 金属储物柜71英寸高 | AF26: 188x49x14 | AG26: 47.4 | AI26: 1 | AJ26: =AI26*AG26 -> 47.4 | AK26: =AI26 -> 1 | AL26: 4.85 | AM26: =AL26*AK26 -> 4.85 | AP26: =AO26*AN26 -> 0 | AS26: =AR26*AQ26 -> 0 | AV26: =AU26*AT26 -> 0 | AW26: =O26 -> 1 | AX26: 3 | AY26: =AX26*AW26 -> 3 | AZ26: =AM26+AP26+AS26+AV26+AY26 -> 7.85 | BA26: 1 | BB26: =AJ26 -> 47.4 | BD26: 50 | BE26: =W26 -> 45145 | BF26: =X26 -> Essen | BG26: =Y26 -> DE | BH26: 46.558575 | BI26: =BH26 -> 46.558575 | BJ26: 2.5 | BK26: =0.024*BD26 -> 1.2 | BL26: 2.5 | BN26: =SUM(BJ26:BM26) -> 6.2 | BQ26: =BO26*BP26 -> 0 | BR26: =BI26+BN26+BQ26 -> 52.758575 | BS26: =AZ26+BR26 -> 60.608575
A27: ABM0009-251008-0002 | B27: =COUNTIF(A:A,A27) -> 1 | C27: 1 | E27: M | F27: 202510 | G27: 2025-10-08 | H27: 2025-10-08 | I27: Delivered | J27: YCD-EX:HUPPER TEK | K27: ABM0009-251008-0002 | L27: B2C | N27: qianhui.xu@miclogistik.de | O27: 1 | P27: NORMAL | Q27: 47.4 | R27: GELF-EML_HUPPERTEK | S27: RetourHermes_M | T27: 4618317437 | U27: =VLOOKUP(T27,[5]semitemu_order_export_251110144!$R:$S,2,0) -> PO-076-03898465820792218 | W27: 45145 | X27: Essen | Y27: DE | AC27: ABM0009-251008-0002 | AD27: B07Q3SQT6C | AE27: 金属储物柜71英寸高 | AF27: 188x49x14 | AG27: 47.4 | AI27: 1 | AJ27: =AI27*AG27 -> 47.4 | AK27: =AI27 -> 1 | AL27: 4.85 | AM27: =AL27*AK27 -> 4.85 | AP27: =AO27*AN27 -> 0 | AS27: =AR27*AQ27 -> 0 | AV27: =AU27*AT27 -> 0 | AW27: =O27 -> 1 | AX27: 3 | AY27: =AX27*AW27 -> 3 | AZ27: =AM27+AP27+AS27+AV27+AY27 -> 7.85 | BA27: 1 | BB27: =AJ27 -> 47.4 | BD27: 50 | BE27: =W27 -> 45145 | BF27: =X27 -> Essen | BG27: =Y27 -> DE | BH27: 46.558575 | BI27: =BH27 -> 46.558575 | BJ27: 2.5 | BK27: =0.024*BD27 -> 1.2 | BL27: 2.5 | BN27: =SUM(BJ27:BM27) -> 6.2 | BQ27: =BO27*BP27 -> 0 | BR27: =BI27+BN27+BQ27 -> 52.758575 | BS27: =AZ27+BR27 -> 60.608575
... A35: ABM0009-251013-0002 | B35: =COUNTIF(A:A,A35) -> 1 | C35: 1 | E35: M | F35: 202510 | G35: 2025-10-13 | H35: 2025-10-13 | I35: Delivered | J35: YCD-EX:HUPPER TEK | K35: ABM0009-251013-0002 | L35: B2C | N35: qianhui.xu@miclogistik.de | O35: 1 | P35: NORMAL | Q35: 47.4 | R35: GELF-EML_HUPPERTEK | S35: RetourHermes_M | T35: 4618357204 | U35: =VLOOKUP(T35,[5]semitemu_order_export_251110144!$R:$S,2,0) -> PO-076-11763896474230904 | W35: 61130 | X35: Nidderau | Y35: DE | AC35: ABM0009-251013-0002 | AD35: B07Q3SQT6C | AE35: 金属储物柜71英寸高 | AF35: 188x49x14 | AG35: 47.4 | AI35: 1 | AJ35: =AI35*AG35 -> 47.4 | AK35: =AI35 -> 1 | AL35: 4.85 | AM35: =AL35*AK35 -> 4.85 | AP35: =AO35*AN35 -> 0 | AS35: =AR35*AQ35 -> 0 | AV35: =AU35*AT35 -> 0 | AW35: =O35 -> 1 | AX35: 3 | AY35: =AX35*AW35 -> 3 | AZ35: =AM35+AP35+AS35+AV35+AY35 -> 7.85 | BA35: 1 | BB35: =AJ35 -> 47.4 | BD35: 50 | BE35: =W35 -> 61130 | BF35: =X35 -> Nidderau | BG35: =Y35 -> DE | BH35: 46.558575 | BI35: =BH35 -> 46.558575 | BJ35: 2.5 | BK35: =0.024*BD35 -> 1.2 | BL35: 2.5 | BN35: =SUM(BJ35:BM35) -> 6.2 | BQ35: =BO35*BP35 -> 0 | BR35: =BI35+BN35+BQ35 -> 52.758575 | BS35: =AZ35+BR35 -> 60.608575
A36: ABM0009-251013-0001 | B36: =COUNTIF(A:A,A36) -> 1 | C36: 1 | E36: M | F36: 202510 | G36: 2025-10-13 | H36: 2025-10-13 | I36: Delivered | J36: YCD-EX:HUPPER TEK | K36: ABM0009-251013-0001 | L36: B2C | N36: qianhui.xu@miclogistik.de | O36: 1 | P36: NORMAL | Q36: 47.4 | R36: GELF-EML_HUPPERTEK | S36: RetourHermes_M | T36: 4618357198 | U36: =VLOOKUP(T36,[6]ebay_order_export_251110145132!$S:$T,2,0) -> 14-13687-11781 | W36: 23569 | X36: Lübeck | Y36: DE | AC36: ABM0009-251013-0001 | AD36: B07Q3SQT6C | AE36: 金属储物柜71英寸高 | AF36: 188x49x14 | AG36: 47.4 | AI36: 1 | AJ36: =AI36*AG36 -> 47.4 | AK36: =AI36 -> 1 | AL36: 4.85 | AM36: =AL36*AK36 -> 4.85 | AP36: =AO36*AN36 -> 0 | AS36: =AR36*AQ36 -> 0 | AV36: =AU36*AT36 -> 0 | AW36: =O36 -> 1 | AX36: 3 | AY36: =AX36*AW36 -> 3 | AZ36: =AM36+AP36+AS36+AV36+AY36 -> 7.85 | BA36: 1 | BB36: =AJ36 -> 47.4 | BD36: 50 | BE36: =W36 -> 23569 | BF36: =X36 -> Lübeck | BG36: =Y36 -> DE | BH36: 46.558575 | BI36: =BH36 -> 46.558575 | BJ36: 2.5 | BK36: =0.024*BD36 -> 1.2 | BL36: 2.5 | BN36: =SUM(BJ36:BM36) -> 6.2 | BQ36: =BO36*BP36 -> 0 | BR36: =BI36+BN36+BQ36 -> 52.758575 | BS36: =AZ36+BR36 -> 60.608575
A37: ABM0009-251011-0002 | B37: =COUNTIF(A:A,A37) -> 1 | C37: 1 | E37: M | F37: 202510 | G37: 2025-10-13 | H37: 2025-10-13 | I37: Delivered | J37: YCD-EX:HUPPER TEK | K37: ABM0009-251011-0002 | L37: B2C | N37: qianhui.xu@miclogistik.de | O37: 1 | P37: NORMAL | Q37: 47.4 | R37: GELF-EML_HUPPERTEK | S37: RetourHermes_M | T37: 4618357181 | U37: =VLOOKUP(T37,[5]semitemu_order_export_251110144!$R:$S,2,0) -> PO-076-20612291739513460 | W37: 23843 | X37: Bad Oldesloe | Y37: DE | AC37: ABM0009-251011-0002 | AD37: B07Q3SQT6C | AE37: 金属储物柜71英寸高 | AF37: 188x49x14 | AG37: 47.4 | AI37: 1 | AJ37: =AI37*AG37 -> 47.4 | AK37: =AI37 -> 1 | AL37: 4.85 | AM37: =AL37*AK37 -> 4.85 | AP37: =AO37*AN37 -> 0 | AS37: =AR37*AQ37 -> 0 | AV37: =AU37*AT37 -> 0 | AW37: =O37 -> 1 | AX37: 3 | AY37: =AX37*AW37 -> 3 | AZ37: =AM37+AP37+AS37+AV37+AY37 -> 7.85 | BA37: 1 | BB37: =AJ37 -> 47.4 | BD37: 50 | BE37: =W37 -> 23843 | BF37: =X37 -> Bad Oldesloe | BG37: =Y37 -> DE | BH37: 46.558575 | BI37: =BH37 -> 46.558575 | BJ37: 2.5 | BK37: =0.024*BD37 -> 1.2 | BL37: 2.5 | BN37: =SUM(BJ37:BM37) -> 6.2 | BQ37: =BO37*BP37 -> 0 | BR37: =BI37+BN37+BQ37 -> 52.758575 | BS37: =AZ37+BR37 -> 60.608575
A38: ABM0009-251011-0001 | B38: =COUNTIF(A:A,A38) -> 1 | C38: 1 | E38: M | F38: 202510 | G38: 2025-10-13 | H38: 2025-10-13 | I38: Delivered | J38: YCD-EX:HUPPER TEK | K38: ABM0009-251011-0001 | L38: B2C | N38: qianhui.xu@miclogistik.de | O38: 1 | P38: NORMAL | Q38: 47.4 | R38: GELF-EML_HUPPERTEK | S38: RetourHermes_M | T38: 4618357174 | U38: =VLOOKUP(T38,[5]semitemu_order_export_251110144!$R:$S,2,0) -> PO-076-20612291739513460 | W38: 23843 | X38: Bad Oldesloe | Y38: DE | AC38: ABM0009-251011-0001 | AD38: B07Q3SQT6C | AE38: 金属储物柜71英寸高 | AF38: 188x49x14 | AG38: 47.4 | AI38: 1 | AJ38: =AI38*AG38 -> 47.4 | AK38: =AI38 -> 1 | AL38: 4.85 | AM38: =AL38*AK38 -> 4.85 | AP38: =AO38*AN38 -> 0 | AS38: =AR38*AQ38 -> 0 | AV38: =AU38*AT38 -> 0 | AW38: =O38 -> 1 | AX38: 3 | AY38: =AX38*AW38 -> 3 | AZ38: =AM38+AP38+AS38+AV38+AY38 -> 7.85 | BA38: 1 | BB38: =AJ38 -> 47.4 | BD38: 50 | BE38: =W38 -> 23843 | BF38: =X38 -> Bad Oldesloe | BG38: =Y38 -> DE | BH38: 46.558575 | BI38: =BH38 -> 46.558575 | BJ38: 2.5 | BK38: =0.024*BD38 -> 1.2 | BL38: 2.5 | BN38: =SUM(BJ38:BM38) -> 6.2 | BQ38: =BO38*BP38 -> 0 | BR38: =BI38+BN38+BQ38 -> 52.758575 | BS38: =AZ38+BR38 -> 60.608575
A39: ABM0009-251014-0002 | B39: =COUNTIF(A:A,A39) -> 1 | C39: 1 | E39: M | F39: 202510 | G39: 2025-10-14 | H39: 2025-10-14 | I39: Delivered | J39: YCD-EX:HUPPER TEK | K39: ABM0009-251014-0002 | L39: B2C | N39: qianhui.xu@miclogistik.de | O39: 1 | P39: NORMAL | Q39: 47.4 | R39: GELF-EML_HUPPERTEK | S39: RetourHermes_M | T39: 4618363328 | U39: =VLOOKUP(T39,[5]semitemu_order_export_251110144!$R:$S,2,0) -> PO-076-06372173758071587 | W39: 73079 | X39: Süßen | Y39: DE | AC39: ABM0009-251014-0002 | AD39: B07Q3SQT6C | AE39: 金属储物柜71英寸高 | AF39: 188x49x14 | AG39: 47.4 | AI39: 1 | AJ39: =AI39*AG39 -> 47.4 | AK39: =AI39 -> 1 | AL39: 4.85 | AM39: =AL39*AK39 -> 4.85 | AP39: =AO39*AN39 -> 0 | AS39: =AR39*AQ39 -> 0 | AV39: =AU39*AT39 -> 0 | AW39: =O39 -> 1 | AX39: 3 | AY39: =AX39*AW39 -> 3 | AZ39: =AM39+AP39+AS39+AV39+AY39 -> 7.85 | BA39: 1 | BB39: =AJ39 -> 47.4 | BD39: 50 | BE39: =W39 -> 73079 | BF39: =X39 -> Süßen | BG39: =Y39 -> DE | BH39: 46.558575 | BI39: =BH39 -> 46.558575 | BJ39: 2.5 | BK39: =0.024*BD39 -> 1.2 | BL39: 2.5 | BN39: =SUM(BJ39:BM39) -> 6.2 | BQ39: =BO39*BP39 -> 0 | BR39: =BI39+BN39+BQ39 -> 52.758575 | BS39: =AZ39+BR39 -> 60.608575
A40: ABM0009-251014-0001 | B40: =COUNTIF(A:A,A40) -> 1 | C40: 1 | E40: M | F40: 202510 | G40: 2025-10-14 | H40: 2025-10-14 | I40: Delivered | J40: YCD-EX:HUPPER TEK | K40: ABM0009-251014-0001 | L40: B2C | N40: qianhui.xu@miclogistik.de | O40: 1 | P40: NORMAL | Q40: 47.4 | R40: GELF-EML_HUPPERTEK | S40: RetourHermes_M | T40: 4618363311 | U40: =VLOOKUP(T40,[5]semitemu_order_export_251110144!$R:$S,2,0) -> PO-076-06750099461753911 | W40: 78054 | X40: Villingen-Schwenningen | Y40: DE | AC40: ABM0009-251014-0001 | AD40: B076THQBHX | AE40: 金属储物柜71英寸灰色 | AF40: 188x49x14 | AG40: 47.4 | AI40: 1 | AJ40: =AI40*AG40 -> 47.4 | AK40: =AI40 -> 1 | AL40: 4.85 | AM40: =AL40*AK40 -> 4.85 | AP40: =AO40*AN40 -> 0 | AS40: =AR40*AQ40 -> 0 | AV40: =AU40*AT40 -> 0 | AW40: =O40 -> 1 | AX40: 3 | AY40: =AX40*AW40 -> 3 | AZ40: =AM40+AP40+AS40+AV40+AY40 -> 7.85 | BA40: 1 | BB40: =AJ40 -> 47.4 | BD40: 50 | BE40: =W40 -> 78054 | BF40: =X40 -> Villingen-Schwenningen | BG40: =Y40 -> DE | BH40: 46.558575 | BI40: =BH40 -> 46.558575 | BJ40: 2.5 | BK40: =0.024*BD40 -> 1.2 | BL40: 2.5 | BN40: =SUM(BJ40:BM40) -> 6.2 | BQ40: =BO40*BP40 -> 0 | BR40: =BI40+BN40+BQ40 -> 52.758575 | BS40: =AZ40+BR40 -> 60.608575
A41: ABM0009-251017-0002 | B41: =COUNTIF(A:A,A41) -> 1 | C41: 1 | E41: M | F41: 202510 | G41: 2025-10-17 | H41: 2025-10-17 | I41: Delivered | J41: YCD-EX:HUPPER TEK | K41: ABM0009-251017-0002 | L41: B2C | N41: qianhui.xu@miclogistik.de | O41: 1 | P41: NORMAL | Q41: 47.4 | R41: GELF-EML_HUPPERTEK | S41: RetourHermes_M | T41: 4618375932 | U41: =VLOOKUP(T41,[5]semitemu_order_export_251110144!$R:$S,2,0) -> PO-076-16156623279992626 | W41: 72766 | X41: Reutlingen | Y41: DE | AC41: ABM0009-251017-0002 | AD41: B07Q3SQT6C | AE41: 金属储物柜71英寸高 | AF41: 188x49x14 | AG41: 47.4 | AI41: 1 | AJ41: =AI41*AG41 -> 47.4 | AK41: =AI41 -> 1 | AL41: 4.85 | AM41: =AL41*AK41 -> 4.85 | AP41: =AO41*AN41 -> 0 | AS41: =AR41*AQ41 -> 0 | AV41: =AU41*AT41 -> 0 | AW41: =O41 -> 1 | AX41: 3 | AY41: =AX41*AW41 -> 3 | AZ41: =AM41+AP41+AS41+AV41+AY41 -> 7.85 | BA41: 1 | BB41: =AJ41 -> 47.4 | BD41: 50 | BE41: =W41 -> 72766 | BF41: =X41 -> Reutlingen | BG41: =Y41 -> DE | BH41: 46.558575 | BI41: =BH41 -> 46.558575 | BJ41: 2.5 | BK41: =0.024*BD41 -> 1.2 | BL41: 2.5 | BN41: =SUM(BJ41:BM41) -> 6.2 | BQ41: =BO41*BP41 -> 0 | BR41: =BI41+BN41+BQ41 -> 52.758575 | BS41: =AZ41+BR41 -> 60.608575
A42: ABM0009-251017-0001 | B42: =COUNTIF(A:A,A42) -> 1 | C42: 1 | E42: M | F42: 202510 | G42: 2025-10-17 | H42: 2025-10-17 | I42: Delivered | J42: YCD-EX:HUPPER TEK | K42: ABM0009-251017-0001 | L42: B2C | N42: qianhui.xu@miclogistik.de | O42: 1 | P42: NORMAL | Q42: 47.4 | R42: GELF-EML_HUPPERTEK | S42: RetourHermes_M | T42: 4618375925 | U42: =VLOOKUP(T42,[6]ebay_order_export_251110145132!$S:$T,2,0) -> 20-13696-61877 | W42: 27777 | X42: Ganderkesee | Y42: DE | AC42: ABM0009-251017-0001 | AD42: B07BK8W5MF | AE42: 金属储物柜71英寸银色 | AF42: 188x49x14 | AG42: 47.4 | AI42: 1 | AJ42: =AI42*AG42 -> 47.4 | AK42: =AI42 -> 1 | AL42: 4.85 | AM42: =AL42*AK42 -> 4.85 | AP42: =AO42*AN42 -> 0 | AS42: =AR42*AQ42 -> 0 | AV42: =AU42*AT42 -> 0 | AW42: =O42 -> 1 | AX42: 3 | AY42: =AX42*AW42 -> 3 | AZ42: =AM42+AP42+AS42+AV42+AY42 -> 7.85 | BA42: 1 | BB42: =AJ42 -> 47.4 | BD42: 50 | BE42: =W42 -> 27777 | BF42: =X42 -> Ganderkesee | BG42: =Y42 -> DE | BH42: 46.558575 | BI42: =BH42 -> 46.558575 | BJ42: 2.5 | BK42: =0.024*BD42 -> 1.2 | BL42: 2.5 | BN42: =SUM(BJ42:BM42) -> 6.2 | BQ42: =BO42*BP42 -> 0 | BR42: =BI42+BN42+BQ42 -> 52.758575 | BS42: =AZ42+BR42 -> 60.608575
A43: ABM0009-251020-0009 | B43: =COUNTIF(A:A,A43) -> 1 | C43: 1 | E43: M | F43: 202510 | G43: 2025-10-20 | H43: 2025-10-20 | I43: Delivered | J43: YCD-EX:HUPPER TEK | K43: ABM0009-251020-0009 | L43: B2C | N43: qianhui.xu@miclogistik.de | O43: 1 | P43: NORMAL | Q43: 47.4 | R43: GELF-EML_HUPPERTEK | S43: RetourHermes_M | T43: 4618385870 | U43: =VLOOKUP(T43,[5]semitemu_order_export_251110144!$R:$S,2,0) -> PO-076-21635569651831488 | W43: 21502 | X43: Geesthacht | Y43: DE | AC43: ABM0009-251020-0009 | AD43: B07BK8W5MF | AE43: 金属储物柜71英寸银色 | AF43: 188x49x14 | AG43: 47.4 | AI43: 1 | AJ43: =AI43*AG43 -> 47.4 | AK43: =AI43 -> 1 | AL43: 4.85 | AM43: =AL43*AK43 -> 4.85 | AP43: =AO43*AN43 -> 0 | AS43: =AR43*AQ43 -> 0 | AV43: =AU43*AT43 -> 0 | AW43: =O43 -> 1 | AX43: 3 | AY43: =AX43*AW43 -> 3 | AZ43: =AM43+AP43+AS43+AV43+AY43 -> 7.85 | BA43: 1 | BB43: =AJ43 -> 47.4 | BD43: 50 | BE43: =W43 -> 21502 | BF43: =X43 -> Geesthacht | BG43: =Y43 -> DE | BH43: 46.558575 | BI43: =BH43 -> 46.558575 | BJ43: 2.5 | BK43: =0.024*BD43 -> 1.2 | BL43: 2.5 | BN43: =SUM(BJ43:BM43) -> 6.2 | BQ43: =BO43*BP43 -> 0 | BR43: =BI43+BN43+BQ43 -> 52.758575 | BS43: =AZ43+BR43 -> 60.608575
A44: ABM0009-251020-0008 | B44: =COUNTIF(A:A,A44) -> 1 | C44: 1 | E44: M | F44: 202510 | G44: 2025-10-20 | H44: 2025-10-20 | I44: Delivered | J44: YCD-EX:HUPPER TEK | K44: ABM0009-251020-0008 | L44: B2C | N44: qianhui.xu@miclogistik.de | O44: 1 | P44: NORMAL | Q44: 47.4 | R44: GELF-EML_HUPPERTEK | S44: RetourHermes_M | T44: 4618385863 | U44: =VLOOKUP(T44,[5]semitemu_order_export_251110144!$R:$S,2,0) -> PO-076-21635569651831488 | W44: 21502 | X44: Geesthacht | Y44: DE | AC44: ABM0009-251020-0008 | AD44: B07BK8W5MF | AE44: 金属储物柜71英寸银色 | AF44: 188x49x14 | AG44: 47.4 | AI44: 1 | AJ44: =AI44*AG44 -> 47.4 | AK44: =AI44 -> 1 | AL44: 4.85 | AM44: =AL44*AK44 -> 4.85 | AP44: =AO44*AN44 -> 0 | AS44: =AR44*AQ44 -> 0 | AV44: =AU44*AT44 -> 0 | AW44: =O44 -> 1 | AX44: 3 | AY44: =AX44*AW44 -> 3 | AZ44: =AM44+AP44+AS44+AV44+AY44 -> 7.85 | BA44: 1 | BB44: =AJ44 -> 47.4 | BD44: 50 | BE44: =W44 -> 21502 | BF44: =X44 -> Geesthacht | BG44: =Y44 -> DE | BH44: 46.558575 | BI44: =BH44 -> 46.558575 | BJ44: 2.5 | BK44: =0.024*BD44 -> 1.2 | BL44: 2.5 | BN44: =SUM(BJ44:BM44) -> 6.2 | BQ44: =BO44*BP44 -> 0 | BR44: =BI44+BN44+BQ44 -> 52.758575 | BS44: =AZ44+BR44 -> 60.608575
A45: ABM0009-251020-0007 | B45: =COUNTIF(A:A,A45) -> 1 | C45: 1 | E45: M | F45: 202510 | G45: 2025-10-20 | H45: 2025-10-20 | I45: Delivered | J45: YCD-EX:HUPPER TEK | K45: ABM0009-251020-0007 | L45: B2C | N45: qianhui.xu@miclogistik.de | O45: 1 | P45: NORMAL | Q45: 47.4 | R45: GELF-EML_HUPPERTEK | S45: RetourHermes_M | T45: 4618385856 | U45: =VLOOKUP(T45,[5]semitemu_order_export_251110144!$R:$S,2,0) -> PO-076-02633160077433872 | W45: 84092 | X45: Bayerbach b. Ergoldsbach | Y45: DE | AC45: ABM0009-251020-0007 | AD45: B07BK8W5MF | AE45: 金属储物柜71英寸银色 | AF45: 188x49x14 | AG45: 47.4 | AI45: 1 | AJ45: =AI45*AG45 -> 47.4 | AK45: =AI45 -> 1 | AL45: 4.85 | AM45: =AL45*AK45 -> 4.85 | AP45: =AO45*AN45 -> 0 | AS45: =AR45*AQ45 -> 0 | AV45: =AU45*AT45 -> 0 | AW45: =O45 -> 1 | AX45: 3 | AY45: =AX45*AW45 -> 3 | AZ45: =AM45+AP45+AS45+AV45+AY45 -> 7.85 | BA45: 1 | BB45: =AJ45 -> 47.4 | BD45: 50 | BE45: =W45 -> 84092 | BF45: =X45 -> Bayerbach b. Ergoldsbach | BG45: =Y45 -> DE | BH45: 46.558575 | BI45: =BH45 -> 46.558575 | BJ45: 2.5 | BK45: =0.024*BD45 -> 1.2 | BL45: 2.5 | BN45: =SUM(BJ45:BM45) -> 6.2 | BQ45: =BO45*BP45 -> 0 | BR45: =BI45+BN45+BQ45 -> 52.758575 | BS45: =AZ45+BR45 -> 60.608575
A46: ABM0009-251020-0006 | B46: =COUNTIF(A:A,A46) -> 1 | C46: 1 | E46: M | F46: 202510 | G46: 2025-10-20 | H46: 2025-10-20 | I46: Delivered | J46: YCD-EX:HUPPER TEK | K46: ABM0009-251020-0006 | L46: B2C | N46: qianhui.xu@miclogistik.de | O46: 1 | P46: NORMAL | Q46: 47.4 | R46: GELF-EML_HUPPERTEK | S46: RetourHermes_M | T46: 4618385849 | U46: =VLOOKUP(T46,[5]semitemu_order_export_251110144!$R:$S,2,0) -> PO-076-02633160077433872 | W46: 84092 | X46: Bayerbach b. Ergoldsbach | Y46: DE | AC46: ABM0009-251020-0006 | AD46: B07BK8W5MF | AE46: 金属储物柜71英寸银色 | AF46: 188x49x14 | AG46: 47.4 | AI46: 1 | AJ46: =AI46*AG46 -> 47.4 | AK46: =AI46 -> 1 | AL46: 4.85 | AM46: =AL46*AK46 -> 4.85 | AP46: =AO46*AN46 -> 0 | AS46: =AR46*AQ46 -> 0 | AV46: =AU46*AT46 -> 0 | AW46: =O46 -> 1 | AX46: 3 | AY46: =AX46*AW46 -> 3 | AZ46: =AM46+AP46+AS46+AV46+AY46 -> 7.85 | BA46: 1 | BB46: =AJ46 -> 47.4 | BD46: 50 | BE46: =W46 -> 84092 | BF46: =X46 -> Bayerbach b. Ergoldsbach | BG46: =Y46 -> DE | BH46: 46.558575 | BI46: =BH46 -> 46.558575 | BJ46: 2.5 | BK46: =0.024*BD46 -> 1.2 | BL46: 2.5 | BN46: =SUM(BJ46:BM46) -> 6.2 | BQ46: =BO46*BP46 -> 0 | BR46: =BI46+BN46+BQ46 -> 52.758575 | BS46: =AZ46+BR46 -> 60.608575
A47: ABM0009-251020-0005 | B47: =COUNTIF(A:A,A47) -> 1 | C47: 1 | E47: M | F47: 202510 | G47: 2025-10-20 | H47: 2025-10-20 | I47: Delivered | J47: YCD-EX:HUPPER TEK | K47: ABM0009-251020-0005 | L47: B2C | N47: qianhui.xu@miclogistik.de | O47: 1 | P47: NORMAL | Q47: 47.4 | R47: GELF-EML_HUPPERTEK | S47: RetourHermes_M | T47: 4618385832 | U47: =VLOOKUP(T47,[5]semitemu_order_export_251110144!$R:$S,2,0) -> PO-076-10937699783033271 | W47: 81245 | X47: München | Y47: DE | AC47: ABM0009-251020-0005 | AD47: B07BK8W5MF | AE47: 金属储物柜71英寸银色 | AF47: 188x49x14 | AG47: 47.4 | AI47: 1 | AJ47: =AI47*AG47 -> 47.4 | AK47: =AI47 -> 1 | AL47: 4.85 | AM47: =AL47*AK47 -> 4.85 | AP47: =AO47*AN47 -> 0 | AS47: =AR47*AQ47 -> 0 | AV47: =AU47*AT47 -> 0 | AW47: =O47 -> 1 | AX47: 3 | AY47: =AX47*AW47 -> 3 | AZ47: =AM47+AP47+AS47+AV47+AY47 -> 7.85 | BA47: 1 | BB47: =AJ47 -> 47.4 | BD47: 50 | BE47: =W47 -> 81245 | BF47: =X47 -> München | BG47: =Y47 -> DE | BH47: 46.558575 | BI47: =BH47 -> 46.558575 | BJ47: 2.5 | BK47: =0.024*BD47 -> 1.2 | BL47: 2.5 | BM47: 7.8 | BN47: =SUM(BJ47:BM47) -> 14 | BQ47: =BO47*BP47 -> 0 | BR47: =BI47+BN47+BQ47 -> 60.558575 | BS47: =AZ47+BR47 -> 68.408575
A48: ABM0009-251020-0004 | B48: =COUNTIF(A:A,A48) -> 1 | C48: 1 | E48: M | F48: 202510 | G48: 2025-10-20 | H48: 2025-10-20 | I48: Delivered | J48: YCD-EX:HUPPER TEK | K48: ABM0009-251020-0004 | L48: B2C | N48: qianhui.xu@miclogistik.de | O48: 1 | P48: NORMAL | Q48: 47.4 | R48: GELF-EML_HUPPERTEK | S48: RetourHermes_M | T48: 4618385825 | U48: =VLOOKUP(T48,[5]semitemu_order_export_251110144!$R:$S,2,0) -> PO-076-02712126638713403 | W48: 34587 | X48: Felsberg | Y48: DE | AC48: ABM0009-251020-0004 | AD48: B07Q3SQT6C | AE48: 金属储物柜71英寸高 | AF48: 188x49x14 | AG48: 47.4 | AI48: 1 | AJ48: =AI48*AG48 -> 47.4 | AK48: =AI48 -> 1 | AL48: 4.85 | AM48: =AL48*AK48 -> 4.85 | AP48: =AO48*AN48 -> 0 | AS48: =AR48*AQ48 -> 0 | AV48: =AU48*AT48 -> 0 | AW48: =O48 -> 1 | AX48: 3 | AY48: =AX48*AW48 -> 3 | AZ48: =AM48+AP48+AS48+AV48+AY48 -> 7.85 | BA48: 1 | BB48: =AJ48 -> 47.4 | BD48: 50 | BE48: =W48 -> 34587 | BF48: =X48 -> Felsberg | BG48: =Y48 -> DE | BH48: 46.558575 | BI48: =BH48 -> 46.558575 | BJ48: 2.5 | BK48: =0.024*BD48 -> 1.2 | BL48: 2.5 | BN48: =SUM(BJ48:BM48) -> 6.2 | BQ48: =BO48*BP48 -> 0 | BR48: =BI48+BN48+BQ48 -> 52.758575 | BS48: =AZ48+BR48 -> 60.608575
A49: ABM0009-251020-0003 | B49: =COUNTIF(A:A,A49) -> 1 | C49: 1 | E49: M | F49: 202510 | G49: 2025-10-20 | H49: 2025-10-20 | I49: Delivered | J49: YCD-EX:HUPPER TEK | K49: ABM0009-251020-0003 | L49: B2C | N49: qianhui.xu@miclogistik.de | O49: 1 | P49: NORMAL | Q49: 47.4 | R49: GELF-EML_HUPPERTEK | S49: RetourHermes_M | T49: 4618385818 | U49: =VLOOKUP(T49,[5]semitemu_order_export_251110144!$R:$S,2,0) -> PO-076-02385536233591508 | W49: 91301 | X49: Forchheim | Y49: DE | AC49: ABM0009-251020-0003 | AD49: B07BK8W5MF | AE49: 金属储物柜71英寸银色 | AF49: 188x49x14 | AG49: 47.4 | AI49: 1 | AJ49: =AI49*AG49 -> 47.4 | AK49: =AI49 -> 1 | AL49: 4.85 | AM49: =AL49*AK49 -> 4.85 | AP49: =AO49*AN49 -> 0 | AS49: =AR49*AQ49 -> 0 | AV49: =AU49*AT49 -> 0 | AW49: =O49 -> 1 | AX49: 3 | AY49: =AX49*AW49 -> 3 | AZ49: =AM49+AP49+AS49+AV49+AY49 -> 7.85 | BA49: 1 | BB49: =AJ49 -> 47.4 | BD49: 50 | BE49: =W49 -> 91301 | BF49: =X49 -> Forchheim | BG49: =Y49 -> DE | BH49: 46.558575 | BI49: =BH49 -> 46.558575 | BJ49: 2.5 | BK49: =0.024*BD49 -> 1.2 | BL49: 2.5 | BN49: =SUM(BJ49:BM49) -> 6.2 | BQ49: =BO49*BP49 -> 0 | BR49: =BI49+BN49+BQ49 -> 52.758575 | BS49: =AZ49+BR49 -> 60.608575
A50: ABM0009-251020-0002 | B50: =COUNTIF(A:A,A50) -> 1 | C50: 1 | E50: M | F50: 202510 | G50: 2025-10-20 | H50: 2025-10-20 | I50: Delivered | J50: YCD-EX:HUPPER TEK | K50: ABM0009-251020-0002 | L50: B2C | N50: qianhui.xu@miclogistik.de | O50: 1 | P50: NORMAL | Q50: 47.4 | R50: GELF-EML_HUPPERTEK | S50: RetourHermes_M | T50: 4618385801 | U50: =VLOOKUP(T50,[6]ebay_order_export_251110145132!$S:$T,2,0) -> 12-13717-51641 | W50: 95652 | X50: Waldsassen | Y50: DE | AC50: ABM0009-251020-0002 | AD50: B07Q3SQT6C | AE50: 金属储物柜71英寸高 | AF50: 188x49x14 | AG50: 47.4 | AI50: 1 | AJ50: =AI50*AG50 -> 47.4 | AK50: =AI50 -> 1 | AL50: 4.85 | AM50: =AL50*AK50 -> 4.85 | AP50: =AO50*AN50 -> 0 | AS50: =AR50*AQ50 -> 0 | AV50: =AU50*AT50 -> 0 | AW50: =O50 -> 1 | AX50: 3 | AY50: =AX50*AW50 -> 3 | AZ50: =AM50+AP50+AS50+AV50+AY50 -> 7.85 | BA50: 1 | BB50: =AJ50 -> 47.4 | BD50: 50 | BE50: =W50 -> 95652 | BF50: =X50 -> Waldsassen | BG50: =Y50 -> DE | BH50: 46.558575 | BI50: =BH50 -> 46.558575 | BJ50: 2.5 | BK50: =0.024*BD50 -> 1.2 | BL50: 2.5 | BN50: =SUM(BJ50:BM50) -> 6.2 | BQ50: =BO50*BP50 -> 0 | BR50: =BI50+BN50+BQ50 -> 52.758575 | BS50: =AZ50+BR50 -> 60.608575
A51: ABM0009-251020-0001 | B51: =COUNTIF(A:A,A51) -> 1 | C51: 1 | E51: M | F51: 202510 | G51: 2025-10-20 | H51: 2025-10-20 | I51: Delivered | J51: YCD-EX:HUPPER TEK | K51: ABM0009-251020-0001 | L51: B2C | N51: qianhui.xu@miclogistik.de | O51: 2 | P51: NORMAL | Q51: 47.4 | R51: GELF-EML_HUPPERTEK | S51: RetourHermes_M | T51: 4618385788 | U51: 16-13714-19478 | W51: 89257 | X51: Illertissen | Y51: DE | AC51: ABM0009-251020-0001 | AD51: B07BK8W5MF | AE51: 金属储物柜71英寸银色 | AF51: 188x49x14 | AG51: 47.4 | AI51: 2 | AJ51: =AI51*AG51 -> 94.8 | AK51: =AI51 -> 2 | AL51: 4.85 | AM51: =AL51*AK51 -> 9.7 | AP51: =AO51*AN51 -> 0 | AS51: =AR51*AQ51 -> 0 | AV51: =AU51*AT51 -> 0 | AW51: =O51 -> 2 | AX51: 3 | AY51: =AX51*AW51 -> 6 | AZ51: =AM51+AP51+AS51+AV51+AY51 -> 15.7 | BA51: 1 | BB51: =AJ51 -> 94.8 | BD51: 100 | BE51: =W51 -> 89257 | BF51: =X51 -> Illertissen | BG51: =Y51 -> DE | BH51: 78.354675 | BI51: =BH51 -> 78.354675 | BJ51: 2.5 | BK51: =0.024*BD51 -> 2.4 | BL51: 2.5 | BN51: =SUM(BJ51:BM51) -> 7.4 | BQ51: =BO51*BP51 -> 0 | BR51: =BI51+BN51+BQ51 -> 85.754675 | BS51: =50.73*2 -> 101.46
A52: ABM0009-251017-0003 | B52: =COUNTIF(A:A,A52) -> 1 | C52: 1 | E52: M | F52: 202510 | G52: 2025-10-20 | H52: 2025-10-20 | I52: Delivered | J52: YCD-EX:HUPPER TEK | K52: ABM0009-251017-0003 | L52: B2C | N52: qianhui.xu@miclogistik.de | O52: 1 | P52: NORMAL | Q52: 47.4 | R52: GELF-EML_HUPPERTEK | S52: RetourHermes_M | T52: 4618385771 | U52: =VLOOKUP(T52,[5]semitemu_order_export_251110144!$R:$S,2,0) -> PO-076-10884624877433843 | W52: 93170 | X52: Bernhardswald | Y52: DE | AC52: ABM0009-251017-0003 | AD52: B07Q3SQT6C | AE52: 金属储物柜71英寸高 | AF52: 188x49x14 | AG52: 47.4 | AI52: 1 | AJ52: =AI52*AG52 -> 47.4 | AK52: =AI52 -> 1 | AL52: 4.85 | AM52: =AL52*AK52 -> 4.85 | AP52: =AO52*AN52 -> 0 | AS52: =AR52*AQ52 -> 0 | AV52: =AU52*AT52 -> 0 | AW52: =O52 -> 1 | AX52: 3 | AY52: =AX52*AW52 -> 3 | AZ52: =AM52+AP52+AS52+AV52+AY52 -> 7.85 | BA52: 1 | BB52: =AJ52 -> 47.4 | BD52: 50 | BE52: =W52 -> 93170 | BF52: =X52 -> Bernhardswald | BG52: =Y52 -> DE | BH52: 46.558575 | BI52: =BH52 -> 46.558575 | BJ52: 2.5 | BK52: =0.024*BD52 -> 1.2 | BL52: 2.5 | BN52: =SUM(BJ52:BM52) -> 6.2 | BQ52: =BO52*BP52 -> 0 | BR52: =BI52+BN52+BQ52 -> 52.758575 | BS52: =AZ52+BR52 -> 60.608575
A53: ABM0009-251021-0001 | B53: =COUNTIF(A:A,A53) -> 1 | C53: 1 | E53: M | F53: 202510 | G53: 2025-10-21 | H53: 2025-10-21 | I53: Delivered | J53: YCD-EX:HUPPER TEK | K53: ABM0009-251021-0001 | L53: B2C | N53: qianhui.xu@miclogistik.de | O53: 1 | P53: NORMAL | Q53: 47.4 | R53: GELF-EML_HUPPERTEK | S53: RetourHermes_M | T53: 4618392564 | U53: =VLOOKUP(T53,[6]ebay_order_export_251110145132!$S:$T,2,0) -> 24-13723-93482 | W53: 95152 | X53: Selbitz | Y53: DE | AC53: ABM0009-251021-0001 | AD53: B076THQBHX | AE53: 金属储物柜71英寸灰色 | AF53: 188x49x14 | AG53: 47.4 | AI53: 1 | AJ53: =AI53*AG53 -> 47.4 | AK53: =AI53 -> 1 | AL53: 4.85 | AM53: =AL53*AK53 -> 4.85 | AP53: =AO53*AN53 -> 0 | AS53: =AR53*AQ53 -> 0 | AV53: =AU53*AT53 -> 0 | AW53: =O53 -> 1 | AX53: 3 | AY53: =AX53*AW53 -> 3 | AZ53: =AM53+AP53+AS53+AV53+AY53 -> 7.85 | BA53: 1 | BB53: =AJ53 -> 47.4 | BD53: 50 | BE53: =W53 -> 95152 | BF53: =X53 -> Selbitz | BG53: =Y53 -> DE | BH53: 46.558575 | BI53: =BH53 -> 46.558575 | BJ53: 2.5 | BK53: =0.024*BD53 -> 1.2 | BL53: 2.5 | BN53: =SUM(BJ53:BM53) -> 6.2 | BQ53: =BO53*BP53 -> 0 | BR53: =BI53+BN53+BQ53 -> 52.758575 | BS53: =AZ53+BR53 -> 60.608575
A54: ABM0009-251022-0002 | B54: =COUNTIF(A:A,A54) -> 1 | C54: 1 | E54: M | F54: 202510 | G54: 2025-10-22 | H54: 2025-10-22 | I54: Delivery Notify | J54: YCD-EX:HUPPER TEK | K54: ABM0009-251022-0002 | L54: B2C | N54: qianhui.xu@miclogistik.de | O54: 1 | P54: NORMAL | Q54: 47.4 | R54: GELF-EML_HUPPERTEK | S54: RetourHermes_M | T54: 4618397668 | U54: =VLOOKUP(T54,[5]semitemu_order_export_251110144!$R:$S,2,0) -> PO-076-08120084790393937 | W54: 71144 | X54: Steinenbronn | Y54: DE | AC54: ABM0009-251022-0002 | AD54: B07Q3SQT6C | AE54: 金属储物柜71英寸高 | AF54: 188x49x14 | AG54: 47.4 | AI54: 1 | AJ54: =AI54*AG54 -> 47.4 | AK54: =AI54 -> 1 | AL54: 4.85 | AM54: =AL54*AK54 -> 4.85 | AP54: =AO54*AN54 -> 0 | AS54: =AR54*AQ54 -> 0 | AV54: =AU54*AT54 -> 0 | AW54: =O54 -> 1 | AX54: 3 | AY54: =AX54*AW54 -> 3 | AZ54: =AM54+AP54+AS54+AV54+AY54 -> 7.85 | BA54: 1 | BB54: =AJ54 -> 47.4 | BD54: 50 | BE54: =W54 -> 71144 | BF54: =X54 -> Steinenbronn | BG54: =Y54 -> DE | BH54: 46.558575 | BI54: =BH54 -> 46.558575 | BJ54: 2.5 | BK54: =0.024*BD54 -> 1.2 | BL54: 2.5 | BN54: =SUM(BJ54:BM54) -> 6.2 | BQ54: =BO54*BP54 -> 0 | BR54: =BI54+BN54+BQ54 -> 52.758575 | BS54: =AZ54+BR54 -> 60.608575
A55: ABM0009-251022-0001 | B55: =COUNTIF(A:A,A55) -> 1 | C55: 1 | E55: M | F55: 202510 | G55: 2025-10-22 | H55: 2025-10-22 | I55: Delivered | J55: YCD-EX:HUPPER TEK | K55: ABM0009-251022-0001 | L55: B2C | N55: qianhui.xu@miclogistik.de | O55: 1 | P55: NORMAL | Q55: 47.4 | R55: GELF-EML_HUPPERTEK | S55: RetourHermes_M | T55: 4618397651 | U55: =VLOOKUP(T55,[5]semitemu_order_export_251110144!$R:$S,2,0) -> PO-076-08223921815673348 | W55: 6179 | X55: Teutschenthal | Y55: DE | AC55: ABM0009-251022-0001 | AD55: B076THQBHX | AE55: 金属储物柜71英寸灰色 | AF55: 188x49x14 | AG55: 47.4 | AI55: 1 | AJ55: =AI55*AG55 -> 47.4 | AK55: =AI55 -> 1 | AL55: 4.85 | AM55: =AL55*AK55 -> 4.85 | AP55: =AO55*AN55 -> 0 | AS55: =AR55*AQ55 -> 0 | AV55: =AU55*AT55 -> 0 | AW55: =O55 -> 1 | AX55: 3 | AY55: =AX55*AW55 -> 3 | AZ55: =AM55+AP55+AS55+AV55+AY55 -> 7.85 | BA55: 1 | BB55: =AJ55 -> 47.4 | BD55: 50 | BE55: =W55 -> 6179 | BF55: =X55 -> Teutschenthal | BG55: =Y55 -> DE | BH55: 46.558575 | BI55: =BH55 -> 46.558575 | BJ55: 2.5 | BK55: =0.024*BD55 -> 1.2 | BL55: 2.5 | BN55: =SUM(BJ55:BM55) -> 6.2 | BQ55: =BO55*BP55 -> 0 | BR55: =BI55+BN55+BQ55 -> 52.758575 | BS55: =AZ55+BR55 -> 60.608575
A56: ABM0009-251023-0002 | B56: =COUNTIF(A:A,A56) -> 1 | C56: 1 | E56: M | F56: 202510 | G56: 2025-10-23 | H56: 2025-10-23 | I56: Delivered | J56: YCD-EX:HUPPER TEK | K56: ABM0009-251023-0002 | L56: B2C | N56: qianhui.xu@miclogistik.de | O56: 1 | P56: NORMAL | Q56: 47.4 | R56: GELF-EML_HUPPERTEK | S56: RetourHermes_M | T56: 4618401976 | U56: =VLOOKUP(T56,[5]semitemu_order_export_251110144!$R:$S,2,0) -> PO-076-19048890705272538 | W56: 78166 | X56: Donaueschingen | Y56: DE | AC56: ABM0009-251023-0002 | AD56: B07BK8W5MF | AE56: 金属储物柜71英寸银色 | AF56: 188x49x14 | AG56: 47.4 | AI56: 1 | AJ56: =AI56*AG56 -> 47.4 | AK56: =AI56 -> 1 | AL56: 4.85 | AM56: =AL56*AK56 -> 4.85 | AP56: =AO56*AN56 -> 0 | AS56: =AR56*AQ56 -> 0 | AV56: =AU56*AT56 -> 0 | AW56: =O56 -> 1 | AX56: 3 | AY56: =AX56*AW56 -> 3 | AZ56: =AM56+AP56+AS56+AV56+AY56 -> 7.85 | BA56: 1 | BB56: =AJ56 -> 47.4 | BD56: 50 | BE56: =W56 -> 78166 | BF56: =X56 -> Donaueschingen | BG56: =Y56 -> DE | BH56: 46.558575 | BI56: =BH56 -> 46.558575 | BJ56: 2.5 | BK56: =0.024*BD56 -> 1.2 | BL56: 2.5 | BN56: =SUM(BJ56:BM56) -> 6.2 | BQ56: =BO56*BP56 -> 0 | BR56: =BI56+BN56+BQ56 -> 52.758575 | BS56: =AZ56+BR56 -> 60.608575
A57: ABM0009-251023-0001 | B57: =COUNTIF(A:A,A57) -> 1 | C57: 1 | E57: M | F57: 202510 | G57: 2025-10-23 | H57: 2025-10-23 | I57: Delivered | J57: YCD-EX:HUPPER TEK | K57: ABM0009-251023-0001 | L57: B2C | N57: qianhui.xu@miclogistik.de | O57: 1 | P57: NORMAL | Q57: 47.4 | R57: GELF-EML_HUPPERTEK | S57: RetourHermes_M | T57: 4618401969 | U57: =VLOOKUP(T57,[6]ebay_order_export_251110145132!$S:$T,2,0) -> 18-13724-67036 | W57: 9518 | X57: Großrückerswalde | Y57: DE | AC57: ABM0009-251023-0001 | AD57: B07Q3SQT6C | AE57: 金属储物柜71英寸高 | AF57: 188x49x14 | AG57: 47.4 | AI57: 1 | AJ57: =AI57*AG57 -> 47.4 | AK57: =AI57 -> 1 | AL57: 4.85 | AM57: =AL57*AK57 -> 4.85 | AP57: =AO57*AN57 -> 0 | AS57: =AR57*AQ57 -> 0 | AV57: =AU57*AT57 -> 0 | AW57: =O57 -> 1 | AX57: 3 | AY57: =AX57*AW57 -> 3 | AZ57: =AM57+AP57+AS57+AV57+AY57 -> 7.85 | BA57: 1 | BB57: =AJ57 -> 47.4 | BD57: 50 | BE57: =W57 -> 9518 | BF57: =X57 -> Großrückerswalde | BG57: =Y57 -> DE | BH57: 46.558575 | BI57: =BH57 -> 46.558575 | BJ57: 2.5 | BK57: =0.024*BD57 -> 1.2 | BL57: 2.5 | BN57: =SUM(BJ57:BM57) -> 6.2 | BQ57: =BO57*BP57 -> 0 | BR57: =BI57+BN57+BQ57 -> 52.758575 | BS57: =AZ57+BR57 -> 60.608575
A58: ABM0009-251024-0001 | B58: =COUNTIF(A:A,A58) -> 1 | C58: 1 | E58: M | F58: 202510 | G58: 2025-10-24 | H58: 2025-10-24 | I58: Delivered | J58: YCD-EX:HUPPER TEK | K58: ABM0009-251024-0001 | L58: B2C | N58: qianhui.xu@miclogistik.de | O58: 2 | P58: NORMAL | Q58: 94.8 | R58: GELF-EML_HUPPERTEK | S58: RetourHermes_M | T58: 4618407107 | U58: 02-13750-15412 | W58: 27246 | X58: Borstel | Y58: DE | AC58: ABM0009-251024-0001 | AD58: B07Q3SQT6C | AE58: 金属储物柜71英寸高 | AF58: 188x49x14 | AG58: 47.4 | AI58: 2 | AJ58: =AI58*AG58 -> 94.8 | AK58: =AI58 -> 2 | AL58: 4.85 | AM58: =AL58*AK58 -> 9.7 | AP58: =AO58*AN58 -> 0 | AS58: =AR58*AQ58 -> 0 | AV58: =AU58*AT58 -> 0 | AW58: =O58 -> 2 | AX58: 3 | AY58: =AX58*AW58 -> 6 | AZ58: =AM58+AP58+AS58+AV58+AY58 -> 15.7 | BA58: 1 | BB58: =AJ58 -> 94.8 | BD58: 100 | BE58: =W58 -> 27246 | BF58: =X58 -> Borstel | BG58: =Y58 -> DE | BH58: 78.354675 | BI58: =BH58 -> 78.354675 | BJ58: 2.5 | BK58: =0.024*BD58 -> 2.4 | BL58: 2.5 | BN58: =SUM(BJ58:BM58) -> 7.4 | BQ58: =BO58*BP58 -> 0 | BR58: =BI58+BN58+BQ58 -> 85.754675 | BS58: =50.73*2 -> 101.46
A59: ABM0009-251027-0006 | B59: =COUNTIF(A:A,A59) -> 1 | C59: 1 | E59: M | F59: 202510 | G59: 2025-10-27 | H59: 2025-10-27 | I59: Shipped | J59: YCD-EX:HUPPER TEK | K59: ABM0009-251027-0006 | L59: B2C | N59: qianhui.xu@miclogistik.de | O59: 1 | P59: NORMAL | Q59: 47.4 | R59: GELF-EML_HUPPERTEK | S59: RetourHermes_M | T59: 4618415140 | U59: =VLOOKUP(T59,[5]semitemu_order_export_251110144!$R:$S,2,0) -> PO-076-08702302439030243 | W59: 59329 | X59: Wadersloh | Y59: DE | AC59: ABM0009-251027-0006 | AD59: B07Q3SQT6C | AE59: 金属储物柜71英寸高 | AF59: 188x49x14 | AG59: 47.4 | AI59: 1 | AJ59: =AI59*AG59 -> 47.4 | AK59: =AI59 -> 1 | AL59: 4.85 | AM59: =AL59*AK59 -> 4.85 | AP59: =AO59*AN59 -> 0 | AS59: =AR59*AQ59 -> 0 | AV59: =AU59*AT59 -> 0 | AW59: =O59 -> 1 | AX59: 3 | AY59: =AX59*AW59 -> 3 | AZ59: =AM59+AP59+AS59+AV59+AY59 -> 7.85 | BA59: 1 | BB59: =AJ59 -> 47.4 | BD59: 50 | BE59: =W59 -> 59329 | BF59: =X59 -> Wadersloh | BG59: =Y59 -> DE | BH59: 46.558575 | BI59: =BH59 -> 46.558575 | BJ59: 2.5 | BK59: =0.024*BD59 -> 1.2 | BL59: 2.5 | BN59: =SUM(BJ59:BM59) -> 6.2 | BQ59: =BO59*BP59 -> 0 | BR59: =BI59+BN59+BQ59 -> 52.758575 | BS59: =AZ59+BR59 -> 60.608575
A60: ABM0009-251027-0005 | B60: =COUNTIF(A:A,A60) -> 1 | C60: 1 | E60: M | F60: 202510 | G60: 2025-10-27 | H60: 2025-10-27 | I60: Shipped | J60: YCD-EX:HUPPER TEK | K60: ABM0009-251027-0005 | L60: B2C | N60: qianhui.xu@miclogistik.de | O60: 1 | P60: NORMAL | Q60: 47.4 | R60: GELF-EML_HUPPERTEK | S60: RetourHermes_M | T60: 4618415133 | U60: =VLOOKUP(T60,[5]semitemu_order_export_251110144!$R:$S,2,0) -> PO-076-08702302439030243 | W60: 59329 | X60: Wadersloh | Y60: DE | AC60: ABM0009-251027-0005 | AD60: B07Q3SQT6C | AE60: 金属储物柜71英寸高 | AF60: 188x49x14 | AG60: 47.4 | AI60: 1 | AJ60: =AI60*AG60 -> 47.4 | AK60: =AI60 -> 1 | AL60: 4.85 | AM60: =AL60*AK60 -> 4.85 | AP60: =AO60*AN60 -> 0 | AS60: =AR60*AQ60 -> 0 | AV60: =AU60*AT60 -> 0 | AW60: =O60 -> 1 | AX60: 3 | AY60: =AX60*AW60 -> 3 | AZ60: =AM60+AP60+AS60+AV60+AY60 -> 7.85 | BA60: 1 | BB60: =AJ60 -> 47.4 | BD60: 50 | BE60: =W60 -> 59329 | BF60: =X60 -> Wadersloh | BG60: =Y60 -> DE | BH60: 46.558575 | BI60: =BH60 -> 46.558575 | BJ60: 2.5 | BK60: =0.024*BD60 -> 1.2 | BL60: 2.5 | BN60: =SUM(BJ60:BM60) -> 6.2 | BQ60: =BO60*BP60 -> 0 | BR60: =BI60+BN60+BQ60 -> 52.758575 | BS60: =AZ60+BR60 -> 60.608575
A61: ABM0009-251027-0004 | B61: =COUNTIF(A:A,A61) -> 1 | C61: 1 | E61: M | F61: 202510 | G61: 2025-10-27 | H61: 2025-10-27 | I61: Shipped | J61: YCD-EX:HUPPER TEK | K61: ABM0009-251027-0004 | L61: B2C | N61: qianhui.xu@miclogistik.de | O61: 1 | P61: NORMAL | Q61: 47.4 | R61: GELF-EML_HUPPERTEK | S61: RetourHermes_M | T61: 4618415126 | U61: =VLOOKUP(T61,[5]semitemu_order_export_251110144!$R:$S,2,0) -> PO-076-14226271655030341 | W61: 93483 | X61: Pösing | Y61: DE | AC61: ABM0009-251027-0004 | AD61: B07BK8W5MF | AE61: 金属储物柜71英寸银色 | AF61: 188x49x14 | AG61: 47.4 | AI61: 1 | AJ61: =AI61*AG61 -> 47.4 | AK61: =AI61 -> 1 | AL61: 4.85 | AM61: =AL61*AK61 -> 4.85 | AP61: =AO61*AN61 -> 0 | AS61: =AR61*AQ61 -> 0 | AV61: =AU61*AT61 -> 0 | AW61: =O61 -> 1 | AX61: 3 | AY61: =AX61*AW61 -> 3 | AZ61: =AM61+AP61+AS61+AV61+AY61 -> 7.85 | BA61: 1 | BB61: =AJ61 -> 47.4 | BD61: 50 | BE61: =W61 -> 93483 | BF61: =X61 -> Pösing | BG61: =Y61 -> DE | BH61: 46.558575 | BI61: =BH61 -> 46.558575 | BJ61: 2.5 | BK61: =0.024*BD61 -> 1.2 | BL61: 2.5 | BN61: =SUM(BJ61:BM61) -> 6.2 | BQ61: =BO61*BP61 -> 0 | BR61: =BI61+BN61+BQ61 -> 52.758575 | BS61: =AZ61+BR61 -> 60.608575
A62: ABM0009-251027-0003 | B62: =COUNTIF(A:A,A62) -> 1 | C62: 1 | E62: M | F62: 202510 | G62: 2025-10-27 | H62: 2025-10-27 | I62: Shipped | J62: YCD-EX:HUPPER TEK | K62: ABM0009-251027-0003 | L62: B2C | N62: qianhui.xu@miclogistik.de | O62: 1 | P62: NORMAL | Q62: 47.4 | R62: GELF-EML_HUPPERTEK | S62: RetourHermes_M | T62: 4618415119 | U62: =VLOOKUP(T62,[5]semitemu_order_export_251110144!$R:$S,2,0) -> PO-076-08266268639352584 | W62: 80937 | X62: München | Y62: DE | AC62: ABM0009-251027-0003 | AD62: B076THQBHX | AE62: 金属储物柜71英寸灰色 | AF62: 188x49x14 | AG62: 47.4 | AI62: 1 | AJ62: =AI62*AG62 -> 47.4 | AK62: =AI62 -> 1 | AL62: 4.85 | AM62: =AL62*AK62 -> 4.85 | AP62: =AO62*AN62 -> 0 | AS62: =AR62*AQ62 -> 0 | AV62: =AU62*AT62 -> 0 | AW62: =O62 -> 1 | AX62: 3 | AY62: =AX62*AW62 -> 3 | AZ62: =AM62+AP62+AS62+AV62+AY62 -> 7.85 | BA62: 1 | BB62: =AJ62 -> 47.4 | BD62: 50 | BE62: =W62 -> 80937 | BF62: =X62 -> München | BG62: =Y62 -> DE | BH62: 46.558575 | BI62: =BH62 -> 46.558575 | BJ62: 2.5 | BK62: =0.024*BD62 -> 1.2 | BL62: 2.5 | BM62: 7.8 | BN62: =SUM(BJ62:BM62) -> 14 | BQ62: =BO62*BP62 -> 0 | BR62: =BI62+BN62+BQ62 -> 60.558575 | BS62: =AZ62+BR62 -> 68.408575
A63: ABM0009-251027-0002 | B63: =COUNTIF(A:A,A63) -> 1 | C63: 1 | E63: M | F63: 202510 | G63: 2025-10-27 | H63: 2025-10-27 | I63: Shipped | J63: YCD-EX:HUPPER TEK | K63: ABM0009-251027-0002 | L63: B2C | N63: qianhui.xu@miclogistik.de | O63: 1 | P63: NORMAL | Q63: 47.4 | R63: GELF-EML_HUPPERTEK | S63: RetourHermes_M | T63: 4618415102 | U63: =VLOOKUP(T63,[5]semitemu_order_export_251110144!$R:$S,2,0) -> PO-076-19521457761913306 | W63: 45891 | X63: Gelsenkirchen | Y63: DE | AC63: ABM0009-251027-0002 | AD63: B07BK8W5MF | AE63: 金属储物柜71英寸银色 | AF63: 188x49x14 | AG63: 47.4 | AI63: 1 | AJ63: =AI63*AG63 -> 47.4 | AK63: =AI63 -> 1 | AL63: 4.85 | AM63: =AL63*AK63 -> 4.85 | AP63: =AO63*AN63 -> 0 | AS63: =AR63*AQ63 -> 0 | AV63: =AU63*AT63 -> 0 | AW63: =O63 -> 1 | AX63: 3 | AY63: =AX63*AW63 -> 3 | AZ63: =AM63+AP63+AS63+AV63+AY63 -> 7.85 | BA63: 1 | BB63: =AJ63 -> 47.4 | BD63: 50 | BE63: =W63 -> 45891 | BF63: =X63 -> Gelsenkirchen | BG63: =Y63 -> DE | BH63: 46.558575 | BI63: =BH63 -> 46.558575 | BJ63: 2.5 | BK63: =0.024*BD63 -> 1.2 | BL63: 2.5 | BN63: =SUM(BJ63:BM63) -> 6.2 | BQ63: =BO63*BP63 -> 0 | BR63: =BI63+BN63+BQ63 -> 52.758575 | BS63: =AZ63+BR63 -> 60.608575
A64: ABM0009-251027-0001 | B64: =COUNTIF(A:A,A64) -> 1 | C64: 1 | E64: M | F64: 202510 | G64: 2025-10-27 | H64: 2025-10-27 | I64: Shipped | J64: YCD-EX:HUPPER TEK | K64: ABM0009-251027-0001 | L64: B2C | N64: qianhui.xu@miclogistik.de | O64: 2 | P64: NORMAL | Q64: 94.8 | R64: GELF-EML_HUPPERTEK | S64: RetourHermes_M | T64: 4618415089 | U64: 07-13750-59151 | W64: 71282 | X64: Hemmingen | Y64: DE | AC64: ABM0009-251027-0001 | AD64: B07Q3SQT6C | AE64: 金属储物柜71英寸高 | AF64: 188x49x14 | AG64: 47.4 | AI64: 2 | AJ64: =AI64*AG64 -> 94.8 | AK64: =AI64 -> 2 | AL64: 4.85 | AM64: =AL64*AK64 -> 9.7 | AP64: =AO64*AN64 -> 0 | AS64: =AR64*AQ64 -> 0 | AV64: =AU64*AT64 -> 0 | AW64: =O64 -> 2 | AX64: 3 | AY64: =AX64*AW64 -> 6 | AZ64: =AM64+AP64+AS64+AV64+AY64 -> 15.7 | BA64: 1 | BB64: =AJ64 -> 94.8 | BD64: 100 | BE64: =W64 -> 71282 | BF64: =X64 -> Hemmingen | BG64: =Y64 -> DE | BH64: 78.354675 | BI64: =BH64 -> 78.354675 | BJ64: 2.5 | BK64: =0.024*BD64 -> 2.4 | BL64: 2.5 | BN64: =SUM(BJ64:BM64) -> 7.4 | BQ64: =BO64*BP64 -> 0 | BR64: =BI64+BN64+BQ64 -> 85.754675 | BS64: =50.73*2 -> 101.46
A65: ABM0009-251029-0001 | B65: =COUNTIF(A:A,A65) -> 1 | C65: 1 | E65: M | F65: 202510 | G65: 2025-10-29 | H65: 2025-10-29 | I65: Shipped | J65: YCD-EX:HUPPER TEK | K65: ABM0009-251029-0001 | L65: B2C | N65: qianhui.xu@miclogistik.de | O65: 2 | P65: NORMAL | Q65: 94.8 | R65: GELF-EML_HUPPERTEK | S65: RetourHermes_M | T65: 4618425231 | U65: 05-13769-25366 | W65: 94060 | X65: Pocking | Y65: DE | AC65: ABM0009-251029-0001 | AD65: B07Q3SQT6C | AE65: 金属储物柜71英寸高 | AF65: 188x49x14 | AG65: 47.4 | AI65: 2 | AJ65: =AI65*AG65 -> 94.8 | AK65: =AI65 -> 2 | AL65: 4.85 | AM65: =AL65*AK65 -> 9.7 | AP65: =AO65*AN65 -> 0 | AS65: =AR65*AQ65 -> 0 | AV65: =AU65*AT65 -> 0 | AW65: =O65 -> 2 | AX65: 3 | AY65: =AX65*AW65 -> 6 | AZ65: =AM65+AP65+AS65+AV65+AY65 -> 15.7 | BA65: 1 | BB65: =AJ65 -> 94.8 | BD65: 100 | BE65: =W65 -> 94060 | BF65: =X65 -> Pocking | BG65: =Y65 -> DE | BH65: 78.354675 | BI65: =BH65 -> 78.354675 | BJ65: 2.5 | BK65: =0.024*BD65 -> 2.4 | BL65: 2.5 | BN65: =SUM(BJ65:BM65) -> 7.4 | BQ65: =BO65*BP65 -> 0 | BR65: =BI65+BN65+BQ65 -> 85.754675 | BS65: =50.73*2 -> 101.46
A66: ABM0009-251030-0003 | B66: =COUNTIF(A:A,A66) -> 1 | C66: 1 | E66: M | F66: 202510 | G66: 2025-10-30 | H66: 2025-10-30 | I66: Shipped | J66: YCD-EX:HUPPER TEK | K66: ABM0009-251030-0003 | L66: B2C | N66: qianhui.xu@miclogistik.de | O66: 1 | P66: NORMAL | Q66: 47.4 | R66: GELF-EML_HUPPERTEK | S66: RetourHermes_M | T66: 4618429406 | U66: =VLOOKUP(T66,[5]semitemu_order_export_251110144!$R:$S,2,0) -> PO-076-16633170412152347 | W66: 24937 | X66: Flensburg | Y66: DE | AC66: ABM0009-251030-0003 | AD66: B07Q3SQT6C | AE66: 金属储物柜71英寸高 | AF66: 188x49x14 | AG66: 47.4 | AI66: 1 | AJ66: =AI66*AG66 -> 47.4 | AK66: =AI66 -> 1 | AL66: 4.85 | AM66: =AL66*AK66 -> 4.85 | AP66: =AO66*AN66 -> 0 | AS66: =AR66*AQ66 -> 0 | AV66: =AU66*AT66 -> 0 | AW66: =O66 -> 1 | AX66: 3 | AY66: =AX66*AW66 -> 3 | AZ66: =AM66+AP66+AS66+AV66+AY66 -> 7.85 | BA66: 1 | BB66: =AJ66 -> 47.4 | BD66: 50 | BE66: =W66 -> 24937 | BF66: =X66 -> Flensburg | BG66: =Y66 -> DE | BH66: 46.558575 | BI66: =BH66 -> 46.558575 | BJ66: 2.5 | BK66: =0.024*BD66 -> 1.2 | BL66: 2.5 | BN66: =SUM(BJ66:BM66) -> 6.2 | BQ66: =BO66*BP66 -> 0 | BR66: =BI66+BN66+BQ66 -> 52.758575 | BS66: =AZ66+BR66 -> 60.608575
A67: ABM0009-251030-0002 | B67: =COUNTIF(A:A,A67) -> 1 | C67: 1 | E67: M | F67: 202510 | G67: 2025-10-30 | H67: 2025-10-30 | I67: Shipped | J67: YCD-EX:HUPPER TEK | K67: ABM0009-251030-0002 | L67: B2C | N67: qianhui.xu@miclogistik.de | O67: 1 | P67: NORMAL | Q67: 47.4 | R67: GELF-EML_HUPPERTEK | S67: RetourHermes_M | T67: 4618429390 | U67: =VLOOKUP(T67,[6]ebay_order_export_251110145132!$S:$T,2,0) -> 20-13751-77631 | W67: 52382 | X67: Niederzier | Y67: DE | AC67: ABM0009-251030-0002 | AD67: B07Q3SQT6C | AE67: 金属储物柜71英寸高 | AF67: 188x49x14 | AG67: 47.4 | AI67: 1 | AJ67: =AI67*AG67 -> 47.4 | AK67: =AI67 -> 1 | AL67: 4.85 | AM67: =AL67*AK67 -> 4.85 | AP67: =AO67*AN67 -> 0 | AS67: =AR67*AQ67 -> 0 | AV67: =AU67*AT67 -> 0 | AW67: =O67 -> 1 | AX67: 3 | AY67: =AX67*AW67 -> 3 | AZ67: =AM67+AP67+AS67+AV67+AY67 -> 7.85 | BA67: 1 | BB67: =AJ67 -> 47.4 | BD67: 50 | BE67: =W67 -> 52382 | BF67: =X67 -> Niederzier | BG67: =Y67 -> DE | BH67: 46.558575 | BI67: =BH67 -> 46.558575 | BJ67: 2.5 | BK67: =0.024*BD67 -> 1.2 | BL67: 2.5 | BN67: =SUM(BJ67:BM67) -> 6.2 | BQ67: =BO67*BP67 -> 0 | BR67: =BI67+BN67+BQ67 -> 52.758575 | BS67: =AZ67+BR67 -> 60.608575
A68: ABM0009-251030-0001 | B68: =COUNTIF(A:A,A68) -> 1 | C68: 1 | E68: M | F68: 202510 | G68: 2025-10-30 | H68: 2025-10-30 | I68: Shipped | J68: YCD-EX:HUPPER TEK | K68: ABM0009-251030-0001 | L68: B2C | N68: qianhui.xu@miclogistik.de | O68: 1 | P68: NORMAL | Q68: 47.4 | R68: GELF-EML_HUPPERTEK | S68: RetourHermes_M | T68: 4618429383 | U68: =VLOOKUP(T68,[6]ebay_order_export_251110145132!$S:$T,2,0) -> 18-13753-94406 | W68: 36199 | X68: Rotenburg | Y68: DE | AC68: ABM0009-251030-0001 | AD68: B07Q3SQT6C | AE68: 金属储物柜71英寸高 | AF68: 188x49x14 | AG68: 47.4 | AI68: 1 | AJ68: =AI68*AG68 -> 47.4 | AK68: =AI68 -> 1 | AL68: 4.85 | AM68: =AL68*AK68 -> 4.85 | AP68: =AO68*AN68 -> 0 | AS68: =AR68*AQ68 -> 0 | AV68: =AU68*AT68 -> 0 | AW68: =O68 -> 1 | AX68: 3 | AY68: =AX68*AW68 -> 3 | AZ68: =AM68+AP68+AS68+AV68+AY68 -> 7.85 | BA68: 1 | BB68: =AJ68 -> 47.4 | BD68: 50 | BE68: =W68 -> 36199 | BF68: =X68 -> Rotenburg | BG68: =Y68 -> DE | BH68: 46.558575 | BI68: =BH68 -> 46.558575 | BJ68: 2.5 | BK68: =0.024*BD68 -> 1.2 | BL68: 2.5 | BN68: =SUM(BJ68:BM68) -> 6.2 | BQ68: =BO68*BP68 -> 0 | BR68: =BI68+BN68+BQ68 -> 52.758575 | BS68: =AZ68+BR68 -> 60.608575
A69: ABM0009-251029-0002 | B69: =COUNTIF(A:A,A69) -> 1 | C69: 1 | E69: M | F69: 202510 | G69: 2025-10-30 | H69: 2025-10-30 | I69: Shipped | J69: YCD-EX:HUPPER TEK | K69: ABM0009-251029-0002 | L69: B2C | N69: qianhui.xu@miclogistik.de | O69: 1 | P69: NORMAL | Q69: 47.4 | R69: GELF-EML_HUPPERTEK | S69: RetourHermes_M | T69: 4618429376 | U69: =VLOOKUP(T69,[6]ebay_order_export_251110145132!$S:$T,2,0) -> 09-13764-00607 | W69: 83126 | X69: Flintsbach a. Inn | Y69: DE | AC69: ABM0009-251029-0002 | AD69: B07Q3SQT6C | AE69: 金属储物柜71英寸高 | AF69: 188x49x14 | AG69: 47.4 | AI69: 1 | AJ69: =AI69*AG69 -> 47.4 | AK69: =AI69 -> 1 | AL69: 4.85 | AM69: =AL69*AK69 -> 4.85 | AP69: =AO69*AN69 -> 0 | AS69: =AR69*AQ69 -> 0 | AV69: =AU69*AT69 -> 0 | AW69: =O69 -> 1 | AX69: 3 | AY69: =AX69*AW69 -> 3 | AZ69: =AM69+AP69+AS69+AV69+AY69 -> 7.85 | BA69: 1 | BB69: =AJ69 -> 47.4 | BD69: 50 | BE69: =W69 -> 83126 | BF69: =X69 -> Flintsbach a. Inn | BG69: =Y69 -> DE | BH69: 46.558575 | BI69: =BH69 -> 46.558575 | BJ69: 2.5 | BK69: =0.024*BD69 -> 1.2 | BL69: 2.5 | BN69: =SUM(BJ69:BM69) -> 6.2 | BQ69: =BO69*BP69 -> 0 | BR69: =BI69+BN69+BQ69 -> 52.758575 | BS69: =AZ69+BR69 -> 60.608575
A70: ABM0009-251031-0001 | B70: =COUNTIF(A:A,A70) -> 1 | C70: 1 | E70: M | F70: 202510 | G70: 2025-10-31 | H70: 2025-10-31 | I70: Shipped | J70: YCD-EX:HUPPER TEK | K70: ABM0009-251031-0001 | L70: B2C | N70: klee.cao@miclogistik.de | O70: 1 | P70: NORMAL | Q70: 47.4 | R70: GELF-EML_HUPPERTEK | S70: RetourHermes_M | T70: 4618433557 | U70: =VLOOKUP(T70,[6]ebay_order_export_251110145132!$S:$T,2,0) -> 14-13763-61044 | W70: 8223 | X70: Falkenstein /Vogtl. | Y70: DE | AC70: ABM0009-251031-0001 | AD70: B07Q3SQT6C | AE70: 金属储物柜71英寸高 | AF70: 188x49x14 | AG70: 47.4 | AI70: 1 | AJ70: =AI70*AG70 -> 47.4 | AK70: =AI70 -> 1 | AL70: 4.85 | AM70: =AL70*AK70 -> 4.85 | AP70: =AO70*AN70 -> 0 | AS70: =AR70*AQ70 -> 0 | AV70: =AU70*AT70 -> 0 | AW70: =O70 -> 1 | AX70: 3 | AY70: =AX70*AW70 -> 3 | AZ70: =AM70+AP70+AS70+AV70+AY70 -> 7.85 | BA70: 1 | BB70: =AJ70 -> 47.4 | BD70: 50 | BE70: =W70 -> 8223 | BF70: =X70 -> Falkenstein /Vogtl. | BG70: =Y70 -> DE | BH70: 46.558575 | BI70: =BH70 -> 46.558575 | BJ70: 2.5 | BK70: =0.024*BD70 -> 1.2 | BL70: 2.5 | BN70: =SUM(BJ70:BM70) -> 6.2 | BQ70: =BO70*BP70 -> 0 | BR70: =BI70+BN70+BQ70 -> 52.758575 | BS70: =AZ70+BR70 -> 60.608575
A71: ABM0009-251030-0004 | B71: =COUNTIF(A:A,A71) -> 1 | C71: 1 | E71: M | F71: 202510 | G71: 2025-10-31 | H71: 2025-10-31 | I71: Shipped | J71: YCD-EX:HUPPER TEK | K71: ABM0009-251030-0004 | L71: B2C | N71: klee.cao@miclogistik.de | O71: 3 | P71: NORMAL | Q71: 142.2 | R71: GELF-EML_HUPPERTEK | S71: RetourHermes_M | T71: 4618433564 | U71: 13-13763-08698 | W71: 66119 | X71: Saarbrücken | Y71: DE | AC71: ABM0009-251030-0004 | AD71: B077RVYZRF | AE71: =VLOOKUP(AD71,物品明细!A:B,2,0) -> 德国联邦快递金属储物柜 | AF71: =VLOOKUP(AD71,物品明细!A:I,9,0) -> 188x49x14 | AG71: =VLOOKUP(AD71,物品明细!A:D,4,0) -> 47.4 | AI71: 3 | AJ71: =AI71*AG71 -> 142.2 | AK71: =AI71 -> 3 | AL71: 4.85 | AM71: =AL71*AK71 -> 14.55 | AP71: =AO71*AN71 -> 0 | AS71: =AR71*AQ71 -> 0 | AV71: =AU71*AT71 -> 0 | AW71: =O71 -> 3 | AX71: 3 | AY71: =AX71*AW71 -> 9 | AZ71: =AM71+AP71+AS71+AV71+AY71 -> 23.55 | BA71: 1 | BB71: =AJ71 -> 142.2 | BD71: 150 | BE71: =W71 -> 66119 | BF71: =X71 -> Saarbrücken | BG71: =Y71 -> DE | BH71: 96.523875 | BI71: =BH71 -> 96.523875 | BJ71: 2.5 | BK71: =0.024*BD71 -> 3.6 | BL71: 2.5 | BN71: =SUM(BJ71:BM71) -> 8.6 | BQ71: =BO71*BP71 -> 0 | BR71: =BI71+BN71+BQ71 -> 105.12387 | BS71: =43*3 -> 129

Sheet 2.3 正向-2C-DHL
A1: MIC德国海外仓一件代发明细表 | AM1: =SUM(AM5:AM10) -> 4.8 | AP1: =SUM(AP5:AP10) -> 0 | AS1: =SUM(AS5:AS10) -> 0 | AV1: =SUM(AV5:AV10) -> 0 | AZ1: =SUM(AZ5:AZ10) -> 4.8 | BF1: =SUM(BF5:BF10) -> 33.14115 | BJ1: =SUM(BJ5:BJ10) -> 123.06851 | BK1: =SUM(BK5:BK10) -> 156.20966 | BL1: =SUM(BL5:BL10) -> 161.00966
A2: ,1m, | BA2: 尾程运输费 | BL2: 总费用合计
A3: 出库指令 | AD3: 物品-拣料及最小包装 | AK3: 拣货费 | AN3: 拣货续件费 | AQ3: 贴标费 | AT3: 包材费-包裹 | AW3: 打包费-包裹 | AZ3: 库内小计 | BA3: 基础费 | BK3: 尾程费用合计
A4: Order No. | B4: 订单 行数 | C4: 订单数 | D4: 对账 | E4: Warehouse | F4: 月份 | G4: Order Created At | H4: Shipped At | I4: Status | J4: Customer | K4: Original Reference | L4: Business Type | M4: Channel | N4: Creator | O4: 运单数 | P4: Priority | Q4: weight | R4: Carrier | S4: Carrier Return | T4: Shipments No1 | U4: Shipments No2 | V4: Retour No | W4: Postal Code | X4: 城市 | Y4: Country | Z4: sndZip | AA4: sndCity | AB4: sndCountry | AC4: RefOnLabel | AD4: Item ID | AE4: 物品描述 | AF4: 物品尺寸 长宽高cm | AG4: 单个物品 重量kg | AH4: Item Batch | AI4: Item Qty | AJ4: 订单重量 kg | AK4: 数量 套 | AL4: 单价 Euro | AM4: 金额 Euro | AN4: 数量 pcs | AO4: 单价 Euro | AP4: 金额 Euro | AQ4: 标签/张 | AR4: 单价 | AS4: 金额 | AT4: 数量 pcs | AU4: 单价 Euro | AV4: 金额 Euro | AW4: 数量 pcs | AX4: 单价 Euro | AY4: 金额 Euro | BA4: 数量 /包裹 | BB4: 实际重kg | BC4: 计费 重量 kg | BD4: 国家 | BE4: 单价 Euro | BF4: 金额 Euro | BG4: 燃油&路桥费 | BH4: 其它 | BI4: 能源附加费 | BJ4: 附加费小计
A5: ABM0009-251031-0009 | B5: =COUNTIF(A:A,A5) -> 1 | C5: 1 | E5: M | F5: 202510 | G5: 2025-10-31 | H5: 2025-10-31 | I5: Shipped | J5: YCD-EX:HUPPER TEK | K5: ABM0009-251031-0009 | L5: B2C | N5: klee.cao@miclogistik.de | O5: 1 | P5: NORMAL | Q5: 14 | R5: DHL_M2CEU_M | S5: RetourHermes_M | T5: 00340434789991020630 | U5: ST-PO-076-04282019543672524 | W5: 23556 | X5: Lübeck | Y5: DE | AC5: ABM0009-251031-0009 | AD5: B07GSF11XX | AE5: =VLOOKUP(AD5,物品明细!A:B,2,0) -> 白板 | AF5: =VLOOKUP(AD5,物品明细!A:I,9,0) -> 133x87x8 | AG5: =VLOOKUP(AD5,物品明细!A:D,4,0) -> 14 | AI5: 1 | AJ5: =AI5*AG5 -> 14 | AK5: =AI5 -> 1 | AL5: 0.8 | AM5: =AL5*AK5 -> 0.8 | AP5: =AO5*AN5 -> 0 | AS5: =AR5*AQ5 -> 0 | AV5: =AU5*AT5 -> 0 | AY5: =AX5*AW5 -> 0 | AZ5: =AM5+AP5+AS5+AV5+AY5 -> 0.8 | BA5: 1 | BB5: =AJ5 -> 14 | BC5: 15 | BD5: =Y5 -> DE | BE5: 5.523525 | BF5: =BA5*BE5 -> 5.523525 | BG5: =BA5*0.19 -> 0.19 | BH5: =BA5*20 -> 20 | BI5: =(BH5+BG5+BF5)*1.25% -> 0.32141906 | BJ5: =SUM(BG5:BI5) -> 20.511419 | BK5: =BF5+BJ5 -> 26.034944 | BL5: =AZ5+BK5 -> 26.834944
A6: ABM0009-251031-0008 | B6: =COUNTIF(A:A,A6) -> 1 | C6: 1 | E6: M | F6: 202510 | G6: 2025-10-31 | H6: 2025-10-31 | I6: Shipped | J6: YCD-EX:HUPPER TEK | K6: ABM0009-251031-0008 | L6: B2C | N6: klee.cao@miclogistik.de | O6: 1 | P6: NORMAL | Q6: 14 | R6: DHL_M2CEU_M | S6: RetourHermes_M | T6: 00340434789991020623 | U6: =VLOOKUP(T6,[5]semitemu_order_export_251110144!$R:$S,2,0) -> PO-076-11313748040313333 | W6: 97846 | X6: Partenstein | Y6: DE | AC6: ABM0009-251031-0008 | AD6: B07GSF11XX | AE6: =VLOOKUP(AD6,物品明细!A:B,2,0) -> 白板 | AF6: =VLOOKUP(AD6,物品明细!A:I,9,0) -> 133x87x8 | AG6: =VLOOKUP(AD6,物品明细!A:D,4,0) -> 14 | AI6: 1 | AJ6: =AI6*AG6 -> 14 | AK6: =AI6 -> 1 | AL6: 0.8 | AM6: =AL6*AK6 -> 0.8 | AP6: =AO6*AN6 -> 0 | AS6: =AR6*AQ6 -> 0 | AV6: =AU6*AT6 -> 0 | AY6: =AX6*AW6 -> 0 | AZ6: =AM6+AP6+AS6+AV6+AY6 -> 0.8 | BA6: 1 | BB6: =AJ6 -> 14 | BC6: 15 | BD6: =Y6 -> DE | BE6: 5.523525 | BF6: =BA6*BE6 -> 5.523525 | BG6: =BA6*0.19 -> 0.19 | BH6: =BA6*20 -> 20 | BI6: =(BH6+BG6+BF6)*1.25% -> 0.32141906 | BJ6: =SUM(BG6:BI6) -> 20.511419 | BK6: =BF6+BJ6 -> 26.034944 | BL6: =AZ6+BK6 -> 26.834944
A7: ABM0009-251031-0007 | B7: =COUNTIF(A:A,A7) -> 1 | C7: 1 | E7: M | F7: 202510 | G7: 2025-10-31 | H7: 2025-10-31 | I7: Shipped | J7: YCD-EX:HUPPER TEK | K7: ABM0009-251031-0007 | L7: B2C | N7: klee.cao@miclogistik.de | O7: 1 | P7: NORMAL | Q7: 14 | R7: DHL_M2CEU_M | S7: RetourHermes_M | T7: 00340434789991020616 | U7: =VLOOKUP(T7,[5]semitemu_order_export_251110144!$R:$S,2,0) -> PO-076-11441826061430008 | W7: 1762 | X7: Hartmannsdorf-Reichenau | Y7: DE | AC7: ABM0009-251031-0007 | AD7: B07GSF11XX | AE7: =VLOOKUP(AD7,物品明细!A:B,2,0) -> 白板 | AF7: =VLOOKUP(AD7,物品明细!A:I,9,0) -> 133x87x8 | AG7: =VLOOKUP(AD7,物品明细!A:D,4,0) -> 14 | AI7: 1 | AJ7: =AI7*AG7 -> 14 | AK7: =AI7 -> 1 | AL7: 0.8 | AM7: =AL7*AK7 -> 0.8 | AP7: =AO7*AN7 -> 0 | AS7: =AR7*AQ7 -> 0 | AV7: =AU7*AT7 -> 0 | AY7: =AX7*AW7 -> 0 | AZ7: =AM7+AP7+AS7+AV7+AY7 -> 0.8 | BA7: 1 | BB7: =AJ7 -> 14 | BC7: 15 | BD7: =Y7 -> DE | BE7: 5.523525 | BF7: =BA7*BE7 -> 5.523525 | BG7: =BA7*0.19 -> 0.19 | BH7: =BA7*20 -> 20 | BI7: =(BH7+BG7+BF7)*1.25% -> 0.32141906 | BJ7: =SUM(BG7:BI7) -> 20.511419 | BK7: =BF7+BJ7 -> 26.034944 | BL7: =AZ7+BK7 -> 26.834944
A8: ABM0009-251031-0006 | B8: =COUNTIF(A:A,A8) -> 1 | C8: 1 | E8: M | F8: 202510 | G8: 2025-10-31 | H8: 2025-10-31 | I8: Shipped | J8: YCD-EX:HUPPER TEK | K8: ABM0009-251031-0006 | L8: B2C | N8: klee.cao@miclogistik.de | O8: 1 | P8: NORMAL | Q8: 14 | R8: DHL_M2CEU_M | S8: RetourHermes_M | T8: 00340434789991020609 | U8: =VLOOKUP(T8,[5]semitemu_order_export_251110144!$R:$S,2,0) -> PO-076-05547350851192886 | W8: 2977 | X8: Hoyerswerda | Y8: DE | AC8: ABM0009-251031-0006 | AD8: B07GSF11XX | AE8: =VLOOKUP(AD8,物品明细!A:B,2,0) -> 白板 | AF8: =VLOOKUP(AD8,物品明细!A:I,9,0) -> 133x87x8 | AG8: =VLOOKUP(AD8,物品明细!A:D,4,0) -> 14 | AI8: 1 | AJ8: =AI8*AG8 -> 14 | AK8: =AI8 -> 1 | AL8: 0.8 | AM8: =AL8*AK8 -> 0.8 | AP8: =AO8*AN8 -> 0 | AS8: =AR8*AQ8 -> 0 | AV8: =AU8*AT8 -> 0 | AY8: =AX8*AW8 -> 0 | AZ8: =AM8+AP8+AS8+AV8+AY8 -> 0.8 | BA8: 1 | BB8: =AJ8 -> 14 | BC8: 15 | BD8: =Y8 -> DE | BE8: 5.523525 | BF8: =BA8*BE8 -> 5.523525 | BG8: =BA8*0.19 -> 0.19 | BH8: =BA8*20 -> 20 | BI8: =(BH8+BG8+BF8)*1.25% -> 0.32141906 | BJ8: =SUM(BG8:BI8) -> 20.511419 | BK8: =BF8+BJ8 -> 26.034944 | BL8: =AZ8+BK8 -> 26.834944
A9: ABM0009-251031-0005 | B9: =COUNTIF(A:A,A9) -> 1 | C9: 1 | E9: M | F9: 202510 | G9: 2025-10-31 | H9: 2025-10-31 | I9: Shipped | J9: YCD-EX:HUPPER TEK | K9: ABM0009-251031-0005 | L9: B2C | N9: klee.cao@miclogistik.de | O9: 1 | P9: NORMAL | Q9: 14 | R9: DHL_M2CEU_M | S9: RetourHermes_M | T9: 00340434789991020593 | U9: =VLOOKUP(T9,[5]semitemu_order_export_251110144!$R:$S,2,0) -> PO-076-16606314678392251 | W9: 73230 | X9: Kirchheim unter Teck | Y9: DE | AC9: ABM0009-251031-0005 | AD9: B07GSF11XX | AE9: =VLOOKUP(AD9,物品明细!A:B,2,0) -> 白板 | AF9: =VLOOKUP(AD9,物品明细!A:I,9,0) -> 133x87x8 | AG9: =VLOOKUP(AD9,物品明细!A:D,4,0) -> 14 | AI9: 1 | AJ9: =AI9*AG9 -> 14 | AK9: =AI9 -> 1 | AL9: 0.8 | AM9: =AL9*AK9 -> 0.8 | AP9: =AO9*AN9 -> 0 | AS9: =AR9*AQ9 -> 0 | AV9: =AU9*AT9 -> 0 | AY9: =AX9*AW9 -> 0 | AZ9: =AM9+AP9+AS9+AV9+AY9 -> 0.8 | BA9: 1 | BB9: =AJ9 -> 14 | BC9: 15 | BD9: =Y9 -> DE | BE9: 5.523525 | BF9: =BA9*BE9 -> 5.523525 | BG9: =BA9*0.19 -> 0.19 | BH9: =BA9*20 -> 20 | BI9: =(BH9+BG9+BF9)*1.25% -> 0.32141906 | BJ9: =SUM(BG9:BI9) -> 20.511419 | BK9: =BF9+BJ9 -> 26.034944 | BL9: =AZ9+BK9 -> 26.834944
A10: ABM0009-251031-0004 | B10: =COUNTIF(A:A,A10) -> 1 | C10: 1 | E10: M | F10: 202510 | G10: 2025-10-31 | H10: 2025-10-31 | I10: Shipped | J10: YCD-EX:HUPPER TEK | K10: ABM0009-251031-0004 | L10: B2C | N10: klee.cao@miclogistik.de | O10: 1 | P10: NORMAL | Q10: 14 | R10: DHL_M2CEU_M | S10: RetourHermes_M | T10: 00340434789991020586 | U10: =VLOOKUP(T10,[5]semitemu_order_export_251110144!$R:$S,2,0) -> PO-076-19667027295350902 | W10: 14770 | X10: Brandenburg an der Havel | Y10: DE | AC10: ABM0009-251031-0004 | AD10: B07GSF11XX | AE10: =VLOOKUP(AD10,物品明细!A:B,2,0) -> 白板 | AF10: =VLOOKUP(AD10,物品明细!A:I,9,0) -> 133x87x8 | AG10: =VLOOKUP(AD10,物品明细!A:D,4,0) -> 14 | AI10: 1 | AJ10: =AI10*AG10 -> 14 | AK10: =AI10 -> 1 | AL10: 0.8 | AM10: =AL10*AK10 -> 0.8 | AP10: =AO10*AN10 -> 0 | AS10: =AR10*AQ10 -> 0 | AV10: =AU10*AT10 -> 0 | AY10: =AX10*AW10 -> 0 | AZ10: =AM10+AP10+AS10+AV10+AY10 -> 0.8 | BA10: 1 | BB10: =AJ10 -> 14 | BC10: 15 | BD10: =Y10 -> DE | BE10: 5.523525 | BF10: =BA10*BE10 -> 5.523525 | BG10: =BA10*0.19 -> 0.19 | BH10: =BA10*20 -> 20 | BI10: =(BH10+BG10+BF10)*1.25% -> 0.32141906 | BJ10: =SUM(BG10:BI10) -> 20.511419 | BK10: =BF10+BJ10 -> 26.034944 | BL10: =AZ10+BK10 -> 26.834944

Sheet 2.4 正向-2C-PlanB 
A1: MIC德国海外仓一件代发明细表 | AY1: =SUM(AY5:AY6) -> 264 | BD1: =SUM(BD5:BD6) -> 0 | BG1: =SUM(BG5:BG6) -> 0 | BH1: =SUM(BH5:BH6) -> 264
A2: ,1m, | AQ2: 尾程运输费
A3: 出库指令 | AD3: 物品-拣料及最小包装 | AQ3: 基础费 | AZ3: 附加费 | BE3: 3件包裹以上运输续件费 | BH3: 尾程费用合计
A4: Order No. | B4: 订单 行数 | C4: 订单数 | D4: 对账 | E4: Warehouse | F4: 月份 | G4: Order Created At | H4: Shipped At | I4: Status | J4: Customer | K4: Original Reference | L4: Business Type | M4: Channel | N4: Creator | O4: 运单数 | P4: Priority | Q4: weight | R4: Carrier | S4: Carrier Return | T4: Shipments No1 | U4: Shipments No2 | V4: Retour No | W4: Postal Code | X4: 城市 | Y4: Country | Z4: sndZip | AA4: sndCity | AB4: sndCountry | AC4: RefOnLabel | AD4: Item ID | AE4: 物品描述 | AF4: 物品尺寸 长宽高cm | AG4: 单个物品 重量kg | AH4: Item Batch | AI4: Item Qty | AJ4: 托盘数量 | AK4: 打托规格 | AL4: 单托重 | AP4: 订单重量 kg | AQ4: 数量 票 | AR4: 实际重kg | AS4: 体积重KG | AT4: 计费 重量 kg | AU4: 邮编所属区域 | AV4: 城市 | AW4: 国家 | AX4: 单价 Euro | AY4: 金额 Euro | AZ4: 运输 订单 管理 * | BA4: 过路 过桥 * | BB4: 预约 通知 * | BC4: 其它 | BD4: 附加费小计 | BE4: 包裹数 个 | BF4: 单价 Euro | BG4: 金额 Euro
A5: MO202510240161 | B5: =COUNTIF(A:A,A5) -> 2 | C5: 1 | F5: 202510 | G5: 2025-10-24 | H5: 0001-01-01 | I5: FinWithoutOutbound | J5: YCD-EX:HUPPER TEK | L5: Transport | N5: vicky.peng@miclogistik.de | O5: 5 | P5: NORMAL | Q5: 290 | R5: PlanB | W5: 40670 | X5: Meerbusch | Y5: DE | Z5: 47533 | AA5: Kleve | AB5: DE | AC5: MO202510240161 | AJ5: 2 | AK5: 132.5X87X210 | AL5: 298.4 | AM5: 0 | AO5: 0 | AP5: =AL5*AJ5 -> 596.8 | AQ5: 1 | AR5: =AP5 -> 596.8 | AT5: 50 | AU5: =W5 -> 40670 | AV5: =X5 -> Meerbusch | AW5: =Y5 -> DE | AX5: 264 | AY5: =AQ5*AX5 -> 264 | BH5: =AY5+BD5+BG5 -> 264
A6: MO202510240161 | B6: =COUNTIF(A:A,A6) -> 2 | C6: 0 | F6: 202510 | G6: 2025-10-24 | H6: 0001-01-01 | I6: FinWithoutOutbound | J6: YCD-EX:HUPPER TEK | L6: Transport | N6: vicky.peng@miclogistik.de | O6: 5 | P6: NORMAL | Q6: 290 | R6: PlanB | W6: 40670 | X6: Meerbusch | Y6: DE | Z6: 47533 | AA6: Kleve | AB6: DE | AC6: MO202510240161 | AJ6: 3 | AK6: 132.5X87X210 | AL6: 283.1 | AM6: 0 | AO6: 0 | AP6: =AL6*AJ6 -> 849.3 | AQ6: 0 | AR6: =AP6 -> 849.3 | AT6: 50 | AU6: =W6 -> 40670 | AV6: =X6 -> Meerbusch | AW6: =Y6 -> DE | BH6: =AY6+BD6+BG6 -> 0

Sheet 3.1 正向-普货-仓储费 
AP1: =SUM(AP6:AP160) -> 829.10948
A2: 计费时间IStorage Charge Date | C2: 入仓信息Inbound Information | I2: 商品信息Product Information | Q2: 装箱信息 | V2: 打托信息 | AA2: 原始入仓数量 | AE2: 进销存信息 | AJ2: 仓储费计费信息/Storage Charge Infromation | AQ2: 备注
A3: 月份 | B3: 日期 | C3: 仓库名称 | D3: 仓库编码 | E3: 客户代码 | F3: 入库任务号 | G3: 原始参考号 | H3: 入库上架时间 | I3: 编码 | J3: 条码 | K3: 商品名称 | L3: 件型 | M3: 长 | N3: 宽 | O3: 高 | P3: 单品体积A | Q3: 装箱数 | R3: 长 | S3: 宽 | T3: 高 | U3: 单箱体积B | V3: 打托数 | W3: 长 | X3: 宽 | Y3: 高 | Z3: 单托体积C | AA3: 托数 | AB3: 箱数 | AC3: 总数 | AD3: 批次号 | AE3: 期初库存数 | AF3: 入库数 | AG3: 出库数 | AH3: 期末库存数 | AI3: 计费单元 | AJ3: 库存体积E | AK3: 实际计费体积F | AL3: 库龄 | AM3: 库龄段 | AN3: 计费单价 | AO3: 币种 | AP3: 仓储费
A4: / | B4: / | C4: / | D4: / | E4: / | F4: / | G4: / | H4: / | I4: / | J4: / | K4: / | M4: cm | N4: cm | O4: cm | P4: CBM/m³ | Q4: pcs | R4: cm | S4: cm | T4: cm | U4: CBM/m³ | V4: pcs/box | W4: cm | X4: cm | Y4: cm | Z4: CBM/m³ | AA4: 托/Pallet | AB4: 箱/Box | AC4: 件/pcs | AE4: 件/pcs | AF4: 件/pcs | AG4: 件/pcs | AH4: 件/pcs | AI4: pcs/box/pallet | AJ4: CBM/m³ | AK4: CBM/m³ | AL4: 天/day | AM4: 天/day | AN4: / | AO4: Euro | AP4: Euro
A5: Month | B5: Date | C5: Warehouse Name | D5: Warehouse Code | E5: Client Code | F5: Task No. | G5: Original Ref. No. | H5: Inbound Time | I5: SKU | J5: Barcode | K5: Product Name | L5: Product Type | M5: Lenth | N5: Width | O5: Height | P5: Product Volume-A | Q5: Qty per Box | R5: Lenth | S5: Width | T5: Height | U5: Box Volume-B | V5: Qty per Pallet | W5: Lenth | X5: Width | Y5: Height | Z5: Pallet Volume-B | AA5: Qty of Pallet | AB5: Qty of Carton | AC5: Total Qty. | AD5: Batch No. | AE5: Beginning Inv | AF5: Inbound | AG5: Outbound | AH5: Ending Inv. | AI5: Charge Unit | AJ5: INV Volume-E | AK5: Charge Volume-F | AL5: Storage Age | AM5: Storage Age Range | AN5: Charge Price | AO5: Curreny | AP5: Storage Amount | AQ5: Rermar
A6: 202510 | B6: 45931 | C6: MIC德国仓 | D6: M » N2 - 1 | E6: YCD-EX:HUPPER TEK | F6: MI202508130012 | G6: DE2508031-G7-MIC | H6: 45889 | I6: B07BK8W5MF | K6: =VLOOKUP(I6,物品明细!A:B,2,0) -> 金属储物柜71英寸银色 | M6: =VLOOKUP(I6,物品明细!A:E,5,0) -> 188 | N6: =VLOOKUP(I6,物品明细!A:F,6,0) -> 49 | O6: =VLOOKUP(I6,物品明细!A:G,7,0) -> 14 | P6: =M6*N6*O6/1000000 -> 0.128968 | R6: =VLOOKUP(I6,物品明细!A:E,5,0) -> 188 | S6: =VLOOKUP(I6,物品明细!A:F,6,0) -> 49 | T6: =VLOOKUP(I6,物品明细!A:G,7,0) -> 14 | U6: =R6*S6*T6/1000000 -> 0.128968 | AA6: 21 | AB6: 247 | AC6: 247 | AD6: 0 | AE6: 108 | AG6: 1 | AH6: =AE6+AF6-AG6 -> 107 | AI6: pcs | AJ6: =AH6*P6 -> 13.799576 | AK6: =AJ6 -> 13.799576 | AL6: =B6-H6+1 -> 43 | AM6: =IF(AL6<=30,"30天内",IF(AL6<=90,"31-90天","91天以上")) -> 31-90天 | AN6: 0.7 | AO6: Euro | AP6: =AK6*AN6 -> 9.6597032
A7: 202510 | B7: 45932 | C7: MIC德国仓 | D7: =D6 -> M » N2 - 1 | E7: =E6 -> YCD-EX:HUPPER TEK | F7: =F6 -> MI202508130012 | G7: =G6 -> DE2508031-G7-MIC | H7: =H6 -> 45889 | I7: =I6 -> B07BK8W5MF | K7: =K6 -> 金属储物柜71英寸银色 | M7: =M6 -> 188 | N7: =N6 -> 49 | O7: =O6 -> 14 | P7: =M7*N7*O7/1000000 -> 0.128968 | R7: =R6 -> 188 | S7: =S6 -> 49 | T7: =T6 -> 14 | U7: =R7*S7*T7/1000000 -> 0.128968 | AA7: =AA6 -> 21 | AB7: =AB6 -> 247 | AC7: =AC6 -> 247 | AD7: 0 | AE7: =AH6 -> 107 | AH7: =AE7+AF7-AG7 -> 107 | AI7: pcs | AJ7: =AH7*P7 -> 13.799576 | AK7: =AJ7 -> 13.799576 | AL7: =B7-H7+1 -> 44 | AM7: =IF(AL7<=30,"30天内",IF(AL7<=90,"31-90天","91天以上")) -> 31-90天 | AN7: 0.7 | AO7: Euro | AP7: =AK7*AN7 -> 9.6597032
A8: 202510 | B8: 45933 | C8: MIC德国仓 | D8: =D7 -> M » N2 - 1 | E8: =E7 -> YCD-EX:HUPPER TEK | F8: =F7 -> MI202508130012 | G8: =G7 -> DE2508031-G7-MIC | H8: =H7 -> 45889 | I8: =I7 -> B07BK8W5MF | K8: =K7 -> 金属储物柜71英寸银色 | M8: =M7 -> 188 | N8: =N7 -> 49 | O8: =O7 -> 14 | P8: =M8*N8*O8/1000000 -> 0.128968 | R8: =R7 -> 188 | S8: =S7 -> 49 | T8: =T7 -> 14 | U8: =R8*S8*T8/1000000 -> 0.128968 | AA8: =AA7 -> 21 | AB8: =AB7 -> 247 | AC8: =AC7 -> 247 | AD8: 0 | AE8: =AH7 -> 107 | AH8: =AE8+AF8-AG8 -> 107 | AI8: pcs | AJ8: =AH8*P8 -> 13.799576 | AK8: =AJ8 -> 13.799576 | AL8: =B8-H8+1 -> 45 | AM8: =IF(AL8<=30,"30天内",IF(AL8<=90,"31-90天","91天以上")) -> 31-90天 | AN8: 0.7 | AO8: Euro | AP8: =AK8*AN8 -> 9.6597032
A9: 202510 | B9: 45934 | C9: MIC德国仓 | D9: =D8 -> M » N2 - 1 | E9: =E8 -> YCD-EX:HUPPER TEK | F9: =F8 -> MI202508130012 | G9: =G8 -> DE2508031-G7-MIC | H9: =H8 -> 45889 | I9: =I8 -> B07BK8W5MF | K9: =K8 -> 金属储物柜71英寸银色 | M9: =M8 -> 188 | N9: =N8 -> 49 | O9: =O8 -> 14 | P9: =M9*N9*O9/1000000 -> 0.128968 | R9: =R8 -> 188 | S9: =S8 -> 49 | T9: =T8 -> 14 | U9: =R9*S9*T9/1000000 -> 0.128968 | AA9: =AA8 -> 21 | AB9: =AB8 -> 247 | AC9: =AC8 -> 247 | AD9: 0 | AE9: =AH8 -> 107 | AH9: =AE9+AF9-AG9 -> 107 | AI9: pcs | AJ9: =AH9*P9 -> 13.799576 | AK9: =AJ9 -> 13.799576 | AL9: =B9-H9+1 -> 46 | AM9: =IF(AL9<=30,"30天内",IF(AL9<=90,"31-90天","91天以上")) -> 31-90天 | AN9: 0.7 | AO9: Euro | AP9: =AK9*AN9 -> 9.6597032
A10: 202510 | B10: 45935 | C10: MIC德国仓 | D10: =D9 -> M » N2 - 1 | E10: =E9 -> YCD-EX:HUPPER TEK | F10: =F9 -> MI202508130012 | G10: =G9 -> DE2508031-G7-MIC | H10: =H9 -> 45889 | I10: =I9 -> B07BK8W5MF | K10: =K9 -> 金属储物柜71英寸银色 | M10: =M9 -> 188 | N10: =N9 -> 49 | O10: =O9 -> 14 | P10: =M10*N10*O10/1000000 -> 0.128968 | R10: =R9 -> 188 | S10: =S9 -> 49 | T10: =T9 -> 14 | U10: =R10*S10*T10/1000000 -> 0.128968 | AA10: =AA9 -> 21 | AB10: =AB9 -> 247 | AC10: =AC9 -> 247 | AD10: 0 | AE10: =AH9 -> 107 | AH10: =AE10+AF10-AG10 -> 107 | AI10: pcs | AJ10: =AH10*P10 -> 13.799576 | AK10: =AJ10 -> 13.799576 | AL10: =B10-H10+1 -> 47 | AM10: =IF(AL10<=30,"30天内",IF(AL10<=90,"31-90天","91天以上")) -> 31-90天 | AN10: 0.7 | AO10: Euro | AP10: =AK10*AN10 -> 9.6597032
A11: 202510 | B11: 45936 | C11: MIC德国仓 | D11: =D10 -> M » N2 - 1 | E11: =E10 -> YCD-EX:HUPPER TEK | F11: =F10 -> MI202508130012 | G11: =G10 -> DE2508031-G7-MIC | H11: =H10 -> 45889 | I11: =I10 -> B07BK8W5MF | K11: =K10 -> 金属储物柜71英寸银色 | M11: =M10 -> 188 | N11: =N10 -> 49 | O11: =O10 -> 14 | P11: =M11*N11*O11/1000000 -> 0.128968 | R11: =R10 -> 188 | S11: =S10 -> 49 | T11: =T10 -> 14 | U11: =R11*S11*T11/1000000 -> 0.128968 | AA11: =AA10 -> 21 | AB11: =AB10 -> 247 | AC11: =AC10 -> 247 | AD11: 0 | AE11: =AH10 -> 107 | AG11: 3 | AH11: =AE11+AF11-AG11 -> 104 | AI11: pcs | AJ11: =AH11*P11 -> 13.412672 | AK11: =AJ11 -> 13.412672 | AL11: =B11-H11+1 -> 48 | AM11: =IF(AL11<=30,"30天内",IF(AL11<=90,"31-90天","91天以上")) -> 31-90天 | AN11: 0.7 | AO11: Euro | AP11: =AK11*AN11 -> 9.3888704
A12: 202510 | B12: 45937 | C12: MIC德国仓 | D12: =D11 -> M » N2 - 1 | E12: =E11 -> YCD-EX:HUPPER TEK | F12: =F11 -> MI202508130012 | G12: =G11 -> DE2508031-G7-MIC | H12: =H11 -> 45889 | I12: =I11 -> B07BK8W5MF | K12: =K11 -> 金属储物柜71英寸银色 | M12: =M11 -> 188 | N12: =N11 -> 49 | O12: =O11 -> 14 | P12: =M12*N12*O12/1000000 -> 0.128968 | R12: =R11 -> 188 | S12: =S11 -> 49 | T12: =T11 -> 14 | U12: =R12*S12*T12/1000000 -> 0.128968 | AA12: =AA11 -> 21 | AB12: =AB11 -> 247 | AC12: =AC11 -> 247 | AD12: 0 | AE12: =AH11 -> 104 | AH12: =AE12+AF12-AG12 -> 104 | AI12: pcs | AJ12: =AH12*P12 -> 13.412672 | AK12: =AJ12 -> 13.412672 | AL12: =B12-H12+1 -> 49 | AM12: =IF(AL12<=30,"30天内",IF(AL12<=90,"31-90天","91天以上")) -> 31-90天 | AN12: 0.7 | AO12: Euro | AP12: =AK12*AN12 -> 9.3888704
A13: 202510 | B13: 45938 | C13: MIC德国仓 | D13: =D12 -> M » N2 - 1 | E13: =E12 -> YCD-EX:HUPPER TEK | F13: =F12 -> MI202508130012 | G13: =G12 -> DE2508031-G7-MIC | H13: =H12 -> 45889 | I13: =I12 -> B07BK8W5MF | K13: =K12 -> 金属储物柜71英寸银色 | M13: =M12 -> 188 | N13: =N12 -> 49 | O13: =O12 -> 14 | P13: =M13*N13*O13/1000000 -> 0.128968 | R13: =R12 -> 188 | S13: =S12 -> 49 | T13: =T12 -> 14 | U13: =R13*S13*T13/1000000 -> 0.128968 | AA13: =AA12 -> 21 | AB13: =AB12 -> 247 | AC13: =AC12 -> 247 | AD13: 0 | AE13: =AH12 -> 104 | AH13: =AE13+AF13-AG13 -> 104 | AI13: pcs | AJ13: =AH13*P13 -> 13.412672 | AK13: =AJ13 -> 13.412672 | AL13: =B13-H13+1 -> 50 | AM13: =IF(AL13<=30,"30天内",IF(AL13<=90,"31-90天","91天以上")) -> 31-90天 | AN13: 0.7 | AO13: Euro | AP13: =AK13*AN13 -> 9.3888704
A14: 202510 | B14: 45939 | C14: MIC德国仓 | D14: =D13 -> M » N2 - 1 | E14: =E13 -> YCD-EX:HUPPER TEK | F14: =F13 -> MI202508130012 | G14: =G13 -> DE2508031-G7-MIC | H14: =H13 -> 45889 | I14: =I13 -> B07BK8W5MF | K14: =K13 -> 金属储物柜71英寸银色 | M14: =M13 -> 188 | N14: =N13 -> 49 | O14: =O13 -> 14 | P14: =M14*N14*O14/1000000 -> 0.128968 | R14: =R13 -> 188 | S14: =S13 -> 49 | T14: =T13 -> 14 | U14: =R14*S14*T14/1000000 -> 0.128968 | AA14: =AA13 -> 21 | AB14: =AB13 -> 247 | AC14: =AC13 -> 247 | AD14: 0 | AE14: =AH13 -> 104 | AH14: =AE14+AF14-AG14 -> 104 | AI14: pcs | AJ14: =AH14*P14 -> 13.412672 | AK14: =AJ14 -> 13.412672 | AL14: =B14-H14+1 -> 51 | AM14: =IF(AL14<=30,"30天内",IF(AL14<=90,"31-90天","91天以上")) -> 31-90天 | AN14: 0.7 | AO14: Euro | AP14: =AK14*AN14 -> 9.3888704
A15: 202510 | B15: 45940 | C15: MIC德国仓 | D15: =D14 -> M » N2 - 1 | E15: =E14 -> YCD-EX:HUPPER TEK | F15: =F14 -> MI202508130012 | G15: =G14 -> DE2508031-G7-MIC | H15: =H14 -> 45889 | I15: =I14 -> B07BK8W5MF | K15: =K14 -> 金属储物柜71英寸银色 | M15: =M14 -> 188 | N15: =N14 -> 49 | O15: =O14 -> 14 | P15: =M15*N15*O15/1000000 -> 0.128968 | R15: =R14 -> 188 | S15: =S14 -> 49 | T15: =T14 -> 14 | U15: =R15*S15*T15/1000000 -> 0.128968 | AA15: =AA14 -> 21 | AB15: =AB14 -> 247 | AC15: =AC14 -> 247 | AD15: 0 | AE15: =AH14 -> 104 | AH15: =AE15+AF15-AG15 -> 104 | AI15: pcs | AJ15: =AH15*P15 -> 13.412672 | AK15: =AJ15 -> 13.412672 | AL15: =B15-H15+1 -> 52 | AM15: =IF(AL15<=30,"30天内",IF(AL15<=90,"31-90天","91天以上")) -> 31-90天 | AN15: 0.7 | AO15: Euro | AP15: =AK15*AN15 -> 9.3888704
A16: 202510 | B16: 45941 | C16: MIC德国仓 | D16: =D15 -> M » N2 - 1 | E16: =E15 -> YCD-EX:HUPPER TEK | F16: =F15 -> MI202508130012 | G16: =G15 -> DE2508031-G7-MIC | H16: =H15 -> 45889 | I16: =I15 -> B07BK8W5MF | K16: =K15 -> 金属储物柜71英寸银色 | M16: =M15 -> 188 | N16: =N15 -> 49 | O16: =O15 -> 14 | P16: =M16*N16*O16/1000000 -> 0.128968 | R16: =R15 -> 188 | S16: =S15 -> 49 | T16: =T15 -> 14 | U16: =R16*S16*T16/1000000 -> 0.128968 | AA16: =AA15 -> 21 | AB16: =AB15 -> 247 | AC16: =AC15 -> 247 | AD16: 0 | AE16: =AH15 -> 104 | AH16: =AE16+AF16-AG16 -> 104 | AI16: pcs | AJ16: =AH16*P16 -> 13.412672 | AK16: =AJ16 -> 13.412672 | AL16: =B16-H16+1 -> 53 | AM16: =IF(AL16<=30,"30天内",IF(AL16<=90,"31-90天","91天以上")) -> 31-90天 | AN16: 0.7 | AO16: Euro | AP16: =AK16*AN16 -> 9.3888704
A17: 202510 | B17: 45942 | C17: MIC德国仓 | D17: =D16 -> M » N2 - 1 | E17: =E16 -> YCD-EX:HUPPER TEK | F17: =F16 -> MI202508130012 | G17: =G16 -> DE2508031-G7-MIC | H17: =H16 -> 45889 | I17: =I16 -> B07BK8W5MF | K17: =K16 -> 金属储物柜71英寸银色 | M17: =M16 -> 188 | N17: =N16 -> 49 | O17: =O16 -> 14 | P17: =M17*N17*O17/1000000 -> 0.128968 | R17: =R16 -> 188 | S17: =S16 -> 49 | T17: =T16 -> 14 | U17: =R17*S17*T17/1000000 -> 0.128968 | AA17: =AA16 -> 21 | AB17: =AB16 -> 247 | AC17: =AC16 -> 247 | AD17: 0 | AE17: =AH16 -> 104 | AH17: =AE17+AF17-AG17 -> 104 | AI17: pcs | AJ17: =AH17*P17 -> 13.412672 | AK17: =AJ17 -> 13.412672 | AL17: =B17-H17+1 -> 54 | AM17: =IF(AL17<=30,"30天内",IF(AL17<=90,"31-90天","91天以上")) -> 31-90天 | AN17: 0.7 | AO17: Euro | AP17: =AK17*AN17 -> 9.3888704
A18: 202510 | B18: 45943 | C18: MIC德国仓 | D18: =D17 -> M » N2 - 1 | E18: =E17 -> YCD-EX:HUPPER TEK | F18: =F17 -> MI202508130012 | G18: =G17 -> DE2508031-G7-MIC | H18: =H17 -> 45889 | I18: =I17 -> B07BK8W5MF | K18: =K17 -> 金属储物柜71英寸银色 | M18: =M17 -> 188 | N18: =N17 -> 49 | O18: =O17 -> 14 | P18: =M18*N18*O18/1000000 -> 0.128968 | R18: =R17 -> 188 | S18: =S17 -> 49 | T18: =T17 -> 14 | U18: =R18*S18*T18/1000000 -> 0.128968 | AA18: =AA17 -> 21 | AB18: =AB17 -> 247 | AC18: =AC17 -> 247 | AD18: 0 | AE18: =AH17 -> 104 | AG18: 1 | AH18: =AE18+AF18-AG18 -> 103 | AI18: pcs | AJ18: =AH18*P18 -> 13.283704 | AK18: =AJ18 -> 13.283704 | AL18: =B18-H18+1 -> 55 | AM18: =IF(AL18<=30,"30天内",IF(AL18<=90,"31-90天","91天以上")) -> 31-90天 | AN18: 0.7 | AO18: Euro | AP18: =AK18*AN18 -> 9.2985928
A19: 202510 | B19: 45944 | C19: MIC德国仓 | D19: =D18 -> M » N2 - 1 | E19: =E18 -> YCD-EX:HUPPER TEK | F19: =F18 -> MI202508130012 | G19: =G18 -> DE2508031-G7-MIC | H19: =H18 -> 45889 | I19: =I18 -> B07BK8W5MF | K19: =K18 -> 金属储物柜71英寸银色 | M19: =M18 -> 188 | N19: =N18 -> 49 | O19: =O18 -> 14 | P19: =M19*N19*O19/1000000 -> 0.128968 | R19: =R18 -> 188 | S19: =S18 -> 49 | T19: =T18 -> 14 | U19: =R19*S19*T19/1000000 -> 0.128968 | AA19: =AA18 -> 21 | AB19: =AB18 -> 247 | AC19: =AC18 -> 247 | AD19: 0 | AE19: =AH18 -> 103 | AH19: =AE19+AF19-AG19 -> 103 | AI19: pcs | AJ19: =AH19*P19 -> 13.283704 | AK19: =AJ19 -> 13.283704 | AL19: =B19-H19+1 -> 56 | AM19: =IF(AL19<=30,"30天内",IF(AL19<=90,"31-90天","91天以上")) -> 31-90天 | AN19: 0.7 | AO19: Euro | AP19: =AK19*AN19 -> 9.2985928
A20: 202510 | B20: 45945 | C20: MIC德国仓 | D20: =D19 -> M » N2 - 1 | E20: =E19 -> YCD-EX:HUPPER TEK | F20: =F19 -> MI202508130012 | G20: =G19 -> DE2508031-G7-MIC | H20: =H19 -> 45889 | I20: =I19 -> B07BK8W5MF | K20: =K19 -> 金属储物柜71英寸银色 | M20: =M19 -> 188 | N20: =N19 -> 49 | O20: =O19 -> 14 | P20: =M20*N20*O20/1000000 -> 0.128968 | R20: =R19 -> 188 | S20: =S19 -> 49 | T20: =T19 -> 14 | U20: =R20*S20*T20/1000000 -> 0.128968 | AA20: =AA19 -> 21 | AB20: =AB19 -> 247 | AC20: =AC19 -> 247 | AD20: 0 | AE20: =AH19 -> 103 | AH20: =AE20+AF20-AG20 -> 103 | AI20: pcs | AJ20: =AH20*P20 -> 13.283704 | AK20: =AJ20 -> 13.283704 | AL20: =B20-H20+1 -> 57 | AM20: =IF(AL20<=30,"30天内",IF(AL20<=90,"31-90天","91天以上")) -> 31-90天 | AN20: 0.7 | AO20: Euro | AP20: =AK20*AN20 -> 9.2985928
A21: 202510 | B21: 45946 | C21: MIC德国仓 | D21: =D20 -> M » N2 - 1 | E21: =E20 -> YCD-EX:HUPPER TEK | F21: =F20 -> MI202508130012 | G21: =G20 -> DE2508031-G7-MIC | H21: =H20 -> 45889 | I21: =I20 -> B07BK8W5MF | K21: =K20 -> 金属储物柜71英寸银色 | M21: =M20 -> 188 | N21: =N20 -> 49 | O21: =O20 -> 14 | P21: =M21*N21*O21/1000000 -> 0.128968 | R21: =R20 -> 188 | S21: =S20 -> 49 | T21: =T20 -> 14 | U21: =R21*S21*T21/1000000 -> 0.128968 | AA21: =AA20 -> 21 | AB21: =AB20 -> 247 | AC21: =AC20 -> 247 | AD21: 0 | AE21: =AH20 -> 103 | AH21: =AE21+AF21-AG21 -> 103 | AI21: pcs | AJ21: =AH21*P21 -> 13.283704 | AK21: =AJ21 -> 13.283704 | AL21: =B21-H21+1 -> 58 | AM21: =IF(AL21<=30,"30天内",IF(AL21<=90,"31-90天","91天以上")) -> 31-90天 | AN21: 0.7 | AO21: Euro | AP21: =AK21*AN21 -> 9.2985928
A22: 202510 | B22: 45947 | C22: MIC德国仓 | D22: =D21 -> M » N2 - 1 | E22: =E21 -> YCD-EX:HUPPER TEK | F22: =F21 -> MI202508130012 | G22: =G21 -> DE2508031-G7-MIC | H22: =H21 -> 45889 | I22: =I21 -> B07BK8W5MF | K22: =K21 -> 金属储物柜71英寸银色 | M22: =M21 -> 188 | N22: =N21 -> 49 | O22: =O21 -> 14 | P22: =M22*N22*O22/1000000 -> 0.128968 | R22: =R21 -> 188 | S22: =S21 -> 49 | T22: =T21 -> 14 | U22: =R22*S22*T22/1000000 -> 0.128968 | AA22: =AA21 -> 21 | AB22: =AB21 -> 247 | AC22: =AC21 -> 247 | AD22: 0 | AE22: =AH21 -> 103 | AG22: 1 | AH22: =AE22+AF22-AG22 -> 102 | AI22: pcs | AJ22: =AH22*P22 -> 13.154736 | AK22: =AJ22 -> 13.154736 | AL22: =B22-H22+1 -> 59 | AM22: =IF(AL22<=30,"30天内",IF(AL22<=90,"31-90天","91天以上")) -> 31-90天 | AN22: 0.7 | AO22: Euro | AP22: =AK22*AN22 -> 9.2083152
A23: 202510 | B23: 45948 | C23: MIC德国仓 | D23: =D22 -> M » N2 - 1 | E23: =E22 -> YCD-EX:HUPPER TEK | F23: =F22 -> MI202508130012 | G23: =G22 -> DE2508031-G7-MIC | H23: =H22 -> 45889 | I23: =I22 -> B07BK8W5MF | K23: =K22 -> 金属储物柜71英寸银色 | M23: =M22 -> 188 | N23: =N22 -> 49 | O23: =O22 -> 14 | P23: =M23*N23*O23/1000000 -> 0.128968 | R23: =R22 -> 188 | S23: =S22 -> 49 | T23: =T22 -> 14 | U23: =R23*S23*T23/1000000 -> 0.128968 | AA23: =AA22 -> 21 | AB23: =AB22 -> 247 | AC23: =AC22 -> 247 | AD23: 0 | AE23: =AH22 -> 102 | AH23: =AE23+AF23-AG23 -> 102 | AI23: pcs | AJ23: =AH23*P23 -> 13.154736 | AK23: =AJ23 -> 13.154736 | AL23: =B23-H23+1 -> 60 | AM23: =IF(AL23<=30,"30天内",IF(AL23<=90,"31-90天","91天以上")) -> 31-90天 | AN23: 0.7 | AO23: Euro | AP23: =AK23*AN23 -> 9.2083152
A24: 202510 | B24: 45949 | C24: MIC德国仓 | D24: =D23 -> M » N2 - 1 | E24: =E23 -> YCD-EX:HUPPER TEK | F24: =F23 -> MI202508130012 | G24: =G23 -> DE2508031-G7-MIC | H24: =H23 -> 45889 | I24: =I23 -> B07BK8W5MF | K24: =K23 -> 金属储物柜71英寸银色 | M24: =M23 -> 188 | N24: =N23 -> 49 | O24: =O23 -> 14 | P24: =M24*N24*O24/1000000 -> 0.128968 | R24: =R23 -> 188 | S24: =S23 -> 49 | T24: =T23 -> 14 | U24: =R24*S24*T24/1000000 -> 0.128968 | AA24: =AA23 -> 21 | AB24: =AB23 -> 247 | AC24: =AC23 -> 247 | AD24: 0 | AE24: =AH23 -> 102 | AH24: =AE24+AF24-AG24 -> 102 | AI24: pcs | AJ24: =AH24*P24 -> 13.154736 | AK24: =AJ24 -> 13.154736 | AL24: =B24-H24+1 -> 61 | AM24: =IF(AL24<=30,"30天内",IF(AL24<=90,"31-90天","91天以上")) -> 31-90天 | AN24: 0.7 | AO24: Euro | AP24: =AK24*AN24 -> 9.2083152
A25: 202510 | B25: 45950 | C25: MIC德国仓 | D25: =D24 -> M » N2 - 1 | E25: =E24 -> YCD-EX:HUPPER TEK | F25: =F24 -> MI202508130012 | G25: =G24 -> DE2508031-G7-MIC | H25: =H24 -> 45889 | I25: =I24 -> B07BK8W5MF | K25: =K24 -> 金属储物柜71英寸银色 | M25: =M24 -> 188 | N25: =N24 -> 49 | O25: =O24 -> 14 | P25: =M25*N25*O25/1000000 -> 0.128968 | R25: =R24 -> 188 | S25: =S24 -> 49 | T25: =T24 -> 14 | U25: =R25*S25*T25/1000000 -> 0.128968 | AA25: =AA24 -> 21 | AB25: =AB24 -> 247 | AC25: =AC24 -> 247 | AD25: 0 | AE25: =AH24 -> 102 | AG25: 8 | AH25: =AE25+AF25-AG25 -> 94 | AI25: pcs | AJ25: =AH25*P25 -> 12.122992 | AK25: =AJ25 -> 12.122992 | AL25: =B25-H25+1 -> 62 | AM25: =IF(AL25<=30,"30天内",IF(AL25<=90,"31-90天","91天以上")) -> 31-90天 | AN25: 0.7 | AO25: Euro | AP25: =AK25*AN25 -> 8.4860944
A26: 202510 | B26: 45951 | C26: MIC德国仓 | D26: =D25 -> M » N2 - 1 | E26: =E25 -> YCD-EX:HUPPER TEK | F26: =F25 -> MI202508130012 | G26: =G25 -> DE2508031-G7-MIC | H26: =H25 -> 45889 | I26: =I25 -> B07BK8W5MF | K26: =K25 -> 金属储物柜71英寸银色 | M26: =M25 -> 188 | N26: =N25 -> 49 | O26: =O25 -> 14 | P26: =M26*N26*O26/1000000 -> 0.128968 | R26: =R25 -> 188 | S26: =S25 -> 49 | T26: =T25 -> 14 | U26: =R26*S26*T26/1000000 -> 0.128968 | AA26: =AA25 -> 21 | AB26: =AB25 -> 247 | AC26: =AC25 -> 247 | AD26: 0 | AE26: =AH25 -> 94 | AH26: =AE26+AF26-AG26 -> 94 | AI26: pcs | AJ26: =AH26*P26 -> 12.122992 | AK26: =AJ26 -> 12.122992 | AL26: =B26-H26+1 -> 63 | AM26: =IF(AL26<=30,"30天内",IF(AL26<=90,"31-90天","91天以上")) -> 31-90天 | AN26: 0.7 | AO26: Euro | AP26: =AK26*AN26 -> 8.4860944
A27: 202510 | B27: 45952 | C27: MIC德国仓 | D27: =D26 -> M » N2 - 1 | E27: =E26 -> YCD-EX:HUPPER TEK | F27: =F26 -> MI202508130012 | G27: =G26 -> DE2508031-G7-MIC | H27: =H26 -> 45889 | I27: =I26 -> B07BK8W5MF | K27: =K26 -> 金属储物柜71英寸银色 | M27: =M26 -> 188 | N27: =N26 -> 49 | O27: =O26 -> 14 | P27: =M27*N27*O27/1000000 -> 0.128968 | R27: =R26 -> 188 | S27: =S26 -> 49 | T27: =T26 -> 14 | U27: =R27*S27*T27/1000000 -> 0.128968 | AA27: =AA26 -> 21 | AB27: =AB26 -> 247 | AC27: =AC26 -> 247 | AD27: 0 | AE27: =AH26 -> 94 | AH27: =AE27+AF27-AG27 -> 94 | AI27: pcs | AJ27: =AH27*P27 -> 12.122992 | AK27: =AJ27 -> 12.122992 | AL27: =B27-H27+1 -> 64 | AM27: =IF(AL27<=30,"30天内",IF(AL27<=90,"31-90天","91天以上")) -> 31-90天 | AN27: 0.7 | AO27: Euro | AP27: =AK27*AN27 -> 8.4860944
A28: 202510 | B28: 45953 | C28: MIC德国仓 | D28: =D27 -> M » N2 - 1 | E28: =E27 -> YCD-EX:HUPPER TEK | F28: =F27 -> MI202508130012 | G28: =G27 -> DE2508031-G7-MIC | H28: =H27 -> 45889 | I28: =I27 -> B07BK8W5MF | K28: =K27 -> 金属储物柜71英寸银色 | M28: =M27 -> 188 | N28: =N27 -> 49 | O28: =O27 -> 14 | P28: =M28*N28*O28/1000000 -> 0.128968 | R28: =R27 -> 188 | S28: =S27 -> 49 | T28: =T27 -> 14 | U28: =R28*S28*T28/1000000 -> 0.128968 | AA28: =AA27 -> 21 | AB28: =AB27 -> 247 | AC28: =AC27 -> 247 | AD28: 0 | AE28: =AH27 -> 94 | AG28: 1 | AH28: =AE28+AF28-AG28 -> 93 | AI28: pcs | AJ28: =AH28*P28 -> 11.994024 | AK28: =AJ28 -> 11.994024 | AL28: =B28-H28+1 -> 65 | AM28: =IF(AL28<=30,"30天内",IF(AL28<=90,"31-90天","91天以上")) -> 31-90天 | AN28: 0.7 | AO28: Euro | AP28: =AK28*AN28 -> 8.3958168
A29: 202510 | B29: 45954 | C29: MIC德国仓 | D29: =D28 -> M » N2 - 1 | E29: =E28 -> YCD-EX:HUPPER TEK | F29: =F28 -> MI202508130012 | G29: =G28 -> DE2508031-G7-MIC | H29: =H28 -> 45889 | I29: =I28 -> B07BK8W5MF | K29: =K28 -> 金属储物柜71英寸银色 | M29: =M28 -> 188 | N29: =N28 -> 49 | O29: =O28 -> 14 | P29: =M29*N29*O29/1000000 -> 0.128968 | R29: =R28 -> 188 | S29: =S28 -> 49 | T29: =T28 -> 14 | U29: =R29*S29*T29/1000000 -> 0.128968 | AA29: =AA28 -> 21 | AB29: =AB28 -> 247 | AC29: =AC28 -> 247 | AD29: 0 | AE29: =AH28 -> 93 | AH29: =AE29+AF29-AG29 -> 93 | AI29: pcs | AJ29: =AH29*P29 -> 11.994024 | AK29: =AJ29 -> 11.994024 | AL29: =B29-H29+1 -> 66 | AM29: =IF(AL29<=30,"30天内",IF(AL29<=90,"31-90天","91天以上")) -> 31-90天 | AN29: 0.7 | AO29: Euro | AP29: =AK29*AN29 -> 8.3958168
A30: 202510 | B30: 45955 | C30: MIC德国仓 | D30: =D29 -> M » N2 - 1 | E30: =E29 -> YCD-EX:HUPPER TEK | F30: =F29 -> MI202508130012 | G30: =G29 -> DE2508031-G7-MIC | H30: =H29 -> 45889 | I30: =I29 -> B07BK8W5MF | K30: =K29 -> 金属储物柜71英寸银色 | M30: =M29 -> 188 | N30: =N29 -> 49 | O30: =O29 -> 14 | P30: =M30*N30*O30/1000000 -> 0.128968 | R30: =R29 -> 188 | S30: =S29 -> 49 | T30: =T29 -> 14 | U30: =R30*S30*T30/1000000 -> 0.128968 | AA30: =AA29 -> 21 | AB30: =AB29 -> 247 | AC30: =AC29 -> 247 | AD30: 0 | AE30: =AH29 -> 93 | AH30: =AE30+AF30-AG30 -> 93 | AI30: pcs | AJ30: =AH30*P30 -> 11.994024 | AK30: =AJ30 -> 11.994024 | AL30: =B30-H30+1 -> 67 | AM30: =IF(AL30<=30,"30天内",IF(AL30<=90,"31-90天","91天以上")) -> 31-90天 | AN30: 0.7 | AO30: Euro | AP30: =AK30*AN30 -> 8.3958168
A31: 202510 | B31: 45956 | C31: MIC德国仓 | D31: =D30 -> M » N2 - 1 | E31: =E30 -> YCD-EX:HUPPER TEK | F31: =F30 -> MI202508130012 | G31: =G30 -> DE2508031-G7-MIC | H31: =H30 -> 45889 | I31: =I30 -> B07BK8W5MF | K31: =K30 -> 金属储物柜71英寸银色 | M31: =M30 -> 188 | N31: =N30 -> 49 | O31: =O30 -> 14 | P31: =M31*N31*O31/1000000 -> 0.128968 | R31: =R30 -> 188 | S31: =S30 -> 49 | T31: =T30 -> 14 | U31: =R31*S31*T31/1000000 -> 0.128968 | AA31: =AA30 -> 21 | AB31: =AB30 -> 247 | AC31: =AC30 -> 247 | AD31: 0 | AE31: =AH30 -> 93 | AH31: =AE31+AF31-AG31 -> 93 | AI31: pcs | AJ31: =AH31*P31 -> 11.994024 | AK31: =AJ31 -> 11.994024 | AL31: =B31-H31+1 -> 68 | AM31: =IF(AL31<=30,"30天内",IF(AL31<=90,"31-90天","91天以上")) -> 31-90天 | AN31: 0.7 | AO31: Euro | AP31: =AK31*AN31 -> 8.3958168
A32: 202510 | B32: 45957 | C32: MIC德国仓 | D32: =D31 -> M » N2 - 1 | E32: =E31 -> YCD-EX:HUPPER TEK | F32: =F31 -> MI202508130012 | G32: =G31 -> DE2508031-G7-MIC | H32: =H31 -> 45889 | I32: =I31 -> B07BK8W5MF | K32: =K31 -> 金属储物柜71英寸银色 | M32: =M31 -> 188 | N32: =N31 -> 49 | O32: =O31 -> 14 | P32: =M32*N32*O32/1000000 -> 0.128968 | R32: =R31 -> 188 | S32: =S31 -> 49 | T32: =T31 -> 14 | U32: =R32*S32*T32/1000000 -> 0.128968 | AA32: =AA31 -> 21 | AB32: =AB31 -> 247 | AC32: =AC31 -> 247 | AD32: 0 | AE32: =AH31 -> 93 | AG32: 2 | AH32: =AE32+AF32-AG32 -> 91 | AI32: pcs | AJ32: =AH32*P32 -> 11.736088 | AK32: =AJ32 -> 11.736088 | AL32: =B32-H32+1 -> 69 | AM32: =IF(AL32<=30,"30天内",IF(AL32<=90,"31-90天","91天以上")) -> 31-90天 | AN32: 0.7 | AO32: Euro | AP32: =AK32*AN32 -> 8.2152616
A33: 202510 | B33: 45958 | C33: MIC德国仓 | D33: =D32 -> M » N2 - 1 | E33: =E32 -> YCD-EX:HUPPER TEK | F33: =F32 -> MI202508130012 | G33: =G32 -> DE2508031-G7-MIC | H33: =H32 -> 45889 | I33: =I32 -> B07BK8W5MF | K33: =K32 -> 金属储物柜71英寸银色 | M33: =M32 -> 188 | N33: =N32 -> 49 | O33: =O32 -> 14 | P33: =M33*N33*O33/1000000 -> 0.128968 | R33: =R32 -> 188 | S33: =S32 -> 49 | T33: =T32 -> 14 | U33: =R33*S33*T33/1000000 -> 0.128968 | AA33: =AA32 -> 21 | AB33: =AB32 -> 247 | AC33: =AC32 -> 247 | AD33: 0 | AE33: =AH32 -> 91 | AH33: =AE33+AF33-AG33 -> 91 | AI33: pcs | AJ33: =AH33*P33 -> 11.736088 | AK33: =AJ33 -> 11.736088 | AL33: =B33-H33+1 -> 70 | AM33: =IF(AL33<=30,"30天内",IF(AL33<=90,"31-90天","91天以上")) -> 31-90天 | AN33: 0.7 | AO33: Euro | AP33: =AK33*AN33 -> 8.2152616
A34: 202510 | B34: 45959 | C34: MIC德国仓 | D34: =D33 -> M » N2 - 1 | E34: =E33 -> YCD-EX:HUPPER TEK | F34: =F33 -> MI202508130012 | G34: =G33 -> DE2508031-G7-MIC | H34: =H33 -> 45889 | I34: =I33 -> B07BK8W5MF | K34: =K33 -> 金属储物柜71英寸银色 | M34: =M33 -> 188 | N34: =N33 -> 49 | O34: =O33 -> 14 | P34: =M34*N34*O34/1000000 -> 0.128968 | R34: =R33 -> 188 | S34: =S33 -> 49 | T34: =T33 -> 14 | U34: =R34*S34*T34/1000000 -> 0.128968 | AA34: =AA33 -> 21 | AB34: =AB33 -> 247 | AC34: =AC33 -> 247 | AD34: 0 | AE34: =AH33 -> 91 | AH34: =AE34+AF34-AG34 -> 91 | AI34: pcs | AJ34: =AH34*P34 -> 11.736088 | AK34: =AJ34 -> 11.736088 | AL34: =B34-H34+1 -> 71 | AM34: =IF(AL34<=30,"30天内",IF(AL34<=90,"31-90天","91天以上")) -> 31-90天 | AN34: 0.7 | AO34: Euro | AP34: =AK34*AN34 -> 8.2152616
A35: 202510 | B35: 45960 | C35: MIC德国仓 | D35: =D34 -> M » N2 - 1 | E35: =E34 -> YCD-EX:HUPPER TEK | F35: =F34 -> MI202508130012 | G35: =G34 -> DE2508031-G7-MIC | H35: =H34 -> 45889 | I35: =I34 -> B07BK8W5MF | K35: =K34 -> 金属储物柜71英寸银色 | M35: =M34 -> 188 | N35: =N34 -> 49 | O35: =O34 -> 14 | P35: =M35*N35*O35/1000000 -> 0.128968 | R35: =R34 -> 188 | S35: =S34 -> 49 | T35: =T34 -> 14 | U35: =R35*S35*T35/1000000 -> 0.128968 | AA35: =AA34 -> 21 | AB35: =AB34 -> 247 | AC35: =AC34 -> 247 | AD35: 0 | AE35: =AH34 -> 91 | AH35: =AE35+AF35-AG35 -> 91 | AI35: pcs | AJ35: =AH35*P35 -> 11.736088 | AK35: =AJ35 -> 11.736088 | AL35: =B35-H35+1 -> 72 | AM35: =IF(AL35<=30,"30天内",IF(AL35<=90,"31-90天","91天以上")) -> 31-90天 | AN35: 0.7 | AO35: Euro | AP35: =AK35*AN35 -> 8.2152616
A36: 202510 | B36: 45961 | C36: MIC德国仓 | D36: =D35 -> M » N2 - 1 | E36: =E35 -> YCD-EX:HUPPER TEK | F36: =F35 -> MI202508130012 | G36: =G35 -> DE2508031-G7-MIC | H36: =H35 -> 45889 | I36: =I35 -> B07BK8W5MF | K36: =K35 -> 金属储物柜71英寸银色 | M36: =M35 -> 188 | N36: =N35 -> 49 | O36: =O35 -> 14 | P36: =M36*N36*O36/1000000 -> 0.128968 | R36: =R35 -> 188 | S36: =S35 -> 49 | T36: =T35 -> 14 | U36: =R36*S36*T36/1000000 -> 0.128968 | AA36: =AA35 -> 21 | AB36: =AB35 -> 247 | AC36: =AC35 -> 247 | AD36: 0 | AE36: =AH35 -> 91 | AH36: =AE36+AF36-AG36 -> 91 | AI36: pcs | AJ36: =AH36*P36 -> 11.736088 | AK36: =AJ36 -> 11.736088 | AL36: =B36-H36+1 -> 73 | AM36: =IF(AL36<=30,"30天内",IF(AL36<=90,"31-90天","91天以上")) -> 31-90天 | AN36: 0.7 | AO36: Euro | AP36: =AK36*AN36 -> 8.2152616
A37: 202510 | B37: 45931 | C37: MIC德国仓 | D37: M » N2 - 1 | E37: YCD-EX:HUPPER TEK | F37: MI202508130012 | G37: DE2508031-G7-MIC | H37: 45889 | I37: B076THQBHX | K37: =VLOOKUP(I37,物品明细!A:B,2,0) -> 金属储物柜71英寸灰色 | M37: =VLOOKUP(I37,物品明细!A:E,5,0) -> 188 | N37: =VLOOKUP(I37,物品明细!A:F,6,0) -> 49 | O37: =VLOOKUP(I37,物品明细!A:G,7,0) -> 14 | P37: =M37*N37*O37/1000000 -> 0.128968 | R37: =VLOOKUP(I37,物品明细!A:E,5,0) -> 188 | S37: =VLOOKUP(I37,物品明细!A:F,6,0) -> 49 | T37: =VLOOKUP(I37,物品明细!A:G,7,0) -> 14 | U37: =R37*S37*T37/1000000 -> 0.128968 | AA37: 19 | AB37: 223 | AC37: 223 | AD37: 0 | AE37: 129 | AH37: =AE37+AF37-AG37 -> 129 | AI37: pcs | AJ37: =AH37*P37 -> 16.636872 | AK37: =AJ37 -> 16.636872 | AL37: =B37-H37+1 -> 43 | AM37: =IF(AL37<=30,"30天内",IF(AL37<=90,"31-90天","91天以上")) -> 31-90天 | AN37: 0.7 | AO37: Euro | AP37: =AK37*AN37 -> 11.64581
A38: 202510 | B38: 45932 | C38: MIC德国仓 | D38: =D37 -> M » N2 - 1 | E38: =E37 -> YCD-EX:HUPPER TEK | F38: =F37 -> MI202508130012 | G38: =G37 -> DE2508031-G7-MIC | H38: =H37 -> 45889 | I38: =I37 -> B076THQBHX | K38: =K37 -> 金属储物柜71英寸灰色 | M38: =M37 -> 188 | N38: =N37 -> 49 | O38: =O37 -> 14 | P38: =M38*N38*O38/1000000 -> 0.128968 | R38: =R37 -> 188 | S38: =S37 -> 49 | T38: =T37 -> 14 | U38: =R38*S38*T38/1000000 -> 0.128968 | AA38: =AA37 -> 19 | AB38: =AB37 -> 223 | AC38: =AC37 -> 223 | AD38: 0 | AE38: =AH37 -> 129 | AH38: =AE38+AF38-AG38 -> 129 | AI38: pcs | AJ38: =AH38*P38 -> 16.636872 | AK38: =AJ38 -> 16.636872 | AL38: =B38-H38+1 -> 44 | AM38: =IF(AL38<=30,"30天内",IF(AL38<=90,"31-90天","91天以上")) -> 31-90天 | AN38: 0.7 | AO38: Euro | AP38: =AK38*AN38 -> 11.64581
A39: 202510 | B39: 45933 | C39: MIC德国仓 | D39: =D38 -> M » N2 - 1 | E39: =E38 -> YCD-EX:HUPPER TEK | F39: =F38 -> MI202508130012 | G39: =G38 -> DE2508031-G7-MIC | H39: =H38 -> 45889 | I39: =I38 -> B076THQBHX | K39: =K38 -> 金属储物柜71英寸灰色 | M39: =M38 -> 188 | N39: =N38 -> 49 | O39: =O38 -> 14 | P39: =M39*N39*O39/1000000 -> 0.128968 | R39: =R38 -> 188 | S39: =S38 -> 49 | T39: =T38 -> 14 | U39: =R39*S39*T39/1000000 -> 0.128968 | AA39: =AA38 -> 19 | AB39: =AB38 -> 223 | AC39: =AC38 -> 223 | AD39: 0 | AE39: =AH38 -> 129 | AH39: =AE39+AF39-AG39 -> 129 | AI39: pcs | AJ39: =AH39*P39 -> 16.636872 | AK39: =AJ39 -> 16.636872 | AL39: =B39-H39+1 -> 45 | AM39: =IF(AL39<=30,"30天内",IF(AL39<=90,"31-90天","91天以上")) -> 31-90天 | AN39: 0.7 | AO39: Euro | AP39: =AK39*AN39 -> 11.64581
A40: 202510 | B40: 45934 | C40: MIC德国仓 | D40: =D39 -> M » N2 - 1 | E40: =E39 -> YCD-EX:HUPPER TEK | F40: =F39 -> MI202508130012 | G40: =G39 -> DE2508031-G7-MIC | H40: =H39 -> 45889 | I40: =I39 -> B076THQBHX | K40: =K39 -> 金属储物柜71英寸灰色 | M40: =M39 -> 188 | N40: =N39 -> 49 | O40: =O39 -> 14 | P40: =M40*N40*O40/1000000 -> 0.128968 | R40: =R39 -> 188 | S40: =S39 -> 49 | T40: =T39 -> 14 | U40: =R40*S40*T40/1000000 -> 0.128968 | AA40: =AA39 -> 19 | AB40: =AB39 -> 223 | AC40: =AC39 -> 223 | AD40: 0 | AE40: =AH39 -> 129 | AH40: =AE40+AF40-AG40 -> 129 | AI40: pcs | AJ40: =AH40*P40 -> 16.636872 | AK40: =AJ40 -> 16.636872 | AL40: =B40-H40+1 -> 46 | AM40: =IF(AL40<=30,"30天内",IF(AL40<=90,"31-90天","91天以上")) -> 31-90天 | AN40: 0.7 | AO40: Euro | AP40: =AK40*AN40 -> 11.64581
A41: 202510 | B41: 45935 | C41: MIC德国仓 | D41: =D40 -> M » N2 - 1 | E41: =E40 -> YCD-EX:HUPPER TEK | F41: =F40 -> MI202508130012 | G41: =G40 -> DE2508031-G7-MIC | H41: =H40 -> 45889 | I41: =I40 -> B076THQBHX | K41: =K40 -> 金属储物柜71英寸灰色 | M41: =M40 -> 188 | N41: =N40 -> 49 | O41: =O40 -> 14 | P41: =M41*N41*O41/1000000 -> 0.128968 | R41: =R40 -> 188 | S41: =S40 -> 49 | T41: =T40 -> 14 | U41: =R41*S41*T41/1000000 -> 0.128968 | AA41: =AA40 -> 19 | AB41: =AB40 -> 223 | AC41: =AC40 -> 223 | AD41: 0 | AE41: =AH40 -> 129 | AH41: =AE41+AF41-AG41 -> 129 | AI41: pcs | AJ41: =AH41*P41 -> 16.636872 | AK41: =AJ41 -> 16.636872 | AL41: =B41-H41+1 -> 47 | AM41: =IF(AL41<=30,"30天内",IF(AL41<=90,"31-90天","91天以上")) -> 31-90天 | AN41: 0.7 | AO41: Euro | AP41: =AK41*AN41 -> 11.64581
A42: 202510 | B42: 45936 | C42: MIC德国仓 | D42: =D41 -> M » N2 - 1 | E42: =E41 -> YCD-EX:HUPPER TEK | F42: =F41 -> MI202508130012 | G42: =G41 -> DE2508031-G7-MIC | H42: =H41 -> 45889 | I42: =I41 -> B076THQBHX | K42: =K41 -> 金属储物柜71英寸灰色 | M42: =M41 -> 188 | N42: =N41 -> 49 | O42: =O41 -> 14 | P42: =M42*N42*O42/1000000 -> 0.128968 | R42: =R41 -> 188 | S42: =S41 -> 49 | T42: =T41 -> 14 | U42: =R42*S42*T42/1000000 -> 0.128968 | AA42: =AA41 -> 19 | AB42: =AB41 -> 223 | AC42: =AC41 -> 223 | AD42: 0 | AE42: =AH41 -> 129 | AG42: 3 | AH42: =AE42+AF42-AG42 -> 126 | AI42: pcs | AJ42: =AH42*P42 -> 16.249968 | AK42: =AJ42 -> 16.249968 | AL42: =B42-H42+1 -> 48 | AM42: =IF(AL42<=30,"30天内",IF(AL42<=90,"31-90天","91天以上")) -> 31-90天 | AN42: 0.7 | AO42: Euro | AP42: =AK42*AN42 -> 11.374978
A43: 202510 | B43: 45937 | C43: MIC德国仓 | D43: =D42 -> M » N2 - 1 | E43: =E42 -> YCD-EX:HUPPER TEK | F43: =F42 -> MI202508130012 | G43: =G42 -> DE2508031-G7-MIC | H43: =H42 -> 45889 | I43: =I42 -> B076THQBHX | K43: =K42 -> 金属储物柜71英寸灰色 | M43: =M42 -> 188 | N43: =N42 -> 49 | O43: =O42 -> 14 | P43: =M43*N43*O43/1000000 -> 0.128968 | R43: =R42 -> 188 | S43: =S42 -> 49 | T43: =T42 -> 14 | U43: =R43*S43*T43/1000000 -> 0.128968 | AA43: =AA42 -> 19 | AB43: =AB42 -> 223 | AC43: =AC42 -> 223 | AD43: 0 | AE43: =AH42 -> 126 | AG43: 1 | AH43: =AE43+AF43-AG43 -> 125 | AI43: pcs | AJ43: =AH43*P43 -> 16.121 | AK43: =AJ43 -> 16.121 | AL43: =B43-H43+1 -> 49 | AM43: =IF(AL43<=30,"30天内",IF(AL43<=90,"31-90天","91天以上")) -> 31-90天 | AN43: 0.7 | AO43: Euro | AP43: =AK43*AN43 -> 11.2847
A44: 202510 | B44: 45938 | C44: MIC德国仓 | D44: =D43 -> M » N2 - 1 | E44: =E43 -> YCD-EX:HUPPER TEK | F44: =F43 -> MI202508130012 | G44: =G43 -> DE2508031-G7-MIC | H44: =H43 -> 45889 | I44: =I43 -> B076THQBHX | K44: =K43 -> 金属储物柜71英寸灰色 | M44: =M43 -> 188 | N44: =N43 -> 49 | O44: =O43 -> 14 | P44: =M44*N44*O44/1000000 -> 0.128968 | R44: =R43 -> 188 | S44: =S43 -> 49 | T44: =T43 -> 14 | U44: =R44*S44*T44/1000000 -> 0.128968 | AA44: =AA43 -> 19 | AB44: =AB43 -> 223 | AC44: =AC43 -> 223 | AD44: 0 | AE44: =AH43 -> 125 | AH44: =AE44+AF44-AG44 -> 125 | AI44: pcs | AJ44: =AH44*P44 -> 16.121 | AK44: =AJ44 -> 16.121 | AL44: =B44-H44+1 -> 50 | AM44: =IF(AL44<=30,"30天内",IF(AL44<=90,"31-90天","91天以上")) -> 31-90天 | AN44: 0.7 | AO44: Euro | AP44: =AK44*AN44 -> 11.2847
A45: 202510 | B45: 45939 | C45: MIC德国仓 | D45: =D44 -> M » N2 - 1 | E45: =E44 -> YCD-EX:HUPPER TEK | F45: =F44 -> MI202508130012 | G45: =G44 -> DE2508031-G7-MIC | H45: =H44 -> 45889 | I45: =I44 -> B076THQBHX | K45: =K44 -> 金属储物柜71英寸灰色 | M45: =M44 -> 188 | N45: =N44 -> 49 | O45: =O44 -> 14 | P45: =M45*N45*O45/1000000 -> 0.128968 | R45: =R44 -> 188 | S45: =S44 -> 49 | T45: =T44 -> 14 | U45: =R45*S45*T45/1000000 -> 0.128968 | AA45: =AA44 -> 19 | AB45: =AB44 -> 223 | AC45: =AC44 -> 223 | AD45: 0 | AE45: =AH44 -> 125 | AH45: =AE45+AF45-AG45 -> 125 | AI45: pcs | AJ45: =AH45*P45 -> 16.121 | AK45: =AJ45 -> 16.121 | AL45: =B45-H45+1 -> 51 | AM45: =IF(AL45<=30,"30天内",IF(AL45<=90,"31-90天","91天以上")) -> 31-90天 | AN45: 0.7 | AO45: Euro | AP45: =AK45*AN45 -> 11.2847
A46: 202510 | B46: 45940 | C46: MIC德国仓 | D46: =D45 -> M » N2 - 1 | E46: =E45 -> YCD-EX:HUPPER TEK | F46: =F45 -> MI202508130012 | G46: =G45 -> DE2508031-G7-MIC | H46: =H45 -> 45889 | I46: =I45 -> B076THQBHX | K46: =K45 -> 金属储物柜71英寸灰色 | M46: =M45 -> 188 | N46: =N45 -> 49 | O46: =O45 -> 14 | P46: =M46*N46*O46/1000000 -> 0.128968 | R46: =R45 -> 188 | S46: =S45 -> 49 | T46: =T45 -> 14 | U46: =R46*S46*T46/1000000 -> 0.128968 | AA46: =AA45 -> 19 | AB46: =AB45 -> 223 | AC46: =AC45 -> 223 | AD46: 0 | AE46: =AH45 -> 125 | AH46: =AE46+AF46-AG46 -> 125 | AI46: pcs | AJ46: =AH46*P46 -> 16.121 | AK46: =AJ46 -> 16.121 | AL46: =B46-H46+1 -> 52 | AM46: =IF(AL46<=30,"30天内",IF(AL46<=90,"31-90天","91天以上")) -> 31-90天 | AN46: 0.7 | AO46: Euro | AP46: =AK46*AN46 -> 11.2847
A47: 202510 | B47: 45941 | C47: MIC德国仓 | D47: =D46 -> M » N2 - 1 | E47: =E46 -> YCD-EX:HUPPER TEK | F47: =F46 -> MI202508130012 | G47: =G46 -> DE2508031-G7-MIC | H47: =H46 -> 45889 | I47: =I46 -> B076THQBHX | K47: =K46 -> 金属储物柜71英寸灰色 | M47: =M46 -> 188 | N47: =N46 -> 49 | O47: =O46 -> 14 | P47: =M47*N47*O47/1000000 -> 0.128968 | R47: =R46 -> 188 | S47: =S46 -> 49 | T47: =T46 -> 14 | U47: =R47*S47*T47/1000000 -> 0.128968 | AA47: =AA46 -> 19 | AB47: =AB46 -> 223 | AC47: =AC46 -> 223 | AD47: 0 | AE47: =AH46 -> 125 | AH47: =AE47+AF47-AG47 -> 125 | AI47: pcs | AJ47: =AH47*P47 -> 16.121 | AK47: =AJ47 -> 16.121 | AL47: =B47-H47+1 -> 53 | AM47: =IF(AL47<=30,"30天内",IF(AL47<=90,"31-90天","91天以上")) -> 31-90天 | AN47: 0.7 | AO47: Euro | AP47: =AK47*AN47 -> 11.2847
A48: 202510 | B48: 45942 | C48: MIC德国仓 | D48: =D47 -> M » N2 - 1 | E48: =E47 -> YCD-EX:HUPPER TEK | F48: =F47 -> MI202508130012 | G48: =G47 -> DE2508031-G7-MIC | H48: =H47 -> 45889 | I48: =I47 -> B076THQBHX | K48: =K47 -> 金属储物柜71英寸灰色 | M48: =M47 -> 188 | N48: =N47 -> 49 | O48: =O47 -> 14 | P48: =M48*N48*O48/1000000 -> 0.128968 | R48: =R47 -> 188 | S48: =S47 -> 49 | T48: =T47 -> 14 | U48: =R48*S48*T48/1000000 -> 0.128968 | AA48: =AA47 -> 19 | AB48: =AB47 -> 223 | AC48: =AC47 -> 223 | AD48: 0 | AE48: =AH47 -> 125 | AH48: =AE48+AF48-AG48 -> 125 | AI48: pcs | AJ48: =AH48*P48 -> 16.121 | AK48: =AJ48 -> 16.121 | AL48: =B48-H48+1 -> 54 | AM48: =IF(AL48<=30,"30天内",IF(AL48<=90,"31-90天","91天以上")) -> 31-90天 | AN48: 0.7 | AO48: Euro | AP48: =AK48*AN48 -> 11.2847
A49: 202510 | B49: 45943 | C49: MIC德国仓 | D49: =D48 -> M » N2 - 1 | E49: =E48 -> YCD-EX:HUPPER TEK | F49: =F48 -> MI202508130012 | G49: =G48 -> DE2508031-G7-MIC | H49: =H48 -> 45889 | I49: =I48 -> B076THQBHX | K49: =K48 -> 金属储物柜71英寸灰色 | M49: =M48 -> 188 | N49: =N48 -> 49 | O49: =O48 -> 14 | P49: =M49*N49*O49/1000000 -> 0.128968 | R49: =R48 -> 188 | S49: =S48 -> 49 | T49: =T48 -> 14 | U49: =R49*S49*T49/1000000 -> 0.128968 | AA49: =AA48 -> 19 | AB49: =AB48 -> 223 | AC49: =AC48 -> 223 | AD49: 0 | AE49: =AH48 -> 125 | AG49: 1 | AH49: =AE49+AF49-AG49 -> 124 | AI49: pcs | AJ49: =AH49*P49 -> 15.992032 | AK49: =AJ49 -> 15.992032 | AL49: =B49-H49+1 -> 55 | AM49: =IF(AL49<=30,"30天内",IF(AL49<=90,"31-90天","91天以上")) -> 31-90天 | AN49: 0.7 | AO49: Euro | AP49: =AK49*AN49 -> 11.194422
A50: 202510 | B50: 45944 | C50: MIC德国仓 | D50: =D49 -> M » N2 - 1 | E50: =E49 -> YCD-EX:HUPPER TEK | F50: =F49 -> MI202508130012 | G50: =G49 -> DE2508031-G7-MIC | H50: =H49 -> 45889 | I50: =I49 -> B076THQBHX | K50: =K49 -> 金属储物柜71英寸灰色 | M50: =M49 -> 188 | N50: =N49 -> 49 | O50: =O49 -> 14 | P50: =M50*N50*O50/1000000 -> 0.128968 | R50: =R49 -> 188 | S50: =S49 -> 49 | T50: =T49 -> 14 | U50: =R50*S50*T50/1000000 -> 0.128968 | AA50: =AA49 -> 19 | AB50: =AB49 -> 223 | AC50: =AC49 -> 223 | AD50: 0 | AE50: =AH49 -> 124 | AG50: 1 | AH50: =AE50+AF50-AG50 -> 123 | AI50: pcs | AJ50: =AH50*P50 -> 15.863064 | AK50: =AJ50 -> 15.863064 | AL50: =B50-H50+1 -> 56 | AM50: =IF(AL50<=30,"30天内",IF(AL50<=90,"31-90天","91天以上")) -> 31-90天 | AN50: 0.7 | AO50: Euro | AP50: =AK50*AN50 -> 11.104145
A51: 202510 | B51: 45945 | C51: MIC德国仓 | D51: =D50 -> M » N2 - 1 | E51: =E50 -> YCD-EX:HUPPER TEK | F51: =F50 -> MI202508130012 | G51: =G50 -> DE2508031-G7-MIC | H51: =H50 -> 45889 | I51: =I50 -> B076THQBHX | K51: =K50 -> 金属储物柜71英寸灰色 | M51: =M50 -> 188 | N51: =N50 -> 49 | O51: =O50 -> 14 | P51: =M51*N51*O51/1000000 -> 0.128968 | R51: =R50 -> 188 | S51: =S50 -> 49 | T51: =T50 -> 14 | U51: =R51*S51*T51/1000000 -> 0.128968 | AA51: =AA50 -> 19 | AB51: =AB50 -> 223 | AC51: =AC50 -> 223 | AD51: 0 | AE51: =AH50 -> 123 | AH51: =AE51+AF51-AG51 -> 123 | AI51: pcs | AJ51: =AH51*P51 -> 15.863064 | AK51: =AJ51 -> 15.863064 | AL51: =B51-H51+1 -> 57 | AM51: =IF(AL51<=30,"30天内",IF(AL51<=90,"31-90天","91天以上")) -> 31-90天 | AN51: 0.7 | AO51: Euro | AP51: =AK51*AN51 -> 11.104145
A52: 202510 | B52: 45946 | C52: MIC德国仓 | D52: =D51 -> M » N2 - 1 | E52: =E51 -> YCD-EX:HUPPER TEK | F52: =F51 -> MI202508130012 | G52: =G51 -> DE2508031-G7-MIC | H52: =H51 -> 45889 | I52: =I51 -> B076THQBHX | K52: =K51 -> 金属储物柜71英寸灰色 | M52: =M51 -> 188 | N52: =N51 -> 49 | O52: =O51 -> 14 | P52: =M52*N52*O52/1000000 -> 0.128968 | R52: =R51 -> 188 | S52: =S51 -> 49 | T52: =T51 -> 14 | U52: =R52*S52*T52/1000000 -> 0.128968 | AA52: =AA51 -> 19 | AB52: =AB51 -> 223 | AC52: =AC51 -> 223 | AD52: 0 | AE52: =AH51 -> 123 | AH52: =AE52+AF52-AG52 -> 123 | AI52: pcs | AJ52: =AH52*P52 -> 15.863064 | AK52: =AJ52 -> 15.863064 | AL52: =B52-H52+1 -> 58 | AM52: =IF(AL52<=30,"30天内",IF(AL52<=90,"31-90天","91天以上")) -> 31-90天 | AN52: 0.7 | AO52: Euro | AP52: =AK52*AN52 -> 11.104145
A53: 202510 | B53: 45947 | C53: MIC德国仓 | D53: =D52 -> M » N2 - 1 | E53: =E52 -> YCD-EX:HUPPER TEK | F53: =F52 -> MI202508130012 | G53: =G52 -> DE2508031-G7-MIC | H53: =H52 -> 45889 | I53: =I52 -> B076THQBHX | K53: =K52 -> 金属储物柜71英寸灰色 | M53: =M52 -> 188 | N53: =N52 -> 49 | O53: =O52 -> 14 | P53: =M53*N53*O53/1000000 -> 0.128968 | R53: =R52 -> 188 | S53: =S52 -> 49 | T53: =T52 -> 14 | U53: =R53*S53*T53/1000000 -> 0.128968 | AA53: =AA52 -> 19 | AB53: =AB52 -> 223 | AC53: =AC52 -> 223 | AD53: 0 | AE53: =AH52 -> 123 | AH53: =AE53+AF53-AG53 -> 123 | AI53: pcs | AJ53: =AH53*P53 -> 15.863064 | AK53: =AJ53 -> 15.863064 | AL53: =B53-H53+1 -> 59 | AM53: =IF(AL53<=30,"30天内",IF(AL53<=90,"31-90天","91天以上")) -> 31-90天 | AN53: 0.7 | AO53: Euro | AP53: =AK53*AN53 -> 11.104145
A54: 202510 | B54: 45948 | C54: MIC德国仓 | D54: =D53 -> M » N2 - 1 | E54: =E53 -> YCD-EX:HUPPER TEK | F54: =F53 -> MI202508130012 | G54: =G53 -> DE2508031-G7-MIC | H54: =H53 -> 45889 | I54: =I53 -> B076THQBHX | K54: =K53 -> 金属储物柜71英寸灰色 | M54: =M53 -> 188 | N54: =N53 -> 49 | O54: =O53 -> 14 | P54: =M54*N54*O54/1000000 -> 0.128968 | R54: =R53 -> 188 | S54: =S53 -> 49 | T54: =T53 -> 14 | U54: =R54*S54*T54/1000000 -> 0.128968 | AA54: =AA53 -> 19 | AB54: =AB53 -> 223 | AC54: =AC53 -> 223 | AD54: 0 | AE54: =AH53 -> 123 | AH54: =AE54+AF54-AG54 -> 123 | AI54: pcs | AJ54: =AH54*P54 -> 15.863064 | AK54: =AJ54 -> 15.863064 | AL54: =B54-H54+1 -> 60 | AM54: =IF(AL54<=30,"30天内",IF(AL54<=90,"31-90天","91天以上")) -> 31-90天 | AN54: 0.7 | AO54: Euro | AP54: =AK54*AN54 -> 11.104145
A55: 202510 | B55: 45949 | C55: MIC德国仓 | D55: =D54 -> M » N2 - 1 | E55: =E54 -> YCD-EX:HUPPER TEK | F55: =F54 -> MI202508130012 | G55: =G54 -> DE2508031-G7-MIC | H55: =H54 -> 45889 | I55: =I54 -> B076THQBHX | K55: =K54 -> 金属储物柜71英寸灰色 | M55: =M54 -> 188 | N55: =N54 -> 49 | O55: =O54 -> 14 | P55: =M55*N55*O55/1000000 -> 0.128968 | R55: =R54 -> 188 | S55: =S54 -> 49 | T55: =T54 -> 14 | U55: =R55*S55*T55/1000000 -> 0.128968 | AA55: =AA54 -> 19 | AB55: =AB54 -> 223 | AC55: =AC54 -> 223 | AD55: 0 | AE55: =AH54 -> 123 | AH55: =AE55+AF55-AG55 -> 123 | AI55: pcs | AJ55: =AH55*P55 -> 15.863064 | AK55: =AJ55 -> 15.863064 | AL55: =B55-H55+1 -> 61 | AM55: =IF(AL55<=30,"30天内",IF(AL55<=90,"31-90天","91天以上")) -> 31-90天 | AN55: 0.7 | AO55: Euro | AP55: =AK55*AN55 -> 11.104145
A56: 202510 | B56: 45950 | C56: MIC德国仓 | D56: =D55 -> M » N2 - 1 | E56: =E55 -> YCD-EX:HUPPER TEK | F56: =F55 -> MI202508130012 | G56: =G55 -> DE2508031-G7-MIC | H56: =H55 -> 45889 | I56: =I55 -> B076THQBHX | K56: =K55 -> 金属储物柜71英寸灰色 | M56: =M55 -> 188 | N56: =N55 -> 49 | O56: =O55 -> 14 | P56: =M56*N56*O56/1000000 -> 0.128968 | R56: =R55 -> 188 | S56: =S55 -> 49 | T56: =T55 -> 14 | U56: =R56*S56*T56/1000000 -> 0.128968 | AA56: =AA55 -> 19 | AB56: =AB55 -> 223 | AC56: =AC55 -> 223 | AD56: 0 | AE56: =AH55 -> 123 | AH56: =AE56+AF56-AG56 -> 123 | AI56: pcs | AJ56: =AH56*P56 -> 15.863064 | AK56: =AJ56 -> 15.863064 | AL56: =B56-H56+1 -> 62 | AM56: =IF(AL56<=30,"30天内",IF(AL56<=90,"31-90天","91天以上")) -> 31-90天 | AN56: 0.7 | AO56: Euro | AP56: =AK56*AN56 -> 11.104145
A57: 202510 | B57: 45951 | C57: MIC德国仓 | D57: =D56 -> M » N2 - 1 | E57: =E56 -> YCD-EX:HUPPER TEK | F57: =F56 -> MI202508130012 | G57: =G56 -> DE2508031-G7-MIC | H57: =H56 -> 45889 | I57: =I56 -> B076THQBHX | K57: =K56 -> 金属储物柜71英寸灰色 | M57: =M56 -> 188 | N57: =N56 -> 49 | O57: =O56 -> 14 | P57: =M57*N57*O57/1000000 -> 0.128968 | R57: =R56 -> 188 | S57: =S56 -> 49 | T57: =T56 -> 14 | U57: =R57*S57*T57/1000000 -> 0.128968 | AA57: =AA56 -> 19 | AB57: =AB56 -> 223 | AC57: =AC56 -> 223 | AD57: 0 | AE57: =AH56 -> 123 | AG57: 1 | AH57: =AE57+AF57-AG57 -> 122 | AI57: pcs | AJ57: =AH57*P57 -> 15.734096 | AK57: =AJ57 -> 15.734096 | AL57: =B57-H57+1 -> 63 | AM57: =IF(AL57<=30,"30天内",IF(AL57<=90,"31-90天","91天以上")) -> 31-90天 | AN57: 0.7 | AO57: Euro | AP57: =AK57*AN57 -> 11.013867
A58: 202510 | B58: 45952 | C58: MIC德国仓 | D58: =D57 -> M » N2 - 1 | E58: =E57 -> YCD-EX:HUPPER TEK | F58: =F57 -> MI202508130012 | G58: =G57 -> DE2508031-G7-MIC | H58: =H57 -> 45889 | I58: =I57 -> B076THQBHX | K58: =K57 -> 金属储物柜71英寸灰色 | M58: =M57 -> 188 | N58: =N57 -> 49 | O58: =O57 -> 14 | P58: =M58*N58*O58/1000000 -> 0.128968 | R58: =R57 -> 188 | S58: =S57 -> 49 | T58: =T57 -> 14 | U58: =R58*S58*T58/1000000 -> 0.128968 | AA58: =AA57 -> 19 | AB58: =AB57 -> 223 | AC58: =AC57 -> 223 | AD58: 0 | AE58: =AH57 -> 122 | AG58: 1 | AH58: =AE58+AF58-AG58 -> 121 | AI58: pcs | AJ58: =AH58*P58 -> 15.605128 | AK58: =AJ58 -> 15.605128 | AL58: =B58-H58+1 -> 64 | AM58: =IF(AL58<=30,"30天内",IF(AL58<=90,"31-90天","91天以上")) -> 31-90天 | AN58: 0.7 | AO58: Euro | AP58: =AK58*AN58 -> 10.92359
A59: 202510 | B59: 45953 | C59: MIC德国仓 | D59: =D58 -> M » N2 - 1 | E59: =E58 -> YCD-EX:HUPPER TEK | F59: =F58 -> MI202508130012 | G59: =G58 -> DE2508031-G7-MIC | H59: =H58 -> 45889 | I59: =I58 -> B076THQBHX | K59: =K58 -> 金属储物柜71英寸灰色 | M59: =M58 -> 188 | N59: =N58 -> 49 | O59: =O58 -> 14 | P59: =M59*N59*O59/1000000 -> 0.128968 | R59: =R58 -> 188 | S59: =S58 -> 49 | T59: =T58 -> 14 | U59: =R59*S59*T59/1000000 -> 0.128968 | AA59: =AA58 -> 19 | AB59: =AB58 -> 223 | AC59: =AC58 -> 223 | AD59: 0 | AE59: =AH58 -> 121 | AH59: =AE59+AF59-AG59 -> 121 | AI59: pcs | AJ59: =AH59*P59 -> 15.605128 | AK59: =AJ59 -> 15.605128 | AL59: =B59-H59+1 -> 65 | AM59: =IF(AL59<=30,"30天内",IF(AL59<=90,"31-90天","91天以上")) -> 31-90天 | AN59: 0.7 | AO59: Euro | AP59: =AK59*AN59 -> 10.92359
A60: 202510 | B60: 45954 | C60: MIC德国仓 | D60: =D59 -> M » N2 - 1 | E60: =E59 -> YCD-EX:HUPPER TEK | F60: =F59 -> MI202508130012 | G60: =G59 -> DE2508031-G7-MIC | H60: =H59 -> 45889 | I60: =I59 -> B076THQBHX | K60: =K59 -> 金属储物柜71英寸灰色 | M60: =M59 -> 188 | N60: =N59 -> 49 | O60: =O59 -> 14 | P60: =M60*N60*O60/1000000 -> 0.128968 | R60: =R59 -> 188 | S60: =S59 -> 49 | T60: =T59 -> 14 | U60: =R60*S60*T60/1000000 -> 0.128968 | AA60: =AA59 -> 19 | AB60: =AB59 -> 223 | AC60: =AC59 -> 223 | AD60: 0 | AE60: =AH59 -> 121 | AH60: =AE60+AF60-AG60 -> 121 | AI60: pcs | AJ60: =AH60*P60 -> 15.605128 | AK60: =AJ60 -> 15.605128 | AL60: =B60-H60+1 -> 66 | AM60: =IF(AL60<=30,"30天内",IF(AL60<=90,"31-90天","91天以上")) -> 31-90天 | AN60: 0.7 | AO60: Euro | AP60: =AK60*AN60 -> 10.92359
A61: 202510 | B61: 45955 | C61: MIC德国仓 | D61: =D60 -> M » N2 - 1 | E61: =E60 -> YCD-EX:HUPPER TEK | F61: =F60 -> MI202508130012 | G61: =G60 -> DE2508031-G7-MIC | H61: =H60 -> 45889 | I61: =I60 -> B076THQBHX | K61: =K60 -> 金属储物柜71英寸灰色 | M61: =M60 -> 188 | N61: =N60 -> 49 | O61: =O60 -> 14 | P61: =M61*N61*O61/1000000 -> 0.128968 | R61: =R60 -> 188 | S61: =S60 -> 49 | T61: =T60 -> 14 | U61: =R61*S61*T61/1000000 -> 0.128968 | AA61: =AA60 -> 19 | AB61: =AB60 -> 223 | AC61: =AC60 -> 223 | AD61: 0 | AE61: =AH60 -> 121 | AH61: =AE61+AF61-AG61 -> 121 | AI61: pcs | AJ61: =AH61*P61 -> 15.605128 | AK61: =AJ61 -> 15.605128 | AL61: =B61-H61+1 -> 67 | AM61: =IF(AL61<=30,"30天内",IF(AL61<=90,"31-90天","91天以上")) -> 31-90天 | AN61: 0.7 | AO61: Euro | AP61: =AK61*AN61 -> 10.92359
A62: 202510 | B62: 45956 | C62: MIC德国仓 | D62: =D61 -> M » N2 - 1 | E62: =E61 -> YCD-EX:HUPPER TEK | F62: =F61 -> MI202508130012 | G62: =G61 -> DE2508031-G7-MIC | H62: =H61 -> 45889 | I62: =I61 -> B076THQBHX | K62: =K61 -> 金属储物柜71英寸灰色 | M62: =M61 -> 188 | N62: =N61 -> 49 | O62: =O61 -> 14 | P62: =M62*N62*O62/1000000 -> 0.128968 | R62: =R61 -> 188 | S62: =S61 -> 49 | T62: =T61 -> 14 | U62: =R62*S62*T62/1000000 -> 0.128968 | AA62: =AA61 -> 19 | AB62: =AB61 -> 223 | AC62: =AC61 -> 223 | AD62: 0 | AE62: =AH61 -> 121 | AH62: =AE62+AF62-AG62 -> 121 | AI62: pcs | AJ62: =AH62*P62 -> 15.605128 | AK62: =AJ62 -> 15.605128 | AL62: =B62-H62+1 -> 68 | AM62: =IF(AL62<=30,"30天内",IF(AL62<=90,"31-90天","91天以上")) -> 31-90天 | AN62: 0.7 | AO62: Euro | AP62: =AK62*AN62 -> 10.92359
A63: 202510 | B63: 45957 | C63: MIC德国仓 | D63: =D62 -> M » N2 - 1 | E63: =E62 -> YCD-EX:HUPPER TEK | F63: =F62 -> MI202508130012 | G63: =G62 -> DE2508031-G7-MIC | H63: =H62 -> 45889 | I63: =I62 -> B076THQBHX | K63: =K62 -> 金属储物柜71英寸灰色 | M63: =M62 -> 188 | N63: =N62 -> 49 | O63: =O62 -> 14 | P63: =M63*N63*O63/1000000 -> 0.128968 | R63: =R62 -> 188 | S63: =S62 -> 49 | T63: =T62 -> 14 | U63: =R63*S63*T63/1000000 -> 0.128968 | AA63: =AA62 -> 19 | AB63: =AB62 -> 223 | AC63: =AC62 -> 223 | AD63: 0 | AE63: =AH62 -> 121 | AG63: 1 | AH63: =AE63+AF63-AG63 -> 120 | AI63: pcs | AJ63: =AH63*P63 -> 15.47616 | AK63: =AJ63 -> 15.47616 | AL63: =B63-H63+1 -> 69 | AM63: =IF(AL63<=30,"30天内",IF(AL63<=90,"31-90天","91天以上")) -> 31-90天 | AN63: 0.7 | AO63: Euro | AP63: =AK63*AN63 -> 10.833312
A64: 202510 | B64: 45958 | C64: MIC德国仓 | D64: =D63 -> M » N2 - 1 | E64: =E63 -> YCD-EX:HUPPER TEK | F64: =F63 -> MI202508130012 | G64: =G63 -> DE2508031-G7-MIC | H64: =H63 -> 45889 | I64: =I63 -> B076THQBHX | K64: =K63 -> 金属储物柜71英寸灰色 | M64: =M63 -> 188 | N64: =N63 -> 49 | O64: =O63 -> 14 | P64: =M64*N64*O64/1000000 -> 0.128968 | R64: =R63 -> 188 | S64: =S63 -> 49 | T64: =T63 -> 14 | U64: =R64*S64*T64/1000000 -> 0.128968 | AA64: =AA63 -> 19 | AB64: =AB63 -> 223 | AC64: =AC63 -> 223 | AD64: 0 | AE64: =AH63 -> 120 | AH64: =AE64+AF64-AG64 -> 120 | AI64: pcs | AJ64: =AH64*P64 -> 15.47616 | AK64: =AJ64 -> 15.47616 | AL64: =B64-H64+1 -> 70 | AM64: =IF(AL64<=30,"30天内",IF(AL64<=90,"31-90天","91天以上")) -> 31-90天 | AN64: 0.7 | AO64: Euro | AP64: =AK64*AN64 -> 10.833312
A65: 202510 | B65: 45959 | C65: MIC德国仓 | D65: =D64 -> M » N2 - 1 | E65: =E64 -> YCD-EX:HUPPER TEK | F65: =F64 -> MI202508130012 | G65: =G64 -> DE2508031-G7-MIC | H65: =H64 -> 45889 | I65: =I64 -> B076THQBHX | K65: =K64 -> 金属储物柜71英寸灰色 | M65: =M64 -> 188 | N65: =N64 -> 49 | O65: =O64 -> 14 | P65: =M65*N65*O65/1000000 -> 0.128968 | R65: =R64 -> 188 | S65: =S64 -> 49 | T65: =T64 -> 14 | U65: =R65*S65*T65/1000000 -> 0.128968 | AA65: =AA64 -> 19 | AB65: =AB64 -> 223 | AC65: =AC64 -> 223 | AD65: 0 | AE65: =AH64 -> 120 | AH65: =AE65+AF65-AG65 -> 120 | AI65: pcs | AJ65: =AH65*P65 -> 15.47616 | AK65: =AJ65 -> 15.47616 | AL65: =B65-H65+1 -> 71 | AM65: =IF(AL65<=30,"30天内",IF(AL65<=90,"31-90天","91天以上")) -> 31-90天 | AN65: 0.7 | AO65: Euro | AP65: =AK65*AN65 -> 10.833312
A66: 202510 | B66: 45960 | C66: MIC德国仓 | D66: =D65 -> M » N2 - 1 | E66: =E65 -> YCD-EX:HUPPER TEK | F66: =F65 -> MI202508130012 | G66: =G65 -> DE2508031-G7-MIC | H66: =H65 -> 45889 | I66: =I65 -> B076THQBHX | K66: =K65 -> 金属储物柜71英寸灰色 | M66: =M65 -> 188 | N66: =N65 -> 49 | O66: =O65 -> 14 | P66: =M66*N66*O66/1000000 -> 0.128968 | R66: =R65 -> 188 | S66: =S65 -> 49 | T66: =T65 -> 14 | U66: =R66*S66*T66/1000000 -> 0.128968 | AA66: =AA65 -> 19 | AB66: =AB65 -> 223 | AC66: =AC65 -> 223 | AD66: 0 | AE66: =AH65 -> 120 | AH66: =AE66+AF66-AG66 -> 120 | AI66: pcs | AJ66: =AH66*P66 -> 15.47616 | AK66: =AJ66 -> 15.47616 | AL66: =B66-H66+1 -> 72 | AM66: =IF(AL66<=30,"30天内",IF(AL66<=90,"31-90天","91天以上")) -> 31-90天 | AN66: 0.7 | AO66: Euro | AP66: =AK66*AN66 -> 10.833312
A67: 202510 | B67: 45961 | C67: MIC德国仓 | D67: =D66 -> M » N2 - 1 | E67: =E66 -> YCD-EX:HUPPER TEK | F67: =F66 -> MI202508130012 | G67: =G66 -> DE2508031-G7-MIC | H67: =H66 -> 45889 | I67: =I66 -> B076THQBHX | K67: =K66 -> 金属储物柜71英寸灰色 | M67: =M66 -> 188 | N67: =N66 -> 49 | O67: =O66 -> 14 | P67: =M67*N67*O67/1000000 -> 0.128968 | R67: =R66 -> 188 | S67: =S66 -> 49 | T67: =T66 -> 14 | U67: =R67*S67*T67/1000000 -> 0.128968 | AA67: =AA66 -> 19 | AB67: =AB66 -> 223 | AC67: =AC66 -> 223 | AD67: 0 | AE67: =AH66 -> 120 | AH67: =AE67+AF67-AG67 -> 120 | AI67: pcs | AJ67: =AH67*P67 -> 15.47616 | AK67: =AJ67 -> 15.47616 | AL67: =B67-H67+1 -> 73 | AM67: =IF(AL67<=30,"30天内",IF(AL67<=90,"31-90天","91天以上")) -> 31-90天 | AN67: 0.7 | AO67: Euro | AP67: =AK67*AN67 -> 10.833312
A68: 202510 | B68: 45931 | C68: MIC德国仓 | D68: M » N2 - 1 | E68: YCD-EX:HUPPER TEK | F68: MI202508130012 | G68: DE2508031-G7-MIC | H68: 45889 | I68: B07Q3SQT6C | K68: =VLOOKUP(I68,物品明细!A:B,2,0) -> 金属储物柜71英寸高 | M68: =VLOOKUP(I68,物品明细!A:E,5,0) -> 188 | N68: =VLOOKUP(I68,物品明细!A:F,6,0) -> 49 | O68: =VLOOKUP(I68,物品明细!A:G,7,0) -> 14 | P68: =M68*N68*O68/1000000 -> 0.128968 | R68: =VLOOKUP(I68,物品明细!A:E,5,0) -> 188 | S68: =VLOOKUP(I68,物品明细!A:F,6,0) -> 49 | T68: =VLOOKUP(I68,物品明细!A:G,7,0) -> 14 | U68: =R68*S68*T68/1000000 -> 0.128968 | AA68: 13 | AB68: 151 | AC68: 151 | AD68: 0 | AE68: 56 | AH68: =AE68+AF68-AG68 -> 56 | AI68: pcs | AJ68: =AH68*P68 -> 7.222208 | AK68: =AJ68 -> 7.222208 | AL68: =B68-H68+1 -> 43 | AM68: =IF(AL68<=30,"30天内",IF(AL68<=90,"31-90天","91天以上")) -> 31-90天 | AN68: 0.7 | AO68: Euro | AP68: =AK68*AN68 -> 5.0555456
A69: 202510 | B69: 45932 | C69: MIC德国仓 | D69: =D68 -> M » N2 - 1 | E69: =E68 -> YCD-EX:HUPPER TEK | F69: =F68 -> MI202508130012 | G69: =G68 -> DE2508031-G7-MIC | H69: =H68 -> 45889 | I69: =I68 -> B07Q3SQT6C | K69: =K68 -> 金属储物柜71英寸高 | M69: =M68 -> 188 | N69: =N68 -> 49 | O69: =O68 -> 14 | P69: =M69*N69*O69/1000000 -> 0.128968 | R69: =R68 -> 188 | S69: =S68 -> 49 | T69: =T68 -> 14 | U69: =R69*S69*T69/1000000 -> 0.128968 | AA69: =AA68 -> 13 | AB69: =AB68 -> 151 | AC69: =AC68 -> 151 | AD69: 0 | AE69: =AH68 -> 56 | AH69: =AE69+AF69-AG69 -> 56 | AI69: pcs | AJ69: =AH69*P69 -> 7.222208 | AK69: =AJ69 -> 7.222208 | AL69: =B69-H69+1 -> 44 | AM69: =IF(AL69<=30,"30天内",IF(AL69<=90,"31-90天","91天以上")) -> 31-90天 | AN69: 0.7 | AO69: Euro | AP69: =AK69*AN69 -> 5.0555456
A70: 202510 | B70: 45933 | C70: MIC德国仓 | D70: =D69 -> M » N2 - 1 | E70: =E69 -> YCD-EX:HUPPER TEK | F70: =F69 -> MI202508130012 | G70: =G69 -> DE2508031-G7-MIC | H70: =H69 -> 45889 | I70: =I69 -> B07Q3SQT6C | K70: =K69 -> 金属储物柜71英寸高 | M70: =M69 -> 188 | N70: =N69 -> 49 | O70: =O69 -> 14 | P70: =M70*N70*O70/1000000 -> 0.128968 | R70: =R69 -> 188 | S70: =S69 -> 49 | T70: =T69 -> 14 | U70: =R70*S70*T70/1000000 -> 0.128968 | AA70: =AA69 -> 13 | AB70: =AB69 -> 151 | AC70: =AC69 -> 151 | AD70: 0 | AE70: =AH69 -> 56 | AH70: =AE70+AF70-AG70 -> 56 | AI70: pcs | AJ70: =AH70*P70 -> 7.222208 | AK70: =AJ70 -> 7.222208 | AL70: =B70-H70+1 -> 45 | AM70: =IF(AL70<=30,"30天内",IF(AL70<=90,"31-90天","91天以上")) -> 31-90天 | AN70: 0.7 | AO70: Euro | AP70: =AK70*AN70 -> 5.0555456
A71: 202510 | B71: 45934 | C71: MIC德国仓 | D71: =D70 -> M » N2 - 1 | E71: =E70 -> YCD-EX:HUPPER TEK | F71: =F70 -> MI202508130012 | G71: =G70 -> DE2508031-G7-MIC | H71: =H70 -> 45889 | I71: =I70 -> B07Q3SQT6C | K71: =K70 -> 金属储物柜71英寸高 | M71: =M70 -> 188 | N71: =N70 -> 49 | O71: =O70 -> 14 | P71: =M71*N71*O71/1000000 -> 0.128968 | R71: =R70 -> 188 | S71: =S70 -> 49 | T71: =T70 -> 14 | U71: =R71*S71*T71/1000000 -> 0.128968 | AA71: =AA70 -> 13 | AB71: =AB70 -> 151 | AC71: =AC70 -> 151 | AD71: 0 | AE71: =AH70 -> 56 | AH71: =AE71+AF71-AG71 -> 56 | AI71: pcs | AJ71: =AH71*P71 -> 7.222208 | AK71: =AJ71 -> 7.222208 | AL71: =B71-H71+1 -> 46 | AM71: =IF(AL71<=30,"30天内",IF(AL71<=90,"31-90天","91天以上")) -> 31-90天 | AN71: 0.7 | AO71: Euro | AP71: =AK71*AN71 -> 5.0555456
A72: 202510 | B72: 45935 | C72: MIC德国仓 | D72: =D71 -> M » N2 - 1 | E72: =E71 -> YCD-EX:HUPPER TEK | F72: =F71 -> MI202508130012 | G72: =G71 -> DE2508031-G7-MIC | H72: =H71 -> 45889 | I72: =I71 -> B07Q3SQT6C | K72: =K71 -> 金属储物柜71英寸高 | M72: =M71 -> 188 | N72: =N71 -> 49 | O72: =O71 -> 14 | P72: =M72*N72*O72/1000000 -> 0.128968 | R72: =R71 -> 188 | S72: =S71 -> 49 | T72: =T71 -> 14 | U72: =R72*S72*T72/1000000 -> 0.128968 | AA72: =AA71 -> 13 | AB72: =AB71 -> 151 | AC72: =AC71 -> 151 | AD72: 0 | AE72: =AH71 -> 56 | AH72: =AE72+AF72-AG72 -> 56 | AI72: pcs | AJ72: =AH72*P72 -> 7.222208 | AK72: =AJ72 -> 7.222208 | AL72: =B72-H72+1 -> 47 | AM72: =IF(AL72<=30,"30天内",IF(AL72<=90,"31-90天","91天以上")) -> 31-90天 | AN72: 0.7 | AO72: Euro | AP72: =AK72*AN72 -> 5.0555456
A73: 202510 | B73: 45936 | C73: MIC德国仓 | D73: =D72 -> M » N2 - 1 | E73: =E72 -> YCD-EX:HUPPER TEK | F73: =F72 -> MI202508130012 | G73: =G72 -> DE2508031-G7-MIC | H73: =H72 -> 45889 | I73: =I72 -> B07Q3SQT6C | K73: =K72 -> 金属储物柜71英寸高 | M73: =M72 -> 188 | N73: =N72 -> 49 | O73: =O72 -> 14 | P73: =M73*N73*O73/1000000 -> 0.128968 | R73: =R72 -> 188 | S73: =S72 -> 49 | T73: =T72 -> 14 | U73: =R73*S73*T73/1000000 -> 0.128968 | AA73: =AA72 -> 13 | AB73: =AB72 -> 151 | AC73: =AC72 -> 151 | AD73: 0 | AE73: =AH72 -> 56 | AG73: 10 | AH73: =AE73+AF73-AG73 -> 46 | AI73: pcs | AJ73: =AH73*P73 -> 5.932528 | AK73: =AJ73 -> 5.932528 | AL73: =B73-H73+1 -> 48 | AM73: =IF(AL73<=30,"30天内",IF(AL73<=90,"31-90天","91天以上")) -> 31-90天 | AN73: 0.7 | AO73: Euro | AP73: =AK73*AN73 -> 4.1527696
A74: 202510 | B74: 45937 | C74: MIC德国仓 | D74: =D73 -> M » N2 - 1 | E74: =E73 -> YCD-EX:HUPPER TEK | F74: =F73 -> MI202508130012 | G74: =G73 -> DE2508031-G7-MIC | H74: =H73 -> 45889 | I74: =I73 -> B07Q3SQT6C | K74: =K73 -> 金属储物柜71英寸高 | M74: =M73 -> 188 | N74: =N73 -> 49 | O74: =O73 -> 14 | P74: =M74*N74*O74/1000000 -> 0.128968 | R74: =R73 -> 188 | S74: =S73 -> 49 | T74: =T73 -> 14 | U74: =R74*S74*T74/1000000 -> 0.128968 | AA74: =AA73 -> 13 | AB74: =AB73 -> 151 | AC74: =AC73 -> 151 | AD74: 0 | AE74: =AH73 -> 46 | AG74: 1 | AH74: =AE74+AF74-AG74 -> 45 | AI74: pcs | AJ74: =AH74*P74 -> 5.80356 | AK74: =AJ74 -> 5.80356 | AL74: =B74-H74+1 -> 49 | AM74: =IF(AL74<=30,"30天内",IF(AL74<=90,"31-90天","91天以上")) -> 31-90天 | AN74: 0.7 | AO74: Euro | AP74: =AK74*AN74 -> 4.062492
A75: 202510 | B75: 45938 | C75: MIC德国仓 | D75: =D74 -> M » N2 - 1 | E75: =E74 -> YCD-EX:HUPPER TEK | F75: =F74 -> MI202508130012 | G75: =G74 -> DE2508031-G7-MIC | H75: =H74 -> 45889 | I75: =I74 -> B07Q3SQT6C | K75: =K74 -> 金属储物柜71英寸高 | M75: =M74 -> 188 | N75: =N74 -> 49 | O75: =O74 -> 14 | P75: =M75*N75*O75/1000000 -> 0.128968 | R75: =R74 -> 188 | S75: =S74 -> 49 | T75: =T74 -> 14 | U75: =R75*S75*T75/1000000 -> 0.128968 | AA75: =AA74 -> 13 | AB75: =AB74 -> 151 | AC75: =AC74 -> 151 | AD75: 0 | AE75: =AH74 -> 45 | AG75: 3 | AH75: =AE75+AF75-AG75 -> 42 | AI75: pcs | AJ75: =AH75*P75 -> 5.416656 | AK75: =AJ75 -> 5.416656 | AL75: =B75-H75+1 -> 50 | AM75: =IF(AL75<=30,"30天内",IF(AL75<=90,"31-90天","91天以上")) -> 31-90天 | AN75: 0.7 | AO75: Euro | AP75: =AK75*AN75 -> 3.7916592
A76: 202510 | B76: 45939 | C76: MIC德国仓 | D76: =D75 -> M » N2 - 1 | E76: =E75 -> YCD-EX:HUPPER TEK | F76: =F75 -> MI202508130012 | G76: =G75 -> DE2508031-G7-MIC | H76: =H75 -> 45889 | I76: =I75 -> B07Q3SQT6C | K76: =K75 -> 金属储物柜71英寸高 | M76: =M75 -> 188 | N76: =N75 -> 49 | O76: =O75 -> 14 | P76: =M76*N76*O76/1000000 -> 0.128968 | R76: =R75 -> 188 | S76: =S75 -> 49 | T76: =T75 -> 14 | U76: =R76*S76*T76/1000000 -> 0.128968 | AA76: =AA75 -> 13 | AB76: =AB75 -> 151 | AC76: =AC75 -> 151 | AD76: 0 | AE76: =AH75 -> 42 | AG76: 1 | AH76: =AE76+AF76-AG76 -> 41 | AI76: pcs | AJ76: =AH76*P76 -> 5.287688 | AK76: =AJ76 -> 5.287688 | AL76: =B76-H76+1 -> 51 | AM76: =IF(AL76<=30,"30天内",IF(AL76<=90,"31-90天","91天以上")) -> 31-90天 | AN76: 0.7 | AO76: Euro | AP76: =AK76*AN76 -> 3.7013816
A77: 202510 | B77: 45940 | C77: MIC德国仓 | D77: =D76 -> M » N2 - 1 | E77: =E76 -> YCD-EX:HUPPER TEK | F77: =F76 -> MI202508130012 | G77: =G76 -> DE2508031-G7-MIC | H77: =H76 -> 45889 | I77: =I76 -> B07Q3SQT6C | K77: =K76 -> 金属储物柜71英寸高 | M77: =M76 -> 188 | N77: =N76 -> 49 | O77: =O76 -> 14 | P77: =M77*N77*O77/1000000 -> 0.128968 | R77: =R76 -> 188 | S77: =S76 -> 49 | T77: =T76 -> 14 | U77: =R77*S77*T77/1000000 -> 0.128968 | AA77: =AA76 -> 13 | AB77: =AB76 -> 151 | AC77: =AC76 -> 151 | AD77: 0 | AE77: =AH76 -> 41 | AG77: 1 | AH77: =AE77+AF77-AG77 -> 40 | AI77: pcs | AJ77: =AH77*P77 -> 5.15872 | AK77: =AJ77 -> 5.15872 | AL77: =B77-H77+1 -> 52 | AM77: =IF(AL77<=30,"30天内",IF(AL77<=90,"31-90天","91天以上")) -> 31-90天 | AN77: 0.7 | AO77: Euro | AP77: =AK77*AN77 -> 3.611104
A78: 202510 | B78: 45941 | C78: MIC德国仓 | D78: =D77 -> M » N2 - 1 | E78: =E77 -> YCD-EX:HUPPER TEK | F78: =F77 -> MI202508130012 | G78: =G77 -> DE2508031-G7-MIC | H78: =H77 -> 45889 | I78: =I77 -> B07Q3SQT6C | K78: =K77 -> 金属储物柜71英寸高 | M78: =M77 -> 188 | N78: =N77 -> 49 | O78: =O77 -> 14 | P78: =M78*N78*O78/1000000 -> 0.128968 | R78: =R77 -> 188 | S78: =S77 -> 49 | T78: =T77 -> 14 | U78: =R78*S78*T78/1000000 -> 0.128968 | AA78: =AA77 -> 13 | AB78: =AB77 -> 151 | AC78: =AC77 -> 151 | AD78: 0 | AE78: =AH77 -> 40 | AH78: =AE78+AF78-AG78 -> 40 | AI78: pcs | AJ78: =AH78*P78 -> 5.15872 | AK78: =AJ78 -> 5.15872 | AL78: =B78-H78+1 -> 53 | AM78: =IF(AL78<=30,"30天内",IF(AL78<=90,"31-90天","91天以上")) -> 31-90天 | AN78: 0.7 | AO78: Euro | AP78: =AK78*AN78 -> 3.611104
A79: 202510 | B79: 45942 | C79: MIC德国仓 | D79: =D78 -> M » N2 - 1 | E79: =E78 -> YCD-EX:HUPPER TEK | F79: =F78 -> MI202508130012 | G79: =G78 -> DE2508031-G7-MIC | H79: =H78 -> 45889 | I79: =I78 -> B07Q3SQT6C | K79: =K78 -> 金属储物柜71英寸高 | M79: =M78 -> 188 | N79: =N78 -> 49 | O79: =O78 -> 14 | P79: =M79*N79*O79/1000000 -> 0.128968 | R79: =R78 -> 188 | S79: =S78 -> 49 | T79: =T78 -> 14 | U79: =R79*S79*T79/1000000 -> 0.128968 | AA79: =AA78 -> 13 | AB79: =AB78 -> 151 | AC79: =AC78 -> 151 | AD79: 0 | AE79: =AH78 -> 40 | AH79: =AE79+AF79-AG79 -> 40 | AI79: pcs | AJ79: =AH79*P79 -> 5.15872 | AK79: =AJ79 -> 5.15872 | AL79: =B79-H79+1 -> 54 | AM79: =IF(AL79<=30,"30天内",IF(AL79<=90,"31-90天","91天以上")) -> 31-90天 | AN79: 0.7 | AO79: Euro | AP79: =AK79*AN79 -> 3.611104
A80: 202510 | B80: 45943 | C80: MIC德国仓 | D80: =D79 -> M » N2 - 1 | E80: =E79 -> YCD-EX:HUPPER TEK | F80: =F79 -> MI202508130012 | G80: =G79 -> DE2508031-G7-MIC | H80: =H79 -> 45889 | I80: =I79 -> B07Q3SQT6C | K80: =K79 -> 金属储物柜71英寸高 | M80: =M79 -> 188 | N80: =N79 -> 49 | O80: =O79 -> 14 | P80: =M80*N80*O80/1000000 -> 0.128968 | R80: =R79 -> 188 | S80: =S79 -> 49 | T80: =T79 -> 14 | U80: =R80*S80*T80/1000000 -> 0.128968 | AA80: =AA79 -> 13 | AB80: =AB79 -> 151 | AC80: =AC79 -> 151 | AD80: 0 | AE80: =AH79 -> 40 | AG80: 6 | AH80: =AE80+AF80-AG80 -> 34 | AI80: pcs | AJ80: =AH80*P80 -> 4.384912 | AK80: =AJ80 -> 4.384912 | AL80: =B80-H80+1 -> 55 | AM80: =IF(AL80<=30,"30天内",IF(AL80<=90,"31-90天","91天以上")) -> 31-90天 | AN80: 0.7 | AO80: Euro | AP80: =AK80*AN80 -> 3.0694384
A81: 202510 | B81: 45944 | C81: MIC德国仓 | D81: =D80 -> M » N2 - 1 | E81: =E80 -> YCD-EX:HUPPER TEK | F81: =F80 -> MI202508130012 | G81: =G80 -> DE2508031-G7-MIC | H81: =H80 -> 45889 | I81: =I80 -> B07Q3SQT6C | K81: =K80 -> 金属储物柜71英寸高 | M81: =M80 -> 188 | N81: =N80 -> 49 | O81: =O80 -> 14 | P81: =M81*N81*O81/1000000 -> 0.128968 | R81: =R80 -> 188 | S81: =S80 -> 49 | T81: =T80 -> 14 | U81: =R81*S81*T81/1000000 -> 0.128968 | AA81: =AA80 -> 13 | AB81: =AB80 -> 151 | AC81: =AC80 -> 151 | AD81: 0 | AE81: =AH80 -> 34 | AG81: 1 | AH81: =AE81+AF81-AG81 -> 33 | AI81: pcs | AJ81: =AH81*P81 -> 4.255944 | AK81: =AJ81 -> 4.255944 | AL81: =B81-H81+1 -> 56 | AM81: =IF(AL81<=30,"30天内",IF(AL81<=90,"31-90天","91天以上")) -> 31-90天 | AN81: 0.7 | AO81: Euro | AP81: =AK81*AN81 -> 2.9791608
A82: 202510 | B82: 45945 | C82: MIC德国仓 | D82: =D81 -> M » N2 - 1 | E82: =E81 -> YCD-EX:HUPPER TEK | F82: =F81 -> MI202508130012 | G82: =G81 -> DE2508031-G7-MIC | H82: =H81 -> 45889 | I82: =I81 -> B07Q3SQT6C | K82: =K81 -> 金属储物柜71英寸高 | M82: =M81 -> 188 | N82: =N81 -> 49 | O82: =O81 -> 14 | P82: =M82*N82*O82/1000000 -> 0.128968 | R82: =R81 -> 188 | S82: =S81 -> 49 | T82: =T81 -> 14 | U82: =R82*S82*T82/1000000 -> 0.128968 | AA82: =AA81 -> 13 | AB82: =AB81 -> 151 | AC82: =AC81 -> 151 | AD82: 0 | AE82: =AH81 -> 33 | AH82: =AE82+AF82-AG82 -> 33 | AI82: pcs | AJ82: =AH82*P82 -> 4.255944 | AK82: =AJ82 -> 4.255944 | AL82: =B82-H82+1 -> 57 | AM82: =IF(AL82<=30,"30天内",IF(AL82<=90,"31-90天","91天以上")) -> 31-90天 | AN82: 0.7 | AO82: Euro | AP82: =AK82*AN82 -> 2.9791608
A83: 202510 | B83: 45946 | C83: MIC德国仓 | D83: =D82 -> M » N2 - 1 | E83: =E82 -> YCD-EX:HUPPER TEK | F83: =F82 -> MI202508130012 | G83: =G82 -> DE2508031-G7-MIC | H83: =H82 -> 45889 | I83: =I82 -> B07Q3SQT6C | K83: =K82 -> 金属储物柜71英寸高 | M83: =M82 -> 188 | N83: =N82 -> 49 | O83: =O82 -> 14 | P83: =M83*N83*O83/1000000 -> 0.128968 | R83: =R82 -> 188 | S83: =S82 -> 49 | T83: =T82 -> 14 | U83: =R83*S83*T83/1000000 -> 0.128968 | AA83: =AA82 -> 13 | AB83: =AB82 -> 151 | AC83: =AC82 -> 151 | AD83: 0 | AE83: =AH82 -> 33 | AH83: =AE83+AF83-AG83 -> 33 | AI83: pcs | AJ83: =AH83*P83 -> 4.255944 | AK83: =AJ83 -> 4.255944 | AL83: =B83-H83+1 -> 58 | AM83: =IF(AL83<=30,"30天内",IF(AL83<=90,"31-90天","91天以上")) -> 31-90天 | AN83: 0.7 | AO83: Euro | AP83: =AK83*AN83 -> 2.9791608
A84: 202510 | B84: 45947 | C84: MIC德国仓 | D84: =D83 -> M » N2 - 1 | E84: =E83 -> YCD-EX:HUPPER TEK | F84: =F83 -> MI202508130012 | G84: =G83 -> DE2508031-G7-MIC | H84: =H83 -> 45889 | I84: =I83 -> B07Q3SQT6C | K84: =K83 -> 金属储物柜71英寸高 | M84: =M83 -> 188 | N84: =N83 -> 49 | O84: =O83 -> 14 | P84: =M84*N84*O84/1000000 -> 0.128968 | R84: =R83 -> 188 | S84: =S83 -> 49 | T84: =T83 -> 14 | U84: =R84*S84*T84/1000000 -> 0.128968 | AA84: =AA83 -> 13 | AB84: =AB83 -> 151 | AC84: =AC83 -> 151 | AD84: 0 | AE84: =AH83 -> 33 | AG84: 1 | AH84: =AE84+AF84-AG84 -> 32 | AI84: pcs | AJ84: =AH84*P84 -> 4.126976 | AK84: =AJ84 -> 4.126976 | AL84: =B84-H84+1 -> 59 | AM84: =IF(AL84<=30,"30天内",IF(AL84<=90,"31-90天","91天以上")) -> 31-90天 | AN84: 0.7 | AO84: Euro | AP84: =AK84*AN84 -> 2.8888832
A85: 202510 | B85: 45948 | C85: MIC德国仓 | D85: =D84 -> M » N2 - 1 | E85: =E84 -> YCD-EX:HUPPER TEK | F85: =F84 -> MI202508130012 | G85: =G84 -> DE2508031-G7-MIC | H85: =H84 -> 45889 | I85: =I84 -> B07Q3SQT6C | K85: =K84 -> 金属储物柜71英寸高 | M85: =M84 -> 188 | N85: =N84 -> 49 | O85: =O84 -> 14 | P85: =M85*N85*O85/1000000 -> 0.128968 | R85: =R84 -> 188 | S85: =S84 -> 49 | T85: =T84 -> 14 | U85: =R85*S85*T85/1000000 -> 0.128968 | AA85: =AA84 -> 13 | AB85: =AB84 -> 151 | AC85: =AC84 -> 151 | AD85: 0 | AE85: =AH84 -> 32 | AH85: =AE85+AF85-AG85 -> 32 | AI85: pcs | AJ85: =AH85*P85 -> 4.126976 | AK85: =AJ85 -> 4.126976 | AL85: =B85-H85+1 -> 60 | AM85: =IF(AL85<=30,"30天内",IF(AL85<=90,"31-90天","91天以上")) -> 31-90天 | AN85: 0.7 | AO85: Euro | AP85: =AK85*AN85 -> 2.8888832
A86: 202510 | B86: 45949 | C86: MIC德国仓 | D86: =D85 -> M » N2 - 1 | E86: =E85 -> YCD-EX:HUPPER TEK | F86: =F85 -> MI202508130012 | G86: =G85 -> DE2508031-G7-MIC | H86: =H85 -> 45889 | I86: =I85 -> B07Q3SQT6C | K86: =K85 -> 金属储物柜71英寸高 | M86: =M85 -> 188 | N86: =N85 -> 49 | O86: =O85 -> 14 | P86: =M86*N86*O86/1000000 -> 0.128968 | R86: =R85 -> 188 | S86: =S85 -> 49 | T86: =T85 -> 14 | U86: =R86*S86*T86/1000000 -> 0.128968 | AA86: =AA85 -> 13 | AB86: =AB85 -> 151 | AC86: =AC85 -> 151 | AD86: 0 | AE86: =AH85 -> 32 | AH86: =AE86+AF86-AG86 -> 32 | AI86: pcs | AJ86: =AH86*P86 -> 4.126976 | AK86: =AJ86 -> 4.126976 | AL86: =B86-H86+1 -> 61 | AM86: =IF(AL86<=30,"30天内",IF(AL86<=90,"31-90天","91天以上")) -> 31-90天 | AN86: 0.7 | AO86: Euro | AP86: =AK86*AN86 -> 2.8888832
A87: 202510 | B87: 45950 | C87: MIC德国仓 | D87: =D86 -> M » N2 - 1 | E87: =E86 -> YCD-EX:HUPPER TEK | F87: =F86 -> MI202508130012 | G87: =G86 -> DE2508031-G7-MIC | H87: =H86 -> 45889 | I87: =I86 -> B07Q3SQT6C | K87: =K86 -> 金属储物柜71英寸高 | M87: =M86 -> 188 | N87: =N86 -> 49 | O87: =O86 -> 14 | P87: =M87*N87*O87/1000000 -> 0.128968 | R87: =R86 -> 188 | S87: =S86 -> 49 | T87: =T86 -> 14 | U87: =R87*S87*T87/1000000 -> 0.128968 | AA87: =AA86 -> 13 | AB87: =AB86 -> 151 | AC87: =AC86 -> 151 | AD87: 0 | AE87: =AH86 -> 32 | AG87: 3 | AH87: =AE87+AF87-AG87 -> 29 | AI87: pcs | AJ87: =AH87*P87 -> 3.740072 | AK87: =AJ87 -> 3.740072 | AL87: =B87-H87+1 -> 62 | AM87: =IF(AL87<=30,"30天内",IF(AL87<=90,"31-90天","91天以上")) -> 31-90天 | AN87: 0.7 | AO87: Euro | AP87: =AK87*AN87 -> 2.6180504
A88: 202510 | B88: 45951 | C88: MIC德国仓 | D88: =D87 -> M » N2 - 1 | E88: =E87 -> YCD-EX:HUPPER TEK | F88: =F87 -> MI202508130012 | G88: =G87 -> DE2508031-G7-MIC | H88: =H87 -> 45889 | I88: =I87 -> B07Q3SQT6C | K88: =K87 -> 金属储物柜71英寸高 | M88: =M87 -> 188 | N88: =N87 -> 49 | O88: =O87 -> 14 | P88: =M88*N88*O88/1000000 -> 0.128968 | R88: =R87 -> 188 | S88: =S87 -> 49 | T88: =T87 -> 14 | U88: =R88*S88*T88/1000000 -> 0.128968 | AA88: =AA87 -> 13 | AB88: =AB87 -> 151 | AC88: =AC87 -> 151 | AD88: 0 | AE88: =AH87 -> 29 | AH88: =AE88+AF88-AG88 -> 29 | AI88: pcs | AJ88: =AH88*P88 -> 3.740072 | AK88: =AJ88 -> 3.740072 | AL88: =B88-H88+1 -> 63 | AM88: =IF(AL88<=30,"30天内",IF(AL88<=90,"31-90天","91天以上")) -> 31-90天 | AN88: 0.7 | AO88: Euro | AP88: =AK88*AN88 -> 2.6180504
A89: 202510 | B89: 45952 | C89: MIC德国仓 | D89: =D88 -> M » N2 - 1 | E89: =E88 -> YCD-EX:HUPPER TEK | F89: =F88 -> MI202508130012 | G89: =G88 -> DE2508031-G7-MIC | H89: =H88 -> 45889 | I89: =I88 -> B07Q3SQT6C | K89: =K88 -> 金属储物柜71英寸高 | M89: =M88 -> 188 | N89: =N88 -> 49 | O89: =O88 -> 14 | P89: =M89*N89*O89/1000000 -> 0.128968 | R89: =R88 -> 188 | S89: =S88 -> 49 | T89: =T88 -> 14 | U89: =R89*S89*T89/1000000 -> 0.128968 | AA89: =AA88 -> 13 | AB89: =AB88 -> 151 | AC89: =AC88 -> 151 | AD89: 0 | AE89: =AH88 -> 29 | AG89: 1 | AH89: =AE89+AF89-AG89 -> 28 | AI89: pcs | AJ89: =AH89*P89 -> 3.611104 | AK89: =AJ89 -> 3.611104 | AL89: =B89-H89+1 -> 64 | AM89: =IF(AL89<=30,"30天内",IF(AL89<=90,"31-90天","91天以上")) -> 31-90天 | AN89: 0.7 | AO89: Euro | AP89: =AK89*AN89 -> 2.5277728
A90: 202510 | B90: 45953 | C90: MIC德国仓 | D90: =D89 -> M » N2 - 1 | E90: =E89 -> YCD-EX:HUPPER TEK | F90: =F89 -> MI202508130012 | G90: =G89 -> DE2508031-G7-MIC | H90: =H89 -> 45889 | I90: =I89 -> B07Q3SQT6C | K90: =K89 -> 金属储物柜71英寸高 | M90: =M89 -> 188 | N90: =N89 -> 49 | O90: =O89 -> 14 | P90: =M90*N90*O90/1000000 -> 0.128968 | R90: =R89 -> 188 | S90: =S89 -> 49 | T90: =T89 -> 14 | U90: =R90*S90*T90/1000000 -> 0.128968 | AA90: =AA89 -> 13 | AB90: =AB89 -> 151 | AC90: =AC89 -> 151 | AD90: 0 | AE90: =AH89 -> 28 | AG90: 1 | AH90: =AE90+AF90-AG90 -> 27 | AI90: pcs | AJ90: =AH90*P90 -> 3.482136 | AK90: =AJ90 -> 3.482136 | AL90: =B90-H90+1 -> 65 | AM90: =IF(AL90<=30,"30天内",IF(AL90<=90,"31-90天","91天以上")) -> 31-90天 | AN90: 0.7 | AO90: Euro | AP90: =AK90*AN90 -> 2.4374952
A91: 202510 | B91: 45954 | C91: MIC德国仓 | D91: =D90 -> M » N2 - 1 | E91: =E90 -> YCD-EX:HUPPER TEK | F91: =F90 -> MI202508130012 | G91: =G90 -> DE2508031-G7-MIC | H91: =H90 -> 45889 | I91: =I90 -> B07Q3SQT6C | K91: =K90 -> 金属储物柜71英寸高 | M91: =M90 -> 188 | N91: =N90 -> 49 | O91: =O90 -> 14 | P91: =M91*N91*O91/1000000 -> 0.128968 | R91: =R90 -> 188 | S91: =S90 -> 49 | T91: =T90 -> 14 | U91: =R91*S91*T91/1000000 -> 0.128968 | AA91: =AA90 -> 13 | AB91: =AB90 -> 151 | AC91: =AC90 -> 151 | AD91: 0 | AE91: =AH90 -> 27 | AG91: 2 | AH91: =AE91+AF91-AG91 -> 25 | AI91: pcs | AJ91: =AH91*P91 -> 3.2242 | AK91: =AJ91 -> 3.2242 | AL91: =B91-H91+1 -> 66 | AM91: =IF(AL91<=30,"30天内",IF(AL91<=90,"31-90天","91天以上")) -> 31-90天 | AN91: 0.7 | AO91: Euro | AP91: =AK91*AN91 -> 2.25694
A92: 202510 | B92: 45955 | C92: MIC德国仓 | D92: =D91 -> M » N2 - 1 | E92: =E91 -> YCD-EX:HUPPER TEK | F92: =F91 -> MI202508130012 | G92: =G91 -> DE2508031-G7-MIC | H92: =H91 -> 45889 | I92: =I91 -> B07Q3SQT6C | K92: =K91 -> 金属储物柜71英寸高 | M92: =M91 -> 188 | N92: =N91 -> 49 | O92: =O91 -> 14 | P92: =M92*N92*O92/1000000 -> 0.128968 | R92: =R91 -> 188 | S92: =S91 -> 49 | T92: =T91 -> 14 | U92: =R92*S92*T92/1000000 -> 0.128968 | AA92: =AA91 -> 13 | AB92: =AB91 -> 151 | AC92: =AC91 -> 151 | AD92: 0 | AE92: =AH91 -> 25 | AH92: =AE92+AF92-AG92 -> 25 | AI92: pcs | AJ92: =AH92*P92 -> 3.2242 | AK92: =AJ92 -> 3.2242 | AL92: =B92-H92+1 -> 67 | AM92: =IF(AL92<=30,"30天内",IF(AL92<=90,"31-90天","91天以上")) -> 31-90天 | AN92: 0.7 | AO92: Euro | AP92: =AK92*AN92 -> 2.25694
A93: 202510 | B93: 45956 | C93: MIC德国仓 | D93: =D92 -> M » N2 - 1 | E93: =E92 -> YCD-EX:HUPPER TEK | F93: =F92 -> MI202508130012 | G93: =G92 -> DE2508031-G7-MIC | H93: =H92 -> 45889 | I93: =I92 -> B07Q3SQT6C | K93: =K92 -> 金属储物柜71英寸高 | M93: =M92 -> 188 | N93: =N92 -> 49 | O93: =O92 -> 14 | P93: =M93*N93*O93/1000000 -> 0.128968 | R93: =R92 -> 188 | S93: =S92 -> 49 | T93: =T92 -> 14 | U93: =R93*S93*T93/1000000 -> 0.128968 | AA93: =AA92 -> 13 | AB93: =AB92 -> 151 | AC93: =AC92 -> 151 | AD93: 0 | AE93: =AH92 -> 25 | AH93: =AE93+AF93-AG93 -> 25 | AI93: pcs | AJ93: =AH93*P93 -> 3.2242 | AK93: =AJ93 -> 3.2242 | AL93: =B93-H93+1 -> 68 | AM93: =IF(AL93<=30,"30天内",IF(AL93<=90,"31-90天","91天以上")) -> 31-90天 | AN93: 0.7 | AO93: Euro | AP93: =AK93*AN93 -> 2.25694
A94: 202510 | B94: 45957 | C94: MIC德国仓 | D94: =D93 -> M » N2 - 1 | E94: =E93 -> YCD-EX:HUPPER TEK | F94: =F93 -> MI202508130012 | G94: =G93 -> DE2508031-G7-MIC | H94: =H93 -> 45889 | I94: =I93 -> B07Q3SQT6C | K94: =K93 -> 金属储物柜71英寸高 | M94: =M93 -> 188 | N94: =N93 -> 49 | O94: =O93 -> 14 | P94: =M94*N94*O94/1000000 -> 0.128968 | R94: =R93 -> 188 | S94: =S93 -> 49 | T94: =T93 -> 14 | U94: =R94*S94*T94/1000000 -> 0.128968 | AA94: =AA93 -> 13 | AB94: =AB93 -> 151 | AC94: =AC93 -> 151 | AD94: 0 | AE94: =AH93 -> 25 | AG94: 4 | AH94: =AE94+AF94-AG94 -> 21 | AI94: pcs | AJ94: =AH94*P94 -> 2.708328 | AK94: =AJ94 -> 2.708328 | AL94: =B94-H94+1 -> 69 | AM94: =IF(AL94<=30,"30天内",IF(AL94<=90,"31-90天","91天以上")) -> 31-90天 | AN94: 0.7 | AO94: Euro | AP94: =AK94*AN94 -> 1.8958296
A95: 202510 | B95: 45958 | C95: MIC德国仓 | D95: =D94 -> M » N2 - 1 | E95: =E94 -> YCD-EX:HUPPER TEK | F95: =F94 -> MI202508130012 | G95: =G94 -> DE2508031-G7-MIC | H95: =H94 -> 45889 | I95: =I94 -> B07Q3SQT6C | K95: =K94 -> 金属储物柜71英寸高 | M95: =M94 -> 188 | N95: =N94 -> 49 | O95: =O94 -> 14 | P95: =M95*N95*O95/1000000 -> 0.128968 | R95: =R94 -> 188 | S95: =S94 -> 49 | T95: =T94 -> 14 | U95: =R95*S95*T95/1000000 -> 0.128968 | AA95: =AA94 -> 13 | AB95: =AB94 -> 151 | AC95: =AC94 -> 151 | AD95: 0 | AE95: =AH94 -> 21 | AH95: =AE95+AF95-AG95 -> 21 | AI95: pcs | AJ95: =AH95*P95 -> 2.708328 | AK95: =AJ95 -> 2.708328 | AL95: =B95-H95+1 -> 70 | AM95: =IF(AL95<=30,"30天内",IF(AL95<=90,"31-90天","91天以上")) -> 31-90天 | AN95: 0.7 | AO95: Euro | AP95: =AK95*AN95 -> 1.8958296
A96: 202510 | B96: 45959 | C96: MIC德国仓 | D96: =D95 -> M » N2 - 1 | E96: =E95 -> YCD-EX:HUPPER TEK | F96: =F95 -> MI202508130012 | G96: =G95 -> DE2508031-G7-MIC | H96: =H95 -> 45889 | I96: =I95 -> B07Q3SQT6C | K96: =K95 -> 金属储物柜71英寸高 | M96: =M95 -> 188 | N96: =N95 -> 49 | O96: =O95 -> 14 | P96: =M96*N96*O96/1000000 -> 0.128968 | R96: =R95 -> 188 | S96: =S95 -> 49 | T96: =T95 -> 14 | U96: =R96*S96*T96/1000000 -> 0.128968 | AA96: =AA95 -> 13 | AB96: =AB95 -> 151 | AC96: =AC95 -> 151 | AD96: 0 | AE96: =AH95 -> 21 | AG96: 2 | AH96: =AE96+AF96-AG96 -> 19 | AI96: pcs | AJ96: =AH96*P96 -> 2.450392 | AK96: =AJ96 -> 2.450392 | AL96: =B96-H96+1 -> 71 | AM96: =IF(AL96<=30,"30天内",IF(AL96<=90,"31-90天","91天以上")) -> 31-90天 | AN96: 0.7 | AO96: Euro | AP96: =AK96*AN96 -> 1.7152744
A97: 202510 | B97: 45960 | C97: MIC德国仓 | D97: =D96 -> M » N2 - 1 | E97: =E96 -> YCD-EX:HUPPER TEK | F97: =F96 -> MI202508130012 | G97: =G96 -> DE2508031-G7-MIC | H97: =H96 -> 45889 | I97: =I96 -> B07Q3SQT6C | K97: =K96 -> 金属储物柜71英寸高 | M97: =M96 -> 188 | N97: =N96 -> 49 | O97: =O96 -> 14 | P97: =M97*N97*O97/1000000 -> 0.128968 | R97: =R96 -> 188 | S97: =S96 -> 49 | T97: =T96 -> 14 | U97: =R97*S97*T97/1000000 -> 0.128968 | AA97: =AA96 -> 13 | AB97: =AB96 -> 151 | AC97: =AC96 -> 151 | AD97: 0 | AE97: =AH96 -> 19 | AG97: 4 | AH97: =AE97+AF97-AG97 -> 15 | AI97: pcs | AJ97: =AH97*P97 -> 1.93452 | AK97: =AJ97 -> 1.93452 | AL97: =B97-H97+1 -> 72 | AM97: =IF(AL97<=30,"30天内",IF(AL97<=90,"31-90天","91天以上")) -> 31-90天 | AN97: 0.7 | AO97: Euro | AP97: =AK97*AN97 -> 1.354164
A98: 202510 | B98: 45961 | C98: MIC德国仓 | D98: =D97 -> M » N2 - 1 | E98: =E97 -> YCD-EX:HUPPER TEK | F98: =F97 -> MI202508130012 | G98: =G97 -> DE2508031-G7-MIC | H98: =H97 -> 45889 | I98: =I97 -> B07Q3SQT6C | K98: =K97 -> 金属储物柜71英寸高 | M98: =M97 -> 188 | N98: =N97 -> 49 | O98: =O97 -> 14 | P98: =M98*N98*O98/1000000 -> 0.128968 | R98: =R97 -> 188 | S98: =S97 -> 49 | T98: =T97 -> 14 | U98: =R98*S98*T98/1000000 -> 0.128968 | AA98: =AA97 -> 13 | AB98: =AB97 -> 151 | AC98: =AC97 -> 151 | AD98: 0 | AE98: =AH97 -> 15 | AG98: 1 | AH98: =AE98+AF98-AG98 -> 14 | AI98: pcs | AJ98: =AH98*P98 -> 1.805552 | AK98: =AJ98 -> 1.805552 | AL98: =B98-H98+1 -> 73 | AM98: =IF(AL98<=30,"30天内",IF(AL98<=90,"31-90天","91天以上")) -> 31-90天 | AN98: 0.7 | AO98: Euro | AP98: =AK98*AN98 -> 1.2638864
A99: 202510 | B99: 45931 | C99: MIC德国仓 | D99: M » N2 - 1 | E99: YCD-EX:HUPPER TEK | F99: MI202508130012 | G99: DE2508031-G7-MIC | H99: 45889 | I99: B077RVYZRF | K99: =VLOOKUP(I99,物品明细!A:B,2,0) -> 德国联邦快递金属储物柜 | M99: =VLOOKUP(I99,物品明细!A:E,5,0) -> 188 | N99: =VLOOKUP(I99,物品明细!A:F,6,0) -> 49 | O99: =VLOOKUP(I99,物品明细!A:G,7,0) -> 14 | P99: =M99*N99*O99/1000000 -> 0.128968 | R99: =VLOOKUP(I99,物品明细!A:E,5,0) -> 188 | S99: =VLOOKUP(I99,物品明细!A:F,6,0) -> 49 | T99: =VLOOKUP(I99,物品明细!A:G,7,0) -> 14 | U99: =R99*S99*T99/1000000 -> 0.128968 | AA99: 10 | AB99: 117 | AC99: 117 | AD99: 0 | AE99: 40 | AG99: 1 | AH99: =AE99+AF99-AG99 -> 39 | AI99: pcs | AJ99: =AH99*P99 -> 5.029752 | AK99: =AJ99 -> 5.029752 | AL99: =B99-H99+1 -> 43 | AM99: =IF(AL99<=30,"30天内",IF(AL99<=90,"31-90天","91天以上")) -> 31-90天 | AN99: 0.7 | AO99: Euro | AP99: =AK99*AN99 -> 3.5208264
A100: 202510 | B100: 45932 | C100: MIC德国仓 | D100: =D99 -> M » N2 - 1 | E100: =E99 -> YCD-EX:HUPPER TEK | F100: =F99 -> MI202508130012 | G100: =G99 -> DE2508031-G7-MIC | H100: =H99 -> 45889 | I100: =I99 -> B077RVYZRF | K100: =K99 -> 德国联邦快递金属储物柜 | M100: =M99 -> 188 | N100: =N99 -> 49 | O100: =O99 -> 14 | P100: =M100*N100*O100/1000000 -> 0.128968 | R100: =R99 -> 188 | S100: =S99 -> 49 | T100: =T99 -> 14 | U100: =R100*S100*T100/1000000 -> 0.128968 | AA100: =AA99 -> 10 | AB100: =AB99 -> 117 | AC100: =AC99 -> 117 | AD100: 0 | AE100: =AH99 -> 39 | AH100: =AE100+AF100-AG100 -> 39 | AI100: pcs | AJ100: =AH100*P100 -> 5.029752 | AK100: =AJ100 -> 5.029752 | AL100: =B100-H100+1 -> 44 | AM100: =IF(AL100<=30,"30天内",IF(AL100<=90,"31-90天","91天以上")) -> 31-90天 | AN100: 0.7 | AO100: Euro | AP100: =AK100*AN100 -> 3.5208264
...

Sheet 4.1 逆向退货&仓租费
AJ1: =SUM(AJ2:AJ120000) -> 19.4 | AQ1: =SUM(AQ2:AQ120000) -> 186.2343 | BH1: =SUM(BH2:BH120000) -> 40.4 | BI1: =SUM(BI2:BI120000) -> 226.6343 | BW1: =SUM(BW5) -> 0 | BX1: =SUM(BX2:BX120000) -> 246.0343
A2: 退货基础信息 | AG2: 逆向入库（同正向）-库内操作费一口价 | AK2: 退货运输费用 | BJ2: 2025.10月逆向-仓储费 | BX2: 逆向 费用总计
S3: 原始订单数据 | AJ3: 逆向收货小计 | AK3: 基础运费 | AR3: 附加费 | BI3: 运费 合计 | BJ3: 库存 | BP3: 仓储费
A4: Tracking Number | B4: Original Order No. | C4: 订单 行数 | D4: 订单数 | E4: Customer | F4: Source | G4: 退货类型1 | H4: 上架情况 | I4: 渠道 | J4: Item ID | K4: 物品描述 | L4: Barcode | M4: Item Qty | N4: 单品 重量 kg | O4: 订单 重量 kg | P4: Status | Q4: 收货 月份 | R4: RecDate | S4: 邮编 | T4: 城市 | U4: 国家 | V4: 长 | W4: 宽 | X4: 高 | Y4: 体积 | Z4: 包裹重量 kg | AA4: 托盘数 | AB4: 原始订单 托盘尺寸 cm | AC4: 原始订单打托重量 kg | AD4: 托盘重 | AE4: 订单 重量 kg | AF4: 备注 | AG4: PCS | AH4: 单价 | AI4: 金额 | AK4: 数量 票 | AL4: 实际重量 KG | AM4: 卡派体积重KG | AN4: 邮编开头前两位 | AO4: 计费 重量 kg | AP4: 单价 Euro | AQ4: 金额 | AR4: 运输 订单 管理 * | AS4: 私人地址附加费 | AT4: 道路附加费&安检费 | AU4: 燃油 附加费 &环保费 | AV4: 燃油 附加费 * | AW4: 过路 过桥 * | AX4: NC件 | AY4: 能源附加费 | AZ4: 安保费 | BA4: 运输 保险 | BB4: 电话预约 | BC4: DSV环境费 | BD4: 上门取货 | BE4: 旺季 附加费 | BF4: 危险品&ADR文件制作费 | BG4: 其它 | BH4: 附加费小计 | BJ4: 期初 库存 | BK4: 入库 | BL4: 出库 | BM4: 期末 库存 | BN4: 平均 库存 | BO4: 计费起始日 | BP4: 计费截止日 | BQ4: 累计存储天数 | BR4: 计费天数 | BS4: 单品 体积m³ | BT4: 计费体积 | BU4: 计费单价段 | BV4: 单价 | BW4: 逆向仓租费
A5: 4618237520 | B5: ABM0009-250922-0003 | C5: 1 | D5: 1 | E5: YCD-EX:HUPPER TEK | F5: Customer Retour | G5: 物流退货 | I5: GELF-EML_HUPPERTEK | J5: B076THQBHX | K5: =VLOOKUP($J5,物品明细!A:L,2,0) -> 金属储物柜71英寸灰色 | M5: 1 | N5: =VLOOKUP(J5,物品明细!A:L,4,0) -> 47.4 | O5: 47.4 | P5: Valid | Q5: 2025-10 | R5: 45943 | S5: 12559 | T5: Berlin | U5: DE | V5: =VLOOKUP(J5,物品明细!A:L,5,0) -> 188 | W5: =VLOOKUP(J5,物品明细!A:L,6,0) -> 49 | X5: =VLOOKUP(J5,物品明细!A:G,7,0) -> 14 | Y5: =VLOOKUP(J5,物品明细!A:K,10,0) -> 0.128968 | Z5: =N5*M5 -> 47.4 | AE5: =SUMIF(B:B,B5,Z:Z) -> 47.4 | AG5: =M5 -> 1 | AH5: 2.5 | AI5: 4.85 | AJ5: =AI5 -> 4.85 | AK5: 1 | AL5: =$AE5 -> 47.4 | AN5: =S5 -> 12559 | AO5: 50 | AP5: 46.558575 | AQ5: =AP5*AK5 -> 46.558575 | AR5: 2.5 | AW5: =$AO5*0.024 -> 1.2 | BB5: 2.5 | BG5: 7.8 | BH5: =SUM(AR5:BG5) -> 14 | BI5: =AQ5+BH5 -> 60.558575 | BK5: =M5 -> 1 | BM5: =BJ5+BK5-BL5 -> 1 | BN5: =(BJ5+BK5+BL5+BM5)/2 -> 1 | BO5: =R5 -> 45943 | BP5: 45961 | BQ5: =BP5-BO5 -> 18 | BR5: =BP5-BO5+1 -> 19 | BS5: =Y5 -> 0.128968 | BT5: =BS5*BN5 -> 0.128968 | BU5: =IF(BR5<=30,"30天内",IF(BR5<=90,"31-90天","91天以上")) -> 30天内 | BV5: =IF(BU5="30天内",0,IF(BU5="31-90天",0.6,1)) -> 0 | BW5: =BV5*BT5*BR5 -> 0 | BX5: =AJ5+BI5+BW5 -> 65.408575
A6: 4618242524 | B6: ABM0009-250923-0002 | C6: 1 | D6: 1 | G6: 物流退货 | I6: GELF-EML_HUPPERTEK | J6: B076THQBHX | K6: =VLOOKUP($J6,物品明细!A:L,2,0) -> 金属储物柜71英寸灰色 | M6: 1 | N6: =VLOOKUP(J6,物品明细!A:L,4,0) -> 47.4 | O6: 47.4 | P6: Valid | Q6: 2025-10 | R6: 45960 | S6: 65618 | T6: Selters (taunus) | U6: DE | V6: =VLOOKUP(J6,物品明细!A:L,5,0) -> 188 | W6: =VLOOKUP(J6,物品明细!A:L,6,0) -> 49 | X6: =VLOOKUP(J6,物品明细!A:G,7,0) -> 14 | Y6: =VLOOKUP(J6,物品明细!A:K,10,0) -> 0.128968 | Z6: =N6*M6 -> 47.4 | AE6: =SUMIF(B:B,B6,Z:Z) -> 47.4 | AG6: =M6 -> 1 | AH6: 2.5 | AI6: 4.85 | AJ6: =AI6 -> 4.85 | AK6: 1 | AL6: =$AE6 -> 47.4 | AN6: =S6 -> 65618 | AO6: 50 | AP6: 46.558575 | AQ6: =AP6*AK6 -> 46.558575 | AR6: 2.5 | AW6: =$AO6*0.024 -> 1.2 | BB6: 2.5 | BH6: =SUM(AR6:BG6) -> 6.2 | BI6: =AQ6+BH6 -> 52.758575 | BJ6: 1 | BK6: =M6 -> 1 | BM6: =BJ6+BK6-BL6 -> 2 | BN6: =(BJ6+BK6+BL6+BM6)/2 -> 2 | BO6: 45960 | BP6: 45961 | BQ6: =BP6-BO6 -> 1 | BR6: =BP6-BO6+1 -> 2 | BS6: =Y6 -> 0.128968 | BT6: =BS6*BN6 -> 0.257936 | BU6: =IF(BR6<=30,"30天内",IF(BR6<=90,"31-90天","91天以上")) -> 30天内 | BV6: =IF(BU6="30天内",0,IF(BU6="31-90天",0.6,1)) -> 0 | BW6: =BV6*BT6*BR6 -> 0 | BX6: =AJ6+BI6+BW6 -> 57.608575
A7: 4618295377 | B7: ABM0009-251005-0003 | C7: 1 | D7: 1 | G7: 物流退货 | I7: GELF-EML_HUPPERTEK | J7: B077RVYZRF | K7: =VLOOKUP($J7,物品明细!A:L,2,0) -> 德国联邦快递金属储物柜 | M7: 1 | N7: =VLOOKUP(J7,物品明细!A:L,4,0) -> 47.4 | O7: 47.4 | P7: Valid | Q7: 2025-10 | R7: 45960 | S7: 10997 | T7: Berlin | U7: DE | V7: =VLOOKUP(J7,物品明细!A:L,5,0) -> 188 | W7: =VLOOKUP(J7,物品明细!A:L,6,0) -> 49 | X7: =VLOOKUP(J7,物品明细!A:G,7,0) -> 14 | Y7: =VLOOKUP(J7,物品明细!A:K,10,0) -> 0.128968 | Z7: =N7*M7 -> 47.4 | AE7: =SUMIF(B:B,B7,Z:Z) -> 47.4 | AG7: =M7 -> 1 | AH7: 2.5 | AI7: 4.85 | AJ7: =AI7 -> 4.85 | AK7: 1 | AL7: =$AE7 -> 47.4 | AN7: =S7 -> 10997 | AO7: 50 | AP7: 46.558575 | AQ7: =AP7*AK7 -> 46.558575 | AR7: 2.5 | AW7: =$AO7*0.024 -> 1.2 | BB7: 2.5 | BG7: 7.8 | BH7: =SUM(AR7:BG7) -> 14 | BI7: =AQ7+BH7 -> 60.558575 | BK7: =M7 -> 1 | BM7: =BJ7+BK7-BL7 -> 1 | BN7: =(BJ7+BK7+BL7+BM7)/2 -> 1 | BO7: 45960 | BP7: 45961 | BQ7: =BP7-BO7 -> 1 | BR7: =BP7-BO7+1 -> 2 | BS7: =Y7 -> 0.128968 | BT7: =BS7*BN7 -> 0.128968 | BU7: =IF(BR7<=30,"30天内",IF(BR7<=90,"31-90天","91天以上")) -> 30天内 | BV7: =IF(BU7="30天内",0,IF(BU7="31-90天",0.6,1)) -> 0 | BW7: =BV7*BT7*BR7 -> 0 | BX7: =AJ7+BI7+BW7 -> 65.408575
A8: 4618251434 | B8: ABM0009-250925-0017 | C8: 1 | D8: 1 | G8: 物流退货 | I8: GELF-EML_HUPPERTEK | J8: B07Q3SQT6C | K8: =VLOOKUP($J8,物品明细!A:L,2,0) -> 金属储物柜71英寸高 | M8: 1 | N8: =VLOOKUP(J8,物品明细!A:L,4,0) -> 47.4 | O8: 47.4 | P8: Valid | Q8: 2025-10 | R8: 45960 | S8: 21337 | T8: Lüneburg | U8: DE | V8: =VLOOKUP(J8,物品明细!A:L,5,0) -> 188 | W8: =VLOOKUP(J8,物品明细!A:L,6,0) -> 49 | X8: =VLOOKUP(J8,物品明细!A:G,7,0) -> 14 | Y8: =VLOOKUP(J8,物品明细!A:K,10,0) -> 0.128968 | Z8: =N8*M8 -> 47.4 | AE8: =SUMIF(B:B,B8,Z:Z) -> 47.4 | AG8: =M8 -> 1 | AH8: 2.5 | AI8: 4.85 | AJ8: =AI8 -> 4.85 | AK8: 1 | AL8: =$AE8 -> 47.4 | AN8: =S8 -> 21337 | AO8: 50 | AP8: 46.558575 | AQ8: =AP8*AK8 -> 46.558575 | AR8: 2.5 | AW8: =$AO8*0.024 -> 1.2 | BB8: 2.5 | BH8: =SUM(AR8:BG8) -> 6.2 | BI8: =AQ8+BH8 -> 52.758575 | BK8: =M8 -> 1 | BM8: =BJ8+BK8-BL8 -> 1 | BN8: =(BJ8+BK8+BL8+BM8)/2 -> 1 | BO8: 45960 | BP8: 45961 | BQ8: =BP8-BO8 -> 1 | BR8: =BP8-BO8+1 -> 2 | BS8: =Y8 -> 0.128968 | BT8: =BS8*BN8 -> 0.128968 | BU8: =IF(BR8<=30,"30天内",IF(BR8<=90,"31-90天","91天以上")) -> 30天内 | BV8: =IF(BU8="30天内",0,IF(BU8="31-90天",0.6,1)) -> 0 | BW8: =BV8*BT8*BR8 -> 0 | BX8: =AJ8+BI8+BW8 -> 57.608575

Sheet 物品明细
A1: Item ID | B1: Name | C1: Barcode | D1: Weight | E1: Length | F1: Width | G1: Height | H1: HS Code | I1: 规格 | J1: 体积 | K1: 原始名称 | L1: 打托数
A2: B076THQBHX | B2: 金属储物柜71英寸灰色 | C2: 7434503987965 | D2: 47.4 | E2: 188 | F2: 49 | G2: 14 | I2: 188x49x14 | J2: 0.128968 | K2: Metal Storage Cabinet 71 inches Gray | L2: 12个/托
A3: B07BK8W5MF | B3: 金属储物柜71英寸银色 | C3: 7434503791791 | D3: 47.4 | E3: 188 | F3: 49 | G3: 14 | I3: 188x49x14 | J3: 0.128968 | K3: Metal Storage Cabinet 71 inches Silver | L3: 12个/托
A4: B077RVYZRF | B4: 德国联邦快递金属储物柜 | C4: 7434503188171 | D4: 47.4 | E4: 188 | F4: 49 | G4: 14 | I4: 188x49x14 | J4: 0.128968 | K4: DE - Fedmax Metal Storage Cabinet | L4: 12个/托
A5: B07Q3SQT6C | B5: 金属储物柜71英寸高 | C5: 600413399021 | D5: 47.4 | E5: 188 | F5: 49 | G5: 14 | I5: 188x49x14 | J5: 0.128968 | K5: Metal Storage Cabinet 71" Tall | L5: 12个/托
A6: B07GSF11XX | B6: 白板 | D6: 14 | E6: 133 | F6: 87 | G6: 8 | I6: =E6&"x"&F6&"x"&G6 -> 133x87x8 | J6: =E6*F6*G6/1000000 -> 0.092568
A7: ABM0009-B07GSF11XX | B7: 白板 | D7: 14 | E7: 133 | F7: 87 | G7: 8 | I7: =E7&"x"&F7&"x"&G7 -> 133x87x8 | J7: =E7*F7*G7/1000000 -> 0.092568
