Workbook
Name _dpx2: '[2]DHL City to Zone OB Vol'!$AF$7:$AO$45

Sheet 对账单-汇总页
A1: 应收账款对账单
A2: 客户：深圳市哈贝尔智能科技有限公司
A3: 联系人：
A4: 账单期间：2025.08.01~2025.09.08
A5: 业务场景 | B5: 费用项 | C5: 库内基础费用 A | D5: 运输基础费用 B | E5: 附加费 C | F5: 账单金额合计 A+B+C | G5: 已收金额 | H5: 应收余额（EUR） | I5: 备注
A6: 1. 正向 | B6: 1.1 入库 | C6: ='1.1 正向-入库'!V1 -> 882 | D6: 750 | F6: =C6+D6+E6 -> 1632 | H6: =F6-G6 -> 1632 | I6: 8月移仓入库费用
B7: 1.2 -1 2C订单-GEL | C7: 0 | D7: 0 | E7: 0 | F7: =C7+D7+E7 -> 0 | H7: =F7-G7 -> 0
A8: 2.仓储 | B8: 2.1 仓储费(8月） | C8: ='2.1 正向-普货&大件-仓储费(8月）'!AP1 -> 0 | F8: =C8+D8+E8 -> 0 | H8: =F8-G8 -> 0
F9: =C9+D9+E9 -> 0 | H9: =F9-G9 -> 0
A10: 3. 其他 | F10: =C10+D10+E10 -> 0 | H10: =F10-G10 -> 0
B15: 合计 | C15: =SUM(C6:C13) -> 882 | D15: =SUM(D6:D13) -> 750 | E15: =SUM(E6:E13) -> 0 | F15: =SUM(F6:F13) -> 1632 | G15: =SUM(G6:G13) -> 0 | H15: =SUM(H6:H13) -> 1632
A16: 应收余额负数代表有余额
A17: 感谢贵司选择我司的服务，烦请贵司仔细核对，如有问题请及时与我司业务员联系，核对无误请在右侧签章回传并及时安排付款，付款账号如下： | E17: 客户盖章
A18: 开户名： MIC Logistik GmbH
A19: 开户公司地址：Künkelstraße 43A, 41063 Mönchengladbach,Germany
A20: 银行名称： Volksbank Krefeld eG
A21: 银行地址：Tönisberger Str. 37-39, 47839 Krefeld,Germany
A22: 账号： DE96 3206 0362 4019 1180 08
A23: BIC: GENODED1HTK

Sheet 1.1 正向-入库
A1: MIC德国海外仓到货&收货&入库明细表 | V1: =SUM(V4:V7) -> 882 | W1: =SUM(W4:W7) -> 1632
A2: 退货信息 | S2: 卸货&收货费 | W2: 合计
A3: 任务号 | B3: 入库月份 | C3: Carrier | D3: 收货日期 | E3: 入库状态 | F3: 客户 | G3: 批次号 | H3: 批次号行数 | I3: 批次数 | J3: 类型 | K3: 物品SKU | L3: 物品描述 | M3: 物品 总数 | N3: 货位 | O3: 箱数 | P3: 托盘数 | Q3: Remark | R3: 运输费 | S3: 托盘数 | T3: 箱数 | U3: 单价 | V3: 金额
A4: MI202508130012 | B4: 8月 | C4: Truck | D4: 45889 | E4: Inbound Completed | F4: YCD-EX:HUPPER TEK | G4: DE2508031-G7-MIC | H4: =COUNTIF(G:G,G4) -> 4 | I4: 1 | J4: 大件 | K4: B07BK8W5MF | L4: =VLOOKUP(K4,物品明细!A:B,2,0) -> 金属储物柜71英寸银色 | M4: 247 | N4: M » N2 - 1 | O4: 247 | P4: 21 | R4: 750 | S4: =P4 -> 21 | U4: 14 | V4: =U4*S4 -> 294 | W4: =V4+R4 -> 1044
A5: MI202508130012 | B5: 8月 | C5: Truck | D5: 45889 | E5: Inbound Completed | F5: YCD-EX:HUPPER TEK | G5: DE2508031-G7-MIC | H5: =COUNTIF(G:G,G5) -> 4 | I5: 0 | J5: 大件 | K5: B076THQBHX | L5: =VLOOKUP(K5,物品明细!A:B,2,0) -> 金属储物柜71英寸灰色 | M5: 223 | N5: M » N2 - 1 | O5: 223 | P5: 19 | S5: =P5 -> 19 | U5: 14 | V5: =U5*S5 -> 266 | W5: =V5+R5 -> 266
A6: MI202508130012 | B6: 8月 | C6: Truck | D6: 45889 | E6: Inbound Completed | F6: YCD-EX:HUPPER TEK | G6: DE2508031-G7-MIC | H6: =COUNTIF(G:G,G6) -> 4 | I6: 0 | J6: 大件 | K6: B07Q3SQT6C | L6: =VLOOKUP(K6,物品明细!A:B,2,0) -> 金属储物柜71英寸高 | M6: 151 | N6: M » N2 - 1 | O6: 151 | P6: 13 | S6: =P6 -> 13 | U6: 14 | V6: =U6*S6 -> 182 | W6: =V6+R6 -> 182
A7: MI202508130012 | B7: 8月 | C7: Truck | D7: 45889 | E7: Inbound Completed | F7: YCD-EX:HUPPER TEK | G7: DE2508031-G7-MIC | H7: =COUNTIF(G:G,G7) -> 4 | I7: 0 | J7: 大件 | K7: B077RVYZRF | L7: =VLOOKUP(K7,物品明细!A:B,2,0) -> 德国联邦快递金属储物柜 | M7: 117 | N7: M » N2 - 1 | O7: 117 | P7: 10 | S7: =P7 -> 10 | U7: 14 | V7: =U7*S7 -> 140 | W7: =V7+R7 -> 140

Sheet 1.2-1正向-2C-GEL
A1: MIC德国海外仓一件代发明细表 | AI1: =SUM(#REF!) -> #REF! | AL1: =SUM(#REF!) -> #REF! | AO1: =SUM(#REF!) -> #REF! | AR1: =SUM(#REF!) -> #REF! | AU1: =SUM(#REF!) -> #REF! | AX1: =SUM(#REF!) -> #REF! | AY1: =SUM(#REF!) -> #REF! | BH1: =SUM(#REF!) -> #REF! | BJ1: =SUM(#REF!) -> #REF! | BQ1: =SUM(#REF!) -> #REF! | BT1: =SUM(#REF!) -> #REF! | BU1: =SUM(#REF!) -> #REF! | BV1: =SUM(#REF!) -> #REF!
AZ2: 尾程运输费 | BV2: 费用合计
A3: 出库指令 | Z3: 物品-拣料及最小包装 | AG3: 订单管理费 | AJ3: 拣货&包装费 | AM3: 拣货续件费 | AP3: 贴标费 | AS3: 包材费-包裹 | AV3: 装车费 | AY3: 合计 | AZ3: 基础费 | BI3: 续重费（超300公斤） | BK3: 附加费 | BR3: 3件包裹以上运输续件费 | BU3: 合计
A4: Order No. | B4: 订单 行数 | C4: 订单数 | D4: 对账 | E4: Warehouse | F4: 月份 | G4: Order Created At | H4: Shipped At | I4: Status | J4: Customer | K4: Original Reference | L4: Business Type | M4: Channel | N4: Creator | O4: 运单数 | P4: Priority | Q4: weight | R4: Carrier | S4: Carrier Return | T4: Shipments No1 | U4: Shipments No2 | V4: Retour No | W4: Postal Code | X4: 城市 | Y4: Country | Z4: Item ID | AA4: 物品描述 | AB4: 物品尺寸 长宽高cm | AC4: 单个物品 重量kg | AD4: Item Batch | AE4: Item Qty | AF4: 订单重量 kg | AG4: 数量 票 | AH4: 单价 Euro | AI4: 金额 Euro | AJ4: 数量 套 | AK4: 单价 Euro | AL4: 金额 Euro | AM4: 数量 pcs | AN4: 单价 Euro | AO4: 金额 Euro | AP4: 标签/张 | AQ4: 单价 | AR4: 金额 | AS4: 数量 pcs | AT4: 单价 Euro | AU4: 金额 Euro | AV4: 数量 /托 | AW4: 单价 Euro | AX4: 金额 Euro | AY4: 库内小计 | AZ4: 数量 票 | BA4: 实际重kg | BB4: 体积重KG | BC4: 计费 重量 kg | BD4: 邮编所属区域 | BE4: 城市 | BF4: 国家 | BG4: 单价 Euro | BH4: 金额 Euro | BI4: 单价 Euro | BJ4: 金额 Euro | BK4: 运输 订单 管理 * | BL4: 燃油 附加费 * | BM4: 过路 过桥 * | BN4: 运输 保险 | BO4: 预约 通知 * | BP4: 其它 | BQ4: 附加费小计 | BR4: 包裹数 个 | BS4: 单价 Euro | BT4: 金额 Euro

Sheet 2.1 正向-普货&大件-仓储费(8月）
AP1: =SUM(AP6:AP36) -> 0
A2: 计费时间IStorage Charge Date | C2: 入仓信息Inbound Information | I2: 商品信息Product Information | Q2: 装箱信息 | V2: 打托信息 | AA2: 原始入仓数量 | AE2: 进销存信息 | AJ2: 仓储费计费信息/Storage Charge Infromation | AQ2: 备注
A3: 月份 | B3: 日期 | C3: 仓库名称 | D3: 仓库编码 | E3: 客户代码 | F3: 入库任务号 | G3: 原始参考号 | H3: 入库上架时间 | I3: 编码 | J3: 条码 | K3: 商品名称 | L3: 件型 | M3: 长 | N3: 宽 | O3: 高 | P3: 单品体积A | Q3: 装箱数 | R3: 长 | S3: 宽 | T3: 高 | U3: 单箱体积B | V3: 打托数 | W3: 长 | X3: 宽 | Y3: 高 | Z3: 单托体积C | AA3: 托数 | AB3: 箱数 | AC3: 总数 | AD3: 批次号 | AE3: 期初库存数 | AF3: 入库数 | AG3: 出库数 | AH3: 期末库存数 | AI3: 计费单元 | AJ3: 库存体积E | AK3: 实际计费体积F | AL3: 库龄 | AM3: 库龄段 | AN3: 计费单价 | AO3: 币种 | AP3: 仓储费
A4: / | B4: / | C4: / | D4: / | E4: / | F4: / | G4: / | H4: / | I4: / | J4: / | K4: / | M4: cm | N4: cm | O4: cm | P4: CBM/m³ | Q4: pcs | R4: cm | S4: cm | T4: cm | U4: CBM/m³ | V4: pcs/box | W4: cm | X4: cm | Y4: cm | Z4: CBM/m³ | AA4: 托/Pallet | AB4: 箱/Box | AC4: 件/pcs | AE4: 件/pcs | AF4: 件/pcs | AG4: 件/pcs | AH4: 件/pcs | AI4: pcs/box/pallet | AJ4: CBM/m³ | AK4: CBM/m³ | AL4: 天/day | AM4: 天/day | AN4: / | AO4: Euro | AP4: Euro
A5: Month | B5: Date | C5: Warehouse Name | D5: Warehouse Code | E5: Client Code | F5: Task No. | G5: Original Ref. No. | H5: Inbound Time | I5: SKU | J5: Barcode | K5: Product Name | L5: Product Type | M5: Lenth | N5: Width | O5: Height | P5: Product Volume-A | Q5: Qty per Box | R5: Lenth | S5: Width | T5: Height | U5: Box Volume-B | V5: Qty per Pallet | W5: Lenth | X5: Width | Y5: Height | Z5: Pallet Volume-B | AA5: Qty of Pallet | AB5: Qty of Carton | AC5: Total Qty. | AD5: Batch No. | AE5: Beginning Inv | AF5: Inbound | AG5: Outbound | AH5: Ending Inv. | AI5: Charge Unit | AJ5: INV Volume-E | AK5: Charge Volume-F | AL5: Storage Age | AM5: Storage Age Range | AN5: Charge Price | AO5: Curreny | AP5: Storage Amount | AQ5: Rermar
A6: 202508 | B6: 45870 | C6: MIC德国仓 | D6: M » N2 - 1 | E6: YCD-EX:HUPPER TEK | F6: MI202508130012 | G6: DE2508031-G7-MIC | H6: 45889 | I6: B07BK8W5MF | K6: =VLOOKUP(I6,物品明细!A:B,2,0) -> 金属储物柜71英寸银色 | M6: =VLOOKUP(I6,物品明细!A:E,5,0) -> 188 | N6: =VLOOKUP(I6,物品明细!A:F,6,0) -> 49 | O6: =VLOOKUP(I6,物品明细!A:G,7,0) -> 14 | P6: =M6*N6*O6/1000000 -> 0.128968 | R6: =VLOOKUP(I6,物品明细!A:E,5,0) -> 188 | S6: =VLOOKUP(I6,物品明细!A:F,6,0) -> 49 | T6: =VLOOKUP(I6,物品明细!A:G,7,0) -> 14 | U6: =R6*S6*T6/1000000 -> 0.128968 | AA6: 21 | AB6: 247 | AC6: 247 | AD6: 0 | AE6: 0 | AH6: =AE6+AF6-AG6 -> 0 | AI6: pcs | AJ6: =AH6*P6 -> 0 | AK6: =AJ6 -> 0 | AL6: =B6-H6+1 -> -18 | AM6: =IF(AL6<=30,"30天内",IF(AL6<=90,"31-90天","91天以上")) -> 30天内 | AN6: 0 | AO6: Euro | AP6: =AK6*AN6 -> 0
A7: 202508 | B7: 45871 | C7: MIC德国仓 | D7: =D6 -> M » N2 - 1 | E7: =E6 -> YCD-EX:HUPPER TEK | F7: =F6 -> MI202508130012 | G7: =G6 -> DE2508031-G7-MIC | H7: =H6 -> 45889 | I7: =I6 -> B07BK8W5MF | K7: =K6 -> 金属储物柜71英寸银色 | M7: =M6 -> 188 | N7: =N6 -> 49 | O7: =O6 -> 14 | P7: =M7*N7*O7/1000000 -> 0.128968 | R7: =R6 -> 188 | S7: =S6 -> 49 | T7: =T6 -> 14 | U7: =R7*S7*T7/1000000 -> 0.128968 | AA7: =AA6 -> 21 | AB7: =AB6 -> 247 | AC7: =AC6 -> 247 | AD7: 0 | AE7: =AH6 -> 0 | AH7: =AE7+AF7-AG7 -> 0 | AI7: pcs | AJ7: =AH7*P7 -> 0 | AK7: =AJ7 -> 0 | AL7: =B7-H7+1 -> -17 | AM7: =IF(AL7<=30,"30天内",IF(AL7<=90,"31-90天","91天以上")) -> 30天内 | AN7: 0 | AO7: Euro | AP7: =AK7*AN7 -> 0
A8: 202508 | B8: 45872 | C8: MIC德国仓 | D8: =D7 -> M » N2 - 1 | E8: =E7 -> YCD-EX:HUPPER TEK | F8: =F7 -> MI202508130012 | G8: =G7 -> DE2508031-G7-MIC | H8: =H7 -> 45889 | I8: =I7 -> B07BK8W5MF | K8: =K7 -> 金属储物柜71英寸银色 | M8: =M7 -> 188 | N8: =N7 -> 49 | O8: =O7 -> 14 | P8: =M8*N8*O8/1000000 -> 0.128968 | R8: =R7 -> 188 | S8: =S7 -> 49 | T8: =T7 -> 14 | U8: =R8*S8*T8/1000000 -> 0.128968 | AA8: =AA7 -> 21 | AB8: =AB7 -> 247 | AC8: =AC7 -> 247 | AD8: 0 | AE8: =AH7 -> 0 | AH8: =AE8+AF8-AG8 -> 0 | AI8: pcs | AJ8: =AH8*P8 -> 0 | AK8: =AJ8 -> 0 | AL8: =B8-H8+1 -> -16 | AM8: =IF(AL8<=30,"30天内",IF(AL8<=90,"31-90天","91天以上")) -> 30天内 | AN8: 0 | AO8: Euro | AP8: =AK8*AN8 -> 0
A9: 202508 | B9: 45873 | C9: MIC德国仓 | D9: =D8 -> M » N2 - 1 | E9: =E8 -> YCD-EX:HUPPER TEK | F9: =F8 -> MI202508130012 | G9: =G8 -> DE2508031-G7-MIC | H9: =H8 -> 45889 | I9: =I8 -> B07BK8W5MF | K9: =K8 -> 金属储物柜71英寸银色 | M9: =M8 -> 188 | N9: =N8 -> 49 | O9: =O8 -> 14 | P9: =M9*N9*O9/1000000 -> 0.128968 | R9: =R8 -> 188 | S9: =S8 -> 49 | T9: =T8 -> 14 | U9: =R9*S9*T9/1000000 -> 0.128968 | AA9: =AA8 -> 21 | AB9: =AB8 -> 247 | AC9: =AC8 -> 247 | AD9: 0 | AE9: =AH8 -> 0 | AH9: =AE9+AF9-AG9 -> 0 | AI9: pcs | AJ9: =AH9*P9 -> 0 | AK9: =AJ9 -> 0 | AL9: =B9-H9+1 -> -15 | AM9: =IF(AL9<=30,"30天内",IF(AL9<=90,"31-90天","91天以上")) -> 30天内 | AN9: 0 | AO9: Euro | AP9: =AK9*AN9 -> 0
A10: 202508 | B10: 45874 | C10: MIC德国仓 | D10: =D9 -> M » N2 - 1 | E10: =E9 -> YCD-EX:HUPPER TEK | F10: =F9 -> MI202508130012 | G10: =G9 -> DE2508031-G7-MIC | H10: =H9 -> 45889 | I10: =I9 -> B07BK8W5MF | K10: =K9 -> 金属储物柜71英寸银色 | M10: =M9 -> 188 | N10: =N9 -> 49 | O10: =O9 -> 14 | P10: =M10*N10*O10/1000000 -> 0.128968 | R10: =R9 -> 188 | S10: =S9 -> 49 | T10: =T9 -> 14 | U10: =R10*S10*T10/1000000 -> 0.128968 | AA10: =AA9 -> 21 | AB10: =AB9 -> 247 | AC10: =AC9 -> 247 | AD10: 0 | AE10: =AH9 -> 0 | AH10: =AE10+AF10-AG10 -> 0 | AI10: pcs | AJ10: =AH10*P10 -> 0 | AK10: =AJ10 -> 0 | AL10: =B10-H10+1 -> -14 | AM10: =IF(AL10<=30,"30天内",IF(AL10<=90,"31-90天","91天以上")) -> 30天内 | AN10: 0 | AO10: Euro | AP10: =AK10*AN10 -> 0
A11: 202508 | B11: 45875 | C11: MIC德国仓 | D11: =D10 -> M » N2 - 1 | E11: =E10 -> YCD-EX:HUPPER TEK | F11: =F10 -> MI202508130012 | G11: =G10 -> DE2508031-G7-MIC | H11: =H10 -> 45889 | I11: =I10 -> B07BK8W5MF | K11: =K10 -> 金属储物柜71英寸银色 | M11: =M10 -> 188 | N11: =N10 -> 49 | O11: =O10 -> 14 | P11: =M11*N11*O11/1000000 -> 0.128968 | R11: =R10 -> 188 | S11: =S10 -> 49 | T11: =T10 -> 14 | U11: =R11*S11*T11/1000000 -> 0.128968 | AA11: =AA10 -> 21 | AB11: =AB10 -> 247 | AC11: =AC10 -> 247 | AD11: 0 | AE11: =AH10 -> 0 | AH11: =AE11+AF11-AG11 -> 0 | AI11: pcs | AJ11: =AH11*P11 -> 0 | AK11: =AJ11 -> 0 | AL11: =B11-H11+1 -> -13 | AM11: =IF(AL11<=30,"30天内",IF(AL11<=90,"31-90天","91天以上")) -> 30天内 | AN11: 0 | AO11: Euro | AP11: =AK11*AN11 -> 0
A12: 202508 | B12: 45876 | C12: MIC德国仓 | D12: =D11 -> M » N2 - 1 | E12: =E11 -> YCD-EX:HUPPER TEK | F12: =F11 -> MI202508130012 | G12: =G11 -> DE2508031-G7-MIC | H12: =H11 -> 45889 | I12: =I11 -> B07BK8W5MF | K12: =K11 -> 金属储物柜71英寸银色 | M12: =M11 -> 188 | N12: =N11 -> 49 | O12: =O11 -> 14 | P12: =M12*N12*O12/1000000 -> 0.128968 | R12: =R11 -> 188 | S12: =S11 -> 49 | T12: =T11 -> 14 | U12: =R12*S12*T12/1000000 -> 0.128968 | AA12: =AA11 -> 21 | AB12: =AB11 -> 247 | AC12: =AC11 -> 247 | AD12: 0 | AE12: =AH11 -> 0 | AH12: =AE12+AF12-AG12 -> 0 | AI12: pcs | AJ12: =AH12*P12 -> 0 | AK12: =AJ12 -> 0 | AL12: =B12-H12+1 -> -12 | AM12: =IF(AL12<=30,"30天内",IF(AL12<=90,"31-90天","91天以上")) -> 30天内 | AN12: 0 | AO12: Euro | AP12: =AK12*AN12 -> 0
A13: 202508 | B13: 45877 | C13: MIC德国仓 | D13: =D12 -> M » N2 - 1 | E13: =E12 -> YCD-EX:HUPPER TEK | F13: =F12 -> MI202508130012 | G13: =G12 -> DE2508031-G7-MIC | H13: =H12 -> 45889 | I13: =I12 -> B07BK8W5MF | K13: =K12 -> 金属储物柜71英寸银色 | M13: =M12 -> 188 | N13: =N12 -> 49 | O13: =O12 -> 14 | P13: =M13*N13*O13/1000000 -> 0.128968 | R13: =R12 -> 188 | S13: =S12 -> 49 | T13: =T12 -> 14 | U13: =R13*S13*T13/1000000 -> 0.128968 | AA13: =AA12 -> 21 | AB13: =AB12 -> 247 | AC13: =AC12 -> 247 | AD13: 0 | AE13: =AH12 -> 0 | AH13: =AE13+AF13-AG13 -> 0 | AI13: pcs | AJ13: =AH13*P13 -> 0 | AK13: =AJ13 -> 0 | AL13: =B13-H13+1 -> -11 | AM13: =IF(AL13<=30,"30天内",IF(AL13<=90,"31-90天","91天以上")) -> 30天内 | AN13: 0 | AO13: Euro | AP13: =AK13*AN13 -> 0
A14: 202508 | B14: 45878 | C14: MIC德国仓 | D14: =D13 -> M » N2 - 1 | E14: =E13 -> YCD-EX:HUPPER TEK | F14: =F13 -> MI202508130012 | G14: =G13 -> DE2508031-G7-MIC | H14: =H13 -> 45889 | I14: =I13 -> B07BK8W5MF | K14: =K13 -> 金属储物柜71英寸银色 | M14: =M13 -> 188 | N14: =N13 -> 49 | O14: =O13 -> 14 | P14: =M14*N14*O14/1000000 -> 0.128968 | R14: =R13 -> 188 | S14: =S13 -> 49 | T14: =T13 -> 14 | U14: =R14*S14*T14/1000000 -> 0.128968 | AA14: =AA13 -> 21 | AB14: =AB13 -> 247 | AC14: =AC13 -> 247 | AD14: 0 | AE14: =AH13 -> 0 | AH14: =AE14+AF14-AG14 -> 0 | AI14: pcs | AJ14: =AH14*P14 -> 0 | AK14: =AJ14 -> 0 | AL14: =B14-H14+1 -> -10 | AM14: =IF(AL14<=30,"30天内",IF(AL14<=90,"31-90天","91天以上")) -> 30天内 | AN14: 0 | AO14: Euro | AP14: =AK14*AN14 -> 0
A15: 202508 | B15: 45879 | C15: MIC德国仓 | D15: =D14 -> M » N2 - 1 | E15: =E14 -> YCD-EX:HUPPER TEK | F15: =F14 -> MI202508130012 | G15: =G14 -> DE2508031-G7-MIC | H15: =H14 -> 45889 | I15: =I14 -> B07BK8W5MF | K15: =K14 -> 金属储物柜71英寸银色 | M15: =M14 -> 188 | N15: =N14 -> 49 | O15: =O14 -> 14 | P15: =M15*N15*O15/1000000 -> 0.128968 | R15: =R14 -> 188 | S15: =S14 -> 49 | T15: =T14 -> 14 | U15: =R15*S15*T15/1000000 -> 0.128968 | AA15: =AA14 -> 21 | AB15: =AB14 -> 247 | AC15: =AC14 -> 247 | AD15: 0 | AE15: =AH14 -> 0 | AH15: =AE15+AF15-AG15 -> 0 | AI15: pcs | AJ15: =AH15*P15 -> 0 | AK15: =AJ15 -> 0 | AL15: =B15-H15+1 -> -9 | AM15: =IF(AL15<=30,"30天内",IF(AL15<=90,"31-90天","91天以上")) -> 30天内 | AN15: 0 | AO15: Euro | AP15: =AK15*AN15 -> 0
A16: 202508 | B16: 45880 | C16: MIC德国仓 | D16: =D15 -> M » N2 - 1 | E16: =E15 -> YCD-EX:HUPPER TEK | F16: =F15 -> MI202508130012 | G16: =G15 -> DE2508031-G7-MIC | H16: =H15 -> 45889 | I16: =I15 -> B07BK8W5MF | K16: =K15 -> 金属储物柜71英寸银色 | M16: =M15 -> 188 | N16: =N15 -> 49 | O16: =O15 -> 14 | P16: =M16*N16*O16/1000000 -> 0.128968 | R16: =R15 -> 188 | S16: =S15 -> 49 | T16: =T15 -> 14 | U16: =R16*S16*T16/1000000 -> 0.128968 | AA16: =AA15 -> 21 | AB16: =AB15 -> 247 | AC16: =AC15 -> 247 | AD16: 0 | AE16: =AH15 -> 0 | AH16: =AE16+AF16-AG16 -> 0 | AI16: pcs | AJ16: =AH16*P16 -> 0 | AK16: =AJ16 -> 0 | AL16: =B16-H16+1 -> -8 | AM16: =IF(AL16<=30,"30天内",IF(AL16<=90,"31-90天","91天以上")) -> 30天内 | AN16: 0 | AO16: Euro | AP16: =AK16*AN16 -> 0
A17: 202508 | B17: 45881 | C17: MIC德国仓 | D17: =D16 -> M » N2 - 1 | E17: =E16 -> YCD-EX:HUPPER TEK | F17: =F16 -> MI202508130012 | G17: =G16 -> DE2508031-G7-MIC | H17: =H16 -> 45889 | I17: =I16 -> B07BK8W5MF | K17: =K16 -> 金属储物柜71英寸银色 | M17: =M16 -> 188 | N17: =N16 -> 49 | O17: =O16 -> 14 | P17: =M17*N17*O17/1000000 -> 0.128968 | R17: =R16 -> 188 | S17: =S16 -> 49 | T17: =T16 -> 14 | U17: =R17*S17*T17/1000000 -> 0.128968 | AA17: =AA16 -> 21 | AB17: =AB16 -> 247 | AC17: =AC16 -> 247 | AD17: 0 | AE17: =AH16 -> 0 | AH17: =AE17+AF17-AG17 -> 0 | AI17: pcs | AJ17: =AH17*P17 -> 0 | AK17: =AJ17 -> 0 | AL17: =B17-H17+1 -> -7 | AM17: =IF(AL17<=30,"30天内",IF(AL17<=90,"31-90天","91天以上")) -> 30天内 | AN17: 0 | AO17: Euro | AP17: =AK17*AN17 -> 0
A18: 202508 | B18: 45882 | C18: MIC德国仓 | D18: =D17 -> M » N2 - 1 | E18: =E17 -> YCD-EX:HUPPER TEK | F18: =F17 -> MI202508130012 | G18: =G17 -> DE2508031-G7-MIC | H18: =H17 -> 45889 | I18: =I17 -> B07BK8W5MF | K18: =K17 -> 金属储物柜71英寸银色 | M18: =M17 -> 188 | N18: =N17 -> 49 | O18: =O17 -> 14 | P18: =M18*N18*O18/1000000 -> 0.128968 | R18: =R17 -> 188 | S18: =S17 -> 49 | T18: =T17 -> 14 | U18: =R18*S18*T18/1000000 -> 0.128968 | AA18: =AA17 -> 21 | AB18: =AB17 -> 247 | AC18: =AC17 -> 247 | AD18: 0 | AE18: =AH17 -> 0 | AH18: =AE18+AF18-AG18 -> 0 | AI18: pcs | AJ18: =AH18*P18 -> 0 | AK18: =AJ18 -> 0 | AL18: =B18-H18+1 -> -6 | AM18: =IF(AL18<=30,"30天内",IF(AL18<=90,"31-90天","91天以上")) -> 30天内 | AN18: 0 | AO18: Euro | AP18: =AK18*AN18 -> 0
... A24: 202508 | B24: 45888 | C24: MIC德国仓 | D24: =D23 -> M » N2 - 1 | E24: =E23 -> YCD-EX:HUPPER TEK | F24: =F23 -> MI202508130012 | G24: =G23 -> DE2508031-G7-MIC | H24: =H23 -> 45889 | I24: =I23 -> B07BK8W5MF | K24: =K23 -> 金属储物柜71英寸银色 | M24: =M23 -> 188 | N24: =N23 -> 49 | O24: =O23 -> 14 | P24: =M24*N24*O24/1000000 -> 0.128968 | R24: =R23 -> 188 | S24: =S23 -> 49 | T24: =T23 -> 14 | U24: =R24*S24*T24/1000000 -> 0.128968 | AA24: =AA23 -> 21 | AB24: =AB23 -> 247 | AC24: =AC23 -> 247 | AD24: 0 | AE24: =AH23 -> 0 | AH24: =AE24+AF24-AG24 -> 0 | AI24: pcs | AJ24: =AH24*P24 -> 0 | AK24: =AJ24 -> 0 | AL24: =B24-H24+1 -> 0 | AM24: =IF(AL24<=30,"30天内",IF(AL24<=90,"31-90天","91天以上")) -> 30天内 | AN24: 0 | AO24: Euro | AP24: =AK24*AN24 -> 0
A25: 202508 | B25: 45889 | C25: MIC德国仓 | D25: =D24 -> M » N2 - 1 | E25: =E24 -> YCD-EX:HUPPER TEK | F25: =F24 -> MI202508130012 | G25: =G24 -> DE2508031-G7-MIC | H25: =H24 -> 45889 | I25: =I24 -> B07BK8W5MF | K25: =K24 -> 金属储物柜71英寸银色 | M25: =M24 -> 188 | N25: =N24 -> 49 | O25: =O24 -> 14 | P25: =M25*N25*O25/1000000 -> 0.128968 | R25: =R24 -> 188 | S25: =S24 -> 49 | T25: =T24 -> 14 | U25: =R25*S25*T25/1000000 -> 0.128968 | AA25: =AA24 -> 21 | AB25: =AB24 -> 247 | AC25: =AC24 -> 247 | AD25: 0 | AE25: =AH24 -> 0 | AF25: 247 | AH25: =AE25+AF25-AG25 -> 247 | AI25: pcs | AJ25: =AH25*P25 -> 31.855096 | AK25: =AJ25 -> 31.855096 | AL25: =B25-H25+1 -> 1 | AM25: =IF(AL25<=30,"30天内",IF(AL25<=90,"31-90天","91天以上")) -> 30天内 | AN25: 0 | AO25: Euro | AP25: =AK25*AN25 -> 0
A26: 202508 | B26: 45890 | C26: MIC德国仓 | D26: =D25 -> M » N2 - 1 | E26: =E25 -> YCD-EX:HUPPER TEK | F26: =F25 -> MI202508130012 | G26: =G25 -> DE2508031-G7-MIC | H26: =H25 -> 45889 | I26: =I25 -> B07BK8W5MF | K26: =K25 -> 金属储物柜71英寸银色 | M26: =M25 -> 188 | N26: =N25 -> 49 | O26: =O25 -> 14 | P26: =M26*N26*O26/1000000 -> 0.128968 | R26: =R25 -> 188 | S26: =S25 -> 49 | T26: =T25 -> 14 | U26: =R26*S26*T26/1000000 -> 0.128968 | AA26: =AA25 -> 21 | AB26: =AB25 -> 247 | AC26: =AC25 -> 247 | AD26: 0 | AE26: =AH25 -> 247 | AH26: =AE26+AF26-AG26 -> 247 | AI26: pcs | AJ26: =AH26*P26 -> 31.855096 | AK26: =AJ26 -> 31.855096 | AL26: =B26-H26+1 -> 2 | AM26: =IF(AL26<=30,"30天内",IF(AL26<=90,"31-90天","91天以上")) -> 30天内 | AN26: 0 | AO26: Euro | AP26: =AK26*AN26 -> 0
A27: 202508 | B27: 45891 | C27: MIC德国仓 | D27: =D26 -> M » N2 - 1 | E27: =E26 -> YCD-EX:HUPPER TEK | F27: =F26 -> MI202508130012 | G27: =G26 -> DE2508031-G7-MIC | H27: =H26 -> 45889 | I27: =I26 -> B07BK8W5MF | K27: =K26 -> 金属储物柜71英寸银色 | M27: =M26 -> 188 | N27: =N26 -> 49 | O27: =O26 -> 14 | P27: =M27*N27*O27/1000000 -> 0.128968 | R27: =R26 -> 188 | S27: =S26 -> 49 | T27: =T26 -> 14 | U27: =R27*S27*T27/1000000 -> 0.128968 | AA27: =AA26 -> 21 | AB27: =AB26 -> 247 | AC27: =AC26 -> 247 | AD27: 0 | AE27: =AH26 -> 247 | AH27: =AE27+AF27-AG27 -> 247 | AI27: pcs | AJ27: =AH27*P27 -> 31.855096 | AK27: =AJ27 -> 31.855096 | AL27: =B27-H27+1 -> 3 | AM27: =IF(AL27<=30,"30天内",IF(AL27<=90,"31-90天","91天以上")) -> 30天内 | AN27: 0 | AO27: Euro | AP27: =AK27*AN27 -> 0
A28: 202508 | B28: 45892 | C28: MIC德国仓 | D28: =D27 -> M » N2 - 1 | E28: =E27 -> YCD-EX:HUPPER TEK | F28: =F27 -> MI202508130012 | G28: =G27 -> DE2508031-G7-MIC | H28: =H27 -> 45889 | I28: =I27 -> B07BK8W5MF | K28: =K27 -> 金属储物柜71英寸银色 | M28: =M27 -> 188 | N28: =N27 -> 49 | O28: =O27 -> 14 | P28: =M28*N28*O28/1000000 -> 0.128968 | R28: =R27 -> 188 | S28: =S27 -> 49 | T28: =T27 -> 14 | U28: =R28*S28*T28/1000000 -> 0.128968 | AA28: =AA27 -> 21 | AB28: =AB27 -> 247 | AC28: =AC27 -> 247 | AD28: 0 | AE28: =AH27 -> 247 | AH28: =AE28+AF28-AG28 -> 247 | AI28: pcs | AJ28: =AH28*P28 -> 31.855096 | AK28: =AJ28 -> 31.855096 | AL28: =B28-H28+1 -> 4 | AM28: =IF(AL28<=30,"30天内",IF(AL28<=90,"31-90天","91天以上")) -> 30天内 | AN28: 0 | AO28: Euro | AP28: =AK28*AN28 -> 0
A29: 202508 | B29: 45893 | C29: MIC德国仓 | D29: =D28 -> M » N2 - 1 | E29: =E28 -> YCD-EX:HUPPER TEK | F29: =F28 -> MI202508130012 | G29: =G28 -> DE2508031-G7-MIC | H29: =H28 -> 45889 | I29: =I28 -> B07BK8W5MF | K29: =K28 -> 金属储物柜71英寸银色 | M29: =M28 -> 188 | N29: =N28 -> 49 | O29: =O28 -> 14 | P29: =M29*N29*O29/1000000 -> 0.128968 | R29: =R28 -> 188 | S29: =S28 -> 49 | T29: =T28 -> 14 | U29: =R29*S29*T29/1000000 -> 0.128968 | AA29: =AA28 -> 21 | AB29: =AB28 -> 247 | AC29: =AC28 -> 247 | AD29: 0 | AE29: =AH28 -> 247 | AH29: =AE29+AF29-AG29 -> 247 | AI29: pcs | AJ29: =AH29*P29 -> 31.855096 | AK29: =AJ29 -> 31.855096 | AL29: =B29-H29+1 -> 5 | AM29: =IF(AL29<=30,"30天内",IF(AL29<=90,"31-90天","91天以上")) -> 30天内 | AN29: 0 | AO29: Euro | AP29: =AK29*AN29 -> 0
A30: 202508 | B30: 45894 | C30: MIC德国仓 | D30: =D29 -> M » N2 - 1 | E30: =E29 -> YCD-EX:HUPPER TEK | F30: =F29 -> MI202508130012 | G30: =G29 -> DE2508031-G7-MIC | H30: =H29 -> 45889 | I30: =I29 -> B07BK8W5MF | K30: =K29 -> 金属储物柜71英寸银色 | M30: =M29 -> 188 | N30: =N29 -> 49 | O30: =O29 -> 14 | P30: =M30*N30*O30/1000000 -> 0.128968 | R30: =R29 -> 188 | S30: =S29 -> 49 | T30: =T29 -> 14 | U30: =R30*S30*T30/1000000 -> 0.128968 | AA30: =AA29 -> 21 | AB30: =AB29 -> 247 | AC30: =AC29 -> 247 | AD30: 0 | AE30: =AH29 -> 247 | AH30: =AE30+AF30-AG30 -> 247 | AI30: pcs | AJ30: =AH30*P30 -> 31.855096 | AK30: =AJ30 -> 31.855096 | AL30: =B30-H30+1 -> 6 | AM30: =IF(AL30<=30,"30天内",IF(AL30<=90,"31-90天","91天以上")) -> 30天内 | AN30: 0 | AO30: Euro | AP30: =AK30*AN30 -> 0
A31: 202508 | B31: 45895 | C31: MIC德国仓 | D31: =D30 -> M » N2 - 1 | E31: =E30 -> YCD-EX:HUPPER TEK | F31: =F30 -> MI202508130012 | G31: =G30 -> DE2508031-G7-MIC | H31: =H30 -> 45889 | I31: =I30 -> B07BK8W5MF | K31: =K30 -> 金属储物柜71英寸银色 | M31: =M30 -> 188 | N31: =N30 -> 49 | O31: =O30 -> 14 | P31: =M31*N31*O31/1000000 -> 0.128968 | R31: =R30 -> 188 | S31: =S30 -> 49 | T31: =T30 -> 14 | U31: =R31*S31*T31/1000000 -> 0.128968 | AA31: =AA30 -> 21 | AB31: =AB30 -> 247 | AC31: =AC30 -> 247 | AD31: 0 | AE31: =AH30 -> 247 | AH31: =AE31+AF31-AG31 -> 247 | AI31: pcs | AJ31: =AH31*P31 -> 31.855096 | AK31: =AJ31 -> 31.855096 | AL31: =B31-H31+1 -> 7 | AM31: =IF(AL31<=30,"30天内",IF(AL31<=90,"31-90天","91天以上")) -> 30天内 | AN31: 0 | AO31: Euro | AP31: =AK31*AN31 -> 0
A32: 202508 | B32: 45896 | C32: MIC德国仓 | D32: =D31 -> M » N2 - 1 | E32: =E31 -> YCD-EX:HUPPER TEK | F32: =F31 -> MI202508130012 | G32: =G31 -> DE2508031-G7-MIC | H32: =H31 -> 45889 | I32: =I31 -> B07BK8W5MF | K32: =K31 -> 金属储物柜71英寸银色 | M32: =M31 -> 188 | N32: =N31 -> 49 | O32: =O31 -> 14 | P32: =M32*N32*O32/1000000 -> 0.128968 | R32: =R31 -> 188 | S32: =S31 -> 49 | T32: =T31 -> 14 | U32: =R32*S32*T32/1000000 -> 0.128968 | AA32: =AA31 -> 21 | AB32: =AB31 -> 247 | AC32: =AC31 -> 247 | AD32: 0 | AE32: =AH31 -> 247 | AH32: =AE32+AF32-AG32 -> 247 | AI32: pcs | AJ32: =AH32*P32 -> 31.855096 | AK32: =AJ32 -> 31.855096 | AL32: =B32-H32+1 -> 8 | AM32: =IF(AL32<=30,"30天内",IF(AL32<=90,"31-90天","91天以上")) -> 30天内 | AN32: 0 | AO32: Euro | AP32: =AK32*AN32 -> 0
A33: 202508 | B33: 45897 | C33: MIC德国仓 | D33: =D32 -> M » N2 - 1 | E33: =E32 -> YCD-EX:HUPPER TEK | F33: =F32 -> MI202508130012 | G33: =G32 -> DE2508031-G7-MIC | H33: =H32 -> 45889 | I33: =I32 -> B07BK8W5MF | K33: =K32 -> 金属储物柜71英寸银色 | M33: =M32 -> 188 | N33: =N32 -> 49 | O33: =O32 -> 14 | P33: =M33*N33*O33/1000000 -> 0.128968 | R33: =R32 -> 188 | S33: =S32 -> 49 | T33: =T32 -> 14 | U33: =R33*S33*T33/1000000 -> 0.128968 | AA33: =AA32 -> 21 | AB33: =AB32 -> 247 | AC33: =AC32 -> 247 | AD33: 0 | AE33: =AH32 -> 247 | AH33: =AE33+AF33-AG33 -> 247 | AI33: pcs | AJ33: =AH33*P33 -> 31.855096 | AK33: =AJ33 -> 31.855096 | AL33: =B33-H33+1 -> 9 | AM33: =IF(AL33<=30,"30天内",IF(AL33<=90,"31-90天","91天以上")) -> 30天内 | AN33: 0 | AO33: Euro | AP33: =AK33*AN33 -> 0
A34: 202508 | B34: 45898 | C34: MIC德国仓 | D34: =D33 -> M » N2 - 1 | E34: =E33 -> YCD-EX:HUPPER TEK | F34: =F33 -> MI202508130012 | G34: =G33 -> DE2508031-G7-MIC | H34: =H33 -> 45889 | I34: =I33 -> B07BK8W5MF | K34: =K33 -> 金属储物柜71英寸银色 | M34: =M33 -> 188 | N34: =N33 -> 49 | O34: =O33 -> 14 | P34: =M34*N34*O34/1000000 -> 0.128968 | R34: =R33 -> 188 | S34: =S33 -> 49 | T34: =T33 -> 14 | U34: =R34*S34*T34/1000000 -> 0.128968 | AA34: =AA33 -> 21 | AB34: =AB33 -> 247 | AC34: =AC33 -> 247 | AD34: 0 | AE34: =AH33 -> 247 | AH34: =AE34+AF34-AG34 -> 247 | AI34: pcs | AJ34: =AH34*P34 -> 31.855096 | AK34: =AJ34 -> 31.855096 | AL34: =B34-H34+1 -> 10 | AM34: =IF(AL34<=30,"30天内",IF(AL34<=90,"31-90天","91天以上")) -> 30天内 | AN34: 0 | AO34: Euro | AP34: =AK34*AN34 -> 0
A35: 202508 | B35: 45899 | C35: MIC德国仓 | D35: =D34 -> M » N2 - 1 | E35: =E34 -> YCD-EX:HUPPER TEK | F35: =F34 -> MI202508130012 | G35: =G34 -> DE2508031-G7-MIC | H35: =H34 -> 45889 | I35: =I34 -> B07BK8W5MF | K35: =K34 -> 金属储物柜71英寸银色 | M35: =M34 -> 188 | N35: =N34 -> 49 | O35: =O34 -> 14 | P35: =M35*N35*O35/1000000 -> 0.128968 | R35: =R34 -> 188 | S35: =S34 -> 49 | T35: =T34 -> 14 | U35: =R35*S35*T35/1000000 -> 0.128968 | AA35: =AA34 -> 21 | AB35: =AB34 -> 247 | AC35: =AC34 -> 247 | AD35: 0 | AE35: =AH34 -> 247 | AH35: =AE35+AF35-AG35 -> 247 | AI35: pcs | AJ35: =AH35*P35 -> 31.855096 | AK35: =AJ35 -> 31.855096 | AL35: =B35-H35+1 -> 11 | AM35: =IF(AL35<=30,"30天内",IF(AL35<=90,"31-90天","91天以上")) -> 30天内 | AN35: 0 | AO35: Euro | AP35: =AK35*AN35 -> 0
A36: 202508 | B36: 45900 | C36: MIC德国仓 | D36: =D35 -> M » N2 - 1 | E36: =E35 -> YCD-EX:HUPPER TEK | F36: =F35 -> MI202508130012 | G36: =G35 -> DE2508031-G7-MIC | H36: =H35 -> 45889 | I36: =I35 -> B07BK8W5MF | K36: =K35 -> 金属储物柜71英寸银色 | M36: =M35 -> 188 | N36: =N35 -> 49 | O36: =O35 -> 14 | P36: =M36*N36*O36/1000000 -> 0.128968 | R36: =R35 -> 188 | S36: =S35 -> 49 | T36: =T35 -> 14 | U36: =R36*S36*T36/1000000 -> 0.128968 | AA36: =AA35 -> 21 | AB36: =AB35 -> 247 | AC36: =AC35 -> 247 | AD36: 0 | AE36: =AH35 -> 247 | AH36: =AE36+AF36-AG36 -> 247 | AI36: pcs | AJ36: =AH36*P36 -> 31.855096 | AK36: =AJ36 -> 31.855096 | AL36: =B36-H36+1 -> 12 | AM36: =IF(AL36<=30,"30天内",IF(AL36<=90,"31-90天","91天以上")) -> 30天内 | AN36: 0 | AO36: Euro | AP36: =AK36*AN36 -> 0
A37: 202508 | B37: 45870 | C37: MIC德国仓 | D37: M » N2 - 1 | E37: YCD-EX:HUPPER TEK | F37: MI202508130012 | G37: DE2508031-G7-MIC | H37: 45889 | I37: B076THQBHX | K37: =VLOOKUP(I37,物品明细!A:B,2,0) -> 金属储物柜71英寸灰色 | M37: =VLOOKUP(I37,物品明细!A:E,5,0) -> 188 | N37: =VLOOKUP(I37,物品明细!A:F,6,0) -> 49 | O37: =VLOOKUP(I37,物品明细!A:G,7,0) -> 14 | P37: =M37*N37*O37/1000000 -> 0.128968 | R37: =VLOOKUP(I37,物品明细!A:E,5,0) -> 188 | S37: =VLOOKUP(I37,物品明细!A:F,6,0) -> 49 | T37: =VLOOKUP(I37,物品明细!A:G,7,0) -> 14 | U37: =R37*S37*T37/1000000 -> 0.128968 | AA37: 19 | AB37: 223 | AC37: 223 | AD37: 0 | AE37: 0 | AH37: =AE37+AF37-AG37 -> 0 | AI37: pcs | AJ37: =AH37*P37 -> 0 | AK37: =AJ37 -> 0 | AL37: =B37-H37+1 -> -18 | AM37: =IF(AL37<=30,"30天内",IF(AL37<=90,"31-90天","91天以上")) -> 30天内 | AN37: 0 | AO37: Euro | AP37: =AK37*AN37 -> 0
A38: 202508 | B38: 45871 | C38: MIC德国仓 | D38: =D37 -> M » N2 - 1 | E38: =E37 -> YCD-EX:HUPPER TEK | F38: =F37 -> MI202508130012 | G38: =G37 -> DE2508031-G7-MIC | H38: =H37 -> 45889 | I38: =I37 -> B076THQBHX | K38: =K37 -> 金属储物柜71英寸灰色 | M38: =M37 -> 188 | N38: =N37 -> 49 | O38: =O37 -> 14 | P38: =M38*N38*O38/1000000 -> 0.128968 | R38: =R37 -> 188 | S38: =S37 -> 49 | T38: =T37 -> 14 | U38: =R38*S38*T38/1000000 -> 0.128968 | AA38: =AA37 -> 19 | AB38: =AB37 -> 223 | AC38: =AC37 -> 223 | AD38: 0 | AE38: =AH37 -> 0 | AH38: =AE38+AF38-AG38 -> 0 | AI38: pcs | AJ38: =AH38*P38 -> 0 | AK38: =AJ38 -> 0 | AL38: =B38-H38+1 -> -17 | AM38: =IF(AL38<=30,"30天内",IF(AL38<=90,"31-90天","91天以上")) -> 30天内 | AN38: 0 | AO38: Euro | AP38: =AK38*AN38 -> 0
A39: 202508 | B39: 45872 | C39: MIC德国仓 | D39: =D38 -> M » N2 - 1 | E39: =E38 -> YCD-EX:HUPPER TEK | F39: =F38 -> MI202508130012 | G39: =G38 -> DE2508031-G7-MIC | H39: =H38 -> 45889 | I39: =I38 -> B076THQBHX | K39: =K38 -> 金属储物柜71英寸灰色 | M39: =M38 -> 188 | N39: =N38 -> 49 | O39: =O38 -> 14 | P39: =M39*N39*O39/1000000 -> 0.128968 | R39: =R38 -> 188 | S39: =S38 -> 49 | T39: =T38 -> 14 | U39: =R39*S39*T39/1000000 -> 0.128968 | AA39: =AA38 -> 19 | AB39: =AB38 -> 223 | AC39: =AC38 -> 223 | AD39: 0 | AE39: =AH38 -> 0 | AH39: =AE39+AF39-AG39 -> 0 | AI39: pcs | AJ39: =AH39*P39 -> 0 | AK39: =AJ39 -> 0 | AL39: =B39-H39+1 -> -16 | AM39: =IF(AL39<=30,"30天内",IF(AL39<=90,"31-90天","91天以上")) -> 30天内 | AN39: 0 | AO39: Euro | AP39: =AK39*AN39 -> 0
A40: 202508 | B40: 45873 | C40: MIC德国仓 | D40: =D39 -> M » N2 - 1 | E40: =E39 -> YCD-EX:HUPPER TEK | F40: =F39 -> MI202508130012 | G40: =G39 -> DE2508031-G7-MIC | H40: =H39 -> 45889 | I40: =I39 -> B076THQBHX | K40: =K39 -> 金属储物柜71英寸灰色 | M40: =M39 -> 188 | N40: =N39 -> 49 | O40: =O39 -> 14 | P40: =M40*N40*O40/1000000 -> 0.128968 | R40: =R39 -> 188 | S40: =S39 -> 49 | T40: =T39 -> 14 | U40: =R40*S40*T40/1000000 -> 0.128968 | AA40: =AA39 -> 19 | AB40: =AB39 -> 223 | AC40: =AC39 -> 223 | AD40: 0 | AE40: =AH39 -> 0 | AH40: =AE40+AF40-AG40 -> 0 | AI40: pcs | AJ40: =AH40*P40 -> 0 | AK40: =AJ40 -> 0 | AL40: =B40-H40+1 -> -15 | AM40: =IF(AL40<=30,"30天内",IF(AL40<=90,"31-90天","91天以上")) -> 30天内 | AN40: 0 | AO40: Euro | AP40: =AK40*AN40 -> 0
A41: 202508 | B41: 45874 | C41: MIC德国仓 | D41: =D40 -> M » N2 - 1 | E41: =E40 -> YCD-EX:HUPPER TEK | F41: =F40 -> MI202508130012 | G41: =G40 -> DE2508031-G7-MIC | H41: =H40 -> 45889 | I41: =I40 -> B076THQBHX | K41: =K40 -> 金属储物柜71英寸灰色 | M41: =M40 -> 188 | N41: =N40 -> 49 | O41: =O40 -> 14 | P41: =M41*N41*O41/1000000 -> 0.128968 | R41: =R40 -> 188 | S41: =S40 -> 49 | T41: =T40 -> 14 | U41: =R41*S41*T41/1000000 -> 0.128968 | AA41: =AA40 -> 19 | AB41: =AB40 -> 223 | AC41: =AC40 -> 223 | AD41: 0 | AE41: =AH40 -> 0 | AH41: =AE41+AF41-AG41 -> 0 | AI41: pcs | AJ41: =AH41*P41 -> 0 | AK41: =AJ41 -> 0 | AL41: =B41-H41+1 -> -14 | AM41: =IF(AL41<=30,"30天内",IF(AL41<=90,"31-90天","91天以上")) -> 30天内 | AN41: 0 | AO41: Euro | AP41: =AK41*AN41 -> 0
A42: 202508 | B42: 45875 | C42: MIC德国仓 | D42: =D41 -> M » N2 - 1 | E42: =E41 -> YCD-EX:HUPPER TEK | F42: =F41 -> MI202508130012 | G42: =G41 -> DE2508031-G7-MIC | H42: =H41 -> 45889 | I42: =I41 -> B076THQBHX | K42: =K41 -> 金属储物柜71英寸灰色 | M42: =M41 -> 188 | N42: =N41 -> 49 | O42: =O41 -> 14 | P42: =M42*N42*O42/1000000 -> 0.128968 | R42: =R41 -> 188 | S42: =S41 -> 49 | T42: =T41 -> 14 | U42: =R42*S42*T42/1000000 -> 0.128968 | AA42: =AA41 -> 19 | AB42: =AB41 -> 223 | AC42: =AC41 -> 223 | AD42: 0 | AE42: =AH41 -> 0 | AH42: =AE42+AF42-AG42 -> 0 | AI42: pcs | AJ42: =AH42*P42 -> 0 | AK42: =AJ42 -> 0 | AL42: =B42-H42+1 -> -13 | AM42: =IF(AL42<=30,"30天内",IF(AL42<=90,"31-90天","91天以上")) -> 30天内 | AN42: 0 | AO42: Euro | AP42: =AK42*AN42 -> 0
A43: 202508 | B43: 45876 | C43: MIC德国仓 | D43: =D42 -> M » N2 - 1 | E43: =E42 -> YCD-EX:HUPPER TEK | F43: =F42 -> MI202508130012 | G43: =G42 -> DE2508031-G7-MIC | H43: =H42 -> 45889 | I43: =I42 -> B076THQBHX | K43: =K42 -> 金属储物柜71英寸灰色 | M43: =M42 -> 188 | N43: =N42 -> 49 | O43: =O42 -> 14 | P43: =M43*N43*O43/1000000 -> 0.128968 | R43: =R42 -> 188 | S43: =S42 -> 49 | T43: =T42 -> 14 | U43: =R43*S43*T43/1000000 -> 0.128968 | AA43: =AA42 -> 19 | AB43: =AB42 -> 223 | AC43: =AC42 -> 223 | AD43: 0 | AE43: =AH42 -> 0 | AH43: =AE43+AF43-AG43 -> 0 | AI43: pcs | AJ43: =AH43*P43 -> 0 | AK43: =AJ43 -> 0 | AL43: =B43-H43+1 -> -12 | AM43: =IF(AL43<=30,"30天内",IF(AL43<=90,"31-90天","91天以上")) -> 30天内 | AN43: 0 | AO43: Euro | AP43: =AK43*AN43 -> 0
A44: 202508 | B44: 45877 | C44: MIC德国仓 | D44: =D43 -> M » N2 - 1 | E44: =E43 -> YCD-EX:HUPPER TEK | F44: =F43 -> MI202508130012 | G44: =G43 -> DE2508031-G7-MIC | H44: =H43 -> 45889 | I44: =I43 -> B076THQBHX | K44: =K43 -> 金属储物柜71英寸灰色 | M44: =M43 -> 188 | N44: =N43 -> 49 | O44: =O43 -> 14 | P44: =M44*N44*O44/1000000 -> 0.128968 | R44: =R43 -> 188 | S44: =S43 -> 49 | T44: =T43 -> 14 | U44: =R44*S44*T44/1000000 -> 0.128968 | AA44: =AA43 -> 19 | AB44: =AB43 -> 223 | AC44: =AC43 -> 223 | AD44: 0 | AE44: =AH43 -> 0 | AH44: =AE44+AF44-AG44 -> 0 | AI44: pcs | AJ44: =AH44*P44 -> 0 | AK44: =AJ44 -> 0 | AL44: =B44-H44+1 -> -11 | AM44: =IF(AL44<=30,"30天内",IF(AL44<=90,"31-90天","91天以上")) -> 30天内 | AN44: 0 | AO44: Euro | AP44: =AK44*AN44 -> 0
A45: 202508 | B45: 45878 | C45: MIC德国仓 | D45: =D44 -> M » N2 - 1 | E45: =E44 -> YCD-EX:HUPPER TEK | F45: =F44 -> MI202508130012 | G45: =G44 -> DE2508031-G7-MIC | H45: =H44 -> 45889 | I45: =I44 -> B076THQBHX | K45: =K44 -> 金属储物柜71英寸灰色 | M45: =M44 -> 188 | N45: =N44 -> 49 | O45: =O44 -> 14 | P45: =M45*N45*O45/1000000 -> 0.128968 | R45: =R44 -> 188 | S45: =S44 -> 49 | T45: =T44 -> 14 | U45: =R45*S45*T45/1000000 -> 0.128968 | AA45: =AA44 -> 19 | AB45: =AB44 -> 223 | AC45: =AC44 -> 223 | AD45: 0 | AE45: =AH44 -> 0 | AH45: =AE45+AF45-AG45 -> 0 | AI45: pcs | AJ45: =AH45*P45 -> 0 | AK45: =AJ45 -> 0 | AL45: =B45-H45+1 -> -10 | AM45: =IF(AL45<=30,"30天内",IF(AL45<=90,"31-90天","91天以上")) -> 30天内 | AN45: 0 | AO45: Euro | AP45: =AK45*AN45 -> 0
A46: 202508 | B46: 45879 | C46: MIC德国仓 | D46: =D45 -> M » N2 - 1 | E46: =E45 -> YCD-EX:HUPPER TEK | F46: =F45 -> MI202508130012 | G46: =G45 -> DE2508031-G7-MIC | H46: =H45 -> 45889 | I46: =I45 -> B076THQBHX | K46: =K45 -> 金属储物柜71英寸灰色 | M46: =M45 -> 188 | N46: =N45 -> 49 | O46: =O45 -> 14 | P46: =M46*N46*O46/1000000 -> 0.128968 | R46: =R45 -> 188 | S46: =S45 -> 49 | T46: =T45 -> 14 | U46: =R46*S46*T46/1000000 -> 0.128968 | AA46: =AA45 -> 19 | AB46: =AB45 -> 223 | AC46: =AC45 -> 223 | AD46: 0 | AE46: =AH45 -> 0 | AH46: =AE46+AF46-AG46 -> 0 | AI46: pcs | AJ46: =AH46*P46 -> 0 | AK46: =AJ46 -> 0 | AL46: =B46-H46+1 -> -9 | AM46: =IF(AL46<=30,"30天内",IF(AL46<=90,"31-90天","91天以上")) -> 30天内 | AN46: 0 | AO46: Euro | AP46: =AK46*AN46 -> 0
A47: 202508 | B47: 45880 | C47: MIC德国仓 | D47: =D46 -> M » N2 - 1 | E47: =E46 -> YCD-EX:HUPPER TEK | F47: =F46 -> MI202508130012 | G47: =G46 -> DE2508031-G7-MIC | H47: =H46 -> 45889 | I47: =I46 -> B076THQBHX | K47: =K46 -> 金属储物柜71英寸灰色 | M47: =M46 -> 188 | N47: =N46 -> 49 | O47: =O46 -> 14 | P47: =M47*N47*O47/1000000 -> 0.128968 | R47: =R46 -> 188 | S47: =S46 -> 49 | T47: =T46 -> 14 | U47: =R47*S47*T47/1000000 -> 0.128968 | AA47: =AA46 -> 19 | AB47: =AB46 -> 223 | AC47: =AC46 -> 223 | AD47: 0 | AE47: =AH46 -> 0 | AH47: =AE47+AF47-AG47 -> 0 | AI47: pcs | AJ47: =AH47*P47 -> 0 | AK47: =AJ47 -> 0 | AL47: =B47-H47+1 -> -8 | AM47: =IF(AL47<=30,"30天内",IF(AL47<=90,"31-90天","91天以上")) -> 30天内 | AN47: 0 | AO47: Euro | AP47: =AK47*AN47 -> 0
A48: 202508 | B48: 45881 | C48: MIC德国仓 | D48: =D47 -> M » N2 - 1 | E48: =E47 -> YCD-EX:HUPPER TEK | F48: =F47 -> MI202508130012 | G48: =G47 -> DE2508031-G7-MIC | H48: =H47 -> 45889 | I48: =I47 -> B076THQBHX | K48: =K47 -> 金属储物柜71英寸灰色 | M48: =M47 -> 188 | N48: =N47 -> 49 | O48: =O47 -> 14 | P48: =M48*N48*O48/1000000 -> 0.128968 | R48: =R47 -> 188 | S48: =S47 -> 49 | T48: =T47 -> 14 | U48: =R48*S48*T48/1000000 -> 0.128968 | AA48: =AA47 -> 19 | AB48: =AB47 -> 223 | AC48: =AC47 -> 223 | AD48: 0 | AE48: =AH47 -> 0 | AH48: =AE48+AF48-AG48 -> 0 | AI48: pcs | AJ48: =AH48*P48 -> 0 | AK48: =AJ48 -> 0 | AL48: =B48-H48+1 -> -7 | AM48: =IF(AL48<=30,"30天内",IF(AL48<=90,"31-90天","91天以上")) -> 30天内 | AN48: 0 | AO48: Euro | AP48: =AK48*AN48 -> 0
A49: 202508 | B49: 45882 | C49: MIC德国仓 | D49: =D48 -> M » N2 - 1 | E49: =E48 -> YCD-EX:HUPPER TEK | F49: =F48 -> MI202508130012 | G49: =G48 -> DE2508031-G7-MIC | H49: =H48 -> 45889 | I49: =I48 -> B076THQBHX | K49: =K48 -> 金属储物柜71英寸灰色 | M49: =M48 -> 188 | N49: =N48 -> 49 | O49: =O48 -> 14 | P49: =M49*N49*O49/1000000 -> 0.128968 | R49: =R48 -> 188 | S49: =S48 -> 49 | T49: =T48 -> 14 | U49: =R49*S49*T49/1000000 -> 0.128968 | AA49: =AA48 -> 19 | AB49: =AB48 -> 223 | AC49: =AC48 -> 223 | AD49: 0 | AE49: =AH48 -> 0 | AH49: =AE49+AF49-AG49 -> 0 | AI49: pcs | AJ49: =AH49*P49 -> 0 | AK49: =AJ49 -> 0 | AL49: =B49-H49+1 -> -6 | AM49: =IF(AL49<=30,"30天内",IF(AL49<=90,"31-90天","91天以上")) -> 30天内 | AN49: 0 | AO49: Euro | AP49: =AK49*AN49 -> 0
... A55: 202508 | B55: 45888 | C55: MIC德国仓 | D55: =D54 -> M » N2 - 1 | E55: =E54 -> YCD-EX:HUPPER TEK | F55: =F54 -> MI202508130012 | G55: =G54 -> DE2508031-G7-MIC | H55: =H54 -> 45889 | I55: =I54 -> B076THQBHX | K55: =K54 -> 金属储物柜71英寸灰色 | M55: =M54 -> 188 | N55: =N54 -> 49 | O55: =O54 -> 14 | P55: =M55*N55*O55/1000000 -> 0.128968 | R55: =R54 -> 188 | S55: =S54 -> 49 | T55: =T54 -> 14 | U55: =R55*S55*T55/1000000 -> 0.128968 | AA55: =AA54 -> 19 | AB55: =AB54 -> 223 | AC55: =AC54 -> 223 | AD55: 0 | AE55: =AH54 -> 0 | AH55: =AE55+AF55-AG55 -> 0 | AI55: pcs | AJ55: =AH55*P55 -> 0 | AK55: =AJ55 -> 0 | AL55: =B55-H55+1 -> 0 | AM55: =IF(AL55<=30,"30天内",IF(AL55<=90,"31-90天","91天以上")) -> 30天内 | AN55: 0 | AO55: Euro | AP55: =AK55*AN55 -> 0
A56: 202508 | B56: 45889 | C56: MIC德国仓 | D56: =D55 -> M » N2 - 1 | E56: =E55 -> YCD-EX:HUPPER TEK | F56: =F55 -> MI202508130012 | G56: =G55 -> DE2508031-G7-MIC | H56: =H55 -> 45889 | I56: =I55 -> B076THQBHX | K56: =K55 -> 金属储物柜71英寸灰色 | M56: =M55 -> 188 | N56: =N55 -> 49 | O56: =O55 -> 14 | P56: =M56*N56*O56/1000000 -> 0.128968 | R56: =R55 -> 188 | S56: =S55 -> 49 | T56: =T55 -> 14 | U56: =R56*S56*T56/1000000 -> 0.128968 | AA56: =AA55 -> 19 | AB56: =AB55 -> 223 | AC56: =AC55 -> 223 | AD56: 0 | AE56: =AH55 -> 0 | AF56: 223 | AH56: =AE56+AF56-AG56 -> 223 | AI56: pcs | AJ56: =AH56*P56 -> 28.759864 | AK56: =AJ56 -> 28.759864 | AL56: =B56-H56+1 -> 1 | AM56: =IF(AL56<=30,"30天内",IF(AL56<=90,"31-90天","91天以上")) -> 30天内 | AN56: 0 | AO56: Euro | AP56: =AK56*AN56 -> 0
A57: 202508 | B57: 45890 | C57: MIC德国仓 | D57: =D56 -> M » N2 - 1 | E57: =E56 -> YCD-EX:HUPPER TEK | F57: =F56 -> MI202508130012 | G57: =G56 -> DE2508031-G7-MIC | H57: =H56 -> 45889 | I57: =I56 -> B076THQBHX | K57: =K56 -> 金属储物柜71英寸灰色 | M57: =M56 -> 188 | N57: =N56 -> 49 | O57: =O56 -> 14 | P57: =M57*N57*O57/1000000 -> 0.128968 | R57: =R56 -> 188 | S57: =S56 -> 49 | T57: =T56 -> 14 | U57: =R57*S57*T57/1000000 -> 0.128968 | AA57: =AA56 -> 19 | AB57: =AB56 -> 223 | AC57: =AC56 -> 223 | AD57: 0 | AE57: =AH56 -> 223 | AH57: =AE57+AF57-AG57 -> 223 | AI57: pcs | AJ57: =AH57*P57 -> 28.759864 | AK57: =AJ57 -> 28.759864 | AL57: =B57-H57+1 -> 2 | AM57: =IF(AL57<=30,"30天内",IF(AL57<=90,"31-90天","91天以上")) -> 30天内 | AN57: 0 | AO57: Euro | AP57: =AK57*AN57 -> 0
A58: 202508 | B58: 45891 | C58: MIC德国仓 | D58: =D57 -> M » N2 - 1 | E58: =E57 -> YCD-EX:HUPPER TEK | F58: =F57 -> MI202508130012 | G58: =G57 -> DE2508031-G7-MIC | H58: =H57 -> 45889 | I58: =I57 -> B076THQBHX | K58: =K57 -> 金属储物柜71英寸灰色 | M58: =M57 -> 188 | N58: =N57 -> 49 | O58: =O57 -> 14 | P58: =M58*N58*O58/1000000 -> 0.128968 | R58: =R57 -> 188 | S58: =S57 -> 49 | T58: =T57 -> 14 | U58: =R58*S58*T58/1000000 -> 0.128968 | AA58: =AA57 -> 19 | AB58: =AB57 -> 223 | AC58: =AC57 -> 223 | AD58: 0 | AE58: =AH57 -> 223 | AH58: =AE58+AF58-AG58 -> 223 | AI58: pcs | AJ58: =AH58*P58 -> 28.759864 | AK58: =AJ58 -> 28.759864 | AL58: =B58-H58+1 -> 3 | AM58: =IF(AL58<=30,"30天内",IF(AL58<=90,"31-90天","91天以上")) -> 30天内 | AN58: 0 | AO58: Euro | AP58: =AK58*AN58 -> 0
A59: 202508 | B59: 45892 | C59: MIC德国仓 | D59: =D58 -> M » N2 - 1 | E59: =E58 -> YCD-EX:HUPPER TEK | F59: =F58 -> MI202508130012 | G59: =G58 -> DE2508031-G7-MIC | H59: =H58 -> 45889 | I59: =I58 -> B076THQBHX | K59: =K58 -> 金属储物柜71英寸灰色 | M59: =M58 -> 188 | N59: =N58 -> 49 | O59: =O58 -> 14 | P59: =M59*N59*O59/1000000 -> 0.128968 | R59: =R58 -> 188 | S59: =S58 -> 49 | T59: =T58 -> 14 | U59: =R59*S59*T59/1000000 -> 0.128968 | AA59: =AA58 -> 19 | AB59: =AB58 -> 223 | AC59: =AC58 -> 223 | AD59: 0 | AE59: =AH58 -> 223 | AH59: =AE59+AF59-AG59 -> 223 | AI59: pcs | AJ59: =AH59*P59 -> 28.759864 | AK59: =AJ59 -> 28.759864 | AL59: =B59-H59+1 -> 4 | AM59: =IF(AL59<=30,"30天内",IF(AL59<=90,"31-90天","91天以上")) -> 30天内 | AN59: 0 | AO59: Euro | AP59: =AK59*AN59 -> 0
A60: 202508 | B60: 45893 | C60: MIC德国仓 | D60: =D59 -> M » N2 - 1 | E60: =E59 -> YCD-EX:HUPPER TEK | F60: =F59 -> MI202508130012 | G60: =G59 -> DE2508031-G7-MIC | H60: =H59 -> 45889 | I60: =I59 -> B076THQBHX | K60: =K59 -> 金属储物柜71英寸灰色 | M60: =M59 -> 188 | N60: =N59 -> 49 | O60: =O59 -> 14 | P60: =M60*N60*O60/1000000 -> 0.128968 | R60: =R59 -> 188 | S60: =S59 -> 49 | T60: =T59 -> 14 | U60: =R60*S60*T60/1000000 -> 0.128968 | AA60: =AA59 -> 19 | AB60: =AB59 -> 223 | AC60: =AC59 -> 223 | AD60: 0 | AE60: =AH59 -> 223 | AH60: =AE60+AF60-AG60 -> 223 | AI60: pcs | AJ60: =AH60*P60 -> 28.759864 | AK60: =AJ60 -> 28.759864 | AL60: =B60-H60+1 -> 5 | AM60: =IF(AL60<=30,"30天内",IF(AL60<=90,"31-90天","91天以上")) -> 30天内 | AN60: 0 | AO60: Euro | AP60: =AK60*AN60 -> 0
A61: 202508 | B61: 45894 | C61: MIC德国仓 | D61: =D60 -> M » N2 - 1 | E61: =E60 -> YCD-EX:HUPPER TEK | F61: =F60 -> MI202508130012 | G61: =G60 -> DE2508031-G7-MIC | H61: =H60 -> 45889 | I61: =I60 -> B076THQBHX | K61: =K60 -> 金属储物柜71英寸灰色 | M61: =M60 -> 188 | N61: =N60 -> 49 | O61: =O60 -> 14 | P61: =M61*N61*O61/1000000 -> 0.128968 | R61: =R60 -> 188 | S61: =S60 -> 49 | T61: =T60 -> 14 | U61: =R61*S61*T61/1000000 -> 0.128968 | AA61: =AA60 -> 19 | AB61: =AB60 -> 223 | AC61: =AC60 -> 223 | AD61: 0 | AE61: =AH60 -> 223 | AH61: =AE61+AF61-AG61 -> 223 | AI61: pcs | AJ61: =AH61*P61 -> 28.759864 | AK61: =AJ61 -> 28.759864 | AL61: =B61-H61+1 -> 6 | AM61: =IF(AL61<=30,"30天内",IF(AL61<=90,"31-90天","91天以上")) -> 30天内 | AN61: 0 | AO61: Euro | AP61: =AK61*AN61 -> 0
A62: 202508 | B62: 45895 | C62: MIC德国仓 | D62: =D61 -> M » N2 - 1 | E62: =E61 -> YCD-EX:HUPPER TEK | F62: =F61 -> MI202508130012 | G62: =G61 -> DE2508031-G7-MIC | H62: =H61 -> 45889 | I62: =I61 -> B076THQBHX | K62: =K61 -> 金属储物柜71英寸灰色 | M62: =M61 -> 188 | N62: =N61 -> 49 | O62: =O61 -> 14 | P62: =M62*N62*O62/1000000 -> 0.128968 | R62: =R61 -> 188 | S62: =S61 -> 49 | T62: =T61 -> 14 | U62: =R62*S62*T62/1000000 -> 0.128968 | AA62: =AA61 -> 19 | AB62: =AB61 -> 223 | AC62: =AC61 -> 223 | AD62: 0 | AE62: =AH61 -> 223 | AH62: =AE62+AF62-AG62 -> 223 | AI62: pcs | AJ62: =AH62*P62 -> 28.759864 | AK62: =AJ62 -> 28.759864 | AL62: =B62-H62+1 -> 7 | AM62: =IF(AL62<=30,"30天内",IF(AL62<=90,"31-90天","91天以上")) -> 30天内 | AN62: 0 | AO62: Euro | AP62: =AK62*AN62 -> 0
A63: 202508 | B63: 45896 | C63: MIC德国仓 | D63: =D62 -> M » N2 - 1 | E63: =E62 -> YCD-EX:HUPPER TEK | F63: =F62 -> MI202508130012 | G63: =G62 -> DE2508031-G7-MIC | H63: =H62 -> 45889 | I63: =I62 -> B076THQBHX | K63: =K62 -> 金属储物柜71英寸灰色 | M63: =M62 -> 188 | N63: =N62 -> 49 | O63: =O62 -> 14 | P63: =M63*N63*O63/1000000 -> 0.128968 | R63: =R62 -> 188 | S63: =S62 -> 49 | T63: =T62 -> 14 | U63: =R63*S63*T63/1000000 -> 0.128968 | AA63: =AA62 -> 19 | AB63: =AB62 -> 223 | AC63: =AC62 -> 223 | AD63: 0 | AE63: =AH62 -> 223 | AH63: =AE63+AF63-AG63 -> 223 | AI63: pcs | AJ63: =AH63*P63 -> 28.759864 | AK63: =AJ63 -> 28.759864 | AL63: =B63-H63+1 -> 8 | AM63: =IF(AL63<=30,"30天内",IF(AL63<=90,"31-90天","91天以上")) -> 30天内 | AN63: 0 | AO63: Euro | AP63: =AK63*AN63 -> 0
A64: 202508 | B64: 45897 | C64: MIC德国仓 | D64: =D63 -> M » N2 - 1 | E64: =E63 -> YCD-EX:HUPPER TEK | F64: =F63 -> MI202508130012 | G64: =G63 -> DE2508031-G7-MIC | H64: =H63 -> 45889 | I64: =I63 -> B076THQBHX | K64: =K63 -> 金属储物柜71英寸灰色 | M64: =M63 -> 188 | N64: =N63 -> 49 | O64: =O63 -> 14 | P64: =M64*N64*O64/1000000 -> 0.128968 | R64: =R63 -> 188 | S64: =S63 -> 49 | T64: =T63 -> 14 | U64: =R64*S64*T64/1000000 -> 0.128968 | AA64: =AA63 -> 19 | AB64: =AB63 -> 223 | AC64: =AC63 -> 223 | AD64: 0 | AE64: =AH63 -> 223 | AH64: =AE64+AF64-AG64 -> 223 | AI64: pcs | AJ64: =AH64*P64 -> 28.759864 | AK64: =AJ64 -> 28.759864 | AL64: =B64-H64+1 -> 9 | AM64: =IF(AL64<=30,"30天内",IF(AL64<=90,"31-90天","91天以上")) -> 30天内 | AN64: 0 | AO64: Euro | AP64: =AK64*AN64 -> 0
A65: 202508 | B65: 45898 | C65: MIC德国仓 | D65: =D64 -> M » N2 - 1 | E65: =E64 -> YCD-EX:HUPPER TEK | F65: =F64 -> MI202508130012 | G65: =G64 -> DE2508031-G7-MIC | H65: =H64 -> 45889 | I65: =I64 -> B076THQBHX | K65: =K64 -> 金属储物柜71英寸灰色 | M65: =M64 -> 188 | N65: =N64 -> 49 | O65: =O64 -> 14 | P65: =M65*N65*O65/1000000 -> 0.128968 | R65: =R64 -> 188 | S65: =S64 -> 49 | T65: =T64 -> 14 | U65: =R65*S65*T65/1000000 -> 0.128968 | AA65: =AA64 -> 19 | AB65: =AB64 -> 223 | AC65: =AC64 -> 223 | AD65: 0 | AE65: =AH64 -> 223 | AH65: =AE65+AF65-AG65 -> 223 | AI65: pcs | AJ65: =AH65*P65 -> 28.759864 | AK65: =AJ65 -> 28.759864 | AL65: =B65-H65+1 -> 10 | AM65: =IF(AL65<=30,"30天内",IF(AL65<=90,"31-90天","91天以上")) -> 30天内 | AN65: 0 | AO65: Euro | AP65: =AK65*AN65 -> 0
A66: 202508 | B66: 45899 | C66: MIC德国仓 | D66: =D65 -> M » N2 - 1 | E66: =E65 -> YCD-EX:HUPPER TEK | F66: =F65 -> MI202508130012 | G66: =G65 -> DE2508031-G7-MIC | H66: =H65 -> 45889 | I66: =I65 -> B076THQBHX | K66: =K65 -> 金属储物柜71英寸灰色 | M66: =M65 -> 188 | N66: =N65 -> 49 | O66: =O65 -> 14 | P66: =M66*N66*O66/1000000 -> 0.128968 | R66: =R65 -> 188 | S66: =S65 -> 49 | T66: =T65 -> 14 | U66: =R66*S66*T66/1000000 -> 0.128968 | AA66: =AA65 -> 19 | AB66: =AB65 -> 223 | AC66: =AC65 -> 223 | AD66: 0 | AE66: =AH65 -> 223 | AH66: =AE66+AF66-AG66 -> 223 | AI66: pcs | AJ66: =AH66*P66 -> 28.759864 | AK66: =AJ66 -> 28.759864 | AL66: =B66-H66+1 -> 11 | AM66: =IF(AL66<=30,"30天内",IF(AL66<=90,"31-90天","91天以上")) -> 30天内 | AN66: 0 | AO66: Euro | AP66: =AK66*AN66 -> 0
A67: 202508 | B67: 45900 | C67: MIC德国仓 | D67: =D66 -> M » N2 - 1 | E67: =E66 -> YCD-EX:HUPPER TEK | F67: =F66 -> MI202508130012 | G67: =G66 -> DE2508031-G7-MIC | H67: =H66 -> 45889 | I67: =I66 -> B076THQBHX | K67: =K66 -> 金属储物柜71英寸灰色 | M67: =M66 -> 188 | N67: =N66 -> 49 | O67: =O66 -> 14 | P67: =M67*N67*O67/1000000 -> 0.128968 | R67: =R66 -> 188 | S67: =S66 -> 49 | T67: =T66 -> 14 | U67: =R67*S67*T67/1000000 -> 0.128968 | AA67: =AA66 -> 19 | AB67: =AB66 -> 223 | AC67: =AC66 -> 223 | AD67: 0 | AE67: =AH66 -> 223 | AH67: =AE67+AF67-AG67 -> 223 | AI67: pcs | AJ67: =AH67*P67 -> 28.759864 | AK67: =AJ67 -> 28.759864 | AL67: =B67-H67+1 -> 12 | AM67: =IF(AL67<=30,"30天内",IF(AL67<=90,"31-90天","91天以上")) -> 30天内 | AN67: 0 | AO67: Euro | AP67: =AK67*AN67 -> 0
A68: 202508 | B68: 45870 | C68: MIC德国仓 | D68: M » N2 - 1 | E68: YCD-EX:HUPPER TEK | F68: MI202508130012 | G68: DE2508031-G7-MIC | H68: 45889 | I68: B07Q3SQT6C | K68: =VLOOKUP(I68,物品明细!A:B,2,0) -> 金属储物柜71英寸高 | M68: =VLOOKUP(I68,物品明细!A:E,5,0) -> 188 | N68: =VLOOKUP(I68,物品明细!A:F,6,0) -> 49 | O68: =VLOOKUP(I68,物品明细!A:G,7,0) -> 14 | P68: =M68*N68*O68/1000000 -> 0.128968 | R68: =VLOOKUP(I68,物品明细!A:E,5,0) -> 188 | S68: =VLOOKUP(I68,物品明细!A:F,6,0) -> 49 | T68: =VLOOKUP(I68,物品明细!A:G,7,0) -> 14 | U68: =R68*S68*T68/1000000 -> 0.128968 | AA68: 13 | AB68: 151 | AC68: 151 | AD68: 0 | AE68: 0 | AH68: =AE68+AF68-AG68 -> 0 | AI68: pcs | AJ68: =AH68*P68 -> 0 | AK68: =AJ68 -> 0 | AL68: =B68-H68+1 -> -18 | AM68: =IF(AL68<=30,"30天内",IF(AL68<=90,"31-90天","91天以上")) -> 30天内 | AN68: 0 | AO68: Euro | AP68: =AK68*AN68 -> 0
A69: 202508 | B69: 45871 | C69: MIC德国仓 | D69: =D68 -> M » N2 - 1 | E69: =E68 -> YCD-EX:HUPPER TEK | F69: =F68 -> MI202508130012 | G69: =G68 -> DE2508031-G7-MIC | H69: =H68 -> 45889 | I69: =I68 -> B07Q3SQT6C | K69: =K68 -> 金属储物柜71英寸高 | M69: =M68 -> 188 | N69: =N68 -> 49 | O69: =O68 -> 14 | P69: =M69*N69*O69/1000000 -> 0.128968 | R69: =R68 -> 188 | S69: =S68 -> 49 | T69: =T68 -> 14 | U69: =R69*S69*T69/1000000 -> 0.128968 | AA69: =AA68 -> 13 | AB69: =AB68 -> 151 | AC69: =AC68 -> 151 | AD69: 0 | AE69: =AH68 -> 0 | AH69: =AE69+AF69-AG69 -> 0 | AI69: pcs | AJ69: =AH69*P69 -> 0 | AK69: =AJ69 -> 0 | AL69: =B69-H69+1 -> -17 | AM69: =IF(AL69<=30,"30天内",IF(AL69<=90,"31-90天","91天以上")) -> 30天内 | AN69: 0 | AO69: Euro | AP69: =AK69*AN69 -> 0
A70: 202508 | B70: 45872 | C70: MIC德国仓 | D70: =D69 -> M » N2 - 1 | E70: =E69 -> YCD-EX:HUPPER TEK | F70: =F69 -> MI202508130012 | G70: =G69 -> DE2508031-G7-MIC | H70: =H69 -> 45889 | I70: =I69 -> B07Q3SQT6C | K70: =K69 -> 金属储物柜71英寸高 | M70: =M69 -> 188 | N70: =N69 -> 49 | O70: =O69 -> 14 | P70: =M70*N70*O70/1000000 -> 0.128968 | R70: =R69 -> 188 | S70: =S69 -> 49 | T70: =T69 -> 14 | U70: =R70*S70*T70/1000000 -> 0.128968 | AA70: =AA69 -> 13 | AB70: =AB69 -> 151 | AC70: =AC69 -> 151 | AD70: 0 | AE70: =AH69 -> 0 | AH70: =AE70+AF70-AG70 -> 0 | AI70: pcs | AJ70: =AH70*P70 -> 0 | AK70: =AJ70 -> 0 | AL70: =B70-H70+1 -> -16 | AM70: =IF(AL70<=30,"30天内",IF(AL70<=90,"31-90天","91天以上")) -> 30天内 | AN70: 0 | AO70: Euro | AP70: =AK70*AN70 -> 0
A71: 202508 | B71: 45873 | C71: MIC德国仓 | D71: =D70 -> M » N2 - 1 | E71: =E70 -> YCD-EX:HUPPER TEK | F71: =F70 -> MI202508130012 | G71: =G70 -> DE2508031-G7-MIC | H71: =H70 -> 45889 | I71: =I70 -> B07Q3SQT6C | K71: =K70 -> 金属储物柜71英寸高 | M71: =M70 -> 188 | N71: =N70 -> 49 | O71: =O70 -> 14 | P71: =M71*N71*O71/1000000 -> 0.128968 | R71: =R70 -> 188 | S71: =S70 -> 49 | T71: =T70 -> 14 | U71: =R71*S71*T71/1000000 -> 0.128968 | AA71: =AA70 -> 13 | AB71: =AB70 -> 151 | AC71: =AC70 -> 151 | AD71: 0 | AE71: =AH70 -> 0 | AH71: =AE71+AF71-AG71 -> 0 | AI71: pcs | AJ71: =AH71*P71 -> 0 | AK71: =AJ71 -> 0 | AL71: =B71-H71+1 -> -15 | AM71: =IF(AL71<=30,"30天内",IF(AL71<=90,"31-90天","91天以上")) -> 30天内 | AN71: 0 | AO71: Euro | AP71: =AK71*AN71 -> 0
A72: 202508 | B72: 45874 | C72: MIC德国仓 | D72: =D71 -> M » N2 - 1 | E72: =E71 -> YCD-EX:HUPPER TEK | F72: =F71 -> MI202508130012 | G72: =G71 -> DE2508031-G7-MIC | H72: =H71 -> 45889 | I72: =I71 -> B07Q3SQT6C | K72: =K71 -> 金属储物柜71英寸高 | M72: =M71 -> 188 | N72: =N71 -> 49 | O72: =O71 -> 14 | P72: =M72*N72*O72/1000000 -> 0.128968 | R72: =R71 -> 188 | S72: =S71 -> 49 | T72: =T71 -> 14 | U72: =R72*S72*T72/1000000 -> 0.128968 | AA72: =AA71 -> 13 | AB72: =AB71 -> 151 | AC72: =AC71 -> 151 | AD72: 0 | AE72: =AH71 -> 0 | AH72: =AE72+AF72-AG72 -> 0 | AI72: pcs | AJ72: =AH72*P72 -> 0 | AK72: =AJ72 -> 0 | AL72: =B72-H72+1 -> -14 | AM72: =IF(AL72<=30,"30天内",IF(AL72<=90,"31-90天","91天以上")) -> 30天内 | AN72: 0 | AO72: Euro | AP72: =AK72*AN72 -> 0
A73: 202508 | B73: 45875 | C73: MIC德国仓 | D73: =D72 -> M » N2 - 1 | E73: =E72 -> YCD-EX:HUPPER TEK | F73: =F72 -> MI202508130012 | G73: =G72 -> DE2508031-G7-MIC | H73: =H72 -> 45889 | I73: =I72 -> B07Q3SQT6C | K73: =K72 -> 金属储物柜71英寸高 | M73: =M72 -> 188 | N73: =N72 -> 49 | O73: =O72 -> 14 | P73: =M73*N73*O73/1000000 -> 0.128968 | R73: =R72 -> 188 | S73: =S72 -> 49 | T73: =T72 -> 14 | U73: =R73*S73*T73/1000000 -> 0.128968 | AA73: =AA72 -> 13 | AB73: =AB72 -> 151 | AC73: =AC72 -> 151 | AD73: 0 | AE73: =AH72 -> 0 | AH73: =AE73+AF73-AG73 -> 0 | AI73: pcs | AJ73: =AH73*P73 -> 0 | AK73: =AJ73 -> 0 | AL73: =B73-H73+1 -> -13 | AM73: =IF(AL73<=30,"30天内",IF(AL73<=90,"31-90天","91天以上")) -> 30天内 | AN73: 0 | AO73: Euro | AP73: =AK73*AN73 -> 0
A74: 202508 | B74: 45876 | C74: MIC德国仓 | D74: =D73 -> M » N2 - 1 | E74: =E73 -> YCD-EX:HUPPER TEK | F74: =F73 -> MI202508130012 | G74: =G73 -> DE2508031-G7-MIC | H74: =H73 -> 45889 | I74: =I73 -> B07Q3SQT6C | K74: =K73 -> 金属储物柜71英寸高 | M74: =M73 -> 188 | N74: =N73 -> 49 | O74: =O73 -> 14 | P74: =M74*N74*O74/1000000 -> 0.128968 | R74: =R73 -> 188 | S74: =S73 -> 49 | T74: =T73 -> 14 | U74: =R74*S74*T74/1000000 -> 0.128968 | AA74: =AA73 -> 13 | AB74: =AB73 -> 151 | AC74: =AC73 -> 151 | AD74: 0 | AE74: =AH73 -> 0 | AH74: =AE74+AF74-AG74 -> 0 | AI74: pcs | AJ74: =AH74*P74 -> 0 | AK74: =AJ74 -> 0 | AL74: =B74-H74+1 -> -12 | AM74: =IF(AL74<=30,"30天内",IF(AL74<=90,"31-90天","91天以上")) -> 30天内 | AN74: 0 | AO74: Euro | AP74: =AK74*AN74 -> 0
A75: 202508 | B75: 45877 | C75: MIC德国仓 | D75: =D74 -> M » N2 - 1 | E75: =E74 -> YCD-EX:HUPPER TEK | F75: =F74 -> MI202508130012 | G75: =G74 -> DE2508031-G7-MIC | H75: =H74 -> 45889 | I75: =I74 -> B07Q3SQT6C | K75: =K74 -> 金属储物柜71英寸高 | M75: =M74 -> 188 | N75: =N74 -> 49 | O75: =O74 -> 14 | P75: =M75*N75*O75/1000000 -> 0.128968 | R75: =R74 -> 188 | S75: =S74 -> 49 | T75: =T74 -> 14 | U75: =R75*S75*T75/1000000 -> 0.128968 | AA75: =AA74 -> 13 | AB75: =AB74 -> 151 | AC75: =AC74 -> 151 | AD75: 0 | AE75: =AH74 -> 0 | AH75: =AE75+AF75-AG75 -> 0 | AI75: pcs | AJ75: =AH75*P75 -> 0 | AK75: =AJ75 -> 0 | AL75: =B75-H75+1 -> -11 | AM75: =IF(AL75<=30,"30天内",IF(AL75<=90,"31-90天","91天以上")) -> 30天内 | AN75: 0 | AO75: Euro | AP75: =AK75*AN75 -> 0
A76: 202508 | B76: 45878 | C76: MIC德国仓 | D76: =D75 -> M » N2 - 1 | E76: =E75 -> YCD-EX:HUPPER TEK | F76: =F75 -> MI202508130012 | G76: =G75 -> DE2508031-G7-MIC | H76: =H75 -> 45889 | I76: =I75 -> B07Q3SQT6C | K76: =K75 -> 金属储物柜71英寸高 | M76: =M75 -> 188 | N76: =N75 -> 49 | O76: =O75 -> 14 | P76: =M76*N76*O76/1000000 -> 0.128968 | R76: =R75 -> 188 | S76: =S75 -> 49 | T76: =T75 -> 14 | U76: =R76*S76*T76/1000000 -> 0.128968 | AA76: =AA75 -> 13 | AB76: =AB75 -> 151 | AC76: =AC75 -> 151 | AD76: 0 | AE76: =AH75 -> 0 | AH76: =AE76+AF76-AG76 -> 0 | AI76: pcs | AJ76: =AH76*P76 -> 0 | AK76: =AJ76 -> 0 | AL76: =B76-H76+1 -> -10 | AM76: =IF(AL76<=30,"30天内",IF(AL76<=90,"31-90天","91天以上")) -> 30天内 | AN76: 0 | AO76: Euro | AP76: =AK76*AN76 -> 0
A77: 202508 | B77: 45879 | C77: MIC德国仓 | D77: =D76 -> M » N2 - 1 | E77: =E76 -> YCD-EX:HUPPER TEK | F77: =F76 -> MI202508130012 | G77: =G76 -> DE2508031-G7-MIC | H77: =H76 -> 45889 | I77: =I76 -> B07Q3SQT6C | K77: =K76 -> 金属储物柜71英寸高 | M77: =M76 -> 188 | N77: =N76 -> 49 | O77: =O76 -> 14 | P77: =M77*N77*O77/1000000 -> 0.128968 | R77: =R76 -> 188 | S77: =S76 -> 49 | T77: =T76 -> 14 | U77: =R77*S77*T77/1000000 -> 0.128968 | AA77: =AA76 -> 13 | AB77: =AB76 -> 151 | AC77: =AC76 -> 151 | AD77: 0 | AE77: =AH76 -> 0 | AH77: =AE77+AF77-AG77 -> 0 | AI77: pcs | AJ77: =AH77*P77 -> 0 | AK77: =AJ77 -> 0 | AL77: =B77-H77+1 -> -9 | AM77: =IF(AL77<=30,"30天内",IF(AL77<=90,"31-90天","91天以上")) -> 30天内 | AN77: 0 | AO77: Euro | AP77: =AK77*AN77 -> 0
A78: 202508 | B78: 45880 | C78: MIC德国仓 | D78: =D77 -> M » N2 - 1 | E78: =E77 -> YCD-EX:HUPPER TEK | F78: =F77 -> MI202508130012 | G78: =G77 -> DE2508031-G7-MIC | H78: =H77 -> 45889 | I78: =I77 -> B07Q3SQT6C | K78: =K77 -> 金属储物柜71英寸高 | M78: =M77 -> 188 | N78: =N77 -> 49 | O78: =O77 -> 14 | P78: =M78*N78*O78/1000000 -> 0.128968 | R78: =R77 -> 188 | S78: =S77 -> 49 | T78: =T77 -> 14 | U78: =R78*S78*T78/1000000 -> 0.128968 | AA78: =AA77 -> 13 | AB78: =AB77 -> 151 | AC78: =AC77 -> 151 | AD78: 0 | AE78: =AH77 -> 0 | AH78: =AE78+AF78-AG78 -> 0 | AI78: pcs | AJ78: =AH78*P78 -> 0 | AK78: =AJ78 -> 0 | AL78: =B78-H78+1 -> -8 | AM78: =IF(AL78<=30,"30天内",IF(AL78<=90,"31-90天","91天以上")) -> 30天内 | AN78: 0 | AO78: Euro | AP78: =AK78*AN78 -> 0
A79: 202508 | B79: 45881 | C79: MIC德国仓 | D79: =D78 -> M » N2 - 1 | E79: =E78 -> YCD-EX:HUPPER TEK | F79: =F78 -> MI202508130012 | G79: =G78 -> DE2508031-G7-MIC | H79: =H78 -> 45889 | I79: =I78 -> B07Q3SQT6C | K79: =K78 -> 金属储物柜71英寸高 | M79: =M78 -> 188 | N79: =N78 -> 49 | O79: =O78 -> 14 | P79: =M79*N79*O79/1000000 -> 0.128968 | R79: =R78 -> 188 | S79: =S78 -> 49 | T79: =T78 -> 14 | U79: =R79*S79*T79/1000000 -> 0.128968 | AA79: =AA78 -> 13 | AB79: =AB78 -> 151 | AC79: =AC78 -> 151 | AD79: 0 | AE79: =AH78 -> 0 | AH79: =AE79+AF79-AG79 -> 0 | AI79: pcs | AJ79: =AH79*P79 -> 0 | AK79: =AJ79 -> 0 | AL79: =B79-H79+1 -> -7 | AM79: =IF(AL79<=30,"30天内",IF(AL79<=90,"31-90天","91天以上")) -> 30天内 | AN79: 0 | AO79: Euro | AP79: =AK79*AN79 -> 0
A80: 202508 | B80: 45882 | C80: MIC德国仓 | D80: =D79 -> M » N2 - 1 | E80: =E79 -> YCD-EX:HUPPER TEK | F80: =F79 -> MI202508130012 | G80: =G79 -> DE2508031-G7-MIC | H80: =H79 -> 45889 | I80: =I79 -> B07Q3SQT6C | K80: =K79 -> 金属储物柜71英寸高 | M80: =M79 -> 188 | N80: =N79 -> 49 | O80: =O79 -> 14 | P80: =M80*N80*O80/1000000 -> 0.128968 | R80: =R79 -> 188 | S80: =S79 -> 49 | T80: =T79 -> 14 | U80: =R80*S80*T80/1000000 -> 0.128968 | AA80: =AA79 -> 13 | AB80: =AB79 -> 151 | AC80: =AC79 -> 151 | AD80: 0 | AE80: =AH79 -> 0 | AH80: =AE80+AF80-AG80 -> 0 | AI80: pcs | AJ80: =AH80*P80 -> 0 | AK80: =AJ80 -> 0 | AL80: =B80-H80+1 -> -6 | AM80: =IF(AL80<=30,"30天内",IF(AL80<=90,"31-90天","91天以上")) -> 30天内 | AN80: 0 | AO80: Euro | AP80: =AK80*AN80 -> 0
... A86: 202508 | B86: 45888 | C86: MIC德国仓 | D86: =D85 -> M » N2 - 1 | E86: =E85 -> YCD-EX:HUPPER TEK | F86: =F85 -> MI202508130012 | G86: =G85 -> DE2508031-G7-MIC | H86: =H85 -> 45889 | I86: =I85 -> B07Q3SQT6C | K86: =K85 -> 金属储物柜71英寸高 | M86: =M85 -> 188 | N86: =N85 -> 49 | O86: =O85 -> 14 | P86: =M86*N86*O86/1000000 -> 0.128968 | R86: =R85 -> 188 | S86: =S85 -> 49 | T86: =T85 -> 14 | U86: =R86*S86*T86/1000000 -> 0.128968 | AA86: =AA85 -> 13 | AB86: =AB85 -> 151 | AC86: =AC85 -> 151 | AD86: 0 | AE86: =AH85 -> 0 | AH86: =AE86+AF86-AG86 -> 0 | AI86: pcs | AJ86: =AH86*P86 -> 0 | AK86: =AJ86 -> 0 | AL86: =B86-H86+1 -> 0 | AM86: =IF(AL86<=30,"30天内",IF(AL86<=90,"31-90天","91天以上")) -> 30天内 | AN86: 0 | AO86: Euro | AP86: =AK86*AN86 -> 0
A87: 202508 | B87: 45889 | C87: MIC德国仓 | D87: =D86 -> M » N2 - 1 | E87: =E86 -> YCD-EX:HUPPER TEK | F87: =F86 -> MI202508130012 | G87: =G86 -> DE2508031-G7-MIC | H87: =H86 -> 45889 | I87: =I86 -> B07Q3SQT6C | K87: =K86 -> 金属储物柜71英寸高 | M87: =M86 -> 188 | N87: =N86 -> 49 | O87: =O86 -> 14 | P87: =M87*N87*O87/1000000 -> 0.128968 | R87: =R86 -> 188 | S87: =S86 -> 49 | T87: =T86 -> 14 | U87: =R87*S87*T87/1000000 -> 0.128968 | AA87: =AA86 -> 13 | AB87: =AB86 -> 151 | AC87: =AC86 -> 151 | AD87: 0 | AE87: =AH86 -> 0 | AF87: 151 | AH87: =AE87+AF87-AG87 -> 151 | AI87: pcs | AJ87: =AH87*P87 -> 19.474168 | AK87: =AJ87 -> 19.474168 | AL87: =B87-H87+1 -> 1 | AM87: =IF(AL87<=30,"30天内",IF(AL87<=90,"31-90天","91天以上")) -> 30天内 | AN87: 0 | AO87: Euro | AP87: =AK87*AN87 -> 0
A88: 202508 | B88: 45890 | C88: MIC德国仓 | D88: =D87 -> M » N2 - 1 | E88: =E87 -> YCD-EX:HUPPER TEK | F88: =F87 -> MI202508130012 | G88: =G87 -> DE2508031-G7-MIC | H88: =H87 -> 45889 | I88: =I87 -> B07Q3SQT6C | K88: =K87 -> 金属储物柜71英寸高 | M88: =M87 -> 188 | N88: =N87 -> 49 | O88: =O87 -> 14 | P88: =M88*N88*O88/1000000 -> 0.128968 | R88: =R87 -> 188 | S88: =S87 -> 49 | T88: =T87 -> 14 | U88: =R88*S88*T88/1000000 -> 0.128968 | AA88: =AA87 -> 13 | AB88: =AB87 -> 151 | AC88: =AC87 -> 151 | AD88: 0 | AE88: =AH87 -> 151 | AH88: =AE88+AF88-AG88 -> 151 | AI88: pcs | AJ88: =AH88*P88 -> 19.474168 | AK88: =AJ88 -> 19.474168 | AL88: =B88-H88+1 -> 2 | AM88: =IF(AL88<=30,"30天内",IF(AL88<=90,"31-90天","91天以上")) -> 30天内 | AN88: 0 | AO88: Euro | AP88: =AK88*AN88 -> 0
A89: 202508 | B89: 45891 | C89: MIC德国仓 | D89: =D88 -> M » N2 - 1 | E89: =E88 -> YCD-EX:HUPPER TEK | F89: =F88 -> MI202508130012 | G89: =G88 -> DE2508031-G7-MIC | H89: =H88 -> 45889 | I89: =I88 -> B07Q3SQT6C | K89: =K88 -> 金属储物柜71英寸高 | M89: =M88 -> 188 | N89: =N88 -> 49 | O89: =O88 -> 14 | P89: =M89*N89*O89/1000000 -> 0.128968 | R89: =R88 -> 188 | S89: =S88 -> 49 | T89: =T88 -> 14 | U89: =R89*S89*T89/1000000 -> 0.128968 | AA89: =AA88 -> 13 | AB89: =AB88 -> 151 | AC89: =AC88 -> 151 | AD89: 0 | AE89: =AH88 -> 151 | AH89: =AE89+AF89-AG89 -> 151 | AI89: pcs | AJ89: =AH89*P89 -> 19.474168 | AK89: =AJ89 -> 19.474168 | AL89: =B89-H89+1 -> 3 | AM89: =IF(AL89<=30,"30天内",IF(AL89<=90,"31-90天","91天以上")) -> 30天内 | AN89: 0 | AO89: Euro | AP89: =AK89*AN89 -> 0
A90: 202508 | B90: 45892 | C90: MIC德国仓 | D90: =D89 -> M » N2 - 1 | E90: =E89 -> YCD-EX:HUPPER TEK | F90: =F89 -> MI202508130012 | G90: =G89 -> DE2508031-G7-MIC | H90: =H89 -> 45889 | I90: =I89 -> B07Q3SQT6C | K90: =K89 -> 金属储物柜71英寸高 | M90: =M89 -> 188 | N90: =N89 -> 49 | O90: =O89 -> 14 | P90: =M90*N90*O90/1000000 -> 0.128968 | R90: =R89 -> 188 | S90: =S89 -> 49 | T90: =T89 -> 14 | U90: =R90*S90*T90/1000000 -> 0.128968 | AA90: =AA89 -> 13 | AB90: =AB89 -> 151 | AC90: =AC89 -> 151 | AD90: 0 | AE90: =AH89 -> 151 | AH90: =AE90+AF90-AG90 -> 151 | AI90: pcs | AJ90: =AH90*P90 -> 19.474168 | AK90: =AJ90 -> 19.474168 | AL90: =B90-H90+1 -> 4 | AM90: =IF(AL90<=30,"30天内",IF(AL90<=90,"31-90天","91天以上")) -> 30天内 | AN90: 0 | AO90: Euro | AP90: =AK90*AN90 -> 0
A91: 202508 | B91: 45893 | C91: MIC德国仓 | D91: =D90 -> M » N2 - 1 | E91: =E90 -> YCD-EX:HUPPER TEK | F91: =F90 -> MI202508130012 | G91: =G90 -> DE2508031-G7-MIC | H91: =H90 -> 45889 | I91: =I90 -> B07Q3SQT6C | K91: =K90 -> 金属储物柜71英寸高 | M91: =M90 -> 188 | N91: =N90 -> 49 | O91: =O90 -> 14 | P91: =M91*N91*O91/1000000 -> 0.128968 | R91: =R90 -> 188 | S91: =S90 -> 49 | T91: =T90 -> 14 | U91: =R91*S91*T91/1000000 -> 0.128968 | AA91: =AA90 -> 13 | AB91: =AB90 -> 151 | AC91: =AC90 -> 151 | AD91: 0 | AE91: =AH90 -> 151 | AH91: =AE91+AF91-AG91 -> 151 | AI91: pcs | AJ91: =AH91*P91 -> 19.474168 | AK91: =AJ91 -> 19.474168 | AL91: =B91-H91+1 -> 5 | AM91: =IF(AL91<=30,"30天内",IF(AL91<=90,"31-90天","91天以上")) -> 30天内 | AN91: 0 | AO91: Euro | AP91: =AK91*AN91 -> 0
A92: 202508 | B92: 45894 | C92: MIC德国仓 | D92: =D91 -> M » N2 - 1 | E92: =E91 -> YCD-EX:HUPPER TEK | F92: =F91 -> MI202508130012 | G92: =G91 -> DE2508031-G7-MIC | H92: =H91 -> 45889 | I92: =I91 -> B07Q3SQT6C | K92: =K91 -> 金属储物柜71英寸高 | M92: =M91 -> 188 | N92: =N91 -> 49 | O92: =O91 -> 14 | P92: =M92*N92*O92/1000000 -> 0.128968 | R92: =R91 -> 188 | S92: =S91 -> 49 | T92: =T91 -> 14 | U92: =R92*S92*T92/1000000 -> 0.128968 | AA92: =AA91 -> 13 | AB92: =AB91 -> 151 | AC92: =AC91 -> 151 | AD92: 0 | AE92: =AH91 -> 151 | AH92: =AE92+AF92-AG92 -> 151 | AI92: pcs | AJ92: =AH92*P92 -> 19.474168 | AK92: =AJ92 -> 19.474168 | AL92: =B92-H92+1 -> 6 | AM92: =IF(AL92<=30,"30天内",IF(AL92<=90,"31-90天","91天以上")) -> 30天内 | AN92: 0 | AO92: Euro | AP92: =AK92*AN92 -> 0
A93: 202508 | B93: 45895 | C93: MIC德国仓 | D93: =D92 -> M » N2 - 1 | E93: =E92 -> YCD-EX:HUPPER TEK | F93: =F92 -> MI202508130012 | G93: =G92 -> DE2508031-G7-MIC | H93: =H92 -> 45889 | I93: =I92 -> B07Q3SQT6C | K93: =K92 -> 金属储物柜71英寸高 | M93: =M92 -> 188 | N93: =N92 -> 49 | O93: =O92 -> 14 | P93: =M93*N93*O93/1000000 -> 0.128968 | R93: =R92 -> 188 | S93: =S92 -> 49 | T93: =T92 -> 14 | U93: =R93*S93*T93/1000000 -> 0.128968 | AA93: =AA92 -> 13 | AB93: =AB92 -> 151 | AC93: =AC92 -> 151 | AD93: 0 | AE93: =AH92 -> 151 | AH93: =AE93+AF93-AG93 -> 151 | AI93: pcs | AJ93: =AH93*P93 -> 19.474168 | AK93: =AJ93 -> 19.474168 | AL93: =B93-H93+1 -> 7 | AM93: =IF(AL93<=30,"30天内",IF(AL93<=90,"31-90天","91天以上")) -> 30天内 | AN93: 0 | AO93: Euro | AP93: =AK93*AN93 -> 0
A94: 202508 | B94: 45896 | C94: MIC德国仓 | D94: =D93 -> M » N2 - 1 | E94: =E93 -> YCD-EX:HUPPER TEK | F94: =F93 -> MI202508130012 | G94: =G93 -> DE2508031-G7-MIC | H94: =H93 -> 45889 | I94: =I93 -> B07Q3SQT6C | K94: =K93 -> 金属储物柜71英寸高 | M94: =M93 -> 188 | N94: =N93 -> 49 | O94: =O93 -> 14 | P94: =M94*N94*O94/1000000 -> 0.128968 | R94: =R93 -> 188 | S94: =S93 -> 49 | T94: =T93 -> 14 | U94: =R94*S94*T94/1000000 -> 0.128968 | AA94: =AA93 -> 13 | AB94: =AB93 -> 151 | AC94: =AC93 -> 151 | AD94: 0 | AE94: =AH93 -> 151 | AH94: =AE94+AF94-AG94 -> 151 | AI94: pcs | AJ94: =AH94*P94 -> 19.474168 | AK94: =AJ94 -> 19.474168 | AL94: =B94-H94+1 -> 8 | AM94: =IF(AL94<=30,"30天内",IF(AL94<=90,"31-90天","91天以上")) -> 30天内 | AN94: 0 | AO94: Euro | AP94: =AK94*AN94 -> 0
A95: 202508 | B95: 45897 | C95: MIC德国仓 | D95: =D94 -> M » N2 - 1 | E95: =E94 -> YCD-EX:HUPPER TEK | F95: =F94 -> MI202508130012 | G95: =G94 -> DE2508031-G7-MIC | H95: =H94 -> 45889 | I95: =I94 -> B07Q3SQT6C | K95: =K94 -> 金属储物柜71英寸高 | M95: =M94 -> 188 | N95: =N94 -> 49 | O95: =O94 -> 14 | P95: =M95*N95*O95/1000000 -> 0.128968 | R95: =R94 -> 188 | S95: =S94 -> 49 | T95: =T94 -> 14 | U95: =R95*S95*T95/1000000 -> 0.128968 | AA95: =AA94 -> 13 | AB95: =AB94 -> 151 | AC95: =AC94 -> 151 | AD95: 0 | AE95: =AH94 -> 151 | AH95: =AE95+AF95-AG95 -> 151 | AI95: pcs | AJ95: =AH95*P95 -> 19.474168 | AK95: =AJ95 -> 19.474168 | AL95: =B95-H95+1 -> 9 | AM95: =IF(AL95<=30,"30天内",IF(AL95<=90,"31-90天","91天以上")) -> 30天内 | AN95: 0 | AO95: Euro | AP95: =AK95*AN95 -> 0
A96: 202508 | B96: 45898 | C96: MIC德国仓 | D96: =D95 -> M » N2 - 1 | E96: =E95 -> YCD-EX:HUPPER TEK | F96: =F95 -> MI202508130012 | G96: =G95 -> DE2508031-G7-MIC | H96: =H95 -> 45889 | I96: =I95 -> B07Q3SQT6C | K96: =K95 -> 金属储物柜71英寸高 | M96: =M95 -> 188 | N96: =N95 -> 49 | O96: =O95 -> 14 | P96: =M96*N96*O96/1000000 -> 0.128968 | R96: =R95 -> 188 | S96: =S95 -> 49 | T96: =T95 -> 14 | U96: =R96*S96*T96/1000000 -> 0.128968 | AA96: =AA95 -> 13 | AB96: =AB95 -> 151 | AC96: =AC95 -> 151 | AD96: 0 | AE96: =AH95 -> 151 | AH96: =AE96+AF96-AG96 -> 151 | AI96: pcs | AJ96: =AH96*P96 -> 19.474168 | AK96: =AJ96 -> 19.474168 | AL96: =B96-H96+1 -> 10 | AM96: =IF(AL96<=30,"30天内",IF(AL96<=90,"31-90天","91天以上")) -> 30天内 | AN96: 0 | AO96: Euro | AP96: =AK96*AN96 -> 0
A97: 202508 | B97: 45899 | C97: MIC德国仓 | D97: =D96 -> M » N2 - 1 | E97: =E96 -> YCD-EX:HUPPER TEK | F97: =F96 -> MI202508130012 | G97: =G96 -> DE2508031-G7-MIC | H97: =H96 -> 45889 | I97: =I96 -> B07Q3SQT6C | K97: =K96 -> 金属储物柜71英寸高 | M97: =M96 -> 188 | N97: =N96 -> 49 | O97: =O96 -> 14 | P97: =M97*N97*O97/1000000 -> 0.128968 | R97: =R96 -> 188 | S97: =S96 -> 49 | T97: =T96 -> 14 | U97: =R97*S97*T97/1000000 -> 0.128968 | AA97: =AA96 -> 13 | AB97: =AB96 -> 151 | AC97: =AC96 -> 151 | AD97: 0 | AE97: =AH96 -> 151 | AH97: =AE97+AF97-AG97 -> 151 | AI97: pcs | AJ97: =AH97*P97 -> 19.474168 | AK97: =AJ97 -> 19.474168 | AL97: =B97-H97+1 -> 11 | AM97: =IF(AL97<=30,"30天内",IF(AL97<=90,"31-90天","91天以上")) -> 30天内 | AN97: 0 | AO97: Euro | AP97: =AK97*AN97 -> 0
A98: 202508 | B98: 45900 | C98: MIC德国仓 | D98: =D97 -> M » N2 - 1 | E98: =E97 -> YCD-EX:HUPPER TEK | F98: =F97 -> MI202508130012 | G98: =G97 -> DE2508031-G7-MIC | H98: =H97 -> 45889 | I98: =I97 -> B07Q3SQT6C | K98: =K97 -> 金属储物柜71英寸高 | M98: =M97 -> 188 | N98: =N97 -> 49 | O98: =O97 -> 14 | P98: =M98*N98*O98/1000000 -> 0.128968 | R98: =R97 -> 188 | S98: =S97 -> 49 | T98: =T97 -> 14 | U98: =R98*S98*T98/1000000 -> 0.128968 | AA98: =AA97 -> 13 | AB98: =AB97 -> 151 | AC98: =AC97 -> 151 | AD98: 0 | AE98: =AH97 -> 151 | AH98: =AE98+AF98-AG98 -> 151 | AI98: pcs | AJ98: =AH98*P98 -> 19.474168 | AK98: =AJ98 -> 19.474168 | AL98: =B98-H98+1 -> 12 | AM98: =IF(AL98<=30,"30天内",IF(AL98<=90,"31-90天","91天以上")) -> 30天内 | AN98: 0 | AO98: Euro | AP98: =AK98*AN98 -> 0
A99: 202508 | B99: 45870 | C99: MIC德国仓 | D99: M » N2 - 1 | E99: YCD-EX:HUPPER TEK | F99: MI202508130012 | G99: DE2508031-G7-MIC | H99: 45889 | I99: B077RVYZRF | K99: =VLOOKUP(I99,物品明细!A:B,2,0) -> 德国联邦快递金属储物柜 | M99: =VLOOKUP(I99,物品明细!A:E,5,0) -> 188 | N99: =VLOOKUP(I99,物品明细!A:F,6,0) -> 49 | O99: =VLOOKUP(I99,物品明细!A:G,7,0) -> 14 | P99: =M99*N99*O99/1000000 -> 0.128968 | R99: =VLOOKUP(I99,物品明细!A:E,5,0) -> 188 | S99: =VLOOKUP(I99,物品明细!A:F,6,0) -> 49 | T99: =VLOOKUP(I99,物品明细!A:G,7,0) -> 14 | U99: =R99*S99*T99/1000000 -> 0.128968 | AA99: 10 | AB99: 117 | AC99: 117 | AD99: 0 | AE99: 0 | AH99: =AE99+AF99-AG99 -> 0 | AI99: pcs | AJ99: =AH99*P99 -> 0 | AK99: =AJ99 -> 0 | AL99: =B99-H99+1 -> -18 | AM99: =IF(AL99<=30,"30天内",IF(AL99<=90,"31-90天","91天以上")) -> 30天内 | AN99: 0 | AO99: Euro | AP99: =AK99*AN99 -> 0
A100: 202508 | B100: 45871 | C100: MIC德国仓 | D100: =D99 -> M » N2 - 1 | E100: =E99 -> YCD-EX:HUPPER TEK | F100: =F99 -> MI202508130012 | G100: =G99 -> DE2508031-G7-MIC | H100: =H99 -> 45889 | I100: =I99 -> B077RVYZRF | K100: =K99 -> 德国联邦快递金属储物柜 | M100: =M99 -> 188 | N100: =N99 -> 49 | O100: =O99 -> 14 | P100: =M100*N100*O100/1000000 -> 0.128968 | R100: =R99 -> 188 | S100: =S99 -> 49 | T100: =T99 -> 14 | U100: =R100*S100*T100/1000000 -> 0.128968 | AA100: =AA99 -> 10 | AB100: =AB99 -> 117 | AC100: =AC99 -> 117 | AD100: 0 | AE100: =AH99 -> 0 | AH100: =AE100+AF100-AG100 -> 0 | AI100: pcs | AJ100: =AH100*P100 -> 0 | AK100: =AJ100 -> 0 | AL100: =B100-H100+1 -> -17 | AM100: =IF(AL100<=30,"30天内",IF(AL100<=90,"31-90天","91天以上")) -> 30天内 | AN100: 0 | AO100: Euro | AP100: =AK100*AN100 -> 0
A101: 202508 | B101: 45872 | C101: MIC德国仓 | D101: =D100 -> M » N2 - 1 | E101: =E100 -> YCD-EX:HUPPER TEK | F101: =F100 -> MI202508130012 | G101: =G100 -> DE2508031-G7-MIC | H101: =H100 -> 45889 | I101: =I100 -> B077RVYZRF | K101: =K100 -> 德国联邦快递金属储物柜 | M101: =M100 -> 188 | N101: =N100 -> 49 | O101: =O100 -> 14 | P101: =M101*N101*O101/1000000 -> 0.128968 | R101: =R100 -> 188 | S101: =S100 -> 49 | T101: =T100 -> 14 | U101: =R101*S101*T101/1000000 -> 0.128968 | AA101: =AA100 -> 10 | AB101: =AB100 -> 117 | AC101: =AC100 -> 117 | AD101: 0 | AE101: =AH100 -> 0 | AH101: =AE101+AF101-AG101 -> 0 | AI101: pcs | AJ101: =AH101*P101 -> 0 | AK101: =AJ101 -> 0 | AL101: =B101-H101+1 -> -16 | AM101: =IF(AL101<=30,"30天内",IF(AL101<=90,"31-90天","91天以上")) -> 30天内 | AN101: 0 | AO101: Euro | AP101: =AK101*AN101 -> 0
A102: 202508 | B102: 45873 | C102: MIC德国仓 | D102: =D101 -> M » N2 - 1 | E102: =E101 -> YCD-EX:HUPPER TEK | F102: =F101 -> MI202508130012 | G102: =G101 -> DE2508031-G7-MIC | H102: =H101 -> 45889 | I102: =I101 -> B077RVYZRF | K102: =K101 -> 德国联邦快递金属储物柜 | M102: =M101 -> 188 | N102: =N101 -> 49 | O102: =O101 -> 14 | P102: =M102*N102*O102/1000000 -> 0.128968 | R102: =R101 -> 188 | S102: =S101 -> 49 | T102: =T101 -> 14 | U102: =R102*S102*T102/1000000 -> 0.128968 | AA102: =AA101 -> 10 | AB102: =AB101 -> 117 | AC102: =AC101 -> 117 | AD102: 0 | AE102: =AH101 -> 0 | AH102: =AE102+AF102-AG102 -> 0 | AI102: pcs | AJ102: =AH102*P102 -> 0 | AK102: =AJ102 -> 0 | AL102: =B102-H102+1 -> -15 | AM102: =IF(AL102<=30,"30天内",IF(AL102<=90,"31-90天","91天以上")) -> 30天内 | AN102: 0 | AO102: Euro | AP102: =AK102*AN102 -> 0
A103: 202508 | B103: 45874 | C103: MIC德国仓 | D103: =D102 -> M » N2 - 1 | E103: =E102 -> YCD-EX:HUPPER TEK | F103: =F102 -> MI202508130012 | G103: =G102 -> DE2508031-G7-MIC | H103: =H102 -> 45889 | I103: =I102 -> B077RVYZRF | K103: =K102 -> 德国联邦快递金属储物柜 | M103: =M102 -> 188 | N103: =N102 -> 49 | O103: =O102 -> 14 | P103: =M103*N103*O103/1000000 -> 0.128968 | R103: =R102 -> 188 | S103: =S102 -> 49 | T103: =T102 -> 14 | U103: =R103*S103*T103/1000000 -> 0.128968 | AA103: =AA102 -> 10 | AB103: =AB102 -> 117 | AC103: =AC102 -> 117 | AD103: 0 | AE103: =AH102 -> 0 | AH103: =AE103+AF103-AG103 -> 0 | AI103: pcs | AJ103: =AH103*P103 -> 0 | AK103: =AJ103 -> 0 | AL103: =B103-H103+1 -> -14 | AM103: =IF(AL103<=30,"30天内",IF(AL103<=90,"31-90天","91天以上")) -> 30天内 | AN103: 0 | AO103: Euro | AP103: =AK103*AN103 -> 0
A104: 202508 | B104: 45875 | C104: MIC德国仓 | D104: =D103 -> M » N2 - 1 | E104: =E103 -> YCD-EX:HUPPER TEK | F104: =F103 -> MI202508130012 | G104: =G103 -> DE2508031-G7-MIC | H104: =H103 -> 45889 | I104: =I103 -> B077RVYZRF | K104: =K103 -> 德国联邦快递金属储物柜 | M104: =M103 -> 188 | N104: =N103 -> 49 | O104: =O103 -> 14 | P104: =M104*N104*O104/1000000 -> 0.128968 | R104: =R103 -> 188 | S104: =S103 -> 49 | T104: =T103 -> 14 | U104: =R104*S104*T104/1000000 -> 0.128968 | AA104: =AA103 -> 10 | AB104: =AB103 -> 117 | AC104: =AC103 -> 117 | AD104: 0 | AE104: =AH103 -> 0 | AH104: =AE104+AF104-AG104 -> 0 | AI104: pcs | AJ104: =AH104*P104 -> 0 | AK104: =AJ104 -> 0 | AL104: =B104-H104+1 -> -13 | AM104: =IF(AL104<=30,"30天内",IF(AL104<=90,"31-90天","91天以上")) -> 30天内 | AN104: 0 | AO104: Euro | AP104: =AK104*AN104 -> 0
A105: 202508 | B105: 45876 | C105: MIC德国仓 | D105: =D104 -> M » N2 - 1 | E105: =E104 -> YCD-EX:HUPPER TEK | F105: =F104 -> MI202508130012 | G105: =G104 -> DE2508031-G7-MIC | H105: =H104 -> 45889 | I105: =I104 -> B077RVYZRF | K105: =K104 -> 德国联邦快递金属储物柜 | M105: =M104 -> 188 | N105: =N104 -> 49 | O105: =O104 -> 14 | P105: =M105*N105*O105/1000000 -> 0.128968 | R105: =R104 -> 188 | S105: =S104 -> 49 | T105: =T104 -> 14 | U105: =R105*S105*T105/1000000 -> 0.128968 | AA105: =AA104 -> 10 | AB105: =AB104 -> 117 | AC105: =AC104 -> 117 | AD105: 0 | AE105: =AH104 -> 0 | AH105: =AE105+AF105-AG105 -> 0 | AI105: pcs | AJ105: =AH105*P105 -> 0 | AK105: =AJ105 -> 0 | AL105: =B105-H105+1 -> -12 | AM105: =IF(AL105<=30,"30天内",IF(AL105<=90,"31-90天","91天以上")) -> 30天内 | AN105: 0 | AO105: Euro | AP105: =AK105*AN105 -> 0
A106: 202508 | B106: 45877 | C106: MIC德国仓 | D106: =D105 -> M » N2 - 1 | E106: =E105 -> YCD-EX:HUPPER TEK | F106: =F105 -> MI202508130012 | G106: =G105 -> DE2508031-G7-MIC | H106: =H105 -> 45889 | I106: =I105 -> B077RVYZRF | K106: =K105 -> 德国联邦快递金属储物柜 | M106: =M105 -> 188 | N106: =N105 -> 49 | O106: =O105 -> 14 | P106: =M106*N106*O106/1000000 -> 0.128968 | R106: =R105 -> 188 | S106: =S105 -> 49 | T106: =T105 -> 14 | U106: =R106*S106*T106/1000000 -> 0.128968 | AA106: =AA105 -> 10 | AB106: =AB105 -> 117 | AC106: =AC105 -> 117 | AD106: 0 | AE106: =AH105 -> 0 | AH106: =AE106+AF106-AG106 -> 0 | AI106: pcs | AJ106: =AH106*P106 -> 0 | AK106: =AJ106 -> 0 | AL106: =B106-H106+1 -> -11 | AM106: =IF(AL106<=30,"30天内",IF(AL106<=90,"31-90天","91天以上")) -> 30天内 | AN106: 0 | AO106: Euro | AP106: =AK106*AN106 -> 0
A107: 202508 | B107: 45878 | C107: MIC德国仓 | D107: =D106 -> M » N2 - 1 | E107: =E106 -> YCD-EX:HUPPER TEK | F107: =F106 -> MI202508130012 | G107: =G106 -> DE2508031-G7-MIC | H107: =H106 -> 45889 | I107: =I106 -> B077RVYZRF | K107: =K106 -> 德国联邦快递金属储物柜 | M107: =M106 -> 188 | N107: =N106 -> 49 | O107: =O106 -> 14 | P107: =M107*N107*O107/1000000 -> 0.128968 | R107: =R106 -> 188 | S107: =S106 -> 49 | T107: =T106 -> 14 | U107: =R107*S107*T107/1000000 -> 0.128968 | AA107: =AA106 -> 10 | AB107: =AB106 -> 117 | AC107: =AC106 -> 117 | AD107: 0 | AE107: =AH106 -> 0 | AH107: =AE107+AF107-AG107 -> 0 | AI107: pcs | AJ107: =AH107*P107 -> 0 | AK107: =AJ107 -> 0 | AL107: =B107-H107+1 -> -10 | AM107: =IF(AL107<=30,"30天内",IF(AL107<=90,"31-90天","91天以上")) -> 30天内 | AN107: 0 | AO107: Euro | AP107: =AK107*AN107 -> 0
A108: 202508 | B108: 45879 | C108: MIC德国仓 | D108: =D107 -> M » N2 - 1 | E108: =E107 -> YCD-EX:HUPPER TEK | F108: =F107 -> MI202508130012 | G108: =G107 -> DE2508031-G7-MIC | H108: =H107 -> 45889 | I108: =I107 -> B077RVYZRF | K108: =K107 -> 德国联邦快递金属储物柜 | M108: =M107 -> 188 | N108: =N107 -> 49 | O108: =O107 -> 14 | P108: =M108*N108*O108/1000000 -> 0.128968 | R108: =R107 -> 188 | S108: =S107 -> 49 | T108: =T107 -> 14 | U108: =R108*S108*T108/1000000 -> 0.128968 | AA108: =AA107 -> 10 | AB108: =AB107 -> 117 | AC108: =AC107 -> 117 | AD108: 0 | AE108: =AH107 -> 0 | AH108: =AE108+AF108-AG108 -> 0 | AI108: pcs | AJ108: =AH108*P108 -> 0 | AK108: =AJ108 -> 0 | AL108: =B108-H108+1 -> -9 | AM108: =IF(AL108<=30,"30天内",IF(AL108<=90,"31-90天","91天以上")) -> 30天内 | AN108: 0 | AO108: Euro | AP108: =AK108*AN108 -> 0
A109: 202508 | B109: 45880 | C109: MIC德国仓 | D109: =D108 -> M » N2 - 1 | E109: =E108 -> YCD-EX:HUPPER TEK | F109: =F108 -> MI202508130012 | G109: =G108 -> DE2508031-G7-MIC | H109: =H108 -> 45889 | I109: =I108 -> B077RVYZRF | K109: =K108 -> 德国联邦快递金属储物柜 | M109: =M108 -> 188 | N109: =N108 -> 49 | O109: =O108 -> 14 | P109: =M109*N109*O109/1000000 -> 0.128968 | R109: =R108 -> 188 | S109: =S108 -> 49 | T109: =T108 -> 14 | U109: =R109*S109*T109/1000000 -> 0.128968 | AA109: =AA108 -> 10 | AB109: =AB108 -> 117 | AC109: =AC108 -> 117 | AD109: 0 | AE109: =AH108 -> 0 | AH109: =AE109+AF109-AG109 -> 0 | AI109: pcs | AJ109: =AH109*P109 -> 0 | AK109: =AJ109 -> 0 | AL109: =B109-H109+1 -> -8 | AM109: =IF(AL109<=30,"30天内",IF(AL109<=90,"31-90天","91天以上")) -> 30天内 | AN109: 0 | AO109: Euro | AP109: =AK109*AN109 -> 0
A110: 202508 | B110: 45881 | C110: MIC德国仓 | D110: =D109 -> M » N2 - 1 | E110: =E109 -> YCD-EX:HUPPER TEK | F110: =F109 -> MI202508130012 | G110: =G109 -> DE2508031-G7-MIC | H110: =H109 -> 45889 | I110: =I109 -> B077RVYZRF | K110: =K109 -> 德国联邦快递金属储物柜 | M110: =M109 -> 188 | N110: =N109 -> 49 | O110: =O109 -> 14 | P110: =M110*N110*O110/1000000 -> 0.128968 | R110: =R109 -> 188 | S110: =S109 -> 49 | T110: =T109 -> 14 | U110: =R110*S110*T110/1000000 -> 0.128968 | AA110: =AA109 -> 10 | AB110: =AB109 -> 117 | AC110: =AC109 -> 117 | AD110: 0 | AE110: =AH109 -> 0 | AH110: =AE110+AF110-AG110 -> 0 | AI110: pcs | AJ110: =AH110*P110 -> 0 | AK110: =AJ110 -> 0 | AL110: =B110-H110+1 -> -7 | AM110: =IF(AL110<=30,"30天内",IF(AL110<=90,"31-90天","91天以上")) -> 30天内 | AN110: 0 | AO110: Euro | AP110: =AK110*AN110 -> 0
A111: 202508 | B111: 45882 | C111: MIC德国仓 | D111: =D110 -> M » N2 - 1 | E111: =E110 -> YCD-EX:HUPPER TEK | F111: =F110 -> MI202508130012 | G111: =G110 -> DE2508031-G7-MIC | H111: =H110 -> 45889 | I111: =I110 -> B077RVYZRF | K111: =K110 -> 德国联邦快递金属储物柜 | M111: =M110 -> 188 | N111: =N110 -> 49 | O111: =O110 -> 14 | P111: =M111*N111*O111/1000000 -> 0.128968 | R111: =R110 -> 188 | S111: =S110 -> 49 | T111: =T110 -> 14 | U111: =R111*S111*T111/1000000 -> 0.128968 | AA111: =AA110 -> 10 | AB111: =AB110 -> 117 | AC111: =AC110 -> 117 | AD111: 0 | AE111: =AH110 -> 0 | AH111: =AE111+AF111-AG111 -> 0 | AI111: pcs | AJ111: =AH111*P111 -> 0 | AK111: =AJ111 -> 0 | AL111: =B111-H111+1 -> -6 | AM111: =IF(AL111<=30,"30天内",IF(AL111<=90,"31-90天","91天以上")) -> 30天内 | AN111: 0 | AO111: Euro | AP111: =AK111*AN111 -> 0
... A117: 202508 | B117: 45888 | C117: MIC德国仓 | D117: =D116 -> M » N2 - 1 | E117: =E116 -> YCD-EX:HUPPER TEK | F117: =F116 -> MI202508130012 | G117: =G116 -> DE2508031-G7-MIC | H117: =H116 -> 45889 | I117: =I116 -> B077RVYZRF | K117: =K116 -> 德国联邦快递金属储物柜 | M117: =M116 -> 188 | N117: =N116 -> 49 | O117: =O116 -> 14 | P117: =M117*N117*O117/1000000 -> 0.128968 | R117: =R116 -> 188 | S117: =S116 -> 49 | T117: =T116 -> 14 | U117: =R117*S117*T117/1000000 -> 0.128968 | AA117: =AA116 -> 10 | AB117: =AB116 -> 117 | AC117: =AC116 -> 117 | AD117: 0 | AE117: =AH116 -> 0 | AH117: =AE117+AF117-AG117 -> 0 | AI117: pcs | AJ117: =AH117*P117 -> 0 | AK117: =AJ117 -> 0 | AL117: =B117-H117+1 -> 0 | AM117: =IF(AL117<=30,"30天内",IF(AL117<=90,"31-90天","91天以上")) -> 30天内 | AN117: 0 | AO117: Euro | AP117: =AK117*AN117 -> 0
A118: 202508 | B118: 45889 | C118: MIC德国仓 | D118: =D117 -> M » N2 - 1 | E118: =E117 -> YCD-EX:HUPPER TEK | F118: =F117 -> MI202508130012 | G118: =G117 -> DE2508031-G7-MIC | H118: =H117 -> 45889 | I118: =I117 -> B077RVYZRF | K118: =K117 -> 德国联邦快递金属储物柜 | M118: =M117 -> 188 | N118: =N117 -> 49 | O118: =O117 -> 14 | P118: =M118*N118*O118/1000000 -> 0.128968 | R118: =R117 -> 188 | S118: =S117 -> 49 | T118: =T117 -> 14 | U118: =R118*S118*T118/1000000 -> 0.128968 | AA118: =AA117 -> 10 | AB118: =AB117 -> 117 | AC118: =AC117 -> 117 | AD118: 0 | AE118: =AH117 -> 0 | AF118: 117 | AH118: =AE118+AF118-AG118 -> 117 | AI118: pcs | AJ118: =AH118*P118 -> 15.089256 | AK118: =AJ118 -> 15.089256 | AL118: =B118-H118+1 -> 1 | AM118: =IF(AL118<=30,"30天内",IF(AL118<=90,"31-90天","91天以上")) -> 30天内 | AN118: 0 | AO118: Euro | AP118: =AK118*AN118 -> 0
A119: 202508 | B119: 45890 | C119: MIC德国仓 | D119: =D118 -> M » N2 - 1 | E119: =E118 -> YCD-EX:HUPPER TEK | F119: =F118 -> MI202508130012 | G119: =G118 -> DE2508031-G7-MIC | H119: =H118 -> 45889 | I119: =I118 -> B077RVYZRF | K119: =K118 -> 德国联邦快递金属储物柜 | M119: =M118 -> 188 | N119: =N118 -> 49 | O119: =O118 -> 14 | P119: =M119*N119*O119/1000000 -> 0.128968 | R119: =R118 -> 188 | S119: =S118 -> 49 | T119: =T118 -> 14 | U119: =R119*S119*T119/1000000 -> 0.128968 | AA119: =AA118 -> 10 | AB119: =AB118 -> 117 | AC119: =AC118 -> 117 | AD119: 0 | AE119: =AH118 -> 117 | AH119: =AE119+AF119-AG119 -> 117 | AI119: pcs | AJ119: =AH119*P119 -> 15.089256 | AK119: =AJ119 -> 15.089256 | AL119: =B119-H119+1 -> 2 | AM119: =IF(AL119<=30,"30天内",IF(AL119<=90,"31-90天","91天以上")) -> 30天内 | AN119: 0 | AO119: Euro | AP119: =AK119*AN119 -> 0
A120: 202508 | B120: 45891 | C120: MIC德国仓 | D120: =D119 -> M » N2 - 1 | E120: =E119 -> YCD-EX:HUPPER TEK | F120: =F119 -> MI202508130012 | G120: =G119 -> DE2508031-G7-MIC | H120: =H119 -> 45889 | I120: =I119 -> B077RVYZRF | K120: =K119 -> 德国联邦快递金属储物柜 | M120: =M119 -> 188 | N120: =N119 -> 49 | O120: =O119 -> 14 | P120: =M120*N120*O120/1000000 -> 0.128968 | R120: =R119 -> 188 | S120: =S119 -> 49 | T120: =T119 -> 14 | U120: =R120*S120*T120/1000000 -> 0.128968 | AA120: =AA119 -> 10 | AB120: =AB119 -> 117 | AC120: =AC119 -> 117 | AD120: 0 | AE120: =AH119 -> 117 | AH120: =AE120+AF120-AG120 -> 117 | AI120: pcs | AJ120: =AH120*P120 -> 15.089256 | AK120: =AJ120 -> 15.089256 | AL120: =B120-H120+1 -> 3 | AM120: =IF(AL120<=30,"30天内",IF(AL120<=90,"31-90天","91天以上")) -> 30天内 | AN120: 0 | AO120: Euro | AP120: =AK120*AN120 -> 0
...

Sheet 物品明细
A1: Item ID | B1: Name | C1: Barcode | D1: Weight | E1: Length | F1: Width | G1: Height | H1: HS Code | I1: 规格 | J1: 体积 | K1: 原始名称 | L1: 打托数
A2: B076THQBHX | B2: 金属储物柜71英寸灰色 | C2: 7434503987965 | D2: 47.4 | E2: 188 | F2: 49 | G2: 14 | I2: =E2&"x"&F2&"x"&G2 -> 188x49x14 | J2: =E2*F2*G2/1000000 -> 0.128968 | K2: Metal Storage Cabinet 71 inches Gray | L2: 12个/托
A3: B07BK8W5MF | B3: 金属储物柜71英寸银色 | C3: 7434503791791 | D3: 47.4 | E3: 188 | F3: 49 | G3: 14 | I3: =E3&"x"&F3&"x"&G3 -> 188x49x14 | J3: =E3*F3*G3/1000000 -> 0.128968 | K3: Metal Storage Cabinet 71 inches Silver | L3: 12个/托
A4: B077RVYZRF | B4: 德国联邦快递金属储物柜 | C4: 7434503188171 | D4: 47.4 | E4: 188 | F4: 49 | G4: 14 | I4: =E4&"x"&F4&"x"&G4 -> 188x49x14 | J4: =E4*F4*G4/1000000 -> 0.128968 | K4: DE - Fedmax Metal Storage Cabinet | L4: 12个/托
A5: B07Q3SQT6C | B5: 金属储物柜71英寸高 | C5: 600413399021 | D5: 47.4 | E5: 188 | F5: 49 | G5: 14 | I5: =E5&"x"&F5&"x"&G5 -> 188x49x14 | J5: =E5*F5*G5/1000000 -> 0.128968 | K5: Metal Storage Cabinet 71" Tall | L5: 12个/托
